Workbook
Name CONST_CNTR_TotProd: #REF!
Name CONST_ElecConsumption: #REF!

Sheet 温室气体盘查清册 (2)
B1: 温室气体盘查清册 | L1: 编号：DY-GHG-2025-01
L2: 版本/版次：A/1
L3: 日期：2025/7/3
B4: 组织名称： | C4: 大冶特殊钢有限公司
B5: 组织边界： | C5: 湖北省黄石市黄石大道316号
B6: 盘查覆盖周期: | C6: 2024年1月1日至2024年12月31日
B7: 编制 ： | E7: 审核： | K7: 核准：
B8: 报告边界 | C8: 运营控制权 | E8: 范围一排放量： | F8: =F14 -> #REF! | K8: 单位：tCO2e
E9: 范围二（基于位置）排放量： | F9: =F47 -> 1043611.1
E10: 范围二（基于市场）排放量： | F10: =F48 -> 1186800.3
B11: 排放 | E11: 范围三排放量： | F11: =SUM(F50,F76,F89,F101,F106,F113,F118,F124,F130,F136) -> #REF!
B12: 编号 | C12: 排放源 | D12: 排放设施 | E12: 备注 | F12: 总排放量 | G12: CO2 | H12: CH4 | I12: N2O | J12: HFCs | K12: PFCs | L12: SF6 | M12: NF3
G13: tCO2e
B14: 范围一 直接排放 | F14: =F15+F24+F27+F33 -> #REF! | G14: =G15+G24+G27+G33 -> #REF! | H14: =H15+H24+H27+H33 -> #REF! | I14: =I15+I24+I27+I33 -> #REF! | J14: =J15+J24+J27+J33 -> #REF! | K14: =K15+K24+K27+K33 -> #REF! | L14: =L15+L24+L27+L33 -> #REF! | M14: =M15+M24+M27+M33 -> #REF!
B15: 1.1 | C15: 固定源燃烧直接排放 | F15: =SUM(G15:M15) -> #REF! | G15: =SUM(G16:G23) -> #REF! | H15: =SUM(H16:H23) -> #REF! | I15: =SUM(I16:I23) -> #REF! | J15: =SUM(J16:J23) -> #REF! | K15: =SUM(K16:K23) -> #REF! | L15: =SUM(L16:L23) -> #REF! | M15: =SUM(M16:M23) -> #REF!
B16: 1.1.1 | C16: =表1温室气体盘查表!C5 -> 天然气燃烧 | D16: =表1温室气体盘查表!D5 -> 热处理炉（加热炉） | F16: =SUM(G16:M16) -> 31469.159 | G16: =表1温室气体盘查表!AF5 -> 31438.225 | H16: =表1温室气体盘查表!AG5 -> 15.635053 | I16: =表1温室气体盘查表!AH5 -> 15.298816 | J16: =表1温室气体盘查表!AI5 -> 0 | K16: =表1温室气体盘查表!AJ5 -> 0 | L16: =表1温室气体盘查表!AK5 -> 0 | M16: =表1温室气体盘查表!AL5 -> 0
B17: 1.1.2 | C17: =表1温室气体盘查表!C6 -> 液化石油气燃烧 | D17: =表1温室气体盘查表!D6 -> 冶钢宾馆 | F17: =SUM(G17:M17) -> 29.286595 | G17: =表1温室气体盘查表!AF6 -> 29.260998 | H17: =表1温室气体盘查表!AG6 -> 0.012937905 | I17: =表1温室气体盘查表!AH6 -> 0.012659671 | J17: =表1温室气体盘查表!AI6 -> 0 | K17: =表1温室气体盘查表!AJ6 -> 0 | L17: =表1温室气体盘查表!AK6 -> 0 | M17: =表1温室气体盘查表!AL6 -> 0
B18: 1.1.3 | C18: =表1温室气体盘查表!C7 -> 烟煤燃烧 | D18: =表1温室气体盘查表!D7 -> 高炉 | F18: =SUM(G18:M18) -> 749580.33 | G18: =表1温室气体盘查表!AF7 -> 746259.74 | H18: =表1温室气体盘查表!AG7 -> 211.80719 | I18: =表1温室气体盘查表!AH7 -> 3108.783 | J18: =表1温室气体盘查表!AI7 -> 0 | K18: =表1温室气体盘查表!AJ7 -> 0 | L18: =表1温室气体盘查表!AK7 -> 0 | M18: =表1温室气体盘查表!AL7 -> 0
B19: 1.1.4 | C19: =表1温室气体盘查表!C8 -> 无烟煤燃烧 | D19: =表1温室气体盘查表!D8 -> 高炉、烧结 | F19: =SUM(G19:M19) -> 820622.2 | G19: =表1温室气体盘查表!AF8 -> 816986.9 | H19: =表1温室气体盘查表!AG8 -> 231.88133 | I19: =表1温室气体盘查表!AH8 -> 3403.4195 | J19: =表1温室气体盘查表!AI8 -> 0 | K19: =表1温室气体盘查表!AJ8 -> 0 | L19: =表1温室气体盘查表!AK8 -> 0 | M19: =表1温室气体盘查表!AL8 -> 0
B20: 1.1.5 | C20: =表1温室气体盘查表!C9 -> 洗精煤燃烧 | D20: =表1温室气体盘查表!D9 -> 焦炉 | F20: =SUM(G20:M20) -> 5189313.3 | G20: =表1温室气体盘查表!AF9 -> 5165430 | H20: =表1温室气体盘查表!AG9 -> 1523.4196 | I20: =表1温室气体盘查表!AH9 -> 22359.869 | J20: =表1温室气体盘查表!AI9 -> 0 | K20: =表1温室气体盘查表!AJ9 -> 0 | L20: =表1温室气体盘查表!AK9 -> 0 | M20: =表1温室气体盘查表!AL9 -> 0
B21: 1.1.6 | C21: =表1温室气体盘查表!C10 -> 焦炭燃烧 | D21: =表1温室气体盘查表!D10 -> 高炉 | F21: =SUM(G21:M21) -> 669939.56 | G21: =表1温室气体盘查表!AF10 -> 667212.1 | H21: =表1温室气体盘查表!AG10 -> 173.974 | I21: =表1温室气体盘查表!AH10 -> 2553.4893 | J21: =表1温室气体盘查表!AI10 -> 0 | K21: =表1温室气体盘查表!AJ10 -> 0 | L21: =表1温室气体盘查表!AK10 -> 0 | M21: =表1温室气体盘查表!AL10 -> 0
B22: 1.1.7 | C22: =表1温室气体盘查表!#REF! -> #REF! | D22: =表1温室气体盘查表!#REF! -> #REF! | F22: =SUM(G22:M22) -> #REF! | G22: =表1温室气体盘查表!#REF! -> #REF! | H22: =表1温室气体盘查表!#REF! -> #REF! | I22: =表1温室气体盘查表!#REF! -> #REF! | J22: =表1温室气体盘查表!#REF! -> #REF! | K22: =表1温室气体盘查表!#REF! -> #REF! | L22: =表1温室气体盘查表!#REF! -> #REF! | M22: =表1温室气体盘查表!#REF! -> #REF!
B23: 1.1.8 | C23: =表1温室气体盘查表!C11 -> 焦炉煤气燃烧 | D23: =表1温室气体盘查表!D11 -> 外售 | F23: =SUM(G23:M23) -> -6034.9102 | G23: =表1温室气体盘查表!AF11 -> -6027.4166 | H23: =表1温室气体盘查表!AG11 -> -3.7874983 | I23: =表1温室气体盘查表!AH11 -> -3.7060467 | J23: =表1温室气体盘查表!AI11 -> 0 | K23: =表1温室气体盘查表!AJ11 -> 0 | L23: =表1温室气体盘查表!AK11 -> 0 | M23: =表1温室气体盘查表!AL11 -> 0
B24: 1.2 | C24: 移动源燃烧直接排放 | F24: =SUM(G24:M24) -> 4620.5168 | G24: =SUM(G25:G26) -> 4544.9741 | H24: =SUM(H25:H26) -> 7.8643134 | I24: =SUM(I25:I26) -> 67.678446 | J24: =SUM(J25:J26) -> 0 | K24: =SUM(K25:K26) -> 0 | L24: =SUM(L25:L26) -> 0 | M24: =SUM(M25:M26) -> 0
B25: 1.2.1 | C25: =表1温室气体盘查表!C12 -> 柴油燃烧 | D25: =表1温室气体盘查表!D12 -> 场内运输 | F25: =SUM(G25:M25) -> 4476.287 | G25: =表1温室气体盘查表!AF12 -> 4406.5019 | H25: =表1温室气体盘查表!AG12 -> 6.4706002 | I25: =表1温室气体盘查表!AH12 -> 63.314475 | J25: =表1温室气体盘查表!AI12 -> 0 | K25: =表1温室气体盘查表!AJ12 -> 0 | L25: =表1温室气体盘查表!AK12 -> 0 | M25: =表1温室气体盘查表!AL12 -> 0
B26: 1.2.2 | C26: =表1温室气体盘查表!C13 -> 汽油燃烧 | D26: =表1温室气体盘查表!D13 -> 公务车 | F26: =SUM(G26:M26) -> 144.22983 | G26: =表1温室气体盘查表!AF13 -> 138.47215 | H26: =表1温室气体盘查表!AG13 -> 1.3937132 | I26: =表1温室气体盘查表!AH13 -> 4.3639708 | J26: =表1温室气体盘查表!AI13 -> 0 | K26: =表1温室气体盘查表!AJ13 -> 0 | L26: =表1温室气体盘查表!AK13 -> 0 | M26: =表1温室气体盘查表!AL13 -> 0
B27: 1.3 | C27: 逸散源直接排放 | F27: =SUM(G27:M27) -> #REF! | G27: =SUM(G28:G32) -> #REF! | H27: =SUM(H28:H32) -> #REF! | I27: =SUM(I28:I32) -> #REF! | J27: =SUM(J28:J32) -> #REF! | K27: =SUM(K28:K32) -> #REF! | L27: =SUM(L28:L32) -> #REF! | M27: =SUM(M28:M32) -> #REF!
B28: 1.3.1 | C28: =表1温室气体盘查表!C14 -> 制冷剂逸散（R32） | D28: =表1温室气体盘查表!D14 -> 分体式空调 | F28: =SUM(G28:M28) -> 570.54 | G28: =表1温室气体盘查表!AF14 -> 0 | H28: =表1温室气体盘查表!AG14 -> 0 | I28: =表1温室气体盘查表!AH14 -> 0 | J28: =表1温室气体盘查表!AI14 -> 570.54 | K28: =表1温室气体盘查表!AJ14 -> 0 | L28: =表1温室气体盘查表!AK14 -> 0 | M28: =表1温室气体盘查表!AL14 -> 0
B29: 1.3.2 | C29: =表1温室气体盘查表!C15 -> CO2逸散 | D29: =表1温室气体盘查表!D15 -> 二氧化碳灭火器 | F29: =SUM(G29:M29) -> 0.56 | G29: =表1温室气体盘查表!AF15 -> 0.56 | H29: =表1温室气体盘查表!AG15 -> 0 | I29: =表1温室气体盘查表!AH15 -> 0 | J29: =表1温室气体盘查表!AI15 -> 0 | K29: =表1温室气体盘查表!AJ15 -> 0 | L29: =表1温室气体盘查表!AK15 -> 0 | M29: =表1温室气体盘查表!AL15 -> 0
B30: 1.3.3 | C30: =表1温室气体盘查表!C16 -> CH4逸散 | D30: =表1温室气体盘查表!D16 -> 化粪池 | F30: =SUM(G30:M30) -> 116.30952 | G30: =表1温室气体盘查表!AF16 -> 0 | H30: =表1温室气体盘查表!AG16 -> 116.30952 | I30: =表1温室气体盘查表!AH16 -> 0 | J30: =表1温室气体盘查表!AI16 -> 0 | K30: =表1温室气体盘查表!AJ16 -> 0 | L30: =表1温室气体盘查表!AK16 -> 0 | M30: =表1温室气体盘查表!AL16 -> 0
B31: 1.3.4 | C31: =表1温室气体盘查表!C17 -> CH4逸散 | D31: =表1温室气体盘查表!D17 -> 耗氧池 | F31: =SUM(G31:M31) -> 8408.8577 | G31: =表1温室气体盘查表!AF17 -> 0 | H31: =表1温室气体盘查表!AG17 -> 8408.8577 | I31: =表1温室气体盘查表!AH17 -> 0 | J31: =表1温室气体盘查表!AI17 -> 0 | K31: =表1温室气体盘查表!AJ17 -> 0 | L31: =表1温室气体盘查表!AK17 -> 0 | M31: =表1温室气体盘查表!AL17 -> 0
B32: 1.3.5 | C32: =表1温室气体盘查表!#REF! -> #REF! | D32: =表1温室气体盘查表!#REF! -> #REF! | F32: =SUM(G32:M32) -> #REF! | G32: =表1温室气体盘查表!#REF! -> #REF! | H32: =表1温室气体盘查表!#REF! -> #REF! | I32: =表1温室气体盘查表!#REF! -> #REF! | J32: =表1温室气体盘查表!#REF! -> #REF! | K32: =表1温室气体盘查表!#REF! -> #REF! | L32: =表1温室气体盘查表!#REF! -> #REF! | M32: =表1温室气体盘查表!#REF! -> #REF!
B33: 1.4 | C33: 制程排放 | F33: =SUM(G33:M33) -> #REF! | G33: =SUM(G34:G45) -> #REF! | H33: =SUM(H34:H45) -> #REF! | I33: =SUM(I34:I45) -> #REF! | J33: =SUM(J34:J45) -> #REF! | K33: =SUM(K34:K45) -> #REF! | L33: =SUM(L34:L45) -> #REF! | M33: =SUM(M34:M45) -> #REF!
B34: 1.4.1 | C34: =表1温室气体盘查表!#REF! -> #REF! | D34: =表1温室气体盘查表!#REF! -> #REF! | F34: =SUM(G34:M34) -> #REF! | G34: =表1温室气体盘查表!#REF! -> #REF! | H34: =表1温室气体盘查表!#REF! -> #REF! | I34: =表1温室气体盘查表!#REF! -> #REF! | J34: =表1温室气体盘查表!#REF! -> #REF! | K34: =表1温室气体盘查表!#REF! -> #REF! | L34: =表1温室气体盘查表!#REF! -> #REF! | M34: =表1温室气体盘查表!#REF! -> #REF!
B35: 1.4.2 | C35: =表1温室气体盘查表!C18 -> 白云石 | D35: =表1温室气体盘查表!D18 -> 高炉 | F35: =SUM(G35:M35) -> 18406.658 | G35: =表1温室气体盘查表!AF18 -> 18406.658 | H35: =表1温室气体盘查表!AG18 -> 0 | I35: =表1温室气体盘查表!AH18 -> 0 | J35: =表1温室气体盘查表!AI18 -> 0 | K35: =表1温室气体盘查表!AJ18 -> 0 | L35: =表1温室气体盘查表!AK18 -> 0 | M35: =表1温室气体盘查表!AL18 -> 0
B36: 1.4.3 | C36: =表1温室气体盘查表!C19 -> 电极 | D36: =表1温室气体盘查表!D19 -> 炼钢 | F36: =SUM(G36:M36) -> 18334.963 | G36: =表1温室气体盘查表!AF19 -> 18334.963 | H36: =表1温室气体盘查表!AG19 -> 0 | I36: =表1温室气体盘查表!AH19 -> 0 | J36: =表1温室气体盘查表!AI19 -> 0 | K36: =表1温室气体盘查表!AJ19 -> 0 | L36: =表1温室气体盘查表!AK19 -> 0 | M36: =表1温室气体盘查表!AL19 -> 0
B37: 1.4.4 | C37: =表1温室气体盘查表!C20 -> 废钢 | D37: =表1温室气体盘查表!D20 -> 炼钢 | F37: =SUM(G37:M37) -> 41425.779 | G37: =表1温室气体盘查表!AF20 -> 41425.779 | H37: =表1温室气体盘查表!AG20 -> 0 | I37: =表1温室气体盘查表!AH20 -> 0 | J37: =表1温室气体盘查表!AI20 -> 0 | K37: =表1温室气体盘查表!AJ20 -> 0 | L37: =表1温室气体盘查表!AK20 -> 0 | M37: =表1温室气体盘查表!AL20 -> 0
B38: 1.4.5 | C38: =表1温室气体盘查表!C21 -> 高碳锰铁 | D38: =表1温室气体盘查表!D21 -> 炼钢 | F38: =SUM(G38:M38) -> 11407.872 | G38: =表1温室气体盘查表!AF21 -> 11407.872 | H38: =表1温室气体盘查表!AG21 -> 0 | I38: =表1温室气体盘查表!AH21 -> 0 | J38: =表1温室气体盘查表!AI21 -> 0 | K38: =表1温室气体盘查表!AJ21 -> 0 | L38: =表1温室气体盘查表!AK21 -> 0 | M38: =表1温室气体盘查表!AL21 -> 0
B39: 1.4.6 | C39: =表1温室气体盘查表!C23 -> 镍铁 | D39: =表1温室气体盘查表!D23 -> 炼钢 | F39: =SUM(G39:M39) -> 367.8984 | G39: =表1温室气体盘查表!AF23 -> 367.8984 | H39: =表1温室气体盘查表!AG23 -> 0 | I39: =表1温室气体盘查表!AH23 -> 0 | J39: =表1温室气体盘查表!AI23 -> 0 | K39: =表1温室气体盘查表!AJ23 -> 0 | L39: =表1温室气体盘查表!AK23 -> 0 | M39: =表1温室气体盘查表!AL23 -> 0
B40: 1.4.7 | C40: =表1温室气体盘查表!C24 -> 高碳铬铁 | D40: =表1温室气体盘查表!D24 -> 炼钢 | F40: =SUM(G40:M40) -> 13992.429 | G40: =表1温室气体盘查表!AF24 -> 13992.429 | H40: =表1温室气体盘查表!AG24 -> 0 | I40: =表1温室气体盘查表!AH24 -> 0 | J40: =表1温室气体盘查表!AI24 -> 0 | K40: =表1温室气体盘查表!AJ24 -> 0 | L40: =表1温室气体盘查表!AK24 -> 0 | M40: =表1温室气体盘查表!AL24 -> 0
B41: 1.4.8 | C41: =表1温室气体盘查表!C25 -> 硅铁 | D41: =表1温室气体盘查表!D25 -> 炼钢 | F41: =SUM(G41:M41) -> 82.65656 | G41: =表1温室气体盘查表!AF25 -> 82.65656 | H41: =表1温室气体盘查表!AG25 -> 0 | I41: =表1温室气体盘查表!AH25 -> 0 | J41: =表1温室气体盘查表!AI25 -> 0 | K41: =表1温室气体盘查表!AJ25 -> 0 | L41: =表1温室气体盘查表!AK25 -> 0 | M41: =表1温室气体盘查表!AL25 -> 0
B42: 1.4.9 | C42: =表1温室气体盘查表!C26 -> 钼铁 | D42: =表1温室气体盘查表!D26 -> 炼钢 | F42: =SUM(G42:M42) -> 130.83696 | G42: =表1温室气体盘查表!AF26 -> 130.83696 | H42: =表1温室气体盘查表!AG26 -> 0 | I42: =表1温室气体盘查表!AH26 -> 0 | J42: =表1温室气体盘查表!AI26 -> 0 | K42: =表1温室气体盘查表!AJ26 -> 0 | L42: =表1温室气体盘查表!AK26 -> 0 | M42: =表1温室气体盘查表!AL26 -> 0
B43: 1.4.10 | C43: =表1温室气体盘查表!C27 -> 粗钢 | D43: =表1温室气体盘查表!D27 -> 固碳产品 | F43: =SUM(G43:M43) -> -165928.08 | G43: =表1温室气体盘查表!AF27 -> -165928.08 | H43: =表1温室气体盘查表!AG27 -> 0 | I43: =表1温室气体盘查表!AH27 -> 0 | J43: =表1温室气体盘查表!AI27 -> 0 | K43: =表1温室气体盘查表!AJ27 -> 0 | L43: =表1温室气体盘查表!AK27 -> 0 | M43: =表1温室气体盘查表!AL27 -> 0
B44: 1.4.11 | C44: =表1温室气体盘查表!C28 -> 粗苯 | D44: =表1温室气体盘查表!D28 -> 外售 | F44: =SUM(G44:M44) -> -68970.885 | G44: =表1温室气体盘查表!AF28 -> -68970.885 | H44: =表1温室气体盘查表!AG28 -> 0 | I44: =表1温室气体盘查表!AH28 -> 0 | J44: =表1温室气体盘查表!AI28 -> 0 | K44: =表1温室气体盘查表!AJ28 -> 0 | L44: =表1温室气体盘查表!AK28 -> 0 | M44: =表1温室气体盘查表!AL28 -> 0
B45: 1.4.12 | C45: =表1温室气体盘查表!C29 -> 焦油 | D45: =表1温室气体盘查表!D29 -> 危废处置 | F45: =SUM(G45:M45) -> -163466.55 | G45: =表1温室气体盘查表!AF29 -> -163466.55 | H45: =表1温室气体盘查表!AG29 -> 0 | I45: =表1温室气体盘查表!AH29 -> 0 | J45: =表1温室气体盘查表!AI29 -> 0 | K45: =表1温室气体盘查表!AJ29 -> 0 | L45: =表1温室气体盘查表!AK29 -> 0 | M45: =表1温室气体盘查表!AL29 -> 0
B46: 范围二 外购电间接排放
B47: 2.1 | C47: =表1温室气体盘查表!C30 -> 外购电力（基于位置） | D47: =表1温室气体盘查表!D30 -> 用电设备 | F47: =SUM(G47:M47) -> 1043611.1 | G47: =表1温室气体盘查表!AF30 -> 1043611.1 | H47: =表1温室气体盘查表!AG30 -> 0 | I47: =表1温室气体盘查表!AH30 -> 0 | J47: =表1温室气体盘查表!AI30 -> 0 | K47: =表1温室气体盘查表!AJ30 -> 0 | L47: =表1温室气体盘查表!AK30 -> 0 | M47: =表1温室气体盘查表!AL30 -> 0
B48: 2.2 | C48: =表1温室气体盘查表!C31 -> 外购电力（基于市场） | D48: =表1温室气体盘查表!D31 -> 用电设备 | F48: =SUM(G48:M48) -> 1186800.3 | G48: =表1温室气体盘查表!AF31 -> 1186800.3 | H48: =表1温室气体盘查表!AG31 -> 0 | I48: =表1温室气体盘查表!AH31 -> 0 | J48: =表1温室气体盘查表!AI31 -> 0 | K48: =表1温室气体盘查表!AJ31 -> 0 | L48: =表1温室气体盘查表!AK31 -> 0 | M48: =表1温室气体盘查表!AL31 -> 0
B50: 范围三 类别1 | C50: 外购商品和服务的上游排放 | F50: =SUM(G50:M50) -> #REF! | G50: =SUM(G51:G74) -> #REF! | H50: =SUM(H51:H69) -> #REF! | I50: =SUM(I51:I69) -> #REF! | J50: =SUM(J51:J69) -> #REF! | K50: =SUM(K51:K69) -> #REF! | L50: =SUM(L51:L69) -> #REF! | M50: =SUM(M51:M69) -> #REF!
B51: 3.1.1 | C51: =表1温室气体盘查表!C32 -> 铁矿石生产 | D51: =表1温室气体盘查表!D32 -> 烧结 | F51: =表1温室气体盘查表!AM32 -> 479835.37 | G51: =表1温室气体盘查表!AF32 -> 479835.37 | H51: =表1温室气体盘查表!AG32 -> 0 | I51: =表1温室气体盘查表!AH32 -> 0 | J51: =表1温室气体盘查表!AI32 -> 0 | K51: =表1温室气体盘查表!AJ32 -> 0 | L51: =表1温室气体盘查表!AK32 -> 0 | M51: =表1温室气体盘查表!AL32 -> 0
B52: 3.1.2 | C52: =表1温室气体盘查表!C33 -> 生石灰生产 | D52: =表1温室气体盘查表!D33 -> 烧结、转炉、电炉 | F52: =表1温室气体盘查表!AM33 -> 236961.26 | G52: =表1温室气体盘查表!AF33 -> 236961.26 | H52: =表1温室气体盘查表!AG33 -> 0 | I52: =表1温室气体盘查表!AH33 -> 0 | J52: =表1温室气体盘查表!AI33 -> 0 | K52: =表1温室气体盘查表!AJ33 -> 0 | L52: =表1温室气体盘查表!AK33 -> 0 | M52: =表1温室气体盘查表!AL33 -> 0
B53: 3.1.3 | C53: =表1温室气体盘查表!#REF! -> #REF! | D53: =表1温室气体盘查表!#REF! -> #REF! | F53: =表1温室气体盘查表!#REF! -> #REF! | G53: =表1温室气体盘查表!#REF! -> #REF! | H53: =表1温室气体盘查表!#REF! -> #REF! | I53: =表1温室气体盘查表!#REF! -> #REF! | J53: =表1温室气体盘查表!#REF! -> #REF! | K53: =表1温室气体盘查表!#REF! -> #REF! | L53: =表1温室气体盘查表!#REF! -> #REF! | M53: =表1温室气体盘查表!#REF! -> #REF!
B54: 3.1.4 | C54: =表1温室气体盘查表!C34 -> 白云石生产 | D54: =表1温室气体盘查表!D34 -> 烧结、转炉、电炉 | F54: =表1温室气体盘查表!AM34 -> 5039.7894 | G54: =表1温室气体盘查表!AF34 -> 5039.7894 | H54: =表1温室气体盘查表!AG34 -> 0 | I54: =表1温室气体盘查表!AH34 -> 0 | J54: =表1温室气体盘查表!AI34 -> 0 | K54: =表1温室气体盘查表!AJ34 -> 0 | L54: =表1温室气体盘查表!AK34 -> 0 | M54: =表1温室气体盘查表!AL34 -> 0
B55: 3.1.5 | C55: =表1温室气体盘查表!#REF! -> #REF! | D55: =表1温室气体盘查表!D35 -> 高炉、转炉 | F55: =表1温室气体盘查表!#REF! -> #REF! | G55: =表1温室气体盘查表!#REF! -> #REF! | H55: =表1温室气体盘查表!#REF! -> #REF! | I55: =表1温室气体盘查表!#REF! -> #REF! | J55: =表1温室气体盘查表!#REF! -> #REF! | K55: =表1温室气体盘查表!#REF! -> #REF! | L55: =表1温室气体盘查表!#REF! -> #REF! | M55: =表1温室气体盘查表!#REF! -> #REF!
B56: 3.1.6 | C56: =表1温室气体盘查表!C35 -> 球团生产 | D56: =表1温室气体盘查表!D36 -> 转炉、电炉 | F56: =表1温室气体盘查表!AM35 -> 71241.082 | G56: =表1温室气体盘查表!AF35 -> 71241.082 | H56: =表1温室气体盘查表!AG35 -> 0 | I56: =表1温室气体盘查表!AH35 -> 0 | J56: =表1温室气体盘查表!AI35 -> 0 | K56: =表1温室气体盘查表!AJ35 -> 0 | L56: =表1温室气体盘查表!AK35 -> 0 | M56: =表1温室气体盘查表!AL35 -> 0
B57: 3.1.7 | C57: =表1温室气体盘查表!C36 -> 废钢生产 | D57: =表1温室气体盘查表!D37 -> 转炉、电炉 | F57: =表1温室气体盘查表!AM36 -> 83051.97 | G57: =表1温室气体盘查表!AF36 -> 83051.97 | H57: =表1温室气体盘查表!AG36 -> 0 | I57: =表1温室气体盘查表!AH36 -> 0 | J57: =表1温室气体盘查表!AI36 -> 0 | K57: =表1温室气体盘查表!AJ36 -> 0 | L57: =表1温室气体盘查表!AK36 -> 0 | M57: =表1温室气体盘查表!AL36 -> 0
B58: 3.1.8 | C58: =表1温室气体盘查表!C37 -> 电极生产 | D58: =表1温室气体盘查表!D38 -> 转炉、电炉 | F58: =表1温室气体盘查表!AM37 -> 60962.024 | G58: =表1温室气体盘查表!AF37 -> 60962.024 | H58: =表1温室气体盘查表!AG37 -> 0 | I58: =表1温室气体盘查表!AH37 -> 0 | J58: =表1温室气体盘查表!AI37 -> 0 | K58: =表1温室气体盘查表!AJ37 -> 0 | L58: =表1温室气体盘查表!AK37 -> 0 | M58: =表1温室气体盘查表!AL37 -> 0
B59: 3.1.9 | C59: =表1温室气体盘查表!C38 -> 锰铁生产 | D59: =表1温室气体盘查表!D39 -> 转炉、电炉 | F59: =表1温室气体盘查表!AM38 -> 123503.69 | G59: =表1温室气体盘查表!AF38 -> 123503.69 | H59: =表1温室气体盘查表!AG38 -> 0 | I59: =表1温室气体盘查表!AH38 -> 0 | J59: =表1温室气体盘查表!AI38 -> 0 | K59: =表1温室气体盘查表!AJ38 -> 0 | L59: =表1温室气体盘查表!AK38 -> 0 | M59: =表1温室气体盘查表!AL38 -> 0
B60: 3.1.10 | C60: =表1温室气体盘查表!C39 -> 镍铁生产 | D60: =表1温室气体盘查表!D40 -> 转炉、电炉 | F60: =表1温室气体盘查表!AM39 -> 87049.733 | G60: =表1温室气体盘查表!AF39 -> 87049.733 | H60: =表1温室气体盘查表!AG39 -> 0 | I60: =表1温室气体盘查表!AH39 -> 0 | J60: =表1温室气体盘查表!AI39 -> 0 | K60: =表1温室气体盘查表!AJ39 -> 0 | L60: =表1温室气体盘查表!AK39 -> 0 | M60: =表1温室气体盘查表!AL39 -> 0
B61: 3.1.11 | C61: =表1温室气体盘查表!C40 -> 铬铁生产 | D61: =表1温室气体盘查表!D41 -> 转炉、电炉 | F61: =表1温室气体盘查表!AM40 -> 204743.82 | G61: =表1温室气体盘查表!AF40 -> 204743.82 | H61: =表1温室气体盘查表!AG40 -> 0 | I61: =表1温室气体盘查表!AH40 -> 0 | J61: =表1温室气体盘查表!AI40 -> 0 | K61: =表1温室气体盘查表!AJ40 -> 0 | L61: =表1温室气体盘查表!AK40 -> 0 | M61: =表1温室气体盘查表!AL40 -> 0
B62: 3.1.12 | C62: =表1温室气体盘查表!C41 -> 萤石生产 | D62: =表1温室气体盘查表!D42 -> 转炉、电炉 | F62: =表1温室气体盘查表!AM41 -> 88473.44 | G62: =表1温室气体盘查表!AF41 -> 88473.44 | H62: =表1温室气体盘查表!AG41 -> 0 | I62: =表1温室气体盘查表!AH41 -> 0 | J62: =表1温室气体盘查表!AI41 -> 0 | K62: =表1温室气体盘查表!AJ41 -> 0 | L62: =表1温室气体盘查表!AK41 -> 0 | M62: =表1温室气体盘查表!AL41 -> 0
B63: 3.1.13 | C63: =表1温室气体盘查表!C42 -> 硅铁生产 | D63: =表1温室气体盘查表!D43 -> 转炉、电炉 | F63: =表1温室气体盘查表!AM42 -> 149088.59 | G63: =表1温室气体盘查表!AF42 -> 149088.59 | H63: =表1温室气体盘查表!AG42 -> 0 | I63: =表1温室气体盘查表!AH42 -> 0 | J63: =表1温室气体盘查表!AI42 -> 0 | K63: =表1温室气体盘查表!AJ42 -> 0 | L63: =表1温室气体盘查表!AK42 -> 0 | M63: =表1温室气体盘查表!AL42 -> 0
B64: 3.1.14 | C64: =表1温室气体盘查表!C43 -> 钼铁生产 | D64: =表1温室气体盘查表!D44 -> 转炉、电炉 | F64: =表1温室气体盘查表!AM43 -> 58876.632 | G64: =表1温室气体盘查表!AF43 -> 58876.632 | H64: =表1温室气体盘查表!AG43 -> 0 | I64: =表1温室气体盘查表!AH43 -> 0 | J64: =表1温室气体盘查表!AI43 -> 0 | K64: =表1温室气体盘查表!AJ43 -> 0 | L64: =表1温室气体盘查表!AK43 -> 0 | M64: =表1温室气体盘查表!AL43 -> 0
B65: 3.1.15 | C65: =表1温室气体盘查表!C44 -> 铝铁生产 | D65: =表1温室气体盘查表!D45 -> 转炉、电炉 | F65: =表1温室气体盘查表!AM44 -> 13585.605 | G65: =表1温室气体盘查表!AF44 -> 13585.605 | H65: =表1温室气体盘查表!AG44 -> 0 | I65: =表1温室气体盘查表!AH44 -> 0 | J65: =表1温室气体盘查表!AI44 -> 0 | K65: =表1温室气体盘查表!AJ44 -> 0 | L65: =表1温室气体盘查表!AK44 -> 0 | M65: =表1温室气体盘查表!AL44 -> 0
B66: 3.1.16 | C66: =表1温室气体盘查表!C45 -> 铝生产 | D66: =表1温室气体盘查表!D46 -> 转炉、电炉 | F66: =表1温室气体盘查表!AM45 -> 165810.57 | G66: =表1温室气体盘查表!AF45 -> 165810.57 | H66: =表1温室气体盘查表!AG45 -> 0 | I66: =表1温室气体盘查表!AH45 -> 0 | J66: =表1温室气体盘查表!AI45 -> 0 | K66: =表1温室气体盘查表!AJ45 -> 0 | L66: =表1温室气体盘查表!AK45 -> 0 | M66: =表1温室气体盘查表!AL45 -> 0
B67: 3.1.17 | C67: =表1温室气体盘查表!C46 -> 增碳剂生产 | D67: =表1温室气体盘查表!D46 -> 转炉、电炉 | F67: =表1温室气体盘查表!AM46 -> 14447.768 | G67: =表1温室气体盘查表!AF46 -> 14447.768 | H67: =表1温室气体盘查表!AG46 -> 0 | I67: =表1温室气体盘查表!AH46 -> 0 | J67: =表1温室气体盘查表!AI46 -> 0 | K67: =表1温室气体盘查表!AJ46 -> 0 | L67: =表1温室气体盘查表!AK46 -> 0 | M67: =表1温室气体盘查表!AL46 -> 0
B68: 3.1.18 | C68: =表1温室气体盘查表!C47 -> 铁鳞生产 | D68: =表1温室气体盘查表!D47 -> 炼钢 | F68: =表1温室气体盘查表!AM47 -> 29.192524 | G68: =表1温室气体盘查表!AF47 -> 29.192524 | H68: =表1温室气体盘查表!AG47 -> 0 | I68: =表1温室气体盘查表!AH47 -> 0 | J68: =表1温室气体盘查表!AI47 -> 0 | K68: =表1温室气体盘查表!AJ47 -> 0 | L68: =表1温室气体盘查表!AK47 -> 0 | M68: =表1温室气体盘查表!AL47 -> 0
B69: 3.1.19 | C69: =表1温室气体盘查表!C48 -> 氨水生产 | D69: =表1温室气体盘查表!D48 -> 烧结 | F69: =表1温室气体盘查表!AM48 -> 26510.816 | G69: =表1温室气体盘查表!AF48 -> 26510.816 | H69: =表1温室气体盘查表!AG48 -> 0 | I69: =表1温室气体盘查表!AH48 -> 0 | J69: =表1温室气体盘查表!AI48 -> 0 | K69: =表1温室气体盘查表!AJ48 -> 0 | L69: =表1温室气体盘查表!AK48 -> 0 | M69: =表1温室气体盘查表!AL48 -> 0
B70: 3.1.20 | C70: =表1温室气体盘查表!C51 -> 碳化硅生产 | D70: =表1温室气体盘查表!D51 -> - | F70: =表1温室气体盘查表!AM51 -> 26760.682 | G70: =表1温室气体盘查表!AF51 -> 26760.682 | H70: =表1温室气体盘查表!AG51 -> 0 | I70: =表1温室气体盘查表!AH51 -> 0 | J70: =表1温室气体盘查表!AI51 -> 0 | K70: =表1温室气体盘查表!AJ51 -> 0 | L70: =表1温室气体盘查表!AK51 -> 0 | M70: =表1温室气体盘查表!AL51 -> 0
B71: 3.1.21 | C71: =表1温室气体盘查表!C52 -> 镁生产 | D71: =表1温室气体盘查表!D52 -> - | F71: =表1温室气体盘查表!AM52 -> 256865.11 | G71: =表1温室气体盘查表!AF52 -> 256865.11 | H71: =表1温室气体盘查表!AG52 -> 0 | I71: =表1温室气体盘查表!AH52 -> 0 | J71: =表1温室气体盘查表!AI52 -> 0 | K71: =表1温室气体盘查表!AJ52 -> 0 | L71: =表1温室气体盘查表!AK52 -> 0 | M71: =表1温室气体盘查表!AL52 -> 0
B72: 3.1.22 | C72: =表1温室气体盘查表!C53 -> 所有其他纸制品加工制造 | D72: =表1温室气体盘查表!D53 -> 办公室 | F72: =表1温室气体盘查表!AM53 -> 5.2434719 | G72: =表1温室气体盘查表!AF53 -> 5.2434719 | H72: =表1温室气体盘查表!AG53 -> 0 | I72: =表1温室气体盘查表!AH53 -> 0 | J72: =表1温室气体盘查表!AI53 -> 0 | K72: =表1温室气体盘查表!AJ53 -> 0 | L72: =表1温室气体盘查表!AK53 -> 0 | M72: =表1温室气体盘查表!AL53 -> 0
B73: 3.1.23 | C73: =表1温室气体盘查表!C54 -> 办公用品(纸张除外)制造 | D73: =表1温室气体盘查表!D54 -> 办公室 | F73: =表1温室气体盘查表!AM54 -> 72.312583 | G73: =表1温室气体盘查表!AF54 -> 72.312583 | H73: =表1温室气体盘查表!AG54 -> 0 | I73: =表1温室气体盘查表!AH54 -> 0 | J73: =表1温室气体盘查表!AI54 -> 0 | K73: =表1温室气体盘查表!AJ54 -> 0 | L73: =表1温室气体盘查表!AK54 -> 0 | M73: =表1温室气体盘查表!AL54 -> 0
B74: 3.1.24 | C74: =表1温室气体盘查表!C55 -> 源水 | D74: =表1温室气体盘查表!D55 -> 水处理工序 | F74: =表1温室气体盘查表!AM55 -> 26397.412 | G74: =表1温室气体盘查表!AF55 -> 26397.412 | H74: =表1温室气体盘查表!AG55 -> 0 | I74: =表1温室气体盘查表!AH55 -> 0 | J74: =表1温室气体盘查表!AI55 -> 0 | K74: =表1温室气体盘查表!AJ55 -> 0 | L74: =表1温室气体盘查表!AK55 -> 0 | M74: =表1温室气体盘查表!AL55 -> 0
B76: 范围三 类别2 | C76: =表1温室气体盘查表!B56 -> 资本货物 | F76: =SUM(G76:M76) -> #REF! | G76: =SUM(G77:G87) -> #REF! | H76: =SUM(H77:H87) -> #REF! | I76: =SUM(I77:I87) -> #REF! | J76: =SUM(J77:J87) -> #REF! | K76: =SUM(K77:K87) -> #REF! | L76: =SUM(L77:L87) -> #REF! | M76: =SUM(M77:M87) -> #REF!
B77: 3.2.1 | C77: =表1温室气体盘查表!C56 -> 采购产品空调和暖空气加热设备和商业和工业制冷设备制造 | D77: =表1温室气体盘查表!D56 -> 办公室、各工序 | F77: =表1温室气体盘查表!AM56 -> 120.11822 | G77: =表1温室气体盘查表!AF56 -> 120.11822 | H77: =表1温室气体盘查表!AG56 -> 0 | I77: =表1温室气体盘查表!AH56 -> 0 | J77: =表1温室气体盘查表!AI56 -> 0 | K77: =表1温室气体盘查表!AJ56 -> 0 | L77: =表1温室气体盘查表!AK56 -> 0 | M77: =表1温室气体盘查表!AL56 -> 0
B78: 3.2.2 | C78: =表1温室气体盘查表!C57 -> 电子计算机制造 | D78: =表1温室气体盘查表!D57 -> 办公室、各工序 | F78: =表1温室气体盘查表!AM57 -> 25.839091 | G78: =表1温室气体盘查表!AF57 -> 25.839091 | H78: =表1温室气体盘查表!AG57 -> 0 | I78: =表1温室气体盘查表!AH57 -> 0 | J78: =表1温室气体盘查表!AI57 -> 0 | K78: =表1温室气体盘查表!AJ57 -> 0 | L78: =表1温室气体盘查表!AK57 -> 0 | M78: =表1温室气体盘查表!AL57 -> 0
B79: 3.2.3 | C79: =表1温室气体盘查表!#REF! -> #REF! | D79: =表1温室气体盘查表!#REF! -> #REF! | F79: =表1温室气体盘查表!#REF! -> #REF! | G79: =表1温室气体盘查表!#REF! -> #REF! | H79: =表1温室气体盘查表!#REF! -> #REF! | I79: =表1温室气体盘查表!#REF! -> #REF! | J79: =表1温室气体盘查表!#REF! -> #REF! | K79: =表1温室气体盘查表!#REF! -> #REF! | L79: =表1温室气体盘查表!#REF! -> #REF! | M79: =表1温室气体盘查表!#REF! -> #REF!
B80: 3.2.4 | C80: =表1温室气体盘查表!C58 -> 其他工业设备制造 | D80: =表1温室气体盘查表!D58 -> 各工序 | F80: =表1温室气体盘查表!AM58 -> 518.69925 | G80: =表1温室气体盘查表!AF58 -> 518.69925 | H80: =表1温室气体盘查表!AG58 -> 0 | I80: =表1温室气体盘查表!AH58 -> 0 | J80: =表1温室气体盘查表!AI58 -> 0 | K80: =表1温室气体盘查表!AJ58 -> 0 | L80: =表1温室气体盘查表!AK58 -> 0 | M80: =表1温室气体盘查表!AL58 -> 0
B81: 3.2.5 | C81: =表1温室气体盘查表!C59 -> 测量和测试电力和电气信号的仪器制造 | D81: =表1温室气体盘查表!D59 -> 各工序 | F81: =表1温室气体盘查表!AM59 -> 220.30499 | G81: =表1温室气体盘查表!AF59 -> 220.30499 | H81: =表1温室气体盘查表!AG59 -> 0 | I81: =表1温室气体盘查表!AH59 -> 0 | J81: =表1温室气体盘查表!AI59 -> 0 | K81: =表1温室气体盘查表!AJ59 -> 0 | L81: =表1温室气体盘查表!AK59 -> 0 | M81: =表1温室气体盘查表!AL59 -> 0
B82: 3.2.6 | C82: =表1温室气体盘查表!#REF! -> #REF! | D82: =表1温室气体盘查表!#REF! -> #REF! | F82: =表1温室气体盘查表!#REF! -> #REF! | G82: =表1温室气体盘查表!#REF! -> #REF! | H82: =表1温室气体盘查表!#REF! -> #REF! | I82: =表1温室气体盘查表!#REF! -> #REF! | J82: =表1温室气体盘查表!#REF! -> #REF! | K82: =表1温室气体盘查表!#REF! -> #REF! | L82: =表1温室气体盘查表!#REF! -> #REF! | M82: =表1温室气体盘查表!#REF! -> #REF!
B83: 3.2.7 | C83: =表1温室气体盘查表!C60 -> 机械动力传动设备制造 | D83: =表1温室气体盘查表!D60 -> 各工序 | F83: =表1温室气体盘查表!AM60 -> 1122.1195 | G83: =表1温室气体盘查表!AF60 -> 1122.1195 | H83: =表1温室气体盘查表!AG60 -> 0 | I83: =表1温室气体盘查表!AH60 -> 0 | J83: =表1温室气体盘查表!AI60 -> 0 | K83: =表1温室气体盘查表!AJ60 -> 0 | L83: =表1温室气体盘查表!AK60 -> 0 | M83: =表1温室气体盘查表!AL60 -> 0
B84: 3.2.8 | C84: =表1温室气体盘查表!C61 -> 测量、分配及其他泵类设备制造 | D84: =表1温室气体盘查表!D61 -> 各工序 | F84: =表1温室气体盘查表!AM61 -> 604.1994 | G84: =表1温室气体盘查表!AF61 -> 604.1994 | H84: =表1温室气体盘查表!AG61 -> 0 | I84: =表1温室气体盘查表!AH61 -> 0 | J84: =表1温室气体盘查表!AI61 -> 0 | K84: =表1温室气体盘查表!AJ61 -> 0 | L84: =表1温室气体盘查表!AK61 -> 0 | M84: =表1温室气体盘查表!AL61 -> 0
B85: 3.2.9 | C85: =表1温室气体盘查表!C62 -> 用于测量、显示和控制工业过程变量的仪器及相关产品制造 | D85: =表1温室气体盘查表!D62 -> 各工序 | F85: =表1温室气体盘查表!AM62 -> 140.41627 | G85: =表1温室气体盘查表!AF62 -> 140.41627 | H85: =表1温室气体盘查表!AG62 -> 0 | I85: =表1温室气体盘查表!AH62 -> 0 | J85: =表1温室气体盘查表!AI62 -> 0 | K85: =表1温室气体盘查表!AJ62 -> 0 | L85: =表1温室气体盘查表!AK62 -> 0 | M85: =表1温室气体盘查表!AL62 -> 0
B86: 3.2.10 | C86: =表1温室气体盘查表!C63 -> 所有其他杂项电气设备及元件制造 | D86: =表1温室气体盘查表!D63 -> 各工序 | F86: =表1温室气体盘查表!AM63 -> 1091.3267 | G86: =表1温室气体盘查表!AF63 -> 1091.3267 | H86: =表1温室气体盘查表!AG63 -> 0 | I86: =表1温室气体盘查表!AH63 -> 0 | J86: =表1温室气体盘查表!AI63 -> 0 | K86: =表1温室气体盘查表!AJ63 -> 0 | L86: =表1温室气体盘查表!AK63 -> 0 | M86: =表1温室气体盘查表!AL63 -> 0
B87: 3.2.11 | C87: =表1温室气体盘查表!C64 -> 所有其他杂项制造 | D87: =表1温室气体盘查表!D64 -> 各工序 | F87: =表1温室气体盘查表!AM64 -> 43034.196 | G87: =表1温室气体盘查表!AF64 -> 43034.196 | H87: =表1温室气体盘查表!AG64 -> 0 | I87: =表1温室气体盘查表!AH64 -> 0 | J87: =表1温室气体盘查表!AI64 -> 0 | K87: =表1温室气体盘查表!AJ64 -> 0 | L87: =表1温室气体盘查表!AK64 -> 0 | M87: =表1温室气体盘查表!AL64 -> 0
B89: 范围三 类别3 | C89: =表1温室气体盘查表!B66 -> 范围一、二相关燃料和能源相关的活动产生的排放 | F89: =SUM(G89:M89) -> #REF! | G89: =SUM(G90:G99) -> #REF! | H89: =SUM(H91:H98) -> #REF! | I89: =SUM(I91:I98) -> #REF! | J89: =SUM(J91:J98) -> #REF! | K89: =SUM(K91:K98) -> #REF! | L89: =SUM(L91:L98) -> #REF! | M89: =SUM(M91:M98) -> #REF!
B90: 3.3.1 | C90: =表1温室气体盘查表!C65 -> 液化石油气生产 | D90: =表1温室气体盘查表!D65 -> 冶钢宾馆 | F90: =表1温室气体盘查表!AM65 -> 9.4887071 | G90: =表1温室气体盘查表!AF65 -> 9.4887071 | H90: =表1温室气体盘查表!AG65 -> 0 | I90: =表1温室气体盘查表!AH65 -> 0 | J90: =表1温室气体盘查表!AI65 -> 0 | K90: =表1温室气体盘查表!AJ65 -> 0 | L90: =表1温室气体盘查表!AK65 -> 0 | M90: =表1温室气体盘查表!AL65 -> 0
B91: 3.3.2 | C91: =表1温室气体盘查表!C66 -> 洗精煤生产 | D91: =表1温室气体盘查表!D66 -> 焦化 | F91: =表1温室气体盘查表!AM66 -> 1204984.6 | G91: =表1温室气体盘查表!AF66 -> 1204984.6 | H91: =表1温室气体盘查表!AG66 -> 0 | I91: =表1温室气体盘查表!AH66 -> 0 | J91: =表1温室气体盘查表!AI66 -> 0 | K91: =表1温室气体盘查表!AJ66 -> 0 | L91: =表1温室气体盘查表!AK66 -> 0 | M91: =表1温室气体盘查表!AL66 -> 0
B92: 3.3.3 | C92: =表1温室气体盘查表!C67 -> 柴油生产 | D92: =表1温室气体盘查表!D67 -> 各工序 | F92: =表1温室气体盘查表!AM67 -> 1198.0757 | G92: =表1温室气体盘查表!AF67 -> 1198.0757 | H92: =表1温室气体盘查表!AG67 -> 0 | I92: =表1温室气体盘查表!AH67 -> 0 | J92: =表1温室气体盘查表!AI67 -> 0 | K92: =表1温室气体盘查表!AJ67 -> 0 | L92: =表1温室气体盘查表!AK67 -> 0 | M92: =表1温室气体盘查表!AL67 -> 0
B93: 3.3.4 | C93: =表1温室气体盘查表!C68 -> 汽油生产 | D93: =表1温室气体盘查表!D68 -> 车队 | F93: =表1温室气体盘查表!AM68 -> 46.740217 | G93: =表1温室气体盘查表!AF68 -> 46.740217 | H93: =表1温室气体盘查表!AG68 -> 0 | I93: =表1温室气体盘查表!AH68 -> 0 | J93: =表1温室气体盘查表!AI68 -> 0 | K93: =表1温室气体盘查表!AJ68 -> 0 | L93: =表1温室气体盘查表!AK68 -> 0 | M93: =表1温室气体盘查表!AL68 -> 0
B94: 3.3.5 | C94: =表1温室气体盘查表!C69 -> 焦炭生产 | D94: =表1温室气体盘查表!D69 -> 烧结、高炉 | F94: =表1温室气体盘查表!AM69 -> 77306.7 | G94: =表1温室气体盘查表!AF69 -> 77306.7 | H94: =表1温室气体盘查表!AG69 -> 0 | I94: =表1温室气体盘查表!AH69 -> 0 | J94: =表1温室气体盘查表!AI69 -> 0 | K94: =表1温室气体盘查表!AJ69 -> 0 | L94: =表1温室气体盘查表!AK69 -> 0 | M94: =表1温室气体盘查表!AL69 -> 0
B95: 3.3.6 | C95: =表1温室气体盘查表!#REF! -> #REF! | D95: =表1温室气体盘查表!#REF! -> #REF! | F95: =表1温室气体盘查表!#REF! -> #REF! | G95: =表1温室气体盘查表!#REF! -> #REF! | H95: =表1温室气体盘查表!#REF! -> #REF! | I95: =表1温室气体盘查表!#REF! -> #REF! | J95: =表1温室气体盘查表!#REF! -> #REF! | K95: =表1温室气体盘查表!#REF! -> #REF! | L95: =表1温室气体盘查表!#REF! -> #REF! | M95: =表1温室气体盘查表!#REF! -> #REF!
B96: 3.3.7 | C96: =表1温室气体盘查表!C70 -> 烟煤生产 | D96: =表1温室气体盘查表!D70 -> 高炉 | F96: =表1温室气体盘查表!AM70 -> 57829.149 | G96: =表1温室气体盘查表!AF70 -> 57829.149 | H96: =表1温室气体盘查表!AG70 -> 0 | I96: =表1温室气体盘查表!AH70 -> 0 | J96: =表1温室气体盘查表!AI70 -> 0 | K96: =表1温室气体盘查表!AJ70 -> 0 | L96: =表1温室气体盘查表!AK70 -> 0 | M96: =表1温室气体盘查表!AL70 -> 0
B97: 3.3.8 | C97: =表1温室气体盘查表!C71 -> 无烟煤生产 | D97: =表1温室气体盘查表!D71 -> 烧结、高炉 | F97: =表1温室气体盘查表!AM71 -> 229469.91 | G97: =表1温室气体盘查表!AF71 -> 229469.91 | H97: =表1温室气体盘查表!AG71 -> 0 | I97: =表1温室气体盘查表!AH71 -> 0 | J97: =表1温室气体盘查表!AI71 -> 0 | K97: =表1温室气体盘查表!AJ71 -> 0 | L97: =表1温室气体盘查表!AK71 -> 0 | M97: =表1温室气体盘查表!AL71 -> 0
B98: 3.3.9 | C98: =表1温室气体盘查表!C72 -> 天然气生产 | D98: =表1温室气体盘查表!D72 -> 转炉、电炉、锻造、热处理 | F98: =表1温室气体盘查表!AM72 -> 9000.26 | G98: =表1温室气体盘查表!AF72 -> 9000.26 | H98: =表1温室气体盘查表!AG72 -> 0 | I98: =表1温室气体盘查表!AH72 -> 0 | J98: =表1温室气体盘查表!AI72 -> 0 | K98: =表1温室气体盘查表!AJ72 -> 0 | L98: =表1温室气体盘查表!AK72 -> 0 | M98: =表1温室气体盘查表!AL72 -> 0
B99: 3.3.10 | C99: =表1温室气体盘查表!C73 -> 外购电力上游排放 | D99: =表1温室气体盘查表!D73 -> 各工序 | F99: =表1温室气体盘查表!AM73 -> 176819.89 | G99: =表1温室气体盘查表!AF73 -> 176819.89 | H99: =表1温室气体盘查表!AG73 -> 0 | I99: =表1温室气体盘查表!AH73 -> 0 | J99: =表1温室气体盘查表!AI73 -> 0 | K99: =表1温室气体盘查表!AJ73 -> 0 | L99: =表1温室气体盘查表!AK73 -> 0 | M99: =表1温室气体盘查表!AL73 -> 0
B101: 范围三 类别4 | C101: =表1温室气体盘查表!B74 -> 上游运输配送产生的排放 | F101: =SUM(G101:M101) -> 400727.03 | G101: =SUM(G102:G104) -> 400727.03 | H101: =SUM(H102:H104) -> 0 | I101: =SUM(I102:I104) -> 0 | J101: =SUM(J102:J104) -> 0 | K101: =SUM(K102:K104) -> 0 | L101: =SUM(L102:L104) -> 0 | M101: =SUM(M102:M104) -> 0
B102: 3.4.1 | C102: =表1温室气体盘查表!C74 -> 船运 | D102: =表1温室气体盘查表!D74 -> - | F102: =表1温室气体盘查表!AM74 -> 250587.64 | G102: =表1温室气体盘查表!AF74 -> 250587.64 | H102: =表1温室气体盘查表!AG74 -> 0 | I102: =表1温室气体盘查表!AH74 -> 0 | J102: =表1温室气体盘查表!AI74 -> 0 | K102: =表1温室气体盘查表!AJ74 -> 0 | L102: =表1温室气体盘查表!AK74 -> 0 | M102: =表1温室气体盘查表!AL74 -> 0
B103: 3.4.2 | C103: =表1温室气体盘查表!C75 -> 汽运 | D103: =表1温室气体盘查表!D75 -> - | F103: =表1温室气体盘查表!AM75 -> 74635.121 | G103: =表1温室气体盘查表!AF75 -> 74635.121 | H103: =表1温室气体盘查表!AG75 -> 0 | I103: =表1温室气体盘查表!AH75 -> 0 | J103: =表1温室气体盘查表!AI75 -> 0 | K103: =表1温室气体盘查表!AJ75 -> 0 | L103: =表1温室气体盘查表!AK75 -> 0 | M103: =表1温室气体盘查表!AL75 -> 0
B104: 3.4.3 | C104: =表1温室气体盘查表!C76 -> 铁路运输 | D104: =表1温室气体盘查表!D76 -> - | F104: =表1温室气体盘查表!AM76 -> 75504.264 | G104: =表1温室气体盘查表!AF76 -> 75504.264 | H104: =表1温室气体盘查表!AG76 -> 0 | I104: =表1温室气体盘查表!AH76 -> 0 | J104: =表1温室气体盘查表!AI76 -> 0 | K104: =表1温室气体盘查表!AJ76 -> 0 | L104: =表1温室气体盘查表!AK76 -> 0 | M104: =表1温室气体盘查表!AL76 -> 0
...

Sheet 修改日志&问题
C2: 修改日志 | D2: 问题
B3: 2026.3.17 | C3: 完成了表1温室气体盘查表数据填写并比对两年数据
B4: 2026.3.18 | C4: 更新了“附表2-EF”，并同步更新了其他表格 | D4: 部分排放因子需和核查老师确认是否需要更新

Sheet 基本信息
A1: 变量名 | B1: 变量名 | C1: 值
A2: 公司名称 | B2: company_name | C2: 大冶特殊钢有限公司
A3: 报告周期 | B3: reporting_period | C3: 2025年1月1日至2025年12月31日
A4: 报告编号 | B4: document_number | C4: DY-GHG-2026-01
A5: 生成日期 | B5: posted_time | C5: 46206
A6: 统一社会信用代码 | B6: Unified_Social_Credit_Identifier | C6: 91420000798750168P
A7: 法人代表 | B7: legal_person | C7: 蒋乔
A8: 注册资金 | B8: registered_capital | C8: 207218.53万元
A9: 注册日期 | B9: date_of_establishment | C9: 39150
A10: 注册地址 | B10: registered_address | C10: 湖北省黄石市黄石大道316号
A11: 生产地址 | B11: production_address | C11: 湖北省黄石市黄石大道316号
A12: 经营范围 | B12: scope_of_business | C12: 大冶特殊钢有限公司成立于2007年03月09日，注册地位于湖北省黄石市黄石大道316号，法定代表人为蒋乔。经营范围包括黑色、有色金属冶炼、压延加工；生产、销售高温合金材料、耐蚀合金材料、铁矿石、钢坯、钢锭、钢材、金属制品、钢管及管件和相应的工业辅助材料及承接来料加工业务；钢铁和合金材料检测；再生资源回收经营；货物或技术进出口（国家限定公司经营或禁止进出口的商品和技术除外）；机械零件、汽车零部件制造和加工；机械、仪表、电器制造和修理；化工产品（不含危险品和限制类产品）制造；港口码头建设及经营；煤气、热力、自来水、工业用水生产和供应；餐饮经营与管理。（涉及许可经营项目，应取得相关部门许可后方可经营）。
A13: 公司简介 | B13: company_profile | C13: 大冶特殊钢有限公司（简称：大冶特钢）是中国近代“钢铁摇篮”，地处中国矿冶之都、先进制造业基地湖北省黄石市。隶属中信泰富特钢集团，是其沿海沿江产业链的战略布局中的重要一环。 大冶特钢是国家高新技术企业、全国首批两化融合示范企业、全国首批绿色制造示范企业、全国绿化模范单位。拥有国家认定企业技术中心、院士专家工作站、博士后科研工作站、高品质特殊钢湖北省重点实验室，先后承担国家多项冶金课题的项目攻关，主持或参与起草修订了多项国家和行业技术标准。先后荣获“全国质量奖”、“全国质量标杆”、“中国工业大奖表彰奖”，多项产品荣获国家冶金产品实物质量“金杯奖”、“国家科学技术进步一等奖、二等奖”、“冶金科学技术奖一等奖”、“国家知识产权优势企业”、“中国航天突出贡献供应商”、“中国工模具行业最具影响力钢厂品牌”等奖项。 大冶特钢是中国品种规格最齐全的高品质棒材、高端中厚壁无缝钢管、高合金锻材三大特钢生产基地，工艺技术和装备具备世界先进水平。主要产品有轴承钢、汽车用钢、能源用钢、工程机械用钢、航空航天用钢等。主要服务于航天航空、海洋、核电、风电、交通、火电、油气、工程机械、重燃、船舶、石化、汽车、高铁等关键领域。 从中国第一炉电渣钢到第一根极薄壁高温合金旋压管，从第一个飞机用高温合金涡轮盘，到第一根轧制的飞机大梁(毛坯)，从中国第一颗人造地球卫星，到神舟系列飞船的上天，到“嫦娥”奔月，再到“天宫”“北斗”发射升空，大冶特钢均提供了关键部件的用钢。工程机械用无缝钢管已连续13年产销量全国第一、13年全球第一，石油工具及装备用中厚壁无缝钢管连续10年产销量全国第一，大口径厚壁高压锅炉用管连续5年产销量全国第一。 大冶特钢秉承“诚信、创新、融合、卓越”的理念，牢记为客户创造价值，为员工创造幸福，为股东创造效益，为社会创造财富的企业使命，致力于为客户提供多规格、多品种、高品质的特殊钢产品及整体服务方案，致力于“创建全球最具竞争力的特钢企业集团”。
A14: DDL | B14: deadline | C14: 2026年6月底前
A15: 规则文件 | B15: rule_file | C15: 《大冶特殊钢温室气体盘查控制程序（DY-GHG-2023）》
A16: GWP值来源文件 | B16: GWP_Value_Reference_Document | C16: IPCC 2021年出具的《第六次评估报告AR6》
B17: source_file | C17: 《温室气体盘查清册》-表2 不确定性评估
A18: 制作 | B18: producer | C18: 杨春英
A19: 审核 | B19: auditor
A20: 核准 | B20: approver
A21: 报告年 | B21: report_year | C21: 2025
A22: 下一年 | B22: next_year | C22: =C21+1 -> 2026

Sheet 温室气体盘查清册
B1: 温室气体盘查清册 | L1: 编号：DY-GHG-2025-01
L2: 版本/版次：A/1
L3: 日期：2026/7/3
B4: 组织名称： | C4: 大冶特殊钢有限公司
B5: 组织边界： | C5: 湖北省黄石市黄石大道316号
B6: 盘查覆盖周期: | C6: 2025年1月1日至2025年12月31日
B7: 编制 ： | E7: 审核： | K7: 核准：
B8: 报告边界 | C8: 运营控制权 | E8: 范围一排放量： | F8: =F14 -> 7174685 | K8: 单位：tCO2e
E9: 范围二（基于位置）排放量： | F9: =F45 -> 1043611.1
E10: 范围二（基于市场）排放量： | F10: =F46 -> 1186800.3
B11: 排放 | E11: 范围三排放量： | F11: =SUM(F48,F74,F85,F96,F101,F107,F112,F119,F125,F134,F131) -> 7161889.5
B12: 编号 | C12: 排放源 | D12: 排放设施 | E12: 备注 | F12: 总排放量 | G12: CO2 | H12: CH4 | I12: N2O | J12: HFCs | K12: PFCs | L12: SF6 | M12: NF3
G13: tCO2e
B14: 范围一 直接排放 | F14: =F15+F23+F26+F31 -> 7174685 | G14: =G15+G23+G26+G31 -> 7131923.6 | H14: =H15+H23+H26+H31 -> 10685.974 | I14: =I15+I23+I26+I31 -> 31504.844 | J14: =J15+J23+J26+J31 -> 570.54 | K14: =K15+K23+K26+K31 -> 0 | L14: =L15+L23+L26+L31 -> 0 | M14: =M15+M23+M26+M31 -> 0
B15: 1.1 | C15: 固定源燃烧直接排放 | F15: =SUM(G15:M15) -> 7454918.9 | G15: =SUM(G16:G22) -> 7421328.8 | H15: =SUM(H16:H22) -> 2152.9426 | I15: =SUM(I16:I22) -> 31437.166 | J15: =SUM(J16:J22) -> 0 | K15: =SUM(K16:K22) -> 0 | L15: =SUM(L16:L22) -> 0 | M15: =SUM(M16:M22) -> 0
B16: 1.1.1 | C16: =表1温室气体盘查表!C5 -> 天然气燃烧 | D16: =表1温室气体盘查表!D5 -> 热处理炉（加热炉） | F16: =SUM(G16:M16) -> 31469.159 | G16: =表1温室气体盘查表!AF5 -> 31438.225 | H16: =表1温室气体盘查表!AG5 -> 15.635053 | I16: =表1温室气体盘查表!AH5 -> 15.298816 | J16: =表1温室气体盘查表!AI5 -> 0 | K16: =表1温室气体盘查表!AJ5 -> 0 | L16: =表1温室气体盘查表!AK5 -> 0 | M16: =表1温室气体盘查表!AL5 -> 0
B17: 1.1.2 | C17: =表1温室气体盘查表!C6 -> 液化石油气燃烧 | D17: =表1温室气体盘查表!D6 -> 冶钢宾馆 | F17: =SUM(G17:M17) -> 29.286595 | G17: =表1温室气体盘查表!AF6 -> 29.260998 | H17: =表1温室气体盘查表!AG6 -> 0.012937905 | I17: =表1温室气体盘查表!AH6 -> 0.012659671 | J17: =表1温室气体盘查表!AI6 -> 0 | K17: =表1温室气体盘查表!AJ6 -> 0 | L17: =表1温室气体盘查表!AK6 -> 0 | M17: =表1温室气体盘查表!AL6 -> 0
B18: 1.1.3 | C18: =表1温室气体盘查表!C7 -> 烟煤燃烧 | D18: =表1温室气体盘查表!D7 -> 高炉 | F18: =SUM(G18:M18) -> 749580.33 | G18: =表1温室气体盘查表!AF7 -> 746259.74 | H18: =表1温室气体盘查表!AG7 -> 211.80719 | I18: =表1温室气体盘查表!AH7 -> 3108.783 | J18: =表1温室气体盘查表!AI7 -> 0 | K18: =表1温室气体盘查表!AJ7 -> 0 | L18: =表1温室气体盘查表!AK7 -> 0 | M18: =表1温室气体盘查表!AL7 -> 0
B19: 1.1.4 | C19: =表1温室气体盘查表!C8 -> 无烟煤燃烧 | D19: =表1温室气体盘查表!D8 -> 高炉、烧结 | F19: =SUM(G19:M19) -> 820622.2 | G19: =表1温室气体盘查表!AF8 -> 816986.9 | H19: =表1温室气体盘查表!AG8 -> 231.88133 | I19: =表1温室气体盘查表!AH8 -> 3403.4195 | J19: =表1温室气体盘查表!AI8 -> 0 | K19: =表1温室气体盘查表!AJ8 -> 0 | L19: =表1温室气体盘查表!AK8 -> 0 | M19: =表1温室气体盘查表!AL8 -> 0
B20: 1.1.5 | C20: =表1温室气体盘查表!C9 -> 洗精煤燃烧 | D20: =表1温室气体盘查表!D9 -> 焦炉 | F20: =SUM(G20:M20) -> 5189313.3 | G20: =表1温室气体盘查表!AF9 -> 5165430 | H20: =表1温室气体盘查表!AG9 -> 1523.4196 | I20: =表1温室气体盘查表!AH9 -> 22359.869 | J20: =表1温室气体盘查表!AI9 -> 0 | K20: =表1温室气体盘查表!AJ9 -> 0 | L20: =表1温室气体盘查表!AK9 -> 0 | M20: =表1温室气体盘查表!AL9 -> 0
B21: 1.1.6 | C21: =表1温室气体盘查表!C10 -> 焦炭燃烧 | D21: =表1温室气体盘查表!D10 -> 高炉 | F21: =SUM(G21:M21) -> 669939.56 | G21: =表1温室气体盘查表!AF10 -> 667212.1 | H21: =表1温室气体盘查表!AG10 -> 173.974 | I21: =表1温室气体盘查表!AH10 -> 2553.4893 | J21: =表1温室气体盘查表!AI10 -> 0 | K21: =表1温室气体盘查表!AJ10 -> 0 | L21: =表1温室气体盘查表!AK10 -> 0 | M21: =表1温室气体盘查表!AL10 -> 0
B22: 1.1.7 | C22: =表1温室气体盘查表!C11 -> 焦炉煤气燃烧 | D22: =表1温室气体盘查表!D11 -> 外售 | F22: =SUM(G22:M22) -> -6034.9102 | G22: =表1温室气体盘查表!AF11 -> -6027.4166 | H22: =表1温室气体盘查表!AG11 -> -3.7874983 | I22: =表1温室气体盘查表!AH11 -> -3.7060467 | J22: =表1温室气体盘查表!AI11 -> 0 | K22: =表1温室气体盘查表!AJ11 -> 0 | L22: =表1温室气体盘查表!AK11 -> 0 | M22: =表1温室气体盘查表!AL11 -> 0
B23: 1.2 | C23: 移动源燃烧直接排放 | F23: =SUM(G23:M23) -> 4620.5168 | G23: =SUM(G24:G25) -> 4544.9741 | H23: =SUM(H24:H25) -> 7.8643134 | I23: =SUM(I24:I25) -> 67.678446 | J23: =SUM(J24:J25) -> 0 | K23: =SUM(K24:K25) -> 0 | L23: =SUM(L24:L25) -> 0 | M23: =SUM(M24:M25) -> 0
B24: 1.2.1 | C24: =表1温室气体盘查表!C12 -> 柴油燃烧 | D24: =表1温室气体盘查表!D12 -> 场内运输 | F24: =SUM(G24:M24) -> 4476.287 | G24: =表1温室气体盘查表!AF12 -> 4406.5019 | H24: =表1温室气体盘查表!AG12 -> 6.4706002 | I24: =表1温室气体盘查表!AH12 -> 63.314475 | J24: =表1温室气体盘查表!AI12 -> 0 | K24: =表1温室气体盘查表!AJ12 -> 0 | L24: =表1温室气体盘查表!AK12 -> 0 | M24: =表1温室气体盘查表!AL12 -> 0
B25: 1.2.2 | C25: =表1温室气体盘查表!C13 -> 汽油燃烧 | D25: =表1温室气体盘查表!D13 -> 公务车 | F25: =SUM(G25:M25) -> 144.22983 | G25: =表1温室气体盘查表!AF13 -> 138.47215 | H25: =表1温室气体盘查表!AG13 -> 1.3937132 | I25: =表1温室气体盘查表!AH13 -> 4.3639708 | J25: =表1温室气体盘查表!AI13 -> 0 | K25: =表1温室气体盘查表!AJ13 -> 0 | L25: =表1温室气体盘查表!AK13 -> 0 | M25: =表1温室气体盘查表!AL13 -> 0
B26: 1.3 | C26: 逸散源直接排放 | F26: =SUM(G26:M26) -> 9096.2672 | G26: =SUM(G27:G30) -> 0.56 | H26: =SUM(H27:H30) -> 8525.1672 | I26: =SUM(I27:I30) -> 0 | J26: =SUM(J27:J30) -> 570.54 | K26: =SUM(K27:K30) -> 0 | L26: =SUM(L27:L30) -> 0 | M26: =SUM(M27:M30) -> 0
B27: 1.3.1 | C27: =表1温室气体盘查表!C14 -> 制冷剂逸散（R32） | D27: =表1温室气体盘查表!D14 -> 分体式空调 | F27: =SUM(G27:M27) -> 570.54 | G27: =表1温室气体盘查表!AF14 -> 0 | H27: =表1温室气体盘查表!AG14 -> 0 | I27: =表1温室气体盘查表!AH14 -> 0 | J27: =表1温室气体盘查表!AI14 -> 570.54 | K27: =表1温室气体盘查表!AJ14 -> 0 | L27: =表1温室气体盘查表!AK14 -> 0 | M27: =表1温室气体盘查表!AL14 -> 0
B28: 1.3.2 | C28: =表1温室气体盘查表!C15 -> CO2逸散 | D28: =表1温室气体盘查表!D15 -> 二氧化碳灭火器 | F28: =SUM(G28:M28) -> 0.56 | G28: =表1温室气体盘查表!AF15 -> 0.56 | H28: =表1温室气体盘查表!AG15 -> 0 | I28: =表1温室气体盘查表!AH15 -> 0 | J28: =表1温室气体盘查表!AI15 -> 0 | K28: =表1温室气体盘查表!AJ15 -> 0 | L28: =表1温室气体盘查表!AK15 -> 0 | M28: =表1温室气体盘查表!AL15 -> 0
B29: 1.3.3 | C29: =表1温室气体盘查表!C16 -> CH4逸散 | D29: =表1温室气体盘查表!D16 -> 化粪池 | F29: =SUM(G29:M29) -> 116.30952 | G29: =表1温室气体盘查表!AF16 -> 0 | H29: =表1温室气体盘查表!AG16 -> 116.30952 | I29: =表1温室气体盘查表!AH16 -> 0 | J29: =表1温室气体盘查表!AI16 -> 0 | K29: =表1温室气体盘查表!AJ16 -> 0 | L29: =表1温室气体盘查表!AK16 -> 0 | M29: =表1温室气体盘查表!AL16 -> 0
B30: 1.3.4 | C30: =表1温室气体盘查表!C17 -> CH4逸散 | D30: =表1温室气体盘查表!D17 -> 耗氧池 | F30: =SUM(G30:M30) -> 8408.8577 | G30: =表1温室气体盘查表!AF17 -> 0 | H30: =表1温室气体盘查表!AG17 -> 8408.8577 | I30: =表1温室气体盘查表!AH17 -> 0 | J30: =表1温室气体盘查表!AI17 -> 0 | K30: =表1温室气体盘查表!AJ17 -> 0 | L30: =表1温室气体盘查表!AK17 -> 0 | M30: =表1温室气体盘查表!AL17 -> 0
B31: 1.4 | C31: 制程排放 | F31: =SUM(G31:M31) -> -293950.76 | G31: =SUM(G32:G43) -> -293950.76 | H31: =SUM(H32:H43) -> 0 | I31: =SUM(I32:I43) -> 0 | J31: =SUM(J32:J43) -> 0 | K31: =SUM(K32:K43) -> 0 | L31: =SUM(L32:L43) -> 0 | M31: =SUM(M32:M43) -> 0
B32: 1.4.1 | C32: =表1温室气体盘查表!C18 -> 白云石 | D32: =表1温室气体盘查表!D18 -> 高炉 | F32: =SUM(G32:M32) -> 18406.658 | G32: =表1温室气体盘查表!AF18 -> 18406.658 | H32: =表1温室气体盘查表!AG18 -> 0 | I32: =表1温室气体盘查表!AH18 -> 0 | J32: =表1温室气体盘查表!AI18 -> 0 | K32: =表1温室气体盘查表!AJ18 -> 0 | L32: =表1温室气体盘查表!AK18 -> 0 | M32: =表1温室气体盘查表!AL18 -> 0
B33: 1.4.2 | C33: =表1温室气体盘查表!C19 -> 电极 | D33: =表1温室气体盘查表!D19 -> 炼钢 | F33: =SUM(G33:M33) -> 18334.963 | G33: =表1温室气体盘查表!AF19 -> 18334.963 | H33: =表1温室气体盘查表!AG19 -> 0 | I33: =表1温室气体盘查表!AH19 -> 0 | J33: =表1温室气体盘查表!AI19 -> 0 | K33: =表1温室气体盘查表!AJ19 -> 0 | L33: =表1温室气体盘查表!AK19 -> 0 | M33: =表1温室气体盘查表!AL19 -> 0
B34: 1.4.3 | C34: =表1温室气体盘查表!C20 -> 废钢 | D34: =表1温室气体盘查表!D20 -> 炼钢 | F34: =SUM(G34:M34) -> 41425.779 | G34: =表1温室气体盘查表!AF20 -> 41425.779 | H34: =表1温室气体盘查表!AG20 -> 0 | I34: =表1温室气体盘查表!AH20 -> 0 | J34: =表1温室气体盘查表!AI20 -> 0 | K34: =表1温室气体盘查表!AJ20 -> 0 | L34: =表1温室气体盘查表!AK20 -> 0 | M34: =表1温室气体盘查表!AL20 -> 0
B35: 1.4.4 | C35: =表1温室气体盘查表!C21 -> 高碳锰铁 | D35: =表1温室气体盘查表!D21 -> 炼钢 | F35: =SUM(G35:M35) -> 11407.872 | G35: =表1温室气体盘查表!AF21 -> 11407.872 | H35: =表1温室气体盘查表!AG21 -> 0 | I35: =表1温室气体盘查表!AH21 -> 0 | J35: =表1温室气体盘查表!AI21 -> 0 | K35: =表1温室气体盘查表!AJ21 -> 0 | L35: =表1温室气体盘查表!AK21 -> 0 | M35: =表1温室气体盘查表!AL21 -> 0
B36: 1.4.5 | C36: =表1温室气体盘查表!C22 -> 锰硅合金 | D36: =表1温室气体盘查表!D22 -> 炼钢 | F36: =SUM(G36:M36) -> 265.66748 | G36: =表1温室气体盘查表!AF22 -> 265.66748 | H36: =表1温室气体盘查表!AG22 -> 0 | I36: =表1温室气体盘查表!AH22 -> 0 | J36: =表1温室气体盘查表!AI22 -> 0 | K36: =表1温室气体盘查表!AJ22 -> 0 | L36: =表1温室气体盘查表!AK22 -> 0 | M36: =表1温室气体盘查表!AL22 -> 0
B37: 1.4.6 | C37: =表1温室气体盘查表!C23 -> 镍铁 | D37: =表1温室气体盘查表!D23 -> 炼钢 | F37: =SUM(G37:M37) -> 367.8984 | G37: =表1温室气体盘查表!AF23 -> 367.8984 | H37: =表1温室气体盘查表!AG23 -> 0 | I37: =表1温室气体盘查表!AH23 -> 0 | J37: =表1温室气体盘查表!AI23 -> 0 | K37: =表1温室气体盘查表!AJ23 -> 0 | L37: =表1温室气体盘查表!AK23 -> 0 | M37: =表1温室气体盘查表!AL23 -> 0
B38: 1.4.7 | C38: =表1温室气体盘查表!C24 -> 高碳铬铁 | D38: =表1温室气体盘查表!D24 -> 炼钢 | F38: =SUM(G38:M38) -> 13992.429 | G38: =表1温室气体盘查表!AF24 -> 13992.429 | H38: =表1温室气体盘查表!AG24 -> 0 | I38: =表1温室气体盘查表!AH24 -> 0 | J38: =表1温室气体盘查表!AI24 -> 0 | K38: =表1温室气体盘查表!AJ24 -> 0 | L38: =表1温室气体盘查表!AK24 -> 0 | M38: =表1温室气体盘查表!AL24 -> 0
B39: 1.4.8 | C39: =表1温室气体盘查表!C25 -> 硅铁 | D39: =表1温室气体盘查表!D25 -> 炼钢 | F39: =SUM(G39:M39) -> 82.65656 | G39: =表1温室气体盘查表!AF25 -> 82.65656 | H39: =表1温室气体盘查表!AG25 -> 0 | I39: =表1温室气体盘查表!AH25 -> 0 | J39: =表1温室气体盘查表!AI25 -> 0 | K39: =表1温室气体盘查表!AJ25 -> 0 | L39: =表1温室气体盘查表!AK25 -> 0 | M39: =表1温室气体盘查表!AL25 -> 0
B40: 1.4.9 | C40: =表1温室气体盘查表!C26 -> 钼铁 | D40: =表1温室气体盘查表!D26 -> 炼钢 | F40: =SUM(G40:M40) -> 130.83696 | G40: =表1温室气体盘查表!AF26 -> 130.83696 | H40: =表1温室气体盘查表!AG26 -> 0 | I40: =表1温室气体盘查表!AH26 -> 0 | J40: =表1温室气体盘查表!AI26 -> 0 | K40: =表1温室气体盘查表!AJ26 -> 0 | L40: =表1温室气体盘查表!AK26 -> 0 | M40: =表1温室气体盘查表!AL26 -> 0
B41: 1.4.10 | C41: =表1温室气体盘查表!C27 -> 粗钢 | D41: =表1温室气体盘查表!D27 -> 固碳产品 | F41: =SUM(G41:M41) -> -165928.08 | G41: =表1温室气体盘查表!AF27 -> -165928.08 | H41: =表1温室气体盘查表!AG27 -> 0 | I41: =表1温室气体盘查表!AH27 -> 0 | J41: =表1温室气体盘查表!AI27 -> 0 | K41: =表1温室气体盘查表!AJ27 -> 0 | L41: =表1温室气体盘查表!AK27 -> 0 | M41: =表1温室气体盘查表!AL27 -> 0
B42: 1.4.11 | C42: =表1温室气体盘查表!C28 -> 粗苯 | D42: =表1温室气体盘查表!D28 -> 外售 | F42: =SUM(G42:M42) -> -68970.885 | G42: =表1温室气体盘查表!AF28 -> -68970.885 | H42: =表1温室气体盘查表!AG28 -> 0 | I42: =表1温室气体盘查表!AH28 -> 0 | J42: =表1温室气体盘查表!AI28 -> 0 | K42: =表1温室气体盘查表!AJ28 -> 0 | L42: =表1温室气体盘查表!AK28 -> 0 | M42: =表1温室气体盘查表!AL28 -> 0
B43: 1.4.12 | C43: =表1温室气体盘查表!C29 -> 焦油 | D43: =表1温室气体盘查表!D29 -> 危废处置 | F43: =SUM(G43:M43) -> -163466.55 | G43: =表1温室气体盘查表!AF29 -> -163466.55 | H43: =表1温室气体盘查表!AG29 -> 0 | I43: =表1温室气体盘查表!AH29 -> 0 | J43: =表1温室气体盘查表!AI29 -> 0 | K43: =表1温室气体盘查表!AJ29 -> 0 | L43: =表1温室气体盘查表!AK29 -> 0 | M43: =表1温室气体盘查表!AL29 -> 0
B44: 范围二 外购电间接排放
B45: 2.1 | C45: =表1温室气体盘查表!C30 -> 外购电力（基于位置） | D45: =表1温室气体盘查表!D30 -> 用电设备 | F45: =SUM(G45:M45) -> 1043611.1 | G45: =表1温室气体盘查表!AF30 -> 1043611.1 | H45: =表1温室气体盘查表!AG30 -> 0 | I45: =表1温室气体盘查表!AH30 -> 0 | J45: =表1温室气体盘查表!AI30 -> 0 | K45: =表1温室气体盘查表!AJ30 -> 0 | L45: =表1温室气体盘查表!AK30 -> 0 | M45: =表1温室气体盘查表!AL30 -> 0
B46: 2.2 | C46: =表1温室气体盘查表!C31 -> 外购电力（基于市场） | D46: =表1温室气体盘查表!D31 -> 用电设备 | F46: =SUM(G46:M46) -> 1186800.3 | G46: =表1温室气体盘查表!AF31 -> 1186800.3 | H46: =表1温室气体盘查表!AG31 -> 0 | I46: =表1温室气体盘查表!AH31 -> 0 | J46: =表1温室气体盘查表!AI31 -> 0 | K46: =表1温室气体盘查表!AJ31 -> 0 | L46: =表1温室气体盘查表!AK31 -> 0 | M46: =表1温室气体盘查表!AL31 -> 0
B48: 范围三 类别1 | C48: 外购商品和服务的上游排放 | F48: =SUM(G48:M48) -> 2179317.5 | G48: =SUM(G49:G72) -> 2179317.5 | H48: =SUM(H49:H65) -> 0 | I48: =SUM(I49:I65) -> 0 | J48: =SUM(J49:J65) -> 0 | K48: =SUM(K49:K65) -> 0 | L48: =SUM(L49:L65) -> 0 | M48: =SUM(M49:M65) -> 0
B49: 3.1.1 | C49: =表1温室气体盘查表!C32 -> 铁矿石生产 | D49: =表1温室气体盘查表!D32 -> 烧结 | F49: =表1温室气体盘查表!AM32 -> 479835.37 | G49: =表1温室气体盘查表!AF32 -> 479835.37 | H49: =表1温室气体盘查表!AG32 -> 0 | I49: =表1温室气体盘查表!AH32 -> 0 | J49: =表1温室气体盘查表!AI32 -> 0 | K49: =表1温室气体盘查表!AJ32 -> 0 | L49: =表1温室气体盘查表!AK32 -> 0 | M49: =表1温室气体盘查表!AL32 -> 0
B50: 3.1.2 | C50: =表1温室气体盘查表!C33 -> 生石灰生产 | D50: =表1温室气体盘查表!D33 -> 烧结、转炉、电炉 | F50: =表1温室气体盘查表!AM33 -> 236961.26 | G50: =表1温室气体盘查表!AF33 -> 236961.26 | H50: =表1温室气体盘查表!AG33 -> 0 | I50: =表1温室气体盘查表!AH33 -> 0 | J50: =表1温室气体盘查表!AI33 -> 0 | K50: =表1温室气体盘查表!AJ33 -> 0 | L50: =表1温室气体盘查表!AK33 -> 0 | M50: =表1温室气体盘查表!AL33 -> 0
B51: 3.1.3 | C51: =表1温室气体盘查表!C34 -> 白云石生产 | D51: =表1温室气体盘查表!D34 -> 烧结、转炉、电炉 | F51: =表1温室气体盘查表!AM34 -> 5039.7894 | G51: =表1温室气体盘查表!AF34 -> 5039.7894 | H51: =表1温室气体盘查表!AG34 -> 0 | I51: =表1温室气体盘查表!AH34 -> 0 | J51: =表1温室气体盘查表!AI34 -> 0 | K51: =表1温室气体盘查表!AJ34 -> 0 | L51: =表1温室气体盘查表!AK34 -> 0 | M51: =表1温室气体盘查表!AL34 -> 0
B52: 3.1.4 | C52: =表1温室气体盘查表!C35 -> 球团生产 | D52: =表1温室气体盘查表!D36 -> 转炉、电炉 | F52: =表1温室气体盘查表!AM35 -> 71241.082 | G52: =表1温室气体盘查表!AF35 -> 71241.082 | H52: =表1温室气体盘查表!AG35 -> 0 | I52: =表1温室气体盘查表!AH35 -> 0 | J52: =表1温室气体盘查表!AI35 -> 0 | K52: =表1温室气体盘查表!AJ35 -> 0 | L52: =表1温室气体盘查表!AK35 -> 0 | M52: =表1温室气体盘查表!AL35 -> 0
B53: 3.1.5 | C53: =表1温室气体盘查表!C36 -> 废钢生产 | D53: =表1温室气体盘查表!D37 -> 转炉、电炉 | F53: =表1温室气体盘查表!AM36 -> 83051.97 | G53: =表1温室气体盘查表!AF36 -> 83051.97 | H53: =表1温室气体盘查表!AG36 -> 0 | I53: =表1温室气体盘查表!AH36 -> 0 | J53: =表1温室气体盘查表!AI36 -> 0 | K53: =表1温室气体盘查表!AJ36 -> 0 | L53: =表1温室气体盘查表!AK36 -> 0 | M53: =表1温室气体盘查表!AL36 -> 0
B54: 3.1.6 | C54: =表1温室气体盘查表!C37 -> 电极生产 | D54: =表1温室气体盘查表!D38 -> 转炉、电炉 | F54: =表1温室气体盘查表!AM37 -> 60962.024 | G54: =表1温室气体盘查表!AF37 -> 60962.024 | H54: =表1温室气体盘查表!AG37 -> 0 | I54: =表1温室气体盘查表!AH37 -> 0 | J54: =表1温室气体盘查表!AI37 -> 0 | K54: =表1温室气体盘查表!AJ37 -> 0 | L54: =表1温室气体盘查表!AK37 -> 0 | M54: =表1温室气体盘查表!AL37 -> 0
B55: 3.1.7 | C55: =表1温室气体盘查表!C38 -> 锰铁生产 | D55: =表1温室气体盘查表!D39 -> 转炉、电炉 | F55: =表1温室气体盘查表!AM38 -> 123503.69 | G55: =表1温室气体盘查表!AF38 -> 123503.69 | H55: =表1温室气体盘查表!AG38 -> 0 | I55: =表1温室气体盘查表!AH38 -> 0 | J55: =表1温室气体盘查表!AI38 -> 0 | K55: =表1温室气体盘查表!AJ38 -> 0 | L55: =表1温室气体盘查表!AK38 -> 0 | M55: =表1温室气体盘查表!AL38 -> 0
B56: 3.1.8 | C56: =表1温室气体盘查表!C39 -> 镍铁生产 | D56: =表1温室气体盘查表!D40 -> 转炉、电炉 | F56: =表1温室气体盘查表!AM39 -> 87049.733 | G56: =表1温室气体盘查表!AF39 -> 87049.733 | H56: =表1温室气体盘查表!AG39 -> 0 | I56: =表1温室气体盘查表!AH39 -> 0 | J56: =表1温室气体盘查表!AI39 -> 0 | K56: =表1温室气体盘查表!AJ39 -> 0 | L56: =表1温室气体盘查表!AK39 -> 0 | M56: =表1温室气体盘查表!AL39 -> 0
B57: 3.1.9 | C57: =表1温室气体盘查表!C40 -> 铬铁生产 | D57: =表1温室气体盘查表!D41 -> 转炉、电炉 | F57: =表1温室气体盘查表!AM40 -> 204743.82 | G57: =表1温室气体盘查表!AF40 -> 204743.82 | H57: =表1温室气体盘查表!AG40 -> 0 | I57: =表1温室气体盘查表!AH40 -> 0 | J57: =表1温室气体盘查表!AI40 -> 0 | K57: =表1温室气体盘查表!AJ40 -> 0 | L57: =表1温室气体盘查表!AK40 -> 0 | M57: =表1温室气体盘查表!AL40 -> 0
B58: 3.1.10 | C58: =表1温室气体盘查表!C41 -> 萤石生产 | D58: =表1温室气体盘查表!D42 -> 转炉、电炉 | F58: =表1温室气体盘查表!AM41 -> 88473.44 | G58: =表1温室气体盘查表!AF41 -> 88473.44 | H58: =表1温室气体盘查表!AG41 -> 0 | I58: =表1温室气体盘查表!AH41 -> 0 | J58: =表1温室气体盘查表!AI41 -> 0 | K58: =表1温室气体盘查表!AJ41 -> 0 | L58: =表1温室气体盘查表!AK41 -> 0 | M58: =表1温室气体盘查表!AL41 -> 0
B59: 3.1.11 | C59: =表1温室气体盘查表!C42 -> 硅铁生产 | D59: =表1温室气体盘查表!D43 -> 转炉、电炉 | F59: =表1温室气体盘查表!AM42 -> 149088.59 | G59: =表1温室气体盘查表!AF42 -> 149088.59 | H59: =表1温室气体盘查表!AG42 -> 0 | I59: =表1温室气体盘查表!AH42 -> 0 | J59: =表1温室气体盘查表!AI42 -> 0 | K59: =表1温室气体盘查表!AJ42 -> 0 | L59: =表1温室气体盘查表!AK42 -> 0 | M59: =表1温室气体盘查表!AL42 -> 0
B60: 3.1.12 | C60: =表1温室气体盘查表!C43 -> 钼铁生产 | D60: =表1温室气体盘查表!D44 -> 转炉、电炉 | F60: =表1温室气体盘查表!AM43 -> 58876.632 | G60: =表1温室气体盘查表!AF43 -> 58876.632 | H60: =表1温室气体盘查表!AG43 -> 0 | I60: =表1温室气体盘查表!AH43 -> 0 | J60: =表1温室气体盘查表!AI43 -> 0 | K60: =表1温室气体盘查表!AJ43 -> 0 | L60: =表1温室气体盘查表!AK43 -> 0 | M60: =表1温室气体盘查表!AL43 -> 0
B61: 3.1.13 | C61: =表1温室气体盘查表!C44 -> 铝铁生产 | D61: =表1温室气体盘查表!D45 -> 转炉、电炉 | F61: =表1温室气体盘查表!AM44 -> 13585.605 | G61: =表1温室气体盘查表!AF44 -> 13585.605 | H61: =表1温室气体盘查表!AG44 -> 0 | I61: =表1温室气体盘查表!AH44 -> 0 | J61: =表1温室气体盘查表!AI44 -> 0 | K61: =表1温室气体盘查表!AJ44 -> 0 | L61: =表1温室气体盘查表!AK44 -> 0 | M61: =表1温室气体盘查表!AL44 -> 0
B62: 3.1.14 | C62: =表1温室气体盘查表!C45 -> 铝生产 | D62: =表1温室气体盘查表!D46 -> 转炉、电炉 | F62: =表1温室气体盘查表!AM45 -> 165810.57 | G62: =表1温室气体盘查表!AF45 -> 165810.57 | H62: =表1温室气体盘查表!AG45 -> 0 | I62: =表1温室气体盘查表!AH45 -> 0 | J62: =表1温室气体盘查表!AI45 -> 0 | K62: =表1温室气体盘查表!AJ45 -> 0 | L62: =表1温室气体盘查表!AK45 -> 0 | M62: =表1温室气体盘查表!AL45 -> 0
B63: 3.1.15 | C63: =表1温室气体盘查表!C46 -> 增碳剂生产 | D63: =表1温室气体盘查表!D46 -> 转炉、电炉 | F63: =表1温室气体盘查表!AM46 -> 14447.768 | G63: =表1温室气体盘查表!AF46 -> 14447.768 | H63: =表1温室气体盘查表!AG46 -> 0 | I63: =表1温室气体盘查表!AH46 -> 0 | J63: =表1温室气体盘查表!AI46 -> 0 | K63: =表1温室气体盘查表!AJ46 -> 0 | L63: =表1温室气体盘查表!AK46 -> 0 | M63: =表1温室气体盘查表!AL46 -> 0
B64: 3.1.16 | C64: =表1温室气体盘查表!C47 -> 铁鳞生产 | D64: =表1温室气体盘查表!D47 -> 炼钢 | F64: =表1温室气体盘查表!AM47 -> 29.192524 | G64: =表1温室气体盘查表!AF47 -> 29.192524 | H64: =表1温室气体盘查表!AG47 -> 0 | I64: =表1温室气体盘查表!AH47 -> 0 | J64: =表1温室气体盘查表!AI47 -> 0 | K64: =表1温室气体盘查表!AJ47 -> 0 | L64: =表1温室气体盘查表!AK47 -> 0 | M64: =表1温室气体盘查表!AL47 -> 0
B65: 3.1.17 | C65: =表1温室气体盘查表!C48 -> 氨水生产 | D65: =表1温室气体盘查表!D48 -> 烧结 | F65: =表1温室气体盘查表!AM48 -> 26510.816 | G65: =表1温室气体盘查表!AF48 -> 26510.816 | H65: =表1温室气体盘查表!AG48 -> 0 | I65: =表1温室气体盘查表!AH48 -> 0 | J65: =表1温室气体盘查表!AI48 -> 0 | K65: =表1温室气体盘查表!AJ48 -> 0 | L65: =表1温室气体盘查表!AK48 -> 0 | M65: =表1温室气体盘查表!AL48 -> 0
B66: 3.1.18 | C66: =表1温室气体盘查表!C49 -> 盐酸生产 | D66: =表1温室气体盘查表!D49 -> 焦化 | F66: =表1温室气体盘查表!AM49 -> 2.1173455 | G66: =表1温室气体盘查表!AF49 -> 2.1173455 | H66: =表1温室气体盘查表!AG49 -> 0 | I66: =表1温室气体盘查表!AH49 -> 0 | J66: =表1温室气体盘查表!AI49 -> 0 | K66: =表1温室气体盘查表!AJ49 -> 0 | L66: =表1温室气体盘查表!AK49 -> 0 | M66: =表1温室气体盘查表!AL49 -> 0
B67: 3.1.19 | C67: =表1温室气体盘查表!C50 -> 氢氧化钠生产 | D67: =表1温室气体盘查表!D50 -> 焦化 | F67: =表1温室气体盘查表!AM50 -> 3.2806275 | G67: =表1温室气体盘查表!AF50 -> 3.2806275 | H67: =表1温室气体盘查表!AG50 -> 0 | I67: =表1温室气体盘查表!AH50 -> 0 | J67: =表1温室气体盘查表!AI50 -> 0 | K67: =表1温室气体盘查表!AJ50 -> 0 | L67: =表1温室气体盘查表!AK50 -> 0 | M67: =表1温室气体盘查表!AL50 -> 0
B68: 3.1.20 | C68: =表1温室气体盘查表!C51 -> 碳化硅生产 | D68: =表1温室气体盘查表!D51 -> - | F68: =表1温室气体盘查表!AM51 -> 26760.682 | G68: =表1温室气体盘查表!AF51 -> 26760.682 | H68: =表1温室气体盘查表!AG51 -> 0 | I68: =表1温室气体盘查表!AH51 -> 0 | J68: =表1温室气体盘查表!AI51 -> 0 | K68: =表1温室气体盘查表!AJ51 -> 0 | L68: =表1温室气体盘查表!AK51 -> 0 | M68: =表1温室气体盘查表!AL51 -> 0
B69: 3.1.21 | C69: =表1温室气体盘查表!C52 -> 镁生产 | D69: =表1温室气体盘查表!D52 -> - | F69: =表1温室气体盘查表!AM52 -> 256865.11 | G69: =表1温室气体盘查表!AF52 -> 256865.11 | H69: =表1温室气体盘查表!AG52 -> 0 | I69: =表1温室气体盘查表!AH52 -> 0 | J69: =表1温室气体盘查表!AI52 -> 0 | K69: =表1温室气体盘查表!AJ52 -> 0 | L69: =表1温室气体盘查表!AK52 -> 0 | M69: =表1温室气体盘查表!AL52 -> 0
B70: 3.1.22 | C70: =表1温室气体盘查表!C53 -> 所有其他纸制品加工制造 | D70: =表1温室气体盘查表!D53 -> 办公室 | F70: =表1温室气体盘查表!AM53 -> 5.2434719 | G70: =表1温室气体盘查表!AF53 -> 5.2434719 | H70: =表1温室气体盘查表!AG53 -> 0 | I70: =表1温室气体盘查表!AH53 -> 0 | J70: =表1温室气体盘查表!AI53 -> 0 | K70: =表1温室气体盘查表!AJ53 -> 0 | L70: =表1温室气体盘查表!AK53 -> 0 | M70: =表1温室气体盘查表!AL53 -> 0
B71: 3.1.23 | C71: =表1温室气体盘查表!C54 -> 办公用品(纸张除外)制造 | D71: =表1温室气体盘查表!D54 -> 办公室 | F71: =表1温室气体盘查表!AM54 -> 72.312583 | G71: =表1温室气体盘查表!AF54 -> 72.312583 | H71: =表1温室气体盘查表!AG54 -> 0 | I71: =表1温室气体盘查表!AH54 -> 0 | J71: =表1温室气体盘查表!AI54 -> 0 | K71: =表1温室气体盘查表!AJ54 -> 0 | L71: =表1温室气体盘查表!AK54 -> 0 | M71: =表1温室气体盘查表!AL54 -> 0
B72: 3.1.24 | C72: =表1温室气体盘查表!C55 -> 源水 | D72: =表1温室气体盘查表!D55 -> 水处理工序 | F72: =表1温室气体盘查表!AM55 -> 26397.412 | G72: =表1温室气体盘查表!AF55 -> 26397.412 | H72: =表1温室气体盘查表!AG55 -> 0 | I72: =表1温室气体盘查表!AH55 -> 0 | J72: =表1温室气体盘查表!AI55 -> 0 | K72: =表1温室气体盘查表!AJ55 -> 0 | L72: =表1温室气体盘查表!AK55 -> 0 | M72: =表1温室气体盘查表!AL55 -> 0
B74: 范围三 类别2 | C74: =表1温室气体盘查表!B56 -> 资本货物 | F74: =SUM(G74:M74) -> 46877.219 | G74: =SUM(G75:G83) -> 46877.219 | H74: =SUM(H75:H83) -> 0 | I74: =SUM(I75:I83) -> 0 | J74: =SUM(J75:J83) -> 0 | K74: =SUM(K75:K83) -> 0 | L74: =SUM(L75:L83) -> 0 | M74: =SUM(M75:M83) -> 0
B75: 3.2.1 | C75: =表1温室气体盘查表!C56 -> 采购产品空调和暖空气加热设备和商业和工业制冷设备制造 | D75: =表1温室气体盘查表!D56 -> 办公室、各工序 | F75: =表1温室气体盘查表!AM56 -> 120.11822 | G75: =表1温室气体盘查表!AF56 -> 120.11822 | H75: =表1温室气体盘查表!AG56 -> 0 | I75: =表1温室气体盘查表!AH56 -> 0 | J75: =表1温室气体盘查表!AI56 -> 0 | K75: =表1温室气体盘查表!AJ56 -> 0 | L75: =表1温室气体盘查表!AK56 -> 0 | M75: =表1温室气体盘查表!AL56 -> 0
B76: 3.2.2 | C76: =表1温室气体盘查表!C57 -> 电子计算机制造 | D76: =表1温室气体盘查表!D57 -> 办公室、各工序 | F76: =表1温室气体盘查表!AM57 -> 25.839091 | G76: =表1温室气体盘查表!AF57 -> 25.839091 | H76: =表1温室气体盘查表!AG57 -> 0 | I76: =表1温室气体盘查表!AH57 -> 0 | J76: =表1温室气体盘查表!AI57 -> 0 | K76: =表1温室气体盘查表!AJ57 -> 0 | L76: =表1温室气体盘查表!AK57 -> 0 | M76: =表1温室气体盘查表!AL57 -> 0
B77: 3.2.3 | C77: =表1温室气体盘查表!C58 -> 其他工业设备制造 | D77: =表1温室气体盘查表!D58 -> 各工序 | F77: =表1温室气体盘查表!AM58 -> 518.69925 | G77: =表1温室气体盘查表!AF58 -> 518.69925 | H77: =表1温室气体盘查表!AG58 -> 0 | I77: =表1温室气体盘查表!AH58 -> 0 | J77: =表1温室气体盘查表!AI58 -> 0 | K77: =表1温室气体盘查表!AJ58 -> 0 | L77: =表1温室气体盘查表!AK58 -> 0 | M77: =表1温室气体盘查表!AL58 -> 0
B78: 3.2.4 | C78: =表1温室气体盘查表!C59 -> 测量和测试电力和电气信号的仪器制造 | D78: =表1温室气体盘查表!D59 -> 各工序 | F78: =表1温室气体盘查表!AM59 -> 220.30499 | G78: =表1温室气体盘查表!AF59 -> 220.30499 | H78: =表1温室气体盘查表!AG59 -> 0 | I78: =表1温室气体盘查表!AH59 -> 0 | J78: =表1温室气体盘查表!AI59 -> 0 | K78: =表1温室气体盘查表!AJ59 -> 0 | L78: =表1温室气体盘查表!AK59 -> 0 | M78: =表1温室气体盘查表!AL59 -> 0
B79: 3.2.5 | C79: =表1温室气体盘查表!C60 -> 机械动力传动设备制造 | D79: =表1温室气体盘查表!D60 -> 各工序 | F79: =表1温室气体盘查表!AM60 -> 1122.1195 | G79: =表1温室气体盘查表!AF60 -> 1122.1195 | H79: =表1温室气体盘查表!AG60 -> 0 | I79: =表1温室气体盘查表!AH60 -> 0 | J79: =表1温室气体盘查表!AI60 -> 0 | K79: =表1温室气体盘查表!AJ60 -> 0 | L79: =表1温室气体盘查表!AK60 -> 0 | M79: =表1温室气体盘查表!AL60 -> 0
B80: 3.2.6 | C80: =表1温室气体盘查表!C61 -> 测量、分配及其他泵类设备制造 | D80: =表1温室气体盘查表!D61 -> 各工序 | F80: =表1温室气体盘查表!AM61 -> 604.1994 | G80: =表1温室气体盘查表!AF61 -> 604.1994 | H80: =表1温室气体盘查表!AG61 -> 0 | I80: =表1温室气体盘查表!AH61 -> 0 | J80: =表1温室气体盘查表!AI61 -> 0 | K80: =表1温室气体盘查表!AJ61 -> 0 | L80: =表1温室气体盘查表!AK61 -> 0 | M80: =表1温室气体盘查表!AL61 -> 0
B81: 3.2.7 | C81: =表1温室气体盘查表!C62 -> 用于测量、显示和控制工业过程变量的仪器及相关产品制造 | D81: =表1温室气体盘查表!D62 -> 各工序 | F81: =表1温室气体盘查表!AM62 -> 140.41627 | G81: =表1温室气体盘查表!AF62 -> 140.41627 | H81: =表1温室气体盘查表!AG62 -> 0 | I81: =表1温室气体盘查表!AH62 -> 0 | J81: =表1温室气体盘查表!AI62 -> 0 | K81: =表1温室气体盘查表!AJ62 -> 0 | L81: =表1温室气体盘查表!AK62 -> 0 | M81: =表1温室气体盘查表!AL62 -> 0
B82: 3.2.8 | C82: =表1温室气体盘查表!C63 -> 所有其他杂项电气设备及元件制造 | D82: =表1温室气体盘查表!D63 -> 各工序 | F82: =表1温室气体盘查表!AM63 -> 1091.3267 | G82: =表1温室气体盘查表!AF63 -> 1091.3267 | H82: =表1温室气体盘查表!AG63 -> 0 | I82: =表1温室气体盘查表!AH63 -> 0 | J82: =表1温室气体盘查表!AI63 -> 0 | K82: =表1温室气体盘查表!AJ63 -> 0 | L82: =表1温室气体盘查表!AK63 -> 0 | M82: =表1温室气体盘查表!AL63 -> 0
B83: 3.2.9 | C83: =表1温室气体盘查表!C64 -> 所有其他杂项制造 | D83: =表1温室气体盘查表!D64 -> 各工序 | F83: =表1温室气体盘查表!AM64 -> 43034.196 | G83: =表1温室气体盘查表!AF64 -> 43034.196 | H83: =表1温室气体盘查表!AG64 -> 0 | I83: =表1温室气体盘查表!AH64 -> 0 | J83: =表1温室气体盘查表!AI64 -> 0 | K83: =表1温室气体盘查表!AJ64 -> 0 | L83: =表1温室气体盘查表!AK64 -> 0 | M83: =表1温室气体盘查表!AL64 -> 0
B85: 范围三 类别3 | C85: =表1温室气体盘查表!B66 -> 范围一、二相关燃料和能源相关的活动产生的排放 | F85: =SUM(G85:M85) -> 1756664.8 | G85: =SUM(G86:G94) -> 1756664.8 | H85: =SUM(H87:H93) -> 0 | I85: =SUM(I87:I93) -> 0 | J85: =SUM(J87:J93) -> 0 | K85: =SUM(K87:K93) -> 0 | L85: =SUM(L87:L93) -> 0 | M85: =SUM(M87:M93) -> 0
B86: 3.3.1 | C86: =表1温室气体盘查表!C65 -> 液化石油气生产 | D86: =表1温室气体盘查表!D65 -> 冶钢宾馆 | F86: =表1温室气体盘查表!AM65 -> 9.4887071 | G86: =表1温室气体盘查表!AF65 -> 9.4887071 | H86: =表1温室气体盘查表!AG65 -> 0 | I86: =表1温室气体盘查表!AH65 -> 0 | J86: =表1温室气体盘查表!AI65 -> 0 | K86: =表1温室气体盘查表!AJ65 -> 0 | L86: =表1温室气体盘查表!AK65 -> 0 | M86: =表1温室气体盘查表!AL65 -> 0
B87: 3.3.2 | C87: =表1温室气体盘查表!C66 -> 洗精煤生产 | D87: =表1温室气体盘查表!D66 -> 焦化 | F87: =表1温室气体盘查表!AM66 -> 1204984.6 | G87: =表1温室气体盘查表!AF66 -> 1204984.6 | H87: =表1温室气体盘查表!AG66 -> 0 | I87: =表1温室气体盘查表!AH66 -> 0 | J87: =表1温室气体盘查表!AI66 -> 0 | K87: =表1温室气体盘查表!AJ66 -> 0 | L87: =表1温室气体盘查表!AK66 -> 0 | M87: =表1温室气体盘查表!AL66 -> 0
B88: 3.3.3 | C88: =表1温室气体盘查表!C67 -> 柴油生产 | D88: =表1温室气体盘查表!D67 -> 各工序 | F88: =表1温室气体盘查表!AM67 -> 1198.0757 | G88: =表1温室气体盘查表!AF67 -> 1198.0757 | H88: =表1温室气体盘查表!AG67 -> 0 | I88: =表1温室气体盘查表!AH67 -> 0 | J88: =表1温室气体盘查表!AI67 -> 0 | K88: =表1温室气体盘查表!AJ67 -> 0 | L88: =表1温室气体盘查表!AK67 -> 0 | M88: =表1温室气体盘查表!AL67 -> 0
B89: 3.3.4 | C89: =表1温室气体盘查表!C68 -> 汽油生产 | D89: =表1温室气体盘查表!D68 -> 车队 | F89: =表1温室气体盘查表!AM68 -> 46.740217 | G89: =表1温室气体盘查表!AF68 -> 46.740217 | H89: =表1温室气体盘查表!AG68 -> 0 | I89: =表1温室气体盘查表!AH68 -> 0 | J89: =表1温室气体盘查表!AI68 -> 0 | K89: =表1温室气体盘查表!AJ68 -> 0 | L89: =表1温室气体盘查表!AK68 -> 0 | M89: =表1温室气体盘查表!AL68 -> 0
B90: 3.3.5 | C90: =表1温室气体盘查表!C69 -> 焦炭生产 | D90: =表1温室气体盘查表!D69 -> 烧结、高炉 | F90: =表1温室气体盘查表!AM69 -> 77306.7 | G90: =表1温室气体盘查表!AF69 -> 77306.7 | H90: =表1温室气体盘查表!AG69 -> 0 | I90: =表1温室气体盘查表!AH69 -> 0 | J90: =表1温室气体盘查表!AI69 -> 0 | K90: =表1温室气体盘查表!AJ69 -> 0 | L90: =表1温室气体盘查表!AK69 -> 0 | M90: =表1温室气体盘查表!AL69 -> 0
B91: 3.3.6 | C91: =表1温室气体盘查表!C70 -> 烟煤生产 | D91: =表1温室气体盘查表!D70 -> 高炉 | F91: =表1温室气体盘查表!AM70 -> 57829.149 | G91: =表1温室气体盘查表!AF70 -> 57829.149 | H91: =表1温室气体盘查表!AG70 -> 0 | I91: =表1温室气体盘查表!AH70 -> 0 | J91: =表1温室气体盘查表!AI70 -> 0 | K91: =表1温室气体盘查表!AJ70 -> 0 | L91: =表1温室气体盘查表!AK70 -> 0 | M91: =表1温室气体盘查表!AL70 -> 0
B92: 3.3.7 | C92: =表1温室气体盘查表!C71 -> 无烟煤生产 | D92: =表1温室气体盘查表!D71 -> 烧结、高炉 | F92: =表1温室气体盘查表!AM71 -> 229469.91 | G92: =表1温室气体盘查表!AF71 -> 229469.91 | H92: =表1温室气体盘查表!AG71 -> 0 | I92: =表1温室气体盘查表!AH71 -> 0 | J92: =表1温室气体盘查表!AI71 -> 0 | K92: =表1温室气体盘查表!AJ71 -> 0 | L92: =表1温室气体盘查表!AK71 -> 0 | M92: =表1温室气体盘查表!AL71 -> 0
B93: 3.3.8 | C93: =表1温室气体盘查表!C72 -> 天然气生产 | D93: =表1温室气体盘查表!D72 -> 转炉、电炉、锻造、热处理 | F93: =表1温室气体盘查表!AM72 -> 9000.26 | G93: =表1温室气体盘查表!AF72 -> 9000.26 | H93: =表1温室气体盘查表!AG72 -> 0 | I93: =表1温室气体盘查表!AH72 -> 0 | J93: =表1温室气体盘查表!AI72 -> 0 | K93: =表1温室气体盘查表!AJ72 -> 0 | L93: =表1温室气体盘查表!AK72 -> 0 | M93: =表1温室气体盘查表!AL72 -> 0
B94: 3.3.9 | C94: =表1温室气体盘查表!C73 -> 外购电力上游排放 | D94: =表1温室气体盘查表!D73 -> 各工序 | F94: =表1温室气体盘查表!AM73 -> 176819.89 | G94: =表1温室气体盘查表!AF73 -> 176819.89 | H94: =表1温室气体盘查表!AG73 -> 0 | I94: =表1温室气体盘查表!AH73 -> 0 | J94: =表1温室气体盘查表!AI73 -> 0 | K94: =表1温室气体盘查表!AJ73 -> 0 | L94: =表1温室气体盘查表!AK73 -> 0 | M94: =表1温室气体盘查表!AL73 -> 0
B96: 范围三 类别4 | C96: =表1温室气体盘查表!B74 -> 上游运输配送产生的排放 | F96: =SUM(G96:M96) -> 400727.03 | G96: =SUM(G97:G99) -> 400727.03 | H96: =SUM(H97:H99) -> 0 | I96: =SUM(I97:I99) -> 0 | J96: =SUM(J97:J99) -> 0 | K96: =SUM(K97:K99) -> 0 | L96: =SUM(L97:L99) -> 0 | M96: =SUM(M97:M99) -> 0
B97: 3.4.1 | C97: =表1温室气体盘查表!C74 -> 船运 | D97: =表1温室气体盘查表!D74 -> - | F97: =表1温室气体盘查表!AM74 -> 250587.64 | G97: =表1温室气体盘查表!AF74 -> 250587.64 | H97: =表1温室气体盘查表!AG74 -> 0 | I97: =表1温室气体盘查表!AH74 -> 0 | J97: =表1温室气体盘查表!AI74 -> 0 | K97: =表1温室气体盘查表!AJ74 -> 0 | L97: =表1温室气体盘查表!AK74 -> 0 | M97: =表1温室气体盘查表!AL74 -> 0
B98: 3.4.2 | C98: =表1温室气体盘查表!C75 -> 汽运 | D98: =表1温室气体盘查表!D75 -> - | F98: =表1温室气体盘查表!AM75 -> 74635.121 | G98: =表1温室气体盘查表!AF75 -> 74635.121 | H98: =表1温室气体盘查表!AG75 -> 0 | I98: =表1温室气体盘查表!AH75 -> 0 | J98: =表1温室气体盘查表!AI75 -> 0 | K98: =表1温室气体盘查表!AJ75 -> 0 | L98: =表1温室气体盘查表!AK75 -> 0 | M98: =表1温室气体盘查表!AL75 -> 0
B99: 3.4.3 | C99: =表1温室气体盘查表!C76 -> 铁路运输 | D99: =表1温室气体盘查表!D76 -> - | F99: =表1温室气体盘查表!AM76 -> 75504.264 | G99: =表1温室气体盘查表!AF76 -> 75504.264 | H99: =表1温室气体盘查表!AG76 -> 0 | I99: =表1温室气体盘查表!AH76 -> 0 | J99: =表1温室气体盘查表!AI76 -> 0 | K99: =表1温室气体盘查表!AJ76 -> 0 | L99: =表1温室气体盘查表!AK76 -> 0 | M99: =表1温室气体盘查表!AL76 -> 0
B101: 范围三 类别5 | C101: =表1温室气体盘查表!B77 -> 运营中产生的废物排放 | F101: =SUM(G101:M101) -> 30952.018 | G101: =SUM(G102:G105) -> 30952.018 | H101: =SUM(H102) -> 0 | I101: =SUM(I102) -> 0 | J101: =SUM(J102) -> 0 | K101: =SUM(K102) -> 0 | L101: =SUM(L102) -> 0 | M101: =SUM(M102) -> 0
B102: 3.5.1 | C102: =表1温室气体盘查表!C77 -> 生活垃圾和厨余垃圾 | D102: =表1温室气体盘查表!D77 -> 垃圾站 | F102: =表1温室气体盘查表!AM77 -> 1040.2559 | G102: =表1温室气体盘查表!AF77 -> 1040.2559 | H102: =表1温室气体盘查表!AG77 -> 0 | I102: =表1温室气体盘查表!AH77 -> 0 | J102: =表1温室气体盘查表!AI77 -> 0 | K102: =表1温室气体盘查表!AJ77 -> 0 | L102: =表1温室气体盘查表!AK77 -> 0 | M102: =表1温室气体盘查表!AL77 -> 0
B103: 3.5.2 | C103: =表1温室气体盘查表!C78 -> 废油 | D103: =表1温室气体盘查表!D78 -> - | F103: =表1温室气体盘查表!AM78 -> 4897.6715 | G103: =表1温室气体盘查表!AF78 -> 4897.6715 | H103: =表1温室气体盘查表!AG78 -> 0 | I103: =表1温室气体盘查表!AH78 -> 0 | J103: =表1温室气体盘查表!AI78 -> 0 | K103: =表1温室气体盘查表!AJ78 -> 0 | L103: =表1温室气体盘查表!AK78 -> 0 | M103: =表1温室气体盘查表!AL78 -> 0
B104: 3.5.3 | C104: =表1温室气体盘查表!C79 -> 废油水 | D104: =表1温室气体盘查表!D79 -> - | F104: =表1温室气体盘查表!AM79 -> 14824.498 | G104: =表1温室气体盘查表!AF79 -> 14824.498 | H104: =表1温室气体盘查表!AG79 -> 0 | I104: =表1温室气体盘查表!AH79 -> 0 | J104: =表1温室气体盘查表!AI79 -> 0 | K104: =表1温室气体盘查表!AJ79 -> 0 | L104: =表1温室气体盘查表!AK79 -> 0 | M104: =表1温室气体盘查表!AL79 -> 0
B105: 3.5.4 | C105: =表1温室气体盘查表!C80 -> 废弃物运输 | D105: =表1温室气体盘查表!D80 -> - | F105: =表1温室气体盘查表!AM80 -> 10189.593 | G105: =表1温室气体盘查表!AF80 -> 10189.593 | H105: =表1温室气体盘查表!AG80 -> 0 | I105: =表1温室气体盘查表!AH80 -> 0 | J105: =表1温室气体盘查表!AI80 -> 0 | K105: =表1温室气体盘查表!AJ80 -> 0 | L105: =表1温室气体盘查表!AK80 -> 0 | M105: =表1温室气体盘查表!AL80 -> 0
...

Sheet 表1温室气体盘查表
A1: 温室气体盘查表
A2: 编号 | B2: GHG排放类别 | C2: 排放源 | D2: 设施 | E2: 报告边界 | F2: 活动数据 | I2: 排放因子&系数 | AF2: 排放量
I3: CO2 | L3: CH4 | O3: N2O | R3: HFCs | V3: PFCs | Z3: SF6 | AC3: NF3 | AF3: CO2 | AG3: CH4 | AH3: N2O | AI3: HFCs | AJ3: PFCs | AK3: SF6 | AL3: NF3 | AM3: 总量
F4: 数值 | G4: 计量单位 | H4: 数据来源 | I4: EF | J4: 计量单位 | K4: GWP | L4: EF | M4: 计量单位 | N4: GWP | O4: EF | P4: 计量单位 | Q4: GWP | R4: EF | S4: 计量单位 | T4: GWP | U4: 型号 | V4: EF | W4: 计量单位 | X4: GWP | Y4: 型号 | Z4: EF | AA4: 计量单位 | AB4: GWP | AC4: EF | AD4: 计量单位 | AE4: GWP | AF4: tCO2e | AO4: 2024 | AP4: 变化量
A5: 1 | B5: 固定燃烧 | C5: 天然气燃烧 | D5: 热处理炉（加热炉） | E5: 范围一 | F5: =ROUND(1454.003,2) -> 1454 | G5: 10000Nm3 | H5: 《天然气发票》 | I5: =SUMIF('附表2-EF'!$D$5:$D$15,表1温室气体盘查表!C5,'附表2-EF'!$L$5:$L$15) -> 21.621888 | J5: tCO2/10000Nm3 | K5: ='附表1-GWP TABLE'!E3 -> 1 | L5: =SUMIF('附表2-EF'!$D$5:$D$15,表1温室气体盘查表!C5,'附表2-EF'!$M$5:$M$15) -> 0.0003854169 | N5: ='附表1-GWP TABLE'!E4 -> 27.9 | O5: =SUMIF('附表2-EF'!$D$5:$D$15,表1温室气体盘查表!C5,'附表2-EF'!$N$5:$N$15) -> 3.854169e-05 | Q5: ='附表1-GWP TABLE'!E5 -> 273 | AF5: =F5*I5*K5 -> 31438.225 | AG5: =F5*L5*N5 -> 15.635053 | AH5: =F5*O5*Q5 -> 15.298816 | AI5: =F5*R5*T5 -> 0 | AJ5: =F5*V5*X5 -> 0 | AK5: =F5*Z5*AB5 -> 0 | AL5: =F5*AC5*AE5 -> 0 | AM5: =SUM(AF5:AL5) -> 31469.159 | AN5: 天然气燃烧 | AO5: 38881.726 | AP5: =AM5-AO5 -> -7412.5669
A6: 2 | B6: 固定燃烧 | C6: 液化石油气燃烧 | D6: 冶钢宾馆 | E6: 范围一 | F6: =ROUND(9.4345,2) -> 9.43 | G6: t | H6: 《2025全年液化气明细表》 | I6: =SUMIF('附表2-EF'!$D$5:$D$15,表1温室气体盘查表!C6,'附表2-EF'!$L$5:$L$15) -> 3.102969 | J6: tCO2/t | K6: 1 | L6: =SUMIF('附表2-EF'!$D$5:$D$15,表1温室气体盘查表!C6,'附表2-EF'!$M$5:$M$15) -> 4.917542e-05 | N6: ='附表1-GWP TABLE'!E4 -> 27.9 | O6: =SUMIF('附表2-EF'!$D$5:$D$15,表1温室气体盘查表!C6,'附表2-EF'!$N$5:$N$15) -> 4.917542e-06 | Q6: ='附表1-GWP TABLE'!E5 -> 273 | AF6: =F6*I6*K6 -> 29.260998 | AG6: =F6*L6*N6 -> 0.012937905 | AH6: =F6*O6*Q6 -> 0.012659671 | AI6: =F6*R6*T6 -> 0 | AJ6: =F6*V6*X6 -> 0 | AK6: =F6*Z6*AB6 -> 0 | AL6: =F6*AC6*AE6 -> 0 | AM6: =SUM(AF6:AL6) -> 29.286595 | AN6: 液化石油气燃烧 | AO6: 29.162368 | AP6: =AM6-AO6 -> 0.12422734
A7: 3 | B7: 固定燃烧 | C7: 烟煤燃烧 | D7: 高炉 | E7: 范围一 | F7: 323067.87 | G7: t | H7: 《冶钢2025年度碳排放报表》（来源为过磅单） | I7: =SUMIF('附表2-EF'!$D$5:$D$15,表1温室气体盘查表!C7,'附表2-EF'!$L$5:$L$15) -> 2.3099163 | J7: tCO2/t | K7: ='附表1-GWP TABLE'!E3 -> 1 | L7: =SUMIF('附表2-EF'!$D$5:$D$15,表1温室气体盘查表!C7,'附表2-EF'!$M$5:$M$15) -> 2.349864e-05 | N7: ='附表1-GWP TABLE'!E4 -> 27.9 | O7: =SUMIF('附表2-EF'!$D$5:$D$15,表1温室气体盘查表!C7,'附表2-EF'!$N$5:$N$15) -> 3.524796e-05 | Q7: ='附表1-GWP TABLE'!E5 -> 273 | AF7: =F7*I7*K7 -> 746259.74 | AG7: =F7*L7*N7 -> 211.80719 | AH7: =F7*O7*Q7 -> 3108.783 | AI7: =F7*R7*T7 -> 0 | AJ7: =F7*V7*X7 -> 0 | AK7: =F7*Z7*AB7 -> 0 | AL7: =F7*AC7*AE7 -> 0 | AM7: =SUM(AF7:AL7) -> 749580.33 | AN7: 烟煤燃烧 | AO7: 925941.32 | AP7: =AM7-AO7 -> -176360.99
A8: 4 | B8: 固定燃烧 | C8: 无烟煤燃烧 | D8: 高炉、烧结 | E8: 范围一 | F8: 335482.33 | G8: t | H8: 《冶钢2025年度碳排放报表》（来源为过磅单） | I8: =SUMIF('附表2-EF'!$D$5:$D$15,表1温室气体盘查表!C8,'附表2-EF'!$L$5:$L$15) -> 2.4352606 | J8: tCO2/t | K8: ='附表1-GWP TABLE'!E3 -> 1 | L8: =SUMIF('附表2-EF'!$D$5:$D$15,表1温室气体盘查表!C8,'附表2-EF'!$M$5:$M$15) -> 2.477376e-05 | N8: ='附表1-GWP TABLE'!E4 -> 27.9 | O8: =SUMIF('附表2-EF'!$D$5:$D$15,表1温室气体盘查表!C8,'附表2-EF'!$N$5:$N$15) -> 3.716064e-05 | Q8: ='附表1-GWP TABLE'!E5 -> 273 | AF8: =F8*I8*K8 -> 816986.9 | AG8: =F8*L8*N8 -> 231.88133 | AH8: =F8*O8*Q8 -> 3403.4195 | AI8: =F8*R8*T8 -> 0 | AJ8: =F8*V8*X8 -> 0 | AK8: =F8*Z8*AB8 -> 0 | AL8: =F8*AC8*AE8 -> 0 | AM8: =SUM(AF8:AL8) -> 820622.2 | AN8: 无烟煤燃烧 | AO8: 637282.39 | AP8: =AM8-AO8 -> 183339.81
A9: 5 | B9: 固定燃烧 | C9: 洗精煤燃烧 | D9: 焦炉 | E9: 范围一 | F9: 2093622.8 | G9: t | H9: 《冶钢2025年度碳排放报表》（来源为过磅单） | I9: =SUMIF('附表2-EF'!$D$5:$D$15,表1温室气体盘查表!C9,'附表2-EF'!$L$5:$L$15) -> 2.467221 | J9: tCO2/t | K9: ='附表1-GWP TABLE'!E3 -> 1 | L9: =SUMIF('附表2-EF'!$D$5:$D$15,表1温室气体盘查表!C9,'附表2-EF'!$M$5:$M$15) -> 2.608056e-05 | N9: ='附表1-GWP TABLE'!E4 -> 27.9 | O9: =SUMIF('附表2-EF'!$D$5:$D$15,表1温室气体盘查表!C9,'附表2-EF'!$N$5:$N$15) -> 3.912084e-05 | Q9: ='附表1-GWP TABLE'!E5 -> 273 | AF9: =F9*I9*K9 -> 5165430 | AG9: =F9*L9*N9 -> 1523.4196 | AH9: =F9*O9*Q9 -> 22359.869 | AI9: =F9*R9*T9 -> 0 | AJ9: =F9*V9*X9 -> 0 | AK9: =F9*Z9*AB9 -> 0 | AL9: =F9*AC9*AE9 -> 0 | AM9: =SUM(AF9:AL9) -> 5189313.3 | AN9: 洗精煤燃烧 | AO9: 4824841.6 | AP9: =AM9-AO9 -> 364471.73
A10: 6 | B10: 固定燃烧 | C10: 焦炭燃烧 | D10: 高炉 | E10: 范围一 | F10: 221509.17 | G10: t | H10: 《冶钢2025年度碳排放报表》（来源为过磅单） | I10: =SUMIF('附表2-EF'!$D$5:$D$15,表1温室气体盘查表!C10,'附表2-EF'!$L$5:$L$15) -> 3.0121195 | J10: tCO2/t | K10: ='附表1-GWP TABLE'!E3 -> 1 | L10: =SUMIF('附表2-EF'!$D$5:$D$15,表1温室气体盘查表!C10,'附表2-EF'!$M$5:$M$15) -> 2.815065e-05 | N10: ='附表1-GWP TABLE'!E4 -> 27.9 | O10: =SUMIF('附表2-EF'!$D$5:$D$15,表1温室气体盘查表!C10,'附表2-EF'!$N$5:$N$15) -> 4.2225975e-05 | Q10: ='附表1-GWP TABLE'!E5 -> 273 | AF10: =F10*I10*K10 -> 667212.1 | AG10: =F10*L10*N10 -> 173.974 | AH10: =F10*O10*Q10 -> 2553.4893 | AI10: =F10*R10*T10 -> 0 | AJ10: =F10*V10*X10 -> 0 | AK10: =F10*Z10*AB10 -> 0 | AL10: =F10*AC10*AE10 -> 0 | AM10: =SUM(AF10:AL10) -> 669939.56 | AN10: 焦炭燃烧 | AO10: 439843.84 | AP10: =AM10-AO10 -> 230095.72
A11: 7 | B11: 固定燃烧 | C11: 焦炉煤气燃烧 | D11: 外售 | E11: 范围一 | F11: =ROUND(-7887272.44/10000,2) -> -788.73 | G11: 10000Nm3 | H11: 焦炉煤气外供结算单 | I11: =SUMIF('附表2-EF'!$D$5:$D$15,表1温室气体盘查表!C11,'附表2-EF'!$L$5:$L$15) -> 7.6419264 | J11: tCO2/10000Nm3 | K11: 1 | L11: =SUMIF('附表2-EF'!$D$5:$D$15,表1温室气体盘查表!C11,'附表2-EF'!$M$5:$M$15) -> 0.00017211546 | N11: ='附表1-GWP TABLE'!E4 -> 27.9 | O11: =SUMIF('附表2-EF'!$D$5:$D$15,表1温室气体盘查表!C11,'附表2-EF'!$N$5:$N$15) -> 1.7211546e-05 | Q11: ='附表1-GWP TABLE'!E5 -> 273 | AF11: =F11*I11*K11 -> -6027.4166 | AG11: =F11*L11*N11 -> -3.7874983 | AH11: =F11*O11*Q11 -> -3.7060467 | AI11: =F11*R11*T11 -> 0 | AJ11: =F11*V11*X11 -> 0 | AK11: =F11*Z11*AB11 -> 0 | AL11: =F11*AC11*AE11 -> 0 | AM11: =SUM(AF11:AL11) -> -6034.9102 | AN11: 焦炉煤气燃烧 | AO11: -3833.1355 | AP11: =AM11-AO11 -> -2201.7747
A12: 8 | B12: 移动燃烧 | C12: 柴油燃烧 | D12: 场内运输 | E12: 范围一 | F12: =ROUND(1422.693,2) -> 1422.69 | G12: t | H12: 《收发存汇总表-发出量》 | I12: =SUMIF('附表2-EF'!$D$5:$D$15,表1温室气体盘查表!C12,'附表2-EF'!$L$5:$L$15) -> 3.0973029 | J12: tCO2/t | K12: 1 | L12: =SUMIF('附表2-EF'!$D$5:$D$15,表1温室气体盘查表!C12,'附表2-EF'!$M$5:$M$15) -> 0.00016301594 | N12: ='附表1-GWP TABLE'!E4 -> 27.9 | O12: =SUMIF('附表2-EF'!$D$5:$D$15,表1温室气体盘查表!C12,'附表2-EF'!$N$5:$N$15) -> 0.00016301594 | Q12: ='附表1-GWP TABLE'!E5 -> 273 | AF12: =F12*I12*K12 -> 4406.5019 | AG12: =F12*L12*N12 -> 6.4706002 | AH12: =F12*O12*Q12 -> 63.314475 | AI12: =F12*R12*T12 -> 0 | AJ12: =F12*V12*X12 -> 0 | AK12: =F12*Z12*AB12 -> 0 | AL12: =F12*AC12*AE12 -> 0 | AM12: =SUM(AF12:AL12) -> 4476.287 | AN12: 0#柴油燃烧 | AO12: 4417.0726 | AP12: =AM12-AO12 -> 59.21439
A13: 9 | B13: 移动燃烧 | C13: 汽油燃烧 | D13: 公务车 | E13: 范围一 | F13: =ROUND(61085.82*0.775/10^3,2) -> 47.34 | G13: t | H13: 《办公室小车队燃油表》 | I13: =SUMIF('附表2-EF'!$D$5:$D$15,表1温室气体盘查表!C13,'附表2-EF'!$L$5:$L$15) -> 2.925056 | J13: tCO2/t | K13: 1 | L13: =SUMIF('附表2-EF'!$D$5:$D$15,表1温室气体盘查表!C13,'附表2-EF'!$M$5:$M$15) -> 0.001055215 | N13: ='附表1-GWP TABLE'!E4 -> 27.9 | O13: =SUMIF('附表2-EF'!$D$5:$D$15,表1温室气体盘查表!C13,'附表2-EF'!$N$5:$N$15) -> 0.0003376688 | Q13: ='附表1-GWP TABLE'!E5 -> 273 | AF13: =F13*I13*K13 -> 138.47215 | AG13: =F13*L13*N13 -> 1.3937132 | AH13: =F13*O13*Q13 -> 4.3639708 | AI13: =F13*R13*T13 -> 0 | AJ13: =F13*V13*X13 -> 0 | AK13: =F13*Z13*AB13 -> 0 | AL13: =F13*AC13*AE13 -> 0 | AM13: =SUM(AF13:AL13) -> 144.22983 | AN13: 92#汽油燃烧 | AO13: 149.47012 | AP13: =AM13-AO13 -> -5.2402897
A14: 10 | B14: 逸散排放 | C14: 制冷剂逸散（R32） | D14: 分体式空调 | E14: 范围一 | F14: =ROUND(1471.6233/1000/2,2) -> 0.74 | G14: t | H14: 《空调加氟汇总表》 | R14: 1 | S14: tHFCs/t | T14: ='附表1-GWP TABLE'!F8 -> 771 | U14: HFC-32 | AF14: =F14*I14*K14 -> 0 | AG14: =F14*L14*N14 -> 0 | AH14: =F14*O14*Q14 -> 0 | AI14: =F14*R14*T14 -> 570.54 | AJ14: =F14*V14*X14 -> 0 | AK14: =F14*Z14*AB14 -> 0 | AL14: =F14*AC14*AE14 -> 0 | AM14: =SUM(AF14:AL14) -> 570.54 | AN14: 制冷剂逸散（R32） | AO14: 717.03 | AP14: =AM14-AO14 -> -146.49
A15: 11 | B15: 逸散排放 | C15: CO2逸散 | D15: 二氧化碳灭火器 | E15: 范围一 | F15: =ROUND(564/1000,2) -> 0.56 | G15: t | H15: 《收发存汇总表》 | I15: ='附表2-EF'!F37 -> 1 | J15: tCO2/t | K15: 1 | AF15: =F15*I15*K15 -> 0.56 | AG15: =F15*L15*N15 -> 0 | AH15: =F15*O15*Q15 -> 0 | AI15: =F15*R15*T15 -> 0 | AJ15: =F15*V15*X15 -> 0 | AK15: =F15*Z15*AB15 -> 0 | AL15: =F15*AC15*AE15 -> 0 | AM15: =SUM(AF15:AL15) -> 0.56 | AN15: CO2逸散 | AO15: 0.66 | AP15: =AM15-AO15 -> -0.1
A16: 12 | B16: 逸散排放 | C16: CH4逸散 | D16: 化粪池 | E16: 范围一 | F16: =ROUND(7003*'附表2-EF'!J41*248/10^6*8/24,2) -> 23.16 | G16: tBOD | H16: 《人数统计表》 | L16: ='附表2-EF'!J39 -> 0.18 | M16: tCH4/tBOD | N16: ='附表1-GWP TABLE'!E4 -> 27.9 | AF16: =F16*I16*K16 -> 0 | AG16: =F16*L16*N16 -> 116.30952 | AH16: =F16*O16*Q16 -> 0 | AI16: =F16*R16*T16 -> 0 | AJ16: =F16*V16*X16 -> 0 | AK16: =F16*Z16*AB16 -> 0 | AL16: =F16*AC16*AE16 -> 0 | AM16: =SUM(AF16:AL16) -> 116.30952 | AN16: CH4逸散 | AO16: 112.29192 | AP16: =AM16-AO16 -> 4.0176
A17: 13 | B17: 逸散排放 | C17: CH4逸散 | D17: 耗氧池 | E17: 范围一 | F17: =ROUND((18.93-8.7)/10^6*2439525+(56.46-5.51)/10^6*9968019+(4234-45.99)/10^6*832316,2) -> 4018.57 | G17: tCOD | H17: 《2025年工业废水处置》 | L17: ='附表2-EF'!J40 -> 0.075 | M17: tCH4/tCOD | N17: ='附表1-GWP TABLE'!E4 -> 27.9 | AF17: =F17*I17*K17 -> 0 | AG17: =F17*L17*N17 -> 8408.8577 | AH17: =F17*O17*Q17 -> 0 | AI17: =F17*R17*T17 -> 0 | AJ17: =F17*V17*X17 -> 0 | AK17: =F17*Z17*AB17 -> 0 | AL17: =F17*AC17*AE17 -> 0 | AM17: =SUM(AF17:AL17) -> 8408.8577 | AN17: CH4逸散 | AO17: 365.58067 | AP17: =AM17-AO17 -> 8043.277
A18: 14 | B18: 制程排放 | C18: 白云石 | D18: 高炉 | E18: 范围一 | F18: =ROUND(38669.446,2) -> 38669.45 | G18: t | H18: 《2025年统计月报（转炉）》 | I18: =SUMIF('附表2-EF'!$D$19:$D$32,表1温室气体盘查表!C18,'附表2-EF'!$F$19:$F$32) -> 0.476 | J18: tCO2/t | K18: 1 | AF18: =F18*I18*K18 -> 18406.658 | AG18: =F18*L18*N18 -> 0 | AH18: =F18*O18*Q18 -> 0 | AI18: =F18*R18*T18 -> 0 | AJ18: =F18*V18*X18 -> 0 | AK18: =F18*Z18*AB18 -> 0 | AL18: =F18*AC18*AE18 -> 0 | AM18: =SUM(AF18:AL18) -> 18406.658 | AN18: 白云石 | AO18: 169593.75 | AP18: =AM18-AO18 -> -151187.09
A19: 15 | B19: 制程排放 | C19: 电极 | D19: 炼钢 | E19: 范围一 | F19: =ROUND(2292.859+709.398+2003.195,2) -> 5005.45 | G19: t | H19: 《2025年统计月报（转炉）》《2025年50t电炉台账》《2025年大电炉台账》 | I19: =SUMIF('附表2-EF'!$D$19:$D$32,表1温室气体盘查表!C19,'附表2-EF'!$F$19:$F$32) -> 3.663 | J19: tCO2/t | K19: 1 | AF19: =F19*I19*K19 -> 18334.963 | AG19: =F19*L19*N19 -> 0 | AH19: =F19*O19*Q19 -> 0 | AI19: =F19*R19*T19 -> 0 | AJ19: =F19*V19*X19 -> 0 | AK19: =F19*Z19*AB19 -> 0 | AL19: =F19*AC19*AE19 -> 0 | AM19: =SUM(AF19:AL19) -> 18334.963 | AN19: 电极 | AO19: 17447.125 | AP19: =AM19-AO19 -> 887.83794
A20: 16 | B20: 制程排放 | C20: 废钢 | D20: 炼钢 | E20: 范围一 | F20: =ROUND(462441.162+136808.562+520365.934,2) -> 1119615.7 | G20: t | H20: 《2025年统计月报（转炉）》《2025年50t电炉台账》《2025年大电炉台账》 | I20: =SUMIF('附表2-EF'!$D$19:$D$32,表1温室气体盘查表!C20,'附表2-EF'!$F$19:$F$32) -> 0.037 | J20: tCO2/t | K20: 1 | AF20: =F20*I20*K20 -> 41425.779 | AG20: =F20*L20*N20 -> 0 | AH20: =F20*O20*Q20 -> 0 | AI20: =F20*R20*T20 -> 0 | AJ20: =F20*V20*X20 -> 0 | AK20: =F20*Z20*AB20 -> 0 | AL20: =F20*AC20*AE20 -> 0 | AM20: =SUM(AF20:AL20) -> 41425.779 | AN20: 废钢 | AO20: 39875.738 | AP20: =AM20-AO20 -> 1550.0416
A21: 17 | B21: 制程排放 | C21: 高碳锰铁 | D21: 炼钢 | E21: 范围一 | F21: =ROUND(33390.439+851.616+7241.11,2) -> 41483.17 | G21: t | H21: 《2025年统计月报（转炉）》《50t电炉原材料 消耗汇总表》《70t电炉原材料 消耗汇总表》 | I21: =SUMIF('附表2-EF'!$D$19:$D$32,表1温室气体盘查表!C21,'附表2-EF'!$F$19:$F$32) -> 0.275 | J21: tCO2/t | K21: 1 | AF21: =F21*I21*K21 -> 11407.872 | AG21: =F21*L21*N21 -> 0 | AH21: =F21*O21*Q21 -> 0 | AI21: =F21*R21*T21 -> 0 | AJ21: =F21*V21*X21 -> 0 | AK21: =F21*Z21*AB21 -> 0 | AL21: =F21*AC21*AE21 -> 0 | AM21: =SUM(AF21:AL21) -> 11407.872 | AN21: 锰铁 | AO21: 13114.101 | AP21: =AM21-AO21 -> -1706.2293
A22: 18 | B22: 制程排放 | C22: 锰硅合金 | D22: 炼钢 | E22: 范围一 | F22: =ROUND(0+189.062+2698.627,2) -> 2887.69 | G22: t | H22: 《50t电炉原材料 消耗汇总表》《70t电炉原材料 消耗汇总表》 | I22: =SUMIF('附表2-EF'!$D$19:$D$32,表1温室气体盘查表!C22,'附表2-EF'!$F$19:$F$32) -> 0.092 | J22: tCO2/t | K22: 1 | AF22: =F22*I22*K22 -> 265.66748 | AG22: =F22*L22*N22 -> 0 | AH22: =F22*O22*Q22 -> 0 | AI22: =F22*R22*T22 -> 0 | AJ22: =F22*V22*X22 -> 0 | AK22: =F22*Z22*AB22 -> 0 | AL22: =F22*AC22*AE22 -> 0 | AM22: =SUM(AF22:AL22) -> 265.66748 | AN22: 锰铁 | AO22: 13114.101 | AP22: =AM22-AO22 -> -12848.434
A23: 19 | B23: 制程排放 | C23: 镍铁 | D23: 炼钢 | E23: 范围一 | F23: =ROUND(7856.706+367.47+1719.027,2) -> 9943.2 | G23: t | H23: 《2025年统计月报（转炉）》《50t电炉原材料 消耗汇总表》《70t电炉原材料 消耗汇总表》 | I23: =SUMIF('附表2-EF'!$D$19:$D$32,表1温室气体盘查表!C23,'附表2-EF'!$F$19:$F$32) -> 0.037 | J23: tCO2/t | K23: 1 | AF23: =F23*I23*K23 -> 367.8984 | AG23: =F23*L23*N23 -> 0 | AH23: =F23*O23*Q23 -> 0 | AI23: =F23*R23*T23 -> 0 | AJ23: =F23*V23*X23 -> 0 | AK23: =F23*Z23*AB23 -> 0 | AL23: =F23*AC23*AE23 -> 0 | AM23: =SUM(AF23:AL23) -> 367.8984 | AN23: 镍铁 | AO23: 349.46907 | AP23: =AM23-AO23 -> 18.42933
A24: 20 | B24: 制程排放 | C24: 高碳铬铁 | D24: 炼钢 | E24: 范围一 | F24: =ROUND(30491.606+3776.482+5940.04,2) -> 40208.13 | G24: t | H24: 《2025年统计月报（转炉）》《50t电炉原材料 消耗汇总表》《70t电炉原材料 消耗汇总表》 | I24: =SUMIF('附表2-EF'!$D$19:$D$32,表1温室气体盘查表!C24,'附表2-EF'!$F$19:$F$32) -> 0.348 | J24: tCO2/t | K24: 1 | AF24: =F24*I24*K24 -> 13992.429 | AG24: =F24*L24*N24 -> 0 | AH24: =F24*O24*Q24 -> 0 | AI24: =F24*R24*T24 -> 0 | AJ24: =F24*V24*X24 -> 0 | AK24: =F24*Z24*AB24 -> 0 | AL24: =F24*AC24*AE24 -> 0 | AM24: =SUM(AF24:AL24) -> 13992.429 | AN24: 铬铁 | AO24: 22918.907 | AP24: =AM24-AO24 -> -8926.4781
A25: 21 | B25: 制程排放 | C25: 硅铁 | D25: 炼钢 | E25: 范围一 | F25: =ROUND(7938.683+997.832+2871.568,2) -> 11808.08 | G25: t | H25: 《2025年统计月报（转炉）》《50t电炉原材料 消耗汇总表》《70t电炉原材料 消耗汇总表》 | I25: =SUMIF('附表2-EF'!$D$19:$D$32,表1温室气体盘查表!C25,'附表2-EF'!$F$19:$F$32) -> 0.007 | J25: tCO2/t | K25: 1 | AF25: =F25*I25*K25 -> 82.65656 | AG25: =F25*L25*N25 -> 0 | AH25: =F25*O25*Q25 -> 0 | AI25: =F25*R25*T25 -> 0 | AJ25: =F25*V25*X25 -> 0 | AK25: =F25*Z25*AB25 -> 0 | AL25: =F25*AC25*AE25 -> 0 | AM25: =SUM(AF25:AL25) -> 82.65656 | AN25: 硅铁 | AO25: 74.70736 | AP25: =AM25-AO25 -> 7.9492
A26: 22 | B26: 制程排放 | C26: 钼铁 | D26: 炼钢 | E26: 范围一 | F26: =ROUND(3621.161+1134.107+2513.451,2) -> 7268.72 | G26: t | H26: 《2025年统计月报（转炉）》《50t电炉原材料 消耗汇总表》《70t电炉原材料 消耗汇总表》 | I26: =SUMIF('附表2-EF'!$D$19:$D$32,表1温室气体盘查表!C26,'附表2-EF'!$F$19:$F$32) -> 0.018 | J26: tCO2/t | K26: 1 | AF26: =F26*I26*K26 -> 130.83696 | AG26: =F26*L26*N26 -> 0 | AH26: =F26*O26*Q26 -> 0 | AI26: =F26*R26*T26 -> 0 | AJ26: =F26*V26*X26 -> 0 | AK26: =F26*Z26*AB26 -> 0 | AL26: =F26*AC26*AE26 -> 0 | AM26: =SUM(AF26:AL26) -> 130.83696 | AN26: 钼铁 | AO26: 143.01295 | AP26: =AM26-AO26 -> -12.175992
A27: 23 | B27: 制程排放 | C27: 粗钢 | D27: 固碳产品 | E27: 范围一 | F27: =-ROUND(3107726.623+1201742.787+175073.244,2) -> -4484542.7 | G27: t | H27: 《2025年统计月报（转炉厂）》《70t电炉台账》《50t电炉台账》 | I27: =SUMIF('附表2-EF'!$D$19:$D$32,表1温室气体盘查表!C27,'附表2-EF'!$F$19:$F$32) -> 0.037 | J27: tCO2/t | K27: 1 | AF27: =F27*I27*K27 -> -165928.08 | AG27: =F27*L27*N27 -> 0 | AH27: =F27*O27*Q27 -> 0 | AI27: =F27*R27*T27 -> 0 | AJ27: =F27*V27*X27 -> 0 | AK27: =F27*Z27*AB27 -> 0 | AL27: =F27*AC27*AE27 -> 0 | AM27: =SUM(AF27:AL27) -> -165928.08 | AN27: 钢坯 | AO27: -160314.41 | AP27: =AM27-AO27 -> -5613.6663
A28: 24 | B28: 制程排放 | C28: 粗苯 | D28: 外售 | E28: 范围一 | F28: =-ROUND(20393.52,2) -> -20393.52 | G28: t | H28: 《附表3：冶钢2025PCF补充数据表》 | I28: =SUMIF('附表2-EF'!$D$19:$D$32,表1温室气体盘查表!C28,'附表2-EF'!$F$19:$F$32) -> 3.382 | J28: tCO2/t | K28: 1 | AF28: =F28*I28*K28 -> -68970.885 | AG28: =F28*L28*N28 -> 0 | AH28: =F28*O28*Q28 -> 0 | AI28: =F28*R28*T28 -> 0 | AJ28: =F28*V28*X28 -> 0 | AK28: =F28*Z28*AB28 -> 0 | AL28: =F28*AC28*AE28 -> 0 | AM28: =SUM(AF28:AL28) -> -68970.885 | AN28: 粗苯 | AO28: -65952.991 | AP28: =AM28-AO28 -> -3017.8939
A29: 25 | B29: 制程排放 | C29: 焦油 | D29: 危废处置 | E29: 范围一 | F29: =-ROUND(60565.6,2) -> -60565.6 | G29: t | H29: 《汽车衡结净计量实绩_焦油2025年度》 | I29: =SUMIF('附表2-EF'!$D$19:$D$32,表1温室气体盘查表!C29,'附表2-EF'!$F$19:$F$32) -> 2.699 | J29: tCO2/t | K29: 1 | AF29: =F29*I29*K29 -> -163466.55 | AG29: =F29*L29*N29 -> 0 | AH29: =F29*O29*Q29 -> 0 | AI29: =F29*R29*T29 -> 0 | AJ29: =F29*V29*X29 -> 0 | AK29: =F29*Z29*AB29 -> 0 | AL29: =F29*AC29*AE29 -> 0 | AM29: =SUM(AF29:AL29) -> -163466.55 | AN29: 煤焦油 | AO29: -159387.02 | AP29: =AM29-AO29 -> -4079.5385
A30: 26 | B30: 输入能源间接温室气体排放 | C30: 外购电力（基于位置） | D30: 用电设备 | E30: 范围二 | F30: =ROUND(1966850.825,2) -> 1966850.8 | G30: MWh | H30: 《电费发票》 | I30: ='附表2-EF'!F44 -> 0.5306 | J30: tCO2/MWh | K30: 1 | AF30: =F30*I30*K30 -> 1043611.1 | AG30: =F30*L30*N30 -> 0 | AH30: =F30*O30*Q30 -> 0 | AI30: =F30*R30*T30 -> 0 | AJ30: =F30*V30*X30 -> 0 | AK30: =F30*Z30*AB30 -> 0 | AL30: =F30*AC30*AE30 -> 0 | AM30: =SUM(AF30:AL30) -> 1043611.1 | AN30: 外购电力（基于位置）
A31: 27 | B31: 输入能源间接温室气体排放 | C31: 外购电力（基于市场） | D31: 用电设备 | E31: 范围二 | F31: =ROUND(1946850.825,2) -> 1946850.8 | G31: MWh | H31: 《电费发票》《绿证》 | I31: ='附表2-EF'!F45 -> 0.6096 | J31: tCO2/MWh | K31: 1 | AF31: =F31*I31*K31 -> 1186800.3 | AG31: =F31*L31*N31 -> 0 | AH31: =F31*O31*Q31 -> 0 | AI31: =F31*R31*T31 -> 0 | AJ31: =F31*V31*X31 -> 0 | AK31: =F31*Z31*AB31 -> 0 | AL31: =F31*AC31*AE31 -> 0 | AM31: =SUM(AF31:AL31) -> 1186800.3 | AN31: 外购电力（基于市场）
A32: 28 | B32: 外购商品和服务的上游排放 | C32: 铁矿石生产 | D32: 烧结 | E32: 范围三 类别1 | F32: =ROUND(816374.146+4037949.92633333,2) -> 4854324.1 | G32: t | H32: 《2025年统计月报（烧结）》《2025年统计报表（中高炉）》 | I32: =SUMIF('附表2-EF'!$D$49:$D$72,表1温室气体盘查表!C32,'附表2-EF'!$G$49:$G$72) -> 0.098847 | J32: tCO2/t | K32: 1 | AF32: =F32*I32*K32 -> 479835.37 | AG32: =F32*L32*N32 -> 0 | AH32: =F32*O32*Q32 -> 0 | AI32: =F32*R32*T32 -> 0 | AJ32: =F32*V32*X32 -> 0 | AK32: =F32*Z32*AB32 -> 0 | AL32: =F32*AC32*AE32 -> 0 | AM32: =SUM(AF32:AL32) -> 479835.37 | AN32: 铁矿石生产 | AO32: 448588.58 | AP32: =AM32-AO32 -> 31246.795
A33: 29 | B33: 外购商品和服务的上游排放 | C33: 生石灰生产 | D33: 烧结、转炉、电炉 | E33: 范围三 类别1 | F33: =ROUND(127889.871+11121.076+60171.413,2) -> 199182.36 | G33: t | H33: 《2025年统计月报（转炉）》《2025年50t电炉台账》《2025年大电炉台账》 | I33: =SUMIF('附表2-EF'!$D$49:$D$72,表1温室气体盘查表!C33,'附表2-EF'!$G$49:$G$72) -> 1.1896699 | J33: tCO2/t | K33: 1 | AF33: =F33*I33*K33 -> 236961.26 | AG33: =F33*L33*N33 -> 0 | AH33: =F33*O33*Q33 -> 0 | AI33: =F33*R33*T33 -> 0 | AJ33: =F33*V33*X33 -> 0 | AK33: =F33*Z33*AB33 -> 0 | AL33: =F33*AC33*AE33 -> 0 | AM33: =SUM(AF33:AL33) -> 236961.26 | AN33: 生石灰生产 | AO33: 727500.38 | AP33: =AM33-AO33 -> -490539.12
A34: 30 | B34: 外购商品和服务的上游排放 | C34: 白云石生产 | D34: 烧结、转炉、电炉 | E34: 范围三 类别1 | F34: =ROUND(38669.446,2) -> 38669.45 | G34: t | H34: 《2025年统计月报（转炉）》 | I34: =SUMIF('附表2-EF'!$D$49:$D$72,表1温室气体盘查表!C34,'附表2-EF'!$G$49:$G$72) -> 0.13033 | J34: tCO2/t | K34: 1 | AF34: =F34*I34*K34 -> 5039.7894 | AG34: =F34*L34*N34 -> 0 | AH34: =F34*O34*Q34 -> 0 | AI34: =F34*R34*T34 -> 0 | AJ34: =F34*V34*X34 -> 0 | AK34: =F34*Z34*AB34 -> 0 | AL34: =F34*AC34*AE34 -> 0 | AM34: =SUM(AF34:AL34) -> 5039.7894 | AN34: 白云石生产 | AO34: 46435.196 | AP34: =AM34-AO34 -> -41395.407
A35: 31 | B35: 外购商品和服务的上游排放 | C35: 球团生产 | D35: 高炉、转炉 | E35: 范围三 类别1 | F35: =ROUND(679912.97+2080.92,2) -> 681993.89 | G35: t | H35: 《2025年统计报表（中高炉）》《2025年统计月报（转炉）》 | I35: =SUMIF('附表2-EF'!$D$49:$D$72,表1温室气体盘查表!C35,'附表2-EF'!$G$49:$G$72) -> 0.10446 | J35: tCO2/t | K35: 1 | AF35: =F35*I35*K35 -> 71241.082 | AG35: =F35*L35*N35 -> 0 | AH35: =F35*O35*Q35 -> 0 | AI35: =F35*R35*T35 -> 0 | AJ35: =F35*V35*X35 -> 0 | AK35: =F35*Z35*AB35 -> 0 | AL35: =F35*AC35*AE35 -> 0 | AM35: =SUM(AF35:AL35) -> 71241.082 | AN35: 球团生产 | AO35: 71601.051 | AP35: =AM35-AO35 -> -359.96916
A36: 32 | B36: 外购商品和服务的上游排放 | C36: 废钢生产 | D36: 转炉、电炉 | E36: 范围三 类别1 | F36: =F20 -> 1119615.7 | G36: t | H36: 《2025年统计月报（转炉）》《2025年50t电炉台账》《2025年大电炉台账》 | I36: =SUMIF('附表2-EF'!$D$49:$D$72,表1温室气体盘查表!C36,'附表2-EF'!$G$49:$G$72) -> 0.074179 | J36: tCO2/t | K36: 1 | AF36: =F36*I36*K36 -> 83051.97 | AG36: =F36*L36*N36 -> 0 | AH36: =F36*O36*Q36 -> 0 | AI36: =F36*R36*T36 -> 0 | AJ36: =F36*V36*X36 -> 0 | AK36: =F36*Z36*AB36 -> 0 | AL36: =F36*AC36*AE36 -> 0 | AM36: =SUM(AF36:AL36) -> 83051.97 | AN36: 废钢生产 | AO36: 79944.388 | AP36: =AM36-AO36 -> 3107.5821
A37: 33 | B37: 外购商品和服务的上游排放 | C37: 电极生产 | D37: 转炉、电炉 | E37: 范围三 类别1 | F37: =ROUND(2292.859+709.398+2003.195,2) -> 5005.45 | G37: t | H37: 《2025年统计月报（转炉）》《2025年50t电炉台账》《2025年大电炉台账》 | I37: =SUMIF('附表2-EF'!$D$49:$D$72,表1温室气体盘查表!C37,'附表2-EF'!$G$49:$G$72) -> 12.17913 | J37: tCO2/t | K37: 1 | AF37: =F37*I37*K37 -> 60962.024 | AG37: =F37*L37*N37 -> 0 | AH37: =F37*O37*Q37 -> 0 | AI37: =F37*R37*T37 -> 0 | AJ37: =F37*V37*X37 -> 0 | AK37: =F37*Z37*AB37 -> 0 | AL37: =F37*AC37*AE37 -> 0 | AM37: =SUM(AF37:AL37) -> 60962.024 | AN37: 电极生产 | AO37: 37742.812 | AP37: =AM37-AO37 -> 23219.212
A38: 34 | B38: 外购商品和服务的上游排放 | C38: 锰铁生产 | D38: 转炉、电炉 | E38: 范围三 类别1 | F38: =F21 -> 41483.17 | G38: t | H38: 《2025年统计月报（转炉）》《50t电炉原材料 消耗汇总表》《70t电炉原材料 消耗汇总表》 | I38: =SUMIF('附表2-EF'!$D$49:$D$72,表1温室气体盘查表!C38,'附表2-EF'!$G$49:$G$72) -> 2.9772 | J38: tCO2/t | K38: 1 | AF38: =F38*I38*K38 -> 123503.69 | AG38: =F38*L38*N38 -> 0 | AH38: =F38*O38*Q38 -> 0 | AI38: =F38*R38*T38 -> 0 | AJ38: =F38*V38*X38 -> 0 | AK38: =F38*Z38*AB38 -> 0 | AL38: =F38*AC38*AE38 -> 0 | AM38: =SUM(AF38:AL38) -> 123503.69 | AN38: 锰铁生产 | AO38: 141868.58 | AP38: =AM38-AO38 -> -18364.888
A39: 35 | B39: 外购商品和服务的上游排放 | C39: 镍铁生产 | D39: 转炉、电炉 | E39: 范围三 类别1 | F39: =F23 -> 9943.2 | G39: t | H39: 《2025年统计月报（转炉）》《50t电炉原材料 消耗汇总表》《70t电炉原材料 消耗汇总表》 | I39: =SUMIF('附表2-EF'!$D$49:$D$72,表1温室气体盘查表!C39,'附表2-EF'!$G$49:$G$72) -> 8.7547 | J39: tCO2/t | K39: 1 | AF39: =F39*I39*K39 -> 87049.733 | AG39: =F39*L39*N39 -> 0 | AH39: =F39*O39*Q39 -> 0 | AI39: =F39*R39*T39 -> 0 | AJ39: =F39*V39*X39 -> 0 | AK39: =F39*Z39*AB39 -> 0 | AL39: =F39*AC39*AE39 -> 0 | AM39: =SUM(AF39:AL39) -> 87049.733 | AN39: 镍铁生产 | AO39: 84819.123 | AP39: =AM39-AO39 -> 2230.61
A40: 36 | B40: 外购商品和服务的上游排放 | C40: 铬铁生产 | D40: 转炉、电炉 | E40: 范围三 类别1 | F40: =F24 -> 40208.13 | G40: t | H40: 《2025年统计月报（转炉）》《50t电炉原材料 消耗汇总表》《70t电炉原材料 消耗汇总表》 | I40: =SUMIF('附表2-EF'!$D$49:$D$72,表1温室气体盘查表!C40,'附表2-EF'!$G$49:$G$72) -> 5.0921 | J40: tCO2/t | K40: 1 | AF40: =F40*I40*K40 -> 204743.82 | AG40: =F40*L40*N40 -> 0 | AH40: =F40*O40*Q40 -> 0 | AI40: =F40*R40*T40 -> 0 | AJ40: =F40*V40*X40 -> 0 | AK40: =F40*Z40*AB40 -> 0 | AL40: =F40*AC40*AE40 -> 0 | AM40: =SUM(AF40:AL40) -> 204743.82 | AN40: 铬铁生产 | AO40: 345101.44 | AP40: =AM40-AO40 -> -140357.63
A41: 37 | B41: 外购商品和服务的上游排放 | C41: 萤石生产 | D41: 转炉、电炉 | E41: 范围三 类别1 | F41: =ROUND(417605+415.582+135.385,2) -> 418155.97 | G41: t | H41: 《2025年统计月报（转炉）》《2025年50t电炉台账》《2025年大电炉台账》 | I41: =SUMIF('附表2-EF'!$D$49:$D$72,表1温室气体盘查表!C41,'附表2-EF'!$G$49:$G$72) -> 0.21158 | J41: tCO2/t | K41: 1 | AF41: =F41*I41*K41 -> 88473.44 | AG41: =F41*L41*N41 -> 0 | AH41: =F41*O41*Q41 -> 0 | AI41: =F41*R41*T41 -> 0 | AJ41: =F41*V41*X41 -> 0 | AK41: =F41*Z41*AB41 -> 0 | AL41: =F41*AC41*AE41 -> 0 | AM41: =SUM(AF41:AL41) -> 88473.44 | AN41: 萤石生产 | AO41: 685.06219 | AP41: =AM41-AO41 -> 87788.378
A42: 38 | B42: 外购商品和服务的上游排放 | C42: 硅铁生产 | D42: 转炉、电炉 | E42: 范围三 类别1 | F42: =F25+F22 -> 14695.77 | G42: t | H42: 《2025年统计月报（转炉）》《50t电炉原材料 消耗汇总表》《70t电炉原材料 消耗汇总表》 | I42: =SUMIF('附表2-EF'!$D$49:$D$72,表1温室气体盘查表!C42,'附表2-EF'!$G$49:$G$72) -> 10.145 | J42: tCO2/t | K42: 1 | AF42: =F42*I42*K42 -> 149088.59 | AG42: =F42*L42*N42 -> 0 | AH42: =F42*O42*Q42 -> 0 | AI42: =F42*R42*T42 -> 0 | AJ42: =F42*V42*X42 -> 0 | AK42: =F42*Z42*AB42 -> 0 | AL42: =F42*AC42*AE42 -> 0 | AM42: =SUM(AF42:AL42) -> 149088.59 | AN42: 硅铁生产 | AO42: 103575.78 | AP42: =AM42-AO42 -> 45512.803
A43: 39 | B43: 外购商品和服务的上游排放 | C43: 钼铁生产 | D43: 转炉、电炉 | E43: 范围三 类别1 | F43: =F26 -> 7268.72 | G43: t | H43: 《2025年统计月报（转炉）》《50t电炉原材料 消耗汇总表》《70t电炉原材料 消耗汇总表》 | I43: =SUMIF('附表2-EF'!$D$49:$D$72,表1温室气体盘查表!C43,'附表2-EF'!$G$49:$G$72) -> 8.1 | J43: tCO2/t | K43: 1 | AF43: =F43*I43*K43 -> 58876.632 | AG43: =F43*L43*N43 -> 0 | AH43: =F43*O43*Q43 -> 0 | AI43: =F43*R43*T43 -> 0 | AJ43: =F43*V43*X43 -> 0 | AK43: =F43*Z43*AB43 -> 0 | AL43: =F43*AC43*AE43 -> 0 | AM43: =SUM(AF43:AL43) -> 58876.632 | AN43: 钼铁生产 | AO43: 66065.4 | AP43: =AM43-AO43 -> -7188.768
A44: 40 | B44: 外购商品和服务的上游排放 | C44: 铝铁生产 | D44: 转炉、电炉 | E44: 范围三 类别1 | F44: =ROUND(1619.511+102.543+648.071,2) -> 2370.13 | G44: t | H44: 《2025年统计月报（转炉）》《50t电炉原材料 消耗汇总表》《70t电炉原材料 消耗汇总表》 | I44: =SUMIF('附表2-EF'!$D$49:$D$72,表1温室气体盘查表!C44,'附表2-EF'!$G$49:$G$72) -> 5.7320082 | J44: tCO2/t | K44: 1 | AF44: =F44*I44*K44 -> 13585.605 | AG44: =F44*L44*N44 -> 0 | AH44: =F44*O44*Q44 -> 0 | AI44: =F44*R44*T44 -> 0 | AJ44: =F44*V44*X44 -> 0 | AK44: =F44*Z44*AB44 -> 0 | AL44: =F44*AC44*AE44 -> 0 | AM44: =SUM(AF44:AL44) -> 13585.605 | AN44: 铝铁生产 | AO44: 63158.19 | AP44: =AM44-AO44 -> -49572.585
A45: 41 | B45: 外购商品和服务的上游排放 | C45: 铝生产 | D45: 转炉、电炉 | E45: 范围三 类别1 | F45: =ROUND(4019.003+595.629+2823.971,2) -> 7438.6 | G45: t | H45: 《2025年统计月报（转炉）》《50t电炉原材料 消耗汇总表》《70t电炉原材料 消耗汇总表》 | I45: =SUMIF('附表2-EF'!$D$49:$D$72,表1温室气体盘查表!C45,'附表2-EF'!$G$49:$G$72) -> 22.290561 | J45: tCO2/t | K45: 1 | AF45: =F45*I45*K45 -> 165810.57 | AG45: =F45*L45*N45 -> 0 | AH45: =F45*O45*Q45 -> 0 | AI45: =F45*R45*T45 -> 0 | AJ45: =F45*V45*X45 -> 0 | AK45: =F45*Z45*AB45 -> 0 | AL45: =F45*AC45*AE45 -> 0 | AM45: =SUM(AF45:AL45) -> 165810.57 | AN45: 铝生产 | AO45: 63342.195 | AP45: =AM45-AO45 -> 102468.37
A46: 42 | B46: 外购商品和服务的上游排放 | C46: 增碳剂生产 | D46: 转炉、电炉 | E46: 范围三 类别1 | F46: =ROUND(8679.765+0+0,2) -> 8679.77 | G46: t | H46: 《2025年统计月报（转炉）》《50t电炉原材料 消耗汇总表》《70t电炉原材料 消耗汇总表》 | I46: =SUMIF('附表2-EF'!$D$49:$D$72,表1温室气体盘查表!C46,'附表2-EF'!$G$49:$G$72) -> 1.6645335 | J46: tCO2/t | K46: 1 | AF46: =F46*I46*K46 -> 14447.768 | AG46: =F46*L46*N46 -> 0 | AH46: =F46*O46*Q46 -> 0 | AI46: =F46*R46*T46 -> 0 | AJ46: =F46*V46*X46 -> 0 | AK46: =F46*Z46*AB46 -> 0 | AL46: =F46*AC46*AE46 -> 0 | AM46: =SUM(AF46:AL46) -> 14447.768 | AN46: 增碳剂生产 | AO46: 17778.323 | AP46: =AM46-AO46 -> -3330.5551
A47: 43 | B47: 外购商品和服务的上游排放 | C47: 铁鳞生产 | D47: 炼钢 | E47: 范围三 类别1 | F47: =ROUND(5675+2611.02,2) -> 8286.02 | G47: t | H47: 《2025年产品、废钢流转情况表》 | I47: =SUMIF('附表2-EF'!$D$49:$D$72,表1温室气体盘查表!C47,'附表2-EF'!$G$49:$G$72) -> 0.0035231057 | J47: tCO2/t | K47: 1 | AF47: =F47*I47*K47 -> 29.192524 | AG47: =F47*L47*N47 -> 0 | AH47: =F47*O47*Q47 -> 0 | AI47: =F47*R47*T47 -> 0 | AJ47: =F47*V47*X47 -> 0 | AK47: =F47*Z47*AB47 -> 0 | AL47: =F47*AC47*AE47 -> 0 | AM47: =SUM(AF47:AL47) -> 29.192524 | AN47: 铁鳞生产 | AO47: 608.38394 | AP47: =AM47-AO47 -> -579.19142
A48: 44 | B48: 外购商品和服务的上游排放 | C48: 氨水生产 | D48: 烧结 | E48: 范围三 类别1 | F48: =ROUND(1472.3+1903.42+1500.22+40*5/1000,2) -> 4876.14 | G48: t | H48: 《脱硫脱硝成本补充》 《水处理用氨水（美萍50kg）（2）》 | I48: =SUMIF('附表2-EF'!$D$49:$D$72,表1温室气体盘查表!C48,'附表2-EF'!$G$49:$G$72) -> 5.4368448 | J48: tCO2/t | K48: 1 | AF48: =F48*I48*K48 -> 26510.816 | AG48: =F48*L48*N48 -> 0 | AH48: =F48*O48*Q48 -> 0 | AI48: =F48*R48*T48 -> 0 | AJ48: =F48*V48*X48 -> 0 | AK48: =F48*Z48*AB48 -> 0 | AL48: =F48*AC48*AE48 -> 0 | AM48: =SUM(AF48:AL48) -> 26510.816 | AN48: 氨水生产 | AO48: 24444.815 | AP48: =AM48-AO48 -> 2066.001
A49: 45 | B49: 外购商品和服务的上游排放 | C49: 盐酸生产 | D49: 焦化 | E49: 范围三 类别1 | F49: =7*31% -> 2.17 | G49: t | H49: 《水处理用氨水（美萍50kg）（2）》 | I49: =SUMIF('附表2-EF'!$D$49:$D$72,表1温室气体盘查表!C49,'附表2-EF'!$G$49:$G$72) -> 0.97573527 | J49: tCO3/t | K49: 1 | AF49: =F49*I49*K49 -> 2.1173455 | AG49: =F49*L49*N49 -> 0 | AH49: =F49*O49*Q49 -> 0 | AI49: =F49*R49*T49 -> 0 | AJ49: =F49*V49*X49 -> 0 | AK49: =F49*Z49*AB49 -> 0 | AL49: =F49*AC49*AE49 -> 0 | AM49: =SUM(AF49:AL49) -> 2.1173455
A50: 46 | B50: 外购商品和服务的上游排放 | C50: 氢氧化钠生产 | D50: 焦化 | E50: 范围三 类别1 | F50: =7*32% -> 2.24 | G50: t | H50: 《水处理用氨水（美萍50kg）（2）》 | I50: =SUMIF('附表2-EF'!$D$49:$D$72,表1温室气体盘查表!C50,'附表2-EF'!$G$49:$G$72) -> 1.4645659 | J50: tCO4/t | K50: 1 | AF50: =F50*I50*K50 -> 3.2806275 | AG50: =F50*L50*N50 -> 0 | AH50: =F50*O50*Q50 -> 0 | AI50: =F50*R50*T50 -> 0 | AJ50: =F50*V50*X50 -> 0 | AK50: =F50*Z50*AB50 -> 0 | AL50: =F50*AC50*AE50 -> 0 | AM50: =SUM(AF50:AL50) -> 3.2806275
A51: 47 | B51: 外购商品和服务的上游排放 | C51: 碳化硅生产 | D51: - | E51: 范围三 类别1 | F51: 3676.387 | G51: t | H51: 《2025年统计月报（转炉）》 | I51: =SUMIF('附表2-EF'!$D$49:$D$72,表1温室气体盘查表!C51,'附表2-EF'!$G$49:$G$72) -> 7.2790711 | J51: tCO2/t | K51: 1 | AF51: =F51*I51*K51 -> 26760.682 | AG51: =F51*L51*N51 -> 0 | AH51: =F51*O51*Q51 -> 0 | AI51: =F51*R51*T51 -> 0 | AJ51: =F51*V51*X51 -> 0 | AK51: =F51*Z51*AB51 -> 0 | AL51: =F51*AC51*AE51 -> 0 | AM51: =SUM(AF51:AL51) -> 26760.682 | AN51: 碳化硅生产 | AO51: 48149.585 | AP51: =AM51-AO51 -> -21388.903
A52: 48 | B52: 外购商品和服务的上游排放 | C52: 镁生产 | D52: - | E52: 范围三 类别1 | F52: 9749.982 | G52: t | H52: 《2025年统计月报（转炉）》 | I52: =SUMIF('附表2-EF'!$D$49:$D$72,表1温室气体盘查表!C52,'附表2-EF'!$G$49:$G$72) -> 26.345188 | J52: tCO2/t | K52: 1 | AF52: =F52*I52*K52 -> 256865.11 | AG52: =F52*L52*N52 -> 0 | AH52: =F52*O52*Q52 -> 0 | AI52: =F52*R52*T52 -> 0 | AJ52: =F52*V52*X52 -> 0 | AK52: =F52*Z52*AB52 -> 0 | AL52: =F52*AC52*AE52 -> 0 | AM52: =SUM(AF52:AL52) -> 256865.11 | AN52: 镁生产 | AO52: 308520.83 | AP52: =AM52-AO52 -> -51655.722
A53: 49 | B53: 外购商品和服务的上游排放 | C53: 所有其他纸制品加工制造 | D53: 办公室 | E53: 范围三 类别1 | F53: =ROUND(15287.0876139219,2) -> 15287.09 | G53: $ | H53: 《收发存-入库量》 | I53: =SUMIF('附表2-EF'!$D$49:$D$72,表1温室气体盘查表!C53,'附表2-EF'!$G$49:$G$72) -> 0.000343 | J53: t CO2e/2022 USD, purchaser price | K53: 1 | AF53: =F53*I53*K53 -> 5.2434719 | AG53: =F53*L53*N53 -> 0 | AH53: =F53*O53*Q53 -> 0 | AI53: =F53*R53*T53 -> 0 | AJ53: =F53*V53*X53 -> 0 | AK53: =F53*Z53*AB53 -> 0 | AL53: =F53*AC53*AE53 -> 0 | AM53: =SUM(AF53:AL53) -> 5.2434719 | AN53: 所有其他纸制品加工制造 | AO53: 5.5436243 | AP53: =AM53-AO53 -> -0.30015244
A54: 50 | B54: 外购商品和服务的上游排放 | C54: 办公用品(纸张除外)制造 | D54: 办公室 | E54: 范围三 类别1 | F54: =ROUND(272877.667593404,2) -> 272877.67 | G54: $ | H54: 《收发存-入库量》 | I54: =SUMIF('附表2-EF'!$D$49:$D$72,表1温室气体盘查表!C54,'附表2-EF'!$G$49:$G$72) -> 0.000265 | J54: t CO2e/2022 USD, purchaser price | K54: 1 | AF54: =F54*I54*K54 -> 72.312583 | AG54: =F54*L54*N54 -> 0 | AH54: =F54*O54*Q54 -> 0 | AI54: =F54*R54*T54 -> 0 | AJ54: =F54*V54*X54 -> 0 | AK54: =F54*Z54*AB54 -> 0 | AL54: =F54*AC54*AE54 -> 0 | AM54: =SUM(AF54:AL54) -> 72.312583 | AN54: 办公用品(纸张除外)制造 | AO54: 47.034256 | AP54: =AM54-AO54 -> 25.278326
A55: 51 | B55: 外购商品和服务的上游排放 | C55: 源水 | D55: 水处理工序 | E55: 范围三 类别1 | F55: =ROUND(20647661.31,2) -> 20647661 | G55: t | H55: 《2025年12月能源报表》 | I55: =SUMIF('附表2-EF'!$D$49:$D$72,表1温室气体盘查表!C55,'附表2-EF'!$G$49:$G$72) -> 0.0012784698 | J55: tCO2/t | K55: 1 | AF55: =F55*I55*K55 -> 26397.412 | AG55: =F55*L55*N55 -> 0 | AH55: =F55*O55*Q55 -> 0 | AI55: =F55*R55*T55 -> 0 | AJ55: =F55*V55*X55 -> 0 | AK55: =F55*Z55*AB55 -> 0 | AL55: =F55*AC55*AE55 -> 0 | AM55: =SUM(AF55:AL55) -> 26397.412 | AN55: 源水 | AO55: 29761.031 | AP55: =AM55-AO55 -> -3363.6191
A56: 52 | B56: 资本货物 | C56: 采购产品空调和暖空气加热设备和商业和工业制冷设备制造 | D56: 办公室、各工序 | E56: 范围三 类别2 | F56: =ROUND(1112205.76113944,2) -> 1112205.8 | G56: $ | H56: 《收发存-入库量》 | I56: =SUMIF('附表2-EF'!$D$76:$D$84,表1温室气体盘查表!C56,'附表2-EF'!$F$76:$F$84) -> 0.000108 | J56: t CO2e/2022 USD, purchaser price | K56: 1 | AF56: =F56*I56*K56 -> 120.11822 | AG56: =F56*L56*N56 -> 0 | AH56: =F56*O56*Q56 -> 0 | AI56: =F56*R56*T56 -> 0 | AJ56: =F56*V56*X56 -> 0 | AK56: =F56*Z56*AB56 -> 0 | AL56: =F56*AC56*AE56 -> 0 | AM56: =SUM(AF56:AL56) -> 120.11822 | AN56: 采购产品空调和暖空气加热设备和商业和工业制冷设备制造
A57: 53 | B57: 资本货物 | C57: 电子计算机制造 | D57: 办公室、各工序 | E57: 范围三 类别2 | F57: =ROUND(445501.572976911,2) -> 445501.57 | G57: $ | H57: 《收发存-入库量》 | I57: =SUMIF('附表2-EF'!$D$76:$D$84,表1温室气体盘查表!C57,'附表2-EF'!$F$76:$F$84) -> 5.8e-05 | J57: t CO2e/2022 USD, purchaser price | K57: 1 | AF57: =F57*I57*K57 -> 25.839091 | AG57: =F57*L57*N57 -> 0 | AH57: =F57*O57*Q57 -> 0 | AI57: =F57*R57*T57 -> 0 | AJ57: =F57*V57*X57 -> 0 | AK57: =F57*Z57*AB57 -> 0 | AL57: =F57*AC57*AE57 -> 0 | AM57: =SUM(AF57:AL57) -> 25.839091 | AN57: 电子计算机制造
A58: 54 | B58: 资本货物 | C58: 其他工业设备制造 | D58: 各工序 | E58: 范围三 类别2 | F58: =ROUND(2803779.73714337,2) -> 2803779.7 | G58: $ | H58: 《收发存-入库量》 | I58: =SUMIF('附表2-EF'!$D$76:$D$84,表1温室气体盘查表!C58,'附表2-EF'!$F$76:$F$84) -> 0.000185 | J58: t CO2e/2022 USD, purchaser price | K58: 1 | AF58: =F58*I58*K58 -> 518.69925 | AG58: =F58*L58*N58 -> 0 | AH58: =F58*O58*Q58 -> 0 | AI58: =F58*R58*T58 -> 0 | AJ58: =F58*V58*X58 -> 0 | AK58: =F58*Z58*AB58 -> 0 | AL58: =F58*AC58*AE58 -> 0 | AM58: =SUM(AF58:AL58) -> 518.69925 | AN58: 其他工业设备制造
A59: 55 | B59: 资本货物 | C59: 测量和测试电力和电气信号的仪器制造 | D59: 各工序 | E59: 范围三 类别2 | F59: =ROUND(2788670.78990797,2) -> 2788670.8 | G59: $ | H59: 《收发存-入库量》 | I59: =SUMIF('附表2-EF'!$D$76:$D$84,表1温室气体盘查表!C59,'附表2-EF'!$F$76:$F$84) -> 7.9e-05 | J59: t CO2e/2022 USD, purchaser price | K59: 1 | AF59: =F59*I59*K59 -> 220.30499 | AG59: =F59*L59*N59 -> 0 | AH59: =F59*O59*Q59 -> 0 | AI59: =F59*R59*T59 -> 0 | AJ59: =F59*V59*X59 -> 0 | AK59: =F59*Z59*AB59 -> 0 | AL59: =F59*AC59*AE59 -> 0 | AM59: =SUM(AF59:AL59) -> 220.30499 | AN59: 测量和测试电力和电气信号的仪器制造
A60: 56 | B60: 资本货物 | C60: 机械动力传动设备制造 | D60: 各工序 | E60: 范围三 类别2 | F60: =ROUND(5368992.60046684,2) -> 5368992.6 | G60: $ | H60: 《收发存-入库量》 | I60: =SUMIF('附表2-EF'!$D$76:$D$84,表1温室气体盘查表!C60,'附表2-EF'!$F$76:$F$84) -> 0.000209 | J60: t CO2e/2022 USD, purchaser price | K60: 1 | AF60: =F60*I60*K60 -> 1122.1195 | AG60: =F60*L60*N60 -> 0 | AH60: =F60*O60*Q60 -> 0 | AI60: =F60*R60*T60 -> 0 | AJ60: =F60*V60*X60 -> 0 | AK60: =F60*Z60*AB60 -> 0 | AL60: =F60*AC60*AE60 -> 0 | AM60: =SUM(AF60:AL60) -> 1122.1195 | AN60: 机械动力传动设备制造
A61: 57 | B61: 资本货物 | C61: 测量、分配及其他泵类设备制造 | D61: 各工序 | E61: 范围三 类别2 | F61: =ROUND(2709414.35452937,2) -> 2709414.4 | G61: $ | H61: 《收发存-入库量》 | I61: =SUMIF('附表2-EF'!$D$76:$D$84,表1温室气体盘查表!C61,'附表2-EF'!$F$76:$F$84) -> 0.000223 | J61: t CO2e/2022 USD, purchaser price | K61: 1 | AF61: =F61*I61*K61 -> 604.1994 | AG61: =F61*L61*N61 -> 0 | AH61: =F61*O61*Q61 -> 0 | AI61: =F61*R61*T61 -> 0 | AJ61: =F61*V61*X61 -> 0 | AK61: =F61*Z61*AB61 -> 0 | AL61: =F61*AC61*AE61 -> 0 | AM61: =SUM(AF61:AL61) -> 604.1994 | AN61: 测量、分配及其他泵类设备制造
A62: 58 | B62: 资本货物 | C62: 用于测量、显示和控制工业过程变量的仪器及相关产品制造 | D62: 各工序 | E62: 范围三 类别2 | F62: =ROUND(2228829.68139041,2) -> 2228829.7 | G62: $ | H62: 《收发存-入库量》 | I62: =SUMIF('附表2-EF'!$D$76:$D$84,表1温室气体盘查表!C62,'附表2-EF'!$F$76:$F$84) -> 6.3e-05 | J62: t CO2e/2022 USD, purchaser price | K62: 1 | AF62: =F62*I62*K62 -> 140.41627 | AG62: =F62*L62*N62 -> 0 | AH62: =F62*O62*Q62 -> 0 | AI62: =F62*R62*T62 -> 0 | AJ62: =F62*V62*X62 -> 0 | AK62: =F62*Z62*AB62 -> 0 | AL62: =F62*AC62*AE62 -> 0 | AM62: =SUM(AF62:AL62) -> 140.41627 | AN62: 用于测量、显示和控制工业过程变量的仪器及相关产品制造
A63: 59 | B63: 资本货物 | C63: 所有其他杂项电气设备及元件制造 | D63: 各工序 | E63: 范围三 类别2 | F63: =ROUND(8525989.88566926,2) -> 8525989.9 | G63: $ | H63: 《收发存-入库量》 | I63: =SUMIF('附表2-EF'!$D$76:$D$84,表1温室气体盘查表!C63,'附表2-EF'!$F$76:$F$84) -> 0.000128 | J63: t CO2e/2022 USD, purchaser price | K63: 1 | AF63: =F63*I63*K63 -> 1091.3267 | AG63: =F63*L63*N63 -> 0 | AH63: =F63*O63*Q63 -> 0 | AI63: =F63*R63*T63 -> 0 | AJ63: =F63*V63*X63 -> 0 | AK63: =F63*Z63*AB63 -> 0 | AL63: =F63*AC63*AE63 -> 0 | AM63: =SUM(AF63:AL63) -> 1091.3267 | AN63: 所有其他杂项电气设备及元件制造
A64: 60 | B64: 资本货物 | C64: 所有其他杂项制造 | D64: 各工序 | E64: 范围三 类别2 | F64: =ROUND(262435008.495265,2)-SUM(F56:F63) -> 2.3645162e+08 | G64: $ | H64: 《收发存-入库量》 | I64: =SUMIF('附表2-EF'!$D$76:$D$84,表1温室气体盘查表!C64,'附表2-EF'!$F$76:$F$84) -> 0.000182 | J64: t CO2e/2022 USD, purchaser price | K64: 1 | AF64: =F64*I64*K64 -> 43034.196 | AG64: =F64*L64*N64 -> 0 | AH64: =F64*O64*Q64 -> 0 | AI64: =F64*R64*T64 -> 0 | AJ64: =F64*V64*X64 -> 0 | AK64: =F64*Z64*AB64 -> 0 | AL64: =F64*AC64*AE64 -> 0 | AM64: =SUM(AF64:AL64) -> 43034.196 | AN64: 所有其他杂项制造
A65: 61 | B65: 范围一、二相关燃料和能源相关的活动产生的排放 | C65: 液化石油气生产 | D65: 冶钢宾馆 | E65: 范围三 类别3 | F65: =F6 -> 9.43 | G65: t | H65: 《2025全年液化气明细表》 | I65: =SUMIF('附表2-EF'!$D$88:$D$96,表1温室气体盘查表!C65,'附表2-EF'!$G$88:$G$96) -> 1.0062256 | J65: tCO2/t | K65: 1 | AF65: =F65*I65*K65 -> 9.4887071 | AG65: =F65*L65*N65 -> 0 | AH65: =F65*O65*Q65 -> 0 | AI65: =F65*R65*T65 -> 0 | AJ65: =F65*V65*X65 -> 0 | AK65: =F65*Z65*AB65 -> 0 | AL65: =F65*AC65*AE65 -> 0 | AM65: =SUM(AF65:AL65) -> 9.4887071 | AN65: 液化石油气生产
A66: 62 | B66: 范围一、二相关燃料和能源相关的活动产生的排放 | C66: 洗精煤生产 | D66: 焦化 | E66: 范围三 类别3 | F66: =F9 -> 2093622.8 | G66: t | H66: =H7 -> 《冶钢2025年度碳排放报表》（来源为过磅单） | I66: =SUMIF('附表2-EF'!$D$88:$D$96,表1温室气体盘查表!C66,'附表2-EF'!$G$88:$G$96) -> 0.57555 | J66: tCO2/t | K66: 1 | AF66: =F66*I66*K66 -> 1204984.6 | AG66: =F66*L66*N66 -> 0 | AH66: =F66*O66*Q66 -> 0 | AI66: =F66*R66*T66 -> 0 | AJ66: =F66*V66*X66 -> 0 | AK66: =F66*Z66*AB66 -> 0 | AL66: =F66*AC66*AE66 -> 0 | AM66: =SUM(AF66:AL66) -> 1204984.6 | AN66: 洗精煤生产
A67: 63 | B67: 范围一、二相关燃料和能源相关的活动产生的排放 | C67: 柴油生产 | D67: 各工序 | E67: 范围三 类别3 | F67: =F12 -> 1422.69 | G67: t | H67: =H8 -> 《冶钢2025年度碳排放报表》（来源为过磅单） | I67: =SUMIF('附表2-EF'!$D$88:$D$96,表1温室气体盘查表!C67,'附表2-EF'!$G$88:$G$96) -> 0.84212 | J67: tCO2/t | K67: 1 | AF67: =F67*I67*K67 -> 1198.0757 | AG67: =F67*L67*N67 -> 0 | AH67: =F67*O67*Q67 -> 0 | AI67: =F67*R67*T67 -> 0 | AJ67: =F67*V67*X67 -> 0 | AK67: =F67*Z67*AB67 -> 0 | AL67: =F67*AC67*AE67 -> 0 | AM67: =SUM(AF67:AL67) -> 1198.0757 | AN67: 柴油生产
A68: 64 | B68: 范围一、二相关燃料和能源相关的活动产生的排放 | C68: 汽油生产 | D68: 车队 | E68: 范围三 类别3 | F68: =F13 -> 47.34 | G68: t | H68: =H9 -> 《冶钢2025年度碳排放报表》（来源为过磅单） | I68: =SUMIF('附表2-EF'!$D$88:$D$96,表1温室气体盘查表!C68,'附表2-EF'!$G$88:$G$96) -> 0.98733031 | J68: tCO2/t | K68: 1 | AF68: =F68*I68*K68 -> 46.740217 | AG68: =F68*L68*N68 -> 0 | AH68: =F68*O68*Q68 -> 0 | AI68: =F68*R68*T68 -> 0 | AJ68: =F68*V68*X68 -> 0 | AK68: =F68*Z68*AB68 -> 0 | AL68: =F68*AC68*AE68 -> 0 | AM68: =SUM(AF68:AL68) -> 46.740217 | AN68: 汽油生产
A69: 65 | B69: 范围一、二相关燃料和能源相关的活动产生的排放 | C69: 焦炭生产 | D69: 烧结、高炉 | E69: 范围三 类别3 | F69: =F10 -> 221509.17 | G69: t | H69: =H10 -> 《冶钢2025年度碳排放报表》（来源为过磅单） | I69: =SUMIF('附表2-EF'!$D$88:$D$96,表1温室气体盘查表!C69,'附表2-EF'!$G$88:$G$96) -> 0.349 | J69: tCO2/t | K69: 1 | AF69: =F69*I69*K69 -> 77306.7 | AG69: =F69*L69*N69 -> 0 | AH69: =F69*O69*Q69 -> 0 | AI69: =F69*R69*T69 -> 0 | AJ69: =F69*V69*X69 -> 0 | AK69: =F69*Z69*AB69 -> 0 | AL69: =F69*AC69*AE69 -> 0 | AM69: =SUM(AF69:AL69) -> 77306.7 | AN69: 焦炭生产
A70: 66 | B70: 范围一、二相关燃料和能源相关的活动产生的排放 | C70: 烟煤生产 | D70: 高炉 | E70: 范围三 类别3 | F70: =F7 -> 323067.87 | G70: t | H70: =H7 -> 《冶钢2025年度碳排放报表》（来源为过磅单） | I70: =SUMIF('附表2-EF'!$D$88:$D$96,表1温室气体盘查表!C70,'附表2-EF'!$G$88:$G$96) -> 0.179 | J70: tCO2/t | K70: 1 | AF70: =F70*I70*K70 -> 57829.149 | AG70: =F70*L70*N70 -> 0 | AH70: =F70*O70*Q70 -> 0 | AI70: =F70*R70*T70 -> 0 | AJ70: =F70*V70*X70 -> 0 | AK70: =F70*Z70*AB70 -> 0 | AL70: =F70*AC70*AE70 -> 0 | AM70: =SUM(AF70:AL70) -> 57829.149 | AN70: 烟煤生产
A71: 67 | B71: 范围一、二相关燃料和能源相关的活动产生的排放 | C71: 无烟煤生产 | D71: 烧结、高炉 | E71: 范围三 类别3 | F71: =F8 -> 335482.33 | G71: t | H71: =H70 -> 《冶钢2025年度碳排放报表》（来源为过磅单） | I71: =SUMIF('附表2-EF'!$D$88:$D$96,表1温室气体盘查表!C71,'附表2-EF'!$G$88:$G$96) -> 0.684 | J71: tCO2/t | K71: 1 | AF71: =F71*I71*K71 -> 229469.91 | AG71: =F71*L71*N71 -> 0 | AH71: =F71*O71*Q71 -> 0 | AI71: =F71*R71*T71 -> 0 | AJ71: =F71*V71*X71 -> 0 | AK71: =F71*Z71*AB71 -> 0 | AL71: =F71*AC71*AE71 -> 0 | AM71: =SUM(AF71:AL71) -> 229469.91 | AN71: 无烟煤生产
A72: 68 | B72: 范围一、二相关燃料和能源相关的活动产生的排放 | C72: 天然气生产 | D72: 转炉、电炉、锻造、热处理 | E72: 范围三 类别3 | F72: =F5 -> 1454 | G72: 10000Nm3 | H72: =H71 -> 《冶钢2025年度碳排放报表》（来源为过磅单） | I72: =SUMIF('附表2-EF'!$D$88:$D$96,表1温室气体盘查表!C72,'附表2-EF'!$G$88:$G$96) -> 6.19 | J72: tCO2/t | K72: 1 | AF72: =F72*I72*K72 -> 9000.26 | AG72: =F72*L72*N72 -> 0 | AH72: =F72*O72*Q72 -> 0 | AI72: =F72*R72*T72 -> 0 | AJ72: =F72*V72*X72 -> 0 | AK72: =F72*Z72*AB72 -> 0 | AL72: =F72*AC72*AE72 -> 0 | AM72: =SUM(AF72:AL72) -> 9000.26 | AN72: 天然气生产
A73: 69 | B73: 范围一、二相关燃料和能源相关的活动产生的排放 | C73: 外购电力上游排放 | D73: 各工序 | E73: 范围三 类别3 | F73: =F30 -> 1966850.8 | G73: MWh | H73: 《收发存汇总表-发出量》 | I73: =SUMIF('附表2-EF'!$D$88:$D$96,表1温室气体盘查表!C73,'附表2-EF'!$G$88:$G$96) -> 0.0899 | J73: tCO2/MWh | K73: 1 | AF73: =F73*I73*K73 -> 176819.89 | AG73: =F73*L73*N73 -> 0 | AH73: =F73*O73*Q73 -> 0 | AI73: =F73*R73*T73 -> 0 | AJ73: =F73*V73*X73 -> 0 | AK73: =F73*Z73*AB73 -> 0 | AL73: =F73*AC73*AE73 -> 0 | AM73: =SUM(AF73:AL73) -> 176819.89 | AN73: 外购电力上游排放
A74: 70 | B74: 上游运输配送产生的排放 | C74: 船运 | D74: - | E74: 范围三 类别4 | F74: =ROUND(4821908726.53105,2) -> 4.8219087e+09 | G74: tkm | H74: 《原辅材料运输统计计算》 | I74: =SUMIF('附表2-EF'!$D$100:$D$102,表1温室气体盘查表!C74,'附表2-EF'!$G$100:$G$102) -> 5.1968558e-05 | J74: ='附表2-EF'!H100 -> tCO2-Eq/tkm | K74: 1 | AF74: =F74*I74*K74 -> 250587.64 | AG74: =F74*L74*N74 -> 0 | AH74: =F74*O74*Q74 -> 0 | AI74: =F74*R74*T74 -> 0 | AJ74: =F74*V74*X74 -> 0 | AK74: =F74*Z74*AB74 -> 0 | AL74: =F74*AC74*AE74 -> 0 | AM74: =SUM(AF74:AL74) -> 250587.64 | AN74: 船运
A75: 71 | B75: 上游运输配送产生的排放 | C75: 汽运 | D75: - | E75: 范围三 类别4 | F75: =ROUND(491140477.412329,2) -> 4.9114048e+08 | G75: tkm | H75: 《原辅材料运输统计计算》 | I75: =SUMIF('附表2-EF'!$D$100:$D$102,表1温室气体盘查表!C75,'附表2-EF'!$G$100:$G$102) -> 0.00015196288 | J75: ='附表2-EF'!H101 -> tCO2-Eq/tkm | K75: 1 | AF75: =F75*I75*K75 -> 74635.121 | AG75: =F75*L75*N75 -> 0 | AH75: =F75*O75*Q75 -> 0 | AI75: =F75*R75*T75 -> 0 | AJ75: =F75*V75*X75 -> 0 | AK75: =F75*Z75*AB75 -> 0 | AL75: =F75*AC75*AE75 -> 0 | AM75: =SUM(AF75:AL75) -> 74635.121 | AN75: 汽运
A76: 72 | B76: 上游运输配送产生的排放 | C76: 铁路运输 | D76: - | E76: 范围三 类别4 | F76: =ROUND(1555767247.09744,2) -> 1.5557672e+09 | G76: tkm | H76: 《原辅材料运输统计计算》 | I76: =SUMIF('附表2-EF'!$D$100:$D$102,表1温室气体盘查表!C76,'附表2-EF'!$G$100:$G$102) -> 4.8531851e-05 | J76: ='附表2-EF'!H102 -> tCO2-Eq/tkm | K76: 1 | AF76: =F76*I76*K76 -> 75504.264 | AG76: =F76*L76*N76 -> 0 | AH76: =F76*O76*Q76 -> 0 | AI76: =F76*R76*T76 -> 0 | AJ76: =F76*V76*X76 -> 0 | AK76: =F76*Z76*AB76 -> 0 | AL76: =F76*AC76*AE76 -> 0 | AM76: =SUM(AF76:AL76) -> 75504.264 | AN76: 铁路运输
A77: 73 | B77: 运营中产生的废物排放 | C77: 生活垃圾和厨余垃圾 | D77: 垃圾站 | E77: 范围三 类别5 | F77: =ROUND(2538.02+263.38,2) -> 2801.4 | G77: t | H77: 《生活、厨余垃圾统计表》 | I77: =SUMIF('附表2-EF'!$D$106:$D$108,表1温室气体盘查表!C77,'附表2-EF'!$G$106:$G$108) -> 0.3713343 | J77: tCO2/t | K77: 1 | AF77: =F77*I77*K77 -> 1040.2559 | AG77: =F77*L77*N77 -> 0 | AH77: =F77*O77*Q77 -> 0 | AI77: =F77*R77*T77 -> 0 | AJ77: =F77*V77*X77 -> 0 | AK77: =F77*Z77*AB77 -> 0 | AL77: =F77*AC77*AE77 -> 0 | AM77: =SUM(AF77:AL77) -> 1040.2559 | AN77: 生活垃圾和厨余垃圾
A78: 74 | B78: 运营中产生的废物排放 | C78: 废油 | D78: - | E78: 范围三 类别5 | F78: =ROUND(1719.049,2) -> 1719.05 | G78: t | H78: 《2025环保指标统计》 | I78: =SUMIF('附表2-EF'!$D$106:$D$108,表1温室气体盘查表!C78,'附表2-EF'!$G$106:$G$108) -> 2.849057 | J78: tCO2/t | K78: 1 | AF78: =F78*I78*K78 -> 4897.6715 | AG78: =F78*L78*N78 -> 0 | AH78: =F78*O78*Q78 -> 0 | AI78: =F78*R78*T78 -> 0 | AJ78: =F78*V78*X78 -> 0 | AK78: =F78*Z78*AB78 -> 0 | AL78: =F78*AC78*AE78 -> 0 | AM78: =SUM(AF78:AL78) -> 4897.6715 | AN78: 废油
A79: 75 | B79: 运营中产生的废物排放 | C79: 废油水 | D79: - | E79: 范围三 类别5 | F79: =ROUND(5203.2956,2) -> 5203.3 | G79: t | H79: 《2025环保指标统计》 | I79: =SUMIF('附表2-EF'!$D$106:$D$108,表1温室气体盘查表!C79,'附表2-EF'!$G$106:$G$108) -> 2.849057 | J79: tCO2/t | K79: 1 | AF79: =F79*I79*K79 -> 14824.498 | AG79: =F79*L79*N79 -> 0 | AH79: =F79*O79*Q79 -> 0 | AI79: =F79*R79*T79 -> 0 | AJ79: =F79*V79*X79 -> 0 | AK79: =F79*Z79*AB79 -> 0 | AL79: =F79*AC79*AE79 -> 0 | AM79: =SUM(AF79:AL79) -> 14824.498 | AN79: 废油水
A80: 76 | B80: 运营中产生的废物排放 | C80: 废弃物运输 | D80: - | E80: 范围三 类别5 | F80: =ROUND(F78*319+F79*319+53786.88+64791153.002,2) -> 67053170 | G80: tkm | H80: 《危险废物转移联单》 | I80: ='附表2-EF'!G101 -> 0.00015196288 | J80: ='附表2-EF'!H93 -> tCO2/t | K80: 1 | AF80: =F80*I80*K80 -> 10189.593 | AG80: =F80*L80*N80 -> 0 | AH80: =F80*O80*Q80 -> 0 | AI80: =F80*R80*T80 -> 0 | AJ80: =F80*V80*X80 -> 0 | AK80: =F80*Z80*AB80 -> 0 | AL80: =F80*AC80*AE80 -> 0 | AM80: =SUM(AF80:AL80) -> 10189.593 | AN80: 废弃物运输
A81: 77 | B81: 商务旅行产生的排放 | C81: 航运 | D81: - | E81: 范围三 类别6 | F81: =ROUND(3709585,2) -> 3709585 | G81: passenger*km | H81: 《公司差旅情况》 | I81: =SUMIF('附表2-EF'!$D$112:$D$114,表1温室气体盘查表!C81,'附表2-EF'!$G$112:$G$114) -> 0.084 | J81: ='附表2-EF'!H112 -> kgCO2/passenger*km | K81: 1 | AF81: =F81*I81*K81/1000 -> 311.60514 | AG81: =F81*L81*N81 -> 0 | AH81: =F81*O81*Q81 -> 0 | AI81: =F81*R81*T81 -> 0 | AJ81: =F81*V81*X81 -> 0 | AK81: =F81*Z81*AB81 -> 0 | AL81: =F81*AC81*AE81 -> 0 | AM81: =SUM(AF81:AL81) -> 311.60514 | AN81: 航运
A82: 78 | B82: 商务旅行产生的排放 | C82: 铁路运输 | D82: - | E82: 范围三 类别6 | F82: =ROUND(9687112,2) -> 9687112 | G82: passenger*km | H82: 《公司差旅情况》 | I82: =SUMIF('附表2-EF'!$D$112:$D$114,表1温室气体盘查表!C82,'附表2-EF'!$G$112:$G$114) -> 0.074873544 | J82: ='附表2-EF'!H113 -> kgCO2/passenger*km | K82: 1 | AF82: =F82*I82*K82/1000 -> 725.30841 | AG82: =F82*L82*N82 -> 0 | AH82: =F82*O82*Q82 -> 0 | AI82: =F82*R82*T82 -> 0 | AJ82: =F82*V82*X82 -> 0 | AK82: =F82*Z82*AB82 -> 0 | AL82: =F82*AC82*AE82 -> 0 | AM82: =SUM(AF82:AL82) -> 725.30841 | AN82: 铁路运输
A83: 79 | B83: 商务旅行产生的排放 | C83: 员工差旅住宿 | D83: - | E83: 范围三 类别6 | F83: =14352 -> 14352 | G83: 总间*晚 | H83: 《公司差旅情况》 | I83: =SUMIF('附表2-EF'!$D$112:$D$114,表1温室气体盘查表!C83,'附表2-EF'!$G$112:$G$114) -> 0.0535 | J83: tCO2/间*晚 | K83: 1 | AF83: =F83*I83*K83 -> 767.832 | AG83: =F83*L83*N83 -> 0 | AH83: =F83*O83*Q83 -> 0 | AI83: =F83*R83*T83 -> 0 | AJ83: =F83*V83*X83 -> 0 | AK83: =F83*Z83*AB83 -> 0 | AL83: =F83*AC83*AE83 -> 0 | AM83: =SUM(AF83:AL83) -> 767.832 | AN83: 员工差旅住宿
A84: 80 | B84: 员工通勤产生的排放 | C84: 通勤车 | D84: - | E84: 范围三 类别7 | F84: 6808531.3 | G84: passenger*km | H84: 《员工通勤情况统计》 | I84: =SUMIF('附表2-EF'!$D$118:$D$122,表1温室气体盘查表!C84,'附表2-EF'!$G$118:$G$122) -> 0.0088 | J84: ='附表2-EF'!H118 -> kgCO2/passenger*km | K84: 1 | AF84: =F84*I84*K84/1000 -> 59.915075 | AG84: =F84*L84*N84 -> 0 | AH84: =F84*O84*Q84 -> 0 | AI84: =F84*R84*T84 -> 0 | AJ84: =F84*V84*X84 -> 0 | AK84: =F84*Z84*AB84 -> 0 | AL84: =F84*AC84*AE84 -> 0 | AM84: =SUM(AF84:AL84) -> 59.915075 | AN84: 通勤车
A85: 81 | B85: 员工通勤产生的排放 | C85: 电力公交 | D85: - | E85: 范围三 类别7 | F85: 316087.41 | G85: passenger*km | H85: 《员工通勤情况统计》 | I85: =SUMIF('附表2-EF'!$D$118:$D$122,表1温室气体盘查表!C85,'附表2-EF'!$G$118:$G$122) -> 0.0088 | J85: ='附表2-EF'!H120 -> kgCO2/passenger*km | K85: 1 | AF85: =F85*I85*K85/1000 -> 2.7815692 | AG85: =F85*L85*N85 -> 0 | AH85: =F85*O85*Q85 -> 0 | AI85: =F85*R85*T85 -> 0 | AJ85: =F85*V85*X85 -> 0 | AK85: =F85*Z85*AB85 -> 0 | AL85: =F85*AC85*AE85 -> 0 | AM85: =SUM(AF85:AL85) -> 2.7815692 | AN85: 电力公交
A86: 82 | B86: 员工通勤产生的排放 | C86: 电瓶车 | D86: - | E86: 范围三 类别7 | F86: 10595750 | G86: passenger*km | H86: 《员工通勤情况统计》 | I86: =SUMIF('附表2-EF'!$D$118:$D$122,表1温室气体盘查表!C86,'附表2-EF'!$G$118:$G$122) -> 0.02702026 | J86: ='附表2-EF'!H120 -> kgCO2/passenger*km | K86: 1 | AF86: =F86*I86*K86/1000 -> 286.29993 | AG86: =F86*L86*N86 -> 0 | AH86: =F86*O86*Q86 -> 0 | AI86: =F86*R86*T86 -> 0 | AJ86: =F86*V86*X86 -> 0 | AK86: =F86*Z86*AB86 -> 0 | AL86: =F86*AC86*AE86 -> 0 | AM86: =SUM(AF86:AL86) -> 286.29993 | AN86: 电动车
A87: 83 | B87: 员工通勤产生的排放 | C87: 自驾油车 | D87: - | E87: 范围三 类别7 | F87: 12199616 | G87: km | H87: 《员工通勤情况统计》 | I87: =SUMIF('附表2-EF'!$D$118:$D$122,表1温室气体盘查表!C87,'附表2-EF'!$G$118:$G$122) -> 0.37142762 | J87: ='附表2-EF'!H121 -> kgCO2/km | K87: 1 | AF87: =F87*I87*K87/1000 -> 4531.2743 | AG87: =F87*L87*N87 -> 0 | AH87: =F87*O87*Q87 -> 0 | AI87: =F87*R87*T87 -> 0 | AJ87: =F87*V87*X87 -> 0 | AK87: =F87*Z87*AB87 -> 0 | AL87: =F87*AC87*AE87 -> 0 | AM87: =SUM(AF87:AL87) -> 4531.2743 | AN87: 自驾油车
A88: 84 | B88: 员工通勤产生的排放 | C88: 自驾电车 | D88: - | E88: 范围三 类别7 | F88: 1527084.8 | G88: km | H88: 《员工通勤情况统计》 | I88: =SUMIF('附表2-EF'!$D$118:$D$122,表1温室气体盘查表!C88,'附表2-EF'!$G$118:$G$122) -> 0.37142762 | J88: ='附表2-EF'!H122 -> kgCO2/km | K88: 1 | AF88: =F88*I88*K88/1000 -> 567.20147 | AG88: =F88*L88*N88 -> 0 | AH88: =F88*O88*Q88 -> 0 | AI88: =F88*R88*T88 -> 0 | AJ88: =F88*V88*X88 -> 0 | AK88: =F88*Z88*AB88 -> 0 | AL88: =F88*AC88*AE88 -> 0 | AM88: =SUM(AF88:AL88) -> 567.20147 | AN88: 自驾电车
A89: 85 | B89: 下游运输配送产生的排放 | C89: 船运 | D89: - | E89: 范围三 类别9 | F89: =ROUND(965477841.624788,2) -> 9.6547784e+08 | G89: tkm | H89: 《附表3：冶钢2025PCF补充数据表》 | I89: =SUMIF('附表2-EF'!$D$100:$D$102,表1温室气体盘查表!C89,'附表2-EF'!$G$100:$G$102) -> 5.1968558e-05 | J89: ='附表2-EF'!H100 -> tCO2-Eq/tkm | K89: 1 | AF89: =F89*I89*K89 -> 50174.491 | AG89: =F89*L89*N89 -> 0 | AH89: =F89*O89*Q89 -> 0 | AI89: =F89*R89*T89 -> 0 | AJ89: =F89*V89*X89 -> 0 | AK89: =F89*Z89*AB89 -> 0 | AL89: =F89*AC89*AE89 -> 0 | AM89: =SUM(AF89:AL89) -> 50174.491 | AN89: 船运
A90: 86 | B90: 下游运输配送产生的排放 | C90: 汽运 | D90: - | E90: 范围三 类别9 | F90: =ROUND(1366758643.75253,2) -> 1.3667586e+09 | G90: tkm | H90: 《附表3：冶钢2025PCF补充数据表》 | I90: =SUMIF('附表2-EF'!$D$100:$D$102,表1温室气体盘查表!C90,'附表2-EF'!$G$100:$G$102) -> 0.00015196288 | J90: ='附表2-EF'!H101 -> tCO2-Eq/tkm | K90: 1 | AF90: =F90*I90*K90 -> 207696.58 | AG90: =F90*L90*N90 -> 0 | AH90: =F90*O90*Q90 -> 0 | AI90: =F90*R90*T90 -> 0 | AJ90: =F90*V90*X90 -> 0 | AK90: =F90*Z90*AB90 -> 0 | AL90: =F90*AC90*AE90 -> 0 | AM90: =SUM(AF90:AL90) -> 207696.58 | AN90: 汽运
A91: 87 | B91: 下游运输配送产生的排放 | C91: 铁路运输 | D91: - | E91: 范围三 类别9 | F91: =ROUND(343519032.619048,2) -> 3.4351903e+08 | G91: tkm | H91: 《附表3：冶钢2025PCF补充数据表》 | I91: =SUMIF('附表2-EF'!$D$100:$D$102,表1温室气体盘查表!C91,'附表2-EF'!$G$100:$G$102) -> 4.8531851e-05 | J91: ='附表2-EF'!H102 -> tCO2-Eq/tkm | K91: 1 | AF91: =F91*I91*K91 -> 16671.614 | AG91: =F91*L91*N91 -> 0 | AH91: =F91*O91*Q91 -> 0 | AI91: =F91*R91*T91 -> 0 | AJ91: =F91*V91*X91 -> 0 | AK91: =F91*Z91*AB91 -> 0 | AL91: =F91*AC91*AE91 -> 0 | AM91: =SUM(AF91:AL91) -> 16671.614 | AN91: 铁路运输
A92: 88 | B92: 下游运输配送产生的排放 | C92: 汽运-副产品 | D92: - | E92: 范围三 类别9 | F92: =ROUND(22869284.996+16009263+4152064.404,2) -> 43030612 | G92: tkm | H92: 《汽车衡净计量实绩_焦油》《粗苯外销明细表》 | I92: ='附表2-EF'!G101 -> 0.00015196288 | J92: ='附表2-EF'!H101 -> tCO2-Eq/tkm | K92: 1 | AF92: =F92*I92*K92 -> 6539.0557 | AG92: =F92*L92*N92 -> 0 | AH92: =F92*O92*Q92 -> 0 | AI92: =F92*R92*T92 -> 0 | AJ92: =F92*V92*X92 -> 0 | AK92: =F92*Z92*AB92 -> 0 | AL92: =F92*AC92*AE92 -> 0 | AM92: =SUM(AF92:AL92) -> 6539.0557 | AN92: 汽运-副产品
A93: 89 | B93: 外销产品加工产生的排放 | C93: 锻材加工 | D93: 下游钢铁厂 | E93: 范围三 类别10 | F93: =ROUND(172270,2) -> 172270 | G93: t | H93: 《附表3：冶钢2025PCF补充数据表》 | I93: =SUMIF('附表2-EF'!$D$126:$D$129,表1温室气体盘查表!C93,'附表2-EF'!$F$126:$F$129) -> 0.78558815 | J93: ='附表2-EF'!G126 -> kgCO2/kg | K93: 1 | AF93: =F93*I93*K93 -> 135333.27 | AG93: =F93*L93*N93 -> 0 | AH93: =F93*O93*Q93 -> 0 | AI93: =F93*R93*T93 -> 0 | AJ93: =F93*V93*X93 -> 0 | AK93: =F93*Z93*AB93 -> 0 | AL93: =F93*AC93*AE93 -> 0 | AM93: =SUM(AF93:AL93) -> 135333.27 | AN93: 锻材加工
A94: 90 | B94: 外销产品加工产生的排放 | C94: 棒材加工 | D94: 下游钢铁厂 | E94: 范围三 类别10 | F94: =ROUND(2063196.544,2) -> 2063196.5 | G94: t | H94: 《附表3：冶钢2025PCF补充数据表》 | I94: =SUMIF('附表2-EF'!$D$126:$D$129,表1温室气体盘查表!C94,'附表2-EF'!$F$126:$F$129) -> 1.0059729 | J94: ='附表2-EF'!G127 -> kgCO2/kg | K94: 1 | AF94: =F94*I94*K94 -> 2075519.7 | AG94: =F94*L94*N94 -> 0 | AH94: =F94*O94*Q94 -> 0 | AI94: =F94*R94*T94 -> 0 | AJ94: =F94*V94*X94 -> 0 | AK94: =F94*Z94*AB94 -> 0 | AL94: =F94*AC94*AE94 -> 0 | AM94: =SUM(AF94:AL94) -> 2075519.7 | AN94: 棒材加工
A95: 91 | B95: 外销产品加工产生的排放 | C95: 钢管加工 | D95: 下游钢铁厂 | E95: 范围三 类别10 | F95: =ROUND(649008.657349997,2) -> 649008.66 | G95: t | H95: 《附表3：冶钢2025PCF补充数据表》 | I95: =SUMIF('附表2-EF'!$D$126:$D$129,表1温室气体盘查表!C95,'附表2-EF'!$F$126:$F$129) -> 0.095451263 | J95: ='附表2-EF'!G128 -> kgCO2/kg | K95: 1 | AF95: =F95*I95*K95 -> 61948.696 | AG95: =F95*L95*N95 -> 0 | AH95: =F95*O95*Q95 -> 0 | AI95: =F95*R95*T95 -> 0 | AJ95: =F95*V95*X95 -> 0 | AK95: =F95*Z95*AB95 -> 0 | AL95: =F95*AC95*AE95 -> 0 | AM95: =SUM(AF95:AL95) -> 61948.696 | AN95: 钢管加工
A96: 92 | B96: 外销产品加工产生的排放 | C96: 钢坯加工 | D96: 下游钢铁厂 | E96: 范围三 类别10 | F96: =ROUND(608494.197000002,2) -> 608494.2 | G96: t | H96: 《附表3：冶钢2025PCF补充数据表》 | I96: =SUMIF('附表2-EF'!$D$126:$D$129,表1温室气体盘查表!C96,'附表2-EF'!$F$126:$F$129) -> 0.29021018 | J96: ='附表2-EF'!G128 -> kgCO2/kg | K96: 1 | AF96: =F96*I96*K96 -> 176591.21 | AG96: =F96*L96*N96 -> 0 | AH96: =F96*O96*Q96 -> 0 | AI96: =F96*R96*T96 -> 0 | AJ96: =F96*V96*X96 -> 0 | AK96: =F96*Z96*AB96 -> 0 | AL96: =F96*AC96*AE96 -> 0 | AM96: =SUM(AF96:AL96) -> 176591.21 | AN96: 钢坯加工
A97: 93 | B97: 外销产品使用产生的排放 | C97: 外售焦炉煤气燃烧 | D97: 下游钢铁厂 | E97: 范围三 类别11 | F97: =ROUND(7887272.44/10000,2) -> 788.73 | G97: 10000Nm3 | H97: 《2025年冶钢能源介质平衡表》 | I97: ='附表2-EF'!L13 -> 7.6419264 | J97: tCO2/10000Nm3 | K97: 1 | L97: ='附表2-EF'!M13 -> 0.00017211546 | N97: ='附表1-GWP TABLE'!E4 -> 27.9 | O97: ='附表2-EF'!N13 -> 1.7211546e-05 | Q97: ='附表1-GWP TABLE'!E5 -> 273 | AF97: =F97*I97*K97 -> 6027.4166 | AG97: =F97*L97*N97 -> 3.7874983 | AH97: =F97*O97*Q97 -> 3.7060467 | AI97: =F97*R97*T97 -> 0 | AJ97: =F97*V97*X97 -> 0 | AK97: =F97*Z97*AB97 -> 0 | AL97: =F97*AC97*AE97 -> 0 | AM97: =SUM(AF97:AL97) -> 6034.9102 | AN97: 外售焦炉煤气燃烧
A98: 94 | B98: 外售产品报废产生的排放 | C98: 产品报废 | D98: 下游钢铁厂 | E98: 范围三 类别12 | F98: =ROUND(SUM(F93:F96)*(2.56-2.14)/2.56,2) -> 573065.29 | G98: t | H98: 《附表3：冶钢2025PCF补充数据表》 | I98: ='附表2-EF'!G140 -> 0.0062630124 | J98: ='附表2-EF'!H140 -> kgCO2/kg | K98: 1 | AF98: =F98*I98*K98 -> 3589.115 | AG98: =F98*L98*N98 -> 0 | AH98: =F98*O98*Q98 -> 0 | AI98: =F98*R98*T98 -> 0 | AJ98: =F98*V98*X98 -> 0 | AK98: =F98*Z98*AB98 -> 0 | AL98: =F98*AC98*AE98 -> 0 | AM98: =SUM(AF98:AL98) -> 3589.115 | AN98: 产品报废
A99: 备注 | B99: R600、R600a、R290、环戊烷、R22、R33、R35不在盘查范围内 | E99: 无需纳入计算 | AD99: 合计（位置法） | AF99: =SUM(AF5:AF30,AF32:AF98) -> 15337417 | AG99: =SUM(AG5:AG30,AG32:AG98) -> 10689.762 | AH99: =SUM(AH5:AH30,AH32:AH98) -> 31508.551 | AI99: =SUM(AI5:AI30,AI32:AI98) -> 570.54 | AJ99: =SUM(AJ5:AJ30,AJ32:AJ98) -> 0 | AK99: =SUM(AK5:AK30,AK32:AK98) -> 0 | AL99: =SUM(AL5:AL30,AL32:AL98) -> 0 | AM99: =SUM(AM5:AM30,AM32:AM98) -> 15380185
B100: R142、R142b、R12属于淘汰制冷剂，不盘查 | E100: 无需纳入计算 | AD100: 合计（市场法） | AF100: =SUM(AF5:AF29,AF31:AF98) -> 15480606 | AG100: =SUM(AG5:AG29,AG31:AG98) -> 10689.762 | AH100: =SUM(AH5:AH29,AH31:AH98) -> 31508.551 | AI100: =SUM(AI5:AI29,AI31:AI98) -> 570.54 | AJ100: =SUM(AJ5:AJ29,AJ31:AJ98) -> 0 | AK100: =SUM(AK5:AK29,AK31:AK98) -> 0 | AL100: =SUM(AL5:AL29,AL31:AL98) -> 0 | AM100: =SUM(AM5:AM29,AM31:AM98) -> 15523375
...

Sheet 表2.1不确定性评估——基于位置
A1: 不确定性评估表
A2: 编号 | B2: 排放源 | C2: 设施 | D2: 活动数据类别 | E2: 排放因子类别 | F2: 校准频率 | G2: 活动数据级别 | H2: 排放因子级别 | I2: 校准级别 | J2: 平均得分 | K2: 排放量(tCO2e) | L2: 排放量占比 | M2: 加权平均积分
A3: 1 | B3: =表1温室气体盘查表!C5 -> 天然气燃烧 | C3: =表1温室气体盘查表!D5 -> 热处理炉（加热炉） | D3: 自动连续量测 | E3: 国际排放因子 | F3: 校准且合格 | G3: =IF(D3="自动连续量测",6,IF(D3="定期量测/抄表/铭牌",3,1)) -> 6 | H3: =IF(E3="量测/质量平衡排放因子",6,IF(E3="制程/设备排放因子",5,IF(E3="制造商提供的排放因子",4,IF(E3="区域排放因子",3,IF(E3="国家排放因子",2,1))))) -> 1 | I3: =IF(F3="校准且合格",6,IF(F3="未校准",1,3)) -> 6 | J3: =AVERAGE(G3:I3) -> 4.3333333 | K3: =表1温室气体盘查表!AM5 -> 31469.159 | L3: =K3/$K$96 -> 0.0020460845 | M3: =J3*L3 -> 0.0088663662
A4: 2 | B4: =表1温室气体盘查表!C6 -> 液化石油气燃烧 | C4: =表1温室气体盘查表!D6 -> 冶钢宾馆 | D4: 定期量测/抄表/铭牌 | E4: 国际排放因子 | F4: 校准且合格 | G4: =IF(D4="自动连续量测",6,IF(D4="定期量测/抄表/铭牌",3,1)) -> 3 | H4: =IF(E4="量测/质量平衡排放因子",6,IF(E4="制程/设备排放因子",5,IF(E4="制造商提供的排放因子",4,IF(E4="区域排放因子",3,IF(E4="国家排放因子",2,1))))) -> 1 | I4: =IF(F4="校准且合格",6,IF(F4="未校准",1,3)) -> 6 | J4: =AVERAGE(G4:I4) -> 3.3333333 | K4: =表1温室气体盘查表!AM6 -> 29.286595 | L4: =K4/$K$96 -> 1.904177e-06 | M4: =J4*L4 -> 6.3472566e-06
A5: 3 | B5: =表1温室气体盘查表!C7 -> 烟煤燃烧 | C5: =表1温室气体盘查表!D7 -> 高炉 | D5: 自动连续量测 | E5: 国际排放因子 | F5: 校准且合格 | G5: =IF(D5="自动连续量测",6,IF(D5="定期量测/抄表/铭牌",3,1)) -> 6 | H5: =IF(E5="量测/质量平衡排放因子",6,IF(E5="制程/设备排放因子",5,IF(E5="制造商提供的排放因子",4,IF(E5="区域排放因子",3,IF(E5="国家排放因子",2,1))))) -> 1 | I5: =IF(F5="校准且合格",6,IF(F5="未校准",1,3)) -> 6 | J5: =AVERAGE(G5:I5) -> 4.3333333 | K5: =表1温室气体盘查表!AM7 -> 749580.33 | L5: =K5/$K$96 -> 0.048736755 | M5: =J5*L5 -> 0.21119261
A6: 4 | B6: =表1温室气体盘查表!C8 -> 无烟煤燃烧 | C6: =表1温室气体盘查表!D8 -> 高炉、烧结 | D6: 自动连续量测 | E6: 国际排放因子 | F6: 校准且合格 | G6: =IF(D6="自动连续量测",6,IF(D6="定期量测/抄表/铭牌",3,1)) -> 6 | H6: =IF(E6="量测/质量平衡排放因子",6,IF(E6="制程/设备排放因子",5,IF(E6="制造商提供的排放因子",4,IF(E6="区域排放因子",3,IF(E6="国家排放因子",2,1))))) -> 1 | I6: =IF(F6="校准且合格",6,IF(F6="未校准",1,3)) -> 6 | J6: =AVERAGE(G6:I6) -> 4.3333333 | K6: =表1温室气体盘查表!AM8 -> 820622.2 | L6: =K6/$K$96 -> 0.053355807 | M6: =J6*L6 -> 0.2312085
A7: 5 | B7: =表1温室气体盘查表!C9 -> 洗精煤燃烧 | C7: =表1温室气体盘查表!D9 -> 焦炉 | D7: 自动连续量测 | E7: 国际排放因子 | F7: 校准且合格 | G7: =IF(D7="自动连续量测",6,IF(D7="定期量测/抄表/铭牌",3,1)) -> 6 | H7: =IF(E7="量测/质量平衡排放因子",6,IF(E7="制程/设备排放因子",5,IF(E7="制造商提供的排放因子",4,IF(E7="区域排放因子",3,IF(E7="国家排放因子",2,1))))) -> 1 | I7: =IF(F7="校准且合格",6,IF(F7="未校准",1,3)) -> 6 | J7: =AVERAGE(G7:I7) -> 4.3333333 | K7: =表1温室气体盘查表!AM9 -> 5189313.3 | L7: =K7/$K$96 -> 0.33740252 | M7: =J7*L7 -> 1.4620776
A8: 6 | B8: =表1温室气体盘查表!C10 -> 焦炭燃烧 | C8: =表1温室气体盘查表!D10 -> 高炉 | D8: 自动连续量测 | E8: 国际排放因子 | F8: 校准且合格 | G8: =IF(D8="自动连续量测",6,IF(D8="定期量测/抄表/铭牌",3,1)) -> 6 | H8: =IF(E8="量测/质量平衡排放因子",6,IF(E8="制程/设备排放因子",5,IF(E8="制造商提供的排放因子",4,IF(E8="区域排放因子",3,IF(E8="国家排放因子",2,1))))) -> 1 | I8: =IF(F8="校准且合格",6,IF(F8="未校准",1,3)) -> 6 | J8: =AVERAGE(G8:I8) -> 4.3333333 | K8: =表1温室气体盘查表!AM10 -> 669939.56 | L8: =K8/$K$96 -> 0.043558614 | M8: =J8*L8 -> 0.18875399
A9: 7 | B9: =表1温室气体盘查表!C11 -> 焦炉煤气燃烧 | C9: =表1温室气体盘查表!D11 -> 外售 | D9: 自动连续量测 | E9: 国际排放因子 | F9: 校准且合格 | G9: =IF(D9="自动连续量测",6,IF(D9="定期量测/抄表/铭牌",3,1)) -> 6 | H9: =IF(E9="量测/质量平衡排放因子",6,IF(E9="制程/设备排放因子",5,IF(E9="制造商提供的排放因子",4,IF(E9="区域排放因子",3,IF(E9="国家排放因子",2,1))))) -> 1 | I9: =IF(F9="校准且合格",6,IF(F9="未校准",1,3)) -> 6 | J9: =AVERAGE(G9:I9) -> 4.3333333 | K9: =表1温室气体盘查表!AM11 -> -6034.9102 | L9: =K9/$K$96 -> -0.00039238215 | M9: =J9*L9 -> -0.0017003226
A10: 8 | B10: =表1温室气体盘查表!C12 -> 柴油燃烧 | C10: =表1温室气体盘查表!D12 -> 场内运输 | D10: 定期量测/抄表/铭牌 | E10: 国际排放因子 | F10: 校准但不合格/未校准但数据可查证 | G10: =IF(D10="自动连续量测",6,IF(D10="定期量测/抄表/铭牌",3,1)) -> 3 | H10: =IF(E10="量测/质量平衡排放因子",6,IF(E10="制程/设备排放因子",5,IF(E10="制造商提供的排放因子",4,IF(E10="区域排放因子",3,IF(E10="国家排放因子",2,1))))) -> 1 | I10: =IF(F10="校准且合格",6,IF(F10="未校准",1,3)) -> 3 | J10: =AVERAGE(G10:I10) -> 2.3333333 | K10: =表1温室气体盘查表!AM12 -> 4476.287 | L10: =K10/$K$96 -> 0.00029104246 | M10: =J10*L10 -> 0.00067909907
A11: 9 | B11: =表1温室气体盘查表!C13 -> 汽油燃烧 | C11: =表1温室气体盘查表!D13 -> 公务车 | D11: 定期量测/抄表/铭牌 | E11: 国际排放因子 | F11: 校准但不合格/未校准但数据可查证 | G11: =IF(D11="自动连续量测",6,IF(D11="定期量测/抄表/铭牌",3,1)) -> 3 | H11: =IF(E11="量测/质量平衡排放因子",6,IF(E11="制程/设备排放因子",5,IF(E11="制造商提供的排放因子",4,IF(E11="区域排放因子",3,IF(E11="国家排放因子",2,1))))) -> 1 | I11: =IF(F11="校准且合格",6,IF(F11="未校准",1,3)) -> 3 | J11: =AVERAGE(G11:I11) -> 2.3333333 | K11: =表1温室气体盘查表!AM13 -> 144.22983 | L11: =K11/$K$96 -> 9.3776394e-06 | M11: =J11*L11 -> 2.1881159e-05
A12: 10 | B12: =表1温室气体盘查表!C14 -> 制冷剂逸散（R32） | C12: =表1温室气体盘查表!D14 -> 分体式空调 | D12: 定期量测/抄表/铭牌 | E12: 国家排放因子 | F12: 校准且合格 | G12: =IF(D12="自动连续量测",6,IF(D12="定期量测/抄表/铭牌",3,1)) -> 3 | H12: =IF(E12="量测/质量平衡排放因子",6,IF(E12="制程/设备排放因子",5,IF(E12="制造商提供的排放因子",4,IF(E12="区域排放因子",3,IF(E12="国家排放因子",2,1))))) -> 2 | I12: =IF(F12="校准且合格",6,IF(F12="未校准",1,3)) -> 6 | J12: =AVERAGE(G12:I12) -> 3.6666667 | K12: =表1温室气体盘查表!AM14 -> 570.54 | L12: =K12/$K$96 -> 3.7095781e-05 | M12: =J12*L12 -> 0.00013601787
A13: 11 | B13: =表1温室气体盘查表!C15 -> CO2逸散 | C13: =表1温室气体盘查表!D15 -> 二氧化碳灭火器 | D13: 定期量测/抄表/铭牌 | E13: 国家排放因子 | F13: 校准且合格 | G13: =IF(D13="自动连续量测",6,IF(D13="定期量测/抄表/铭牌",3,1)) -> 3 | H13: =IF(E13="量测/质量平衡排放因子",6,IF(E13="制程/设备排放因子",5,IF(E13="制造商提供的排放因子",4,IF(E13="区域排放因子",3,IF(E13="国家排放因子",2,1))))) -> 2 | I13: =IF(F13="校准且合格",6,IF(F13="未校准",1,3)) -> 6 | J13: =AVERAGE(G13:I13) -> 3.6666667 | K13: =表1温室气体盘查表!AM15 -> 0.56 | L13: =K13/$K$96 -> 3.6410484e-08 | M13: =J13*L13 -> 1.3350511e-07
A14: 12 | B14: =表1温室气体盘查表!C16 -> CH4逸散 | C14: =表1温室气体盘查表!D16 -> 化粪池 | D14: 定期量测/抄表/铭牌 | E14: 国际排放因子 | F14: 校准且合格 | G14: =IF(D14="自动连续量测",6,IF(D14="定期量测/抄表/铭牌",3,1)) -> 3 | H14: =IF(E14="量测/质量平衡排放因子",6,IF(E14="制程/设备排放因子",5,IF(E14="制造商提供的排放因子",4,IF(E14="区域排放因子",3,IF(E14="国家排放因子",2,1))))) -> 1 | I14: =IF(F14="校准且合格",6,IF(F14="未校准",1,3)) -> 6 | J14: =AVERAGE(G14:I14) -> 3.3333333 | K14: =表1温室气体盘查表!AM16 -> 116.30952 | L14: =K14/$K$96 -> 7.5622963e-06 | M14: =J14*L14 -> 2.5207654e-05
... A28: 26 | B28: =表1温室气体盘查表!C30 -> 外购电力（基于位置） | C28: =表1温室气体盘查表!D30 -> 用电设备 | D28: 自动连续量测 | E28: 国家排放因子 | F28: 校准且合格 | G28: =IF(D28="自动连续量测",6,IF(D28="定期量测/抄表/铭牌",3,1)) -> 6 | H28: =IF(E28="量测/质量平衡排放因子",6,IF(E28="制程/设备排放因子",5,IF(E28="制造商提供的排放因子",4,IF(E28="区域排放因子",3,IF(E28="国家排放因子",2,1))))) -> 2 | I28: =IF(F28="校准且合格",6,IF(F28="未校准",1,3)) -> 6 | J28: =AVERAGE(G28:I28) -> 4.6666667 | K28: =表1温室气体盘查表!AM30 -> 1043611.1 | L28: =K28/$K$96 -> 0.067854256 | M28: =J28*L28 -> 0.3166532
A29: 27 | B29: =表1温室气体盘查表!C32 -> 铁矿石生产 | C29: =表1温室气体盘查表!D32 -> 烧结 | D29: 定期量测/抄表/铭牌 | E29: 国家排放因子 | F29: 校准且合格 | G29: =IF(D29="自动连续量测",6,IF(D29="定期量测/抄表/铭牌",3,1)) -> 3 | H29: =IF(E29="量测/质量平衡排放因子",6,IF(E29="制程/设备排放因子",5,IF(E29="制造商提供的排放因子",4,IF(E29="区域排放因子",3,IF(E29="国家排放因子",2,1))))) -> 2 | I29: =IF(F29="校准且合格",6,IF(F29="未校准",1,3)) -> 6 | J29: =AVERAGE(G29:I29) -> 3.6666667 | K29: =表1温室气体盘查表!AM32 -> 479835.37 | L29: =K29/$K$96 -> 0.031198282 | M29: =J29*L29 -> 0.1143937
A30: 28 | B30: =表1温室气体盘查表!C33 -> 生石灰生产 | C30: =表1温室气体盘查表!D33 -> 烧结、转炉、电炉 | D30: 定期量测/抄表/铭牌 | E30: 国际排放因子 | F30: 校准且合格 | G30: =IF(D30="自动连续量测",6,IF(D30="定期量测/抄表/铭牌",3,1)) -> 3 | H30: =IF(E30="量测/质量平衡排放因子",6,IF(E30="制程/设备排放因子",5,IF(E30="制造商提供的排放因子",4,IF(E30="区域排放因子",3,IF(E30="国家排放因子",2,1))))) -> 1 | I30: =IF(F30="校准且合格",6,IF(F30="未校准",1,3)) -> 6 | J30: =AVERAGE(G30:I30) -> 3.3333333 | K30: =表1温室气体盘查表!AM33 -> 236961.26 | L30: =K30/$K$96 -> 0.015406918 | M30: =J30*L30 -> 0.051356394
A31: 29 | B31: =表1温室气体盘查表!C34 -> 白云石生产 | C31: =表1温室气体盘查表!D34 -> 烧结、转炉、电炉 | D31: 定期量测/抄表/铭牌 | E31: 国际排放因子 | F31: 校准且合格 | G31: =IF(D31="自动连续量测",6,IF(D31="定期量测/抄表/铭牌",3,1)) -> 3 | H31: =IF(E31="量测/质量平衡排放因子",6,IF(E31="制程/设备排放因子",5,IF(E31="制造商提供的排放因子",4,IF(E31="区域排放因子",3,IF(E31="国家排放因子",2,1))))) -> 1 | I31: =IF(F31="校准且合格",6,IF(F31="未校准",1,3)) -> 6 | J31: =AVERAGE(G31:I31) -> 3.3333333 | K31: =表1温室气体盘查表!AM34 -> 5039.7894 | L31: =K31/$K$96 -> 0.00032768067 | M31: =J31*L31 -> 0.0010922689
A32: 30 | B32: =表1温室气体盘查表!C35 -> 球团生产 | C32: =表1温室气体盘查表!D35 -> 高炉、转炉 | D32: 定期量测/抄表/铭牌 | E32: 国际排放因子 | F32: 校准且合格 | G32: =IF(D32="自动连续量测",6,IF(D32="定期量测/抄表/铭牌",3,1)) -> 3 | H32: =IF(E32="量测/质量平衡排放因子",6,IF(E32="制程/设备排放因子",5,IF(E32="制造商提供的排放因子",4,IF(E32="区域排放因子",3,IF(E32="国家排放因子",2,1))))) -> 1 | I32: =IF(F32="校准且合格",6,IF(F32="未校准",1,3)) -> 6 | J32: =AVERAGE(G32:I32) -> 3.3333333 | K32: =表1温室气体盘查表!AM35 -> 71241.082 | L32: =K32/$K$96 -> 0.0046320041 | M32: =J32*L32 -> 0.015440014
A33: 31 | B33: =表1温室气体盘查表!C36 -> 废钢生产 | C33: =表1温室气体盘查表!D36 -> 转炉、电炉 | D33: 定期量测/抄表/铭牌 | E33: 国际排放因子 | F33: 校准且合格 | G33: =IF(D33="自动连续量测",6,IF(D33="定期量测/抄表/铭牌",3,1)) -> 3 | H33: =IF(E33="量测/质量平衡排放因子",6,IF(E33="制程/设备排放因子",5,IF(E33="制造商提供的排放因子",4,IF(E33="区域排放因子",3,IF(E33="国家排放因子",2,1))))) -> 1 | I33: =IF(F33="校准且合格",6,IF(F33="未校准",1,3)) -> 6 | J33: =AVERAGE(G33:I33) -> 3.3333333 | K33: =表1温室气体盘查表!AM36 -> 83051.97 | L33: =K33/$K$96 -> 0.0053999329 | M33: =J33*L33 -> 0.017999776
A34: 32 | B34: =表1温室气体盘查表!C37 -> 电极生产 | C34: =表1温室气体盘查表!D37 -> 转炉、电炉 | D34: 定期量测/抄表/铭牌 | E34: 国际排放因子 | F34: 校准且合格 | G34: =IF(D34="自动连续量测",6,IF(D34="定期量测/抄表/铭牌",3,1)) -> 3 | H34: =IF(E34="量测/质量平衡排放因子",6,IF(E34="制程/设备排放因子",5,IF(E34="制造商提供的排放因子",4,IF(E34="区域排放因子",3,IF(E34="国家排放因子",2,1))))) -> 1 | I34: =IF(F34="校准且合格",6,IF(F34="未校准",1,3)) -> 6 | J34: =AVERAGE(G34:I34) -> 3.3333333 | K34: =表1温室气体盘查表!AM37 -> 60962.024 | L34: =K34/$K$96 -> 0.0039636729 | M34: =J34*L34 -> 0.013212243
A35: 33 | B35: =表1温室气体盘查表!C38 -> 锰铁生产 | C35: =表1温室气体盘查表!D38 -> 转炉、电炉 | D35: 定期量测/抄表/铭牌 | E35: 国际排放因子 | F35: 校准且合格 | G35: =IF(D35="自动连续量测",6,IF(D35="定期量测/抄表/铭牌",3,1)) -> 3 | H35: =IF(E35="量测/质量平衡排放因子",6,IF(E35="制程/设备排放因子",5,IF(E35="制造商提供的排放因子",4,IF(E35="区域排放因子",3,IF(E35="国家排放因子",2,1))))) -> 1 | I35: =IF(F35="校准且合格",6,IF(F35="未校准",1,3)) -> 6 | J35: =AVERAGE(G35:I35) -> 3.3333333 | K35: =表1温室气体盘查表!AM38 -> 123503.69 | L35: =K35/$K$96 -> 0.0080300523 | M35: =J35*L35 -> 0.026766841
A36: 34 | B36: =表1温室气体盘查表!C39 -> 镍铁生产 | C36: =表1温室气体盘查表!D39 -> 转炉、电炉 | D36: 定期量测/抄表/铭牌 | E36: 国际排放因子 | F36: 校准且合格 | G36: =IF(D36="自动连续量测",6,IF(D36="定期量测/抄表/铭牌",3,1)) -> 3 | H36: =IF(E36="量测/质量平衡排放因子",6,IF(E36="制程/设备排放因子",5,IF(E36="制造商提供的排放因子",4,IF(E36="区域排放因子",3,IF(E36="国家排放因子",2,1))))) -> 1 | I36: =IF(F36="校准且合格",6,IF(F36="未校准",1,3)) -> 6 | J36: =AVERAGE(G36:I36) -> 3.3333333 | K36: =表1温室气体盘查表!AM39 -> 87049.733 | L36: =K36/$K$96 -> 0.0056598624 | M36: =J36*L36 -> 0.018866208
A37: 35 | B37: =表1温室气体盘查表!C40 -> 铬铁生产 | C37: =表1温室气体盘查表!D40 -> 转炉、电炉 | D37: 定期量测/抄表/铭牌 | E37: 国际排放因子 | F37: 校准且合格 | G37: =IF(D37="自动连续量测",6,IF(D37="定期量测/抄表/铭牌",3,1)) -> 3 | H37: =IF(E37="量测/质量平衡排放因子",6,IF(E37="制程/设备排放因子",5,IF(E37="制造商提供的排放因子",4,IF(E37="区域排放因子",3,IF(E37="国家排放因子",2,1))))) -> 1 | I37: =IF(F37="校准且合格",6,IF(F37="未校准",1,3)) -> 6 | J37: =AVERAGE(G37:I37) -> 3.3333333 | K37: =表1温室气体盘查表!AM40 -> 204743.82 | L37: =K37/$K$96 -> 0.013312181 | M37: =J37*L37 -> 0.044373938
A38: 36 | B38: =表1温室气体盘查表!C41 -> 萤石生产 | C38: =表1温室气体盘查表!D41 -> 转炉、电炉 | D38: 定期量测/抄表/铭牌 | E38: 国际排放因子 | F38: 校准且合格 | G38: =IF(D38="自动连续量测",6,IF(D38="定期量测/抄表/铭牌",3,1)) -> 3 | H38: =IF(E38="量测/质量平衡排放因子",6,IF(E38="制程/设备排放因子",5,IF(E38="制造商提供的排放因子",4,IF(E38="区域排放因子",3,IF(E38="国家排放因子",2,1))))) -> 1 | I38: =IF(F38="校准且合格",6,IF(F38="未校准",1,3)) -> 6 | J38: =AVERAGE(G38:I38) -> 3.3333333 | K38: =表1温室气体盘查表!AM41 -> 88473.44 | L38: =K38/$K$96 -> 0.00575243 | M38: =J38*L38 -> 0.019174767
A39: 37 | B39: =表1温室气体盘查表!C42 -> 硅铁生产 | C39: =表1温室气体盘查表!D42 -> 转炉、电炉 | D39: 定期量测/抄表/铭牌 | E39: 国际排放因子 | F39: 校准且合格 | G39: =IF(D39="自动连续量测",6,IF(D39="定期量测/抄表/铭牌",3,1)) -> 3 | H39: =IF(E39="量测/质量平衡排放因子",6,IF(E39="制程/设备排放因子",5,IF(E39="制造商提供的排放因子",4,IF(E39="区域排放因子",3,IF(E39="国家排放因子",2,1))))) -> 1 | I39: =IF(F39="校准且合格",6,IF(F39="未校准",1,3)) -> 6 | J39: =AVERAGE(G39:I39) -> 3.3333333 | K39: =表1温室气体盘查表!AM42 -> 149088.59 | L39: =K39/$K$96 -> 0.0096935493 | M39: =J39*L39 -> 0.032311831
A40: 38 | B40: =表1温室气体盘查表!C43 -> 钼铁生产 | C40: =表1温室气体盘查表!D43 -> 转炉、电炉 | D40: 定期量测/抄表/铭牌 | E40: 国际排放因子 | F40: 校准且合格 | G40: =IF(D40="自动连续量测",6,IF(D40="定期量测/抄表/铭牌",3,1)) -> 3 | H40: =IF(E40="量测/质量平衡排放因子",6,IF(E40="制程/设备排放因子",5,IF(E40="制造商提供的排放因子",4,IF(E40="区域排放因子",3,IF(E40="国家排放因子",2,1))))) -> 1 | I40: =IF(F40="校准且合格",6,IF(F40="未校准",1,3)) -> 6 | J40: =AVERAGE(G40:I40) -> 3.3333333 | K40: =表1温室气体盘查表!AM43 -> 58876.632 | L40: =K40/$K$96 -> 0.0038280834 | M40: =J40*L40 -> 0.012760278
... A95: 93 | B95: =表1温室气体盘查表!C98 -> 产品报废 | C95: =表1温室气体盘查表!D98 -> 下游钢铁厂 | D95: 自行推估 | E95: 国际排放因子 | F95: 校准但不合格/未校准但数据可查证 | G95: =IF(D95="自动连续量测",6,IF(D95="定期量测/抄表/铭牌",3,1)) -> 1 | H95: =IF(E95="量测/质量平衡排放因子",6,IF(E95="制程/设备排放因子",5,IF(E95="制造商提供的排放因子",4,IF(E95="区域排放因子",3,IF(E95="国家排放因子",2,1))))) -> 1 | I95: =IF(F95="校准且合格",6,IF(F95="未校准",1,3)) -> 3 | J95: =AVERAGE(G95:I95) -> 1.6666667 | K95: =表1温室气体盘查表!AM98 -> 3589.115 | L95: =K95/$K$96 -> 0.00023335967 | M95: =J95*L95 -> 0.00038893278
K96: =SUM(K3:K95) -> 15380185 | L96: 加权合计 | M96: =SUM(M3:M95) -> 3.6885263 | N96: uncertainty_score_location_based
L97: 加权等级 | M97: =IF(M96<2,"差",IF(M96<3,"一般",IF(M96<4,"良",IF(M96<5,"优","优+")))) -> 良
A107: 优+ | B107: >=5.0
A108: 优 | B108: <5.0,>=4.0
A109: 良 | B109: <4.0,>=3.0
A110: 一般 | B110: <3.0,>=2.0
A111: 差 | B111: <2.0

Sheet 表2.1不确定性评估——基于市场
A1: 不确定性评估表
A2: 编号 | B2: 排放源 | C2: 设施 | D2: 活动数据类别 | E2: 排放因子类别 | F2: 校准频率 | G2: 活动数据级别 | H2: 排放因子级别 | I2: 校准级别 | J2: 平均得分 | K2: 排放量(tCO2e) | L2: 排放量占比 | M2: 加权平均积分
A3: 1 | B3: =表1温室气体盘查表!C5 -> 天然气燃烧 | C3: =表1温室气体盘查表!D5 -> 热处理炉（加热炉） | D3: 自动连续量测 | E3: 国际排放因子 | F3: 校准且合格 | G3: =IF(D3="自动连续量测",6,IF(D3="定期量测/抄表/铭牌",3,1)) -> 6 | H3: =IF(E3="量测/质量平衡排放因子",6,IF(E3="制程/设备排放因子",5,IF(E3="制造商提供的排放因子",4,IF(E3="区域排放因子",3,IF(E3="国家排放因子",2,1))))) -> 1 | I3: =IF(F3="校准且合格",6,IF(F3="未校准",1,3)) -> 6 | J3: =AVERAGE(G3:I3) -> 4.3333333 | K3: =表1温室气体盘查表!AM5 -> 31469.159 | L3: =K3/$K$96 -> 0.0020272112 | M3: =J3*L3 -> 0.0087845819
A4: 2 | B4: =表1温室气体盘查表!C6 -> 液化石油气燃烧 | C4: =表1温室气体盘查表!D6 -> 冶钢宾馆 | D4: 定期量测/抄表/铭牌 | E4: 国际排放因子 | F4: 校准且合格 | G4: =IF(D4="自动连续量测",6,IF(D4="定期量测/抄表/铭牌",3,1)) -> 3 | H4: =IF(E4="量测/质量平衡排放因子",6,IF(E4="制程/设备排放因子",5,IF(E4="制造商提供的排放因子",4,IF(E4="区域排放因子",3,IF(E4="国家排放因子",2,1))))) -> 1 | I4: =IF(F4="校准且合格",6,IF(F4="未校准",1,3)) -> 6 | J4: =AVERAGE(G4:I4) -> 3.3333333 | K4: =表1温室气体盘查表!AM6 -> 29.286595 | L4: =K4/$K$96 -> 1.8866127e-06 | M4: =J4*L4 -> 6.2887089e-06
A5: 3 | B5: =表1温室气体盘查表!C7 -> 烟煤燃烧 | C5: =表1温室气体盘查表!D7 -> 高炉 | D5: 自动连续量测 | E5: 国际排放因子 | F5: 校准且合格 | G5: =IF(D5="自动连续量测",6,IF(D5="定期量测/抄表/铭牌",3,1)) -> 6 | H5: =IF(E5="量测/质量平衡排放因子",6,IF(E5="制程/设备排放因子",5,IF(E5="制造商提供的排放因子",4,IF(E5="区域排放因子",3,IF(E5="国家排放因子",2,1))))) -> 1 | I5: =IF(F5="校准且合格",6,IF(F5="未校准",1,3)) -> 6 | J5: =AVERAGE(G5:I5) -> 4.3333333 | K5: =表1温室气体盘查表!AM7 -> 749580.33 | L5: =K5/$K$96 -> 0.048287202 | M5: =J5*L5 -> 0.20924454
A6: 4 | B6: =表1温室气体盘查表!C8 -> 无烟煤燃烧 | C6: =表1温室气体盘查表!D8 -> 高炉、烧结 | D6: 自动连续量测 | E6: 国际排放因子 | F6: 校准且合格 | G6: =IF(D6="自动连续量测",6,IF(D6="定期量测/抄表/铭牌",3,1)) -> 6 | H6: =IF(E6="量测/质量平衡排放因子",6,IF(E6="制程/设备排放因子",5,IF(E6="制造商提供的排放因子",4,IF(E6="区域排放因子",3,IF(E6="国家排放因子",2,1))))) -> 1 | I6: =IF(F6="校准且合格",6,IF(F6="未校准",1,3)) -> 6 | J6: =AVERAGE(G6:I6) -> 4.3333333 | K6: =表1温室气体盘查表!AM8 -> 820622.2 | L6: =K6/$K$96 -> 0.052863647 | M6: =J6*L6 -> 0.2290758
A7: 5 | B7: =表1温室气体盘查表!C9 -> 洗精煤燃烧 | C7: =表1温室气体盘查表!D9 -> 焦炉 | D7: 自动连续量测 | E7: 国际排放因子 | F7: 校准且合格 | G7: =IF(D7="自动连续量测",6,IF(D7="定期量测/抄表/铭牌",3,1)) -> 6 | H7: =IF(E7="量测/质量平衡排放因子",6,IF(E7="制程/设备排放因子",5,IF(E7="制造商提供的排放因子",4,IF(E7="区域排放因子",3,IF(E7="国家排放因子",2,1))))) -> 1 | I7: =IF(F7="校准且合格",6,IF(F7="未校准",1,3)) -> 6 | J7: =AVERAGE(G7:I7) -> 4.3333333 | K7: =表1温室气体盘查表!AM9 -> 5189313.3 | L7: =K7/$K$96 -> 0.33429028 | M7: =J7*L7 -> 1.4485912
A8: 6 | B8: =表1温室气体盘查表!C10 -> 焦炭燃烧 | C8: =表1温室气体盘查表!D10 -> 高炉 | D8: 自动连续量测 | E8: 国际排放因子 | F8: 校准且合格 | G8: =IF(D8="自动连续量测",6,IF(D8="定期量测/抄表/铭牌",3,1)) -> 6 | H8: =IF(E8="量测/质量平衡排放因子",6,IF(E8="制程/设备排放因子",5,IF(E8="制造商提供的排放因子",4,IF(E8="区域排放因子",3,IF(E8="国家排放因子",2,1))))) -> 1 | I8: =IF(F8="校准且合格",6,IF(F8="未校准",1,3)) -> 6 | J8: =AVERAGE(G8:I8) -> 4.3333333 | K8: =表1温室气体盘查表!AM10 -> 669939.56 | L8: =K8/$K$96 -> 0.043156825 | M8: =J8*L8 -> 0.18701291
A9: 7 | B9: =表1温室气体盘查表!C11 -> 焦炉煤气燃烧 | C9: =表1温室气体盘查表!D11 -> 外售 | D9: 自动连续量测 | E9: 国际排放因子 | F9: 校准且合格 | G9: =IF(D9="自动连续量测",6,IF(D9="定期量测/抄表/铭牌",3,1)) -> 6 | H9: =IF(E9="量测/质量平衡排放因子",6,IF(E9="制程/设备排放因子",5,IF(E9="制造商提供的排放因子",4,IF(E9="区域排放因子",3,IF(E9="国家排放因子",2,1))))) -> 1 | I9: =IF(F9="校准且合格",6,IF(F9="未校准",1,3)) -> 6 | J9: =AVERAGE(G9:I9) -> 4.3333333 | K9: =表1温室气体盘查表!AM11 -> -6034.9102 | L9: =K9/$K$96 -> -0.00038876277 | M9: =J9*L9 -> -0.0016846387
A10: 8 | B10: =表1温室气体盘查表!C12 -> 柴油燃烧 | C10: =表1温室气体盘查表!D12 -> 场内运输 | D10: 定期量测/抄表/铭牌 | E10: 国际排放因子 | F10: 校准但不合格/未校准但数据可查证 | G10: =IF(D10="自动连续量测",6,IF(D10="定期量测/抄表/铭牌",3,1)) -> 3 | H10: =IF(E10="量测/质量平衡排放因子",6,IF(E10="制程/设备排放因子",5,IF(E10="制造商提供的排放因子",4,IF(E10="区域排放因子",3,IF(E10="国家排放因子",2,1))))) -> 1 | I10: =IF(F10="校准且合格",6,IF(F10="未校准",1,3)) -> 3 | J10: =AVERAGE(G10:I10) -> 2.3333333 | K10: =表1温室气体盘查表!AM12 -> 4476.287 | L10: =K10/$K$96 -> 0.00028835785 | M10: =J10*L10 -> 0.00067283499
A11: 9 | B11: =表1温室气体盘查表!C13 -> 汽油燃烧 | C11: =表1温室气体盘查表!D13 -> 公务车 | D11: 定期量测/抄表/铭牌 | E11: 国际排放因子 | F11: 校准但不合格/未校准但数据可查证 | G11: =IF(D11="自动连续量测",6,IF(D11="定期量测/抄表/铭牌",3,1)) -> 3 | H11: =IF(E11="量测/质量平衡排放因子",6,IF(E11="制程/设备排放因子",5,IF(E11="制造商提供的排放因子",4,IF(E11="区域排放因子",3,IF(E11="国家排放因子",2,1))))) -> 1 | I11: =IF(F11="校准且合格",6,IF(F11="未校准",1,3)) -> 3 | J11: =AVERAGE(G11:I11) -> 2.3333333 | K11: =表1温室气体盘查表!AM13 -> 144.22983 | L11: =K11/$K$96 -> 9.2911391e-06 | M11: =J11*L11 -> 2.1679325e-05
A12: 10 | B12: =表1温室气体盘查表!C14 -> 制冷剂逸散（R32） | C12: =表1温室气体盘查表!D14 -> 分体式空调 | D12: 定期量测/抄表/铭牌 | E12: 国家排放因子 | F12: 校准且合格 | G12: =IF(D12="自动连续量测",6,IF(D12="定期量测/抄表/铭牌",3,1)) -> 3 | H12: =IF(E12="量测/质量平衡排放因子",6,IF(E12="制程/设备排放因子",5,IF(E12="制造商提供的排放因子",4,IF(E12="区域排放因子",3,IF(E12="国家排放因子",2,1))))) -> 2 | I12: =IF(F12="校准且合格",6,IF(F12="未校准",1,3)) -> 6 | J12: =AVERAGE(G12:I12) -> 3.6666667 | K12: =表1温室气体盘查表!AM14 -> 570.54 | L12: =K12/$K$96 -> 3.6753606e-05 | M12: =J12*L12 -> 0.00013476322
A13: 11 | B13: =表1温室气体盘查表!C15 -> CO2逸散 | C13: =表1温室气体盘查表!D15 -> 二氧化碳灭火器 | D13: 定期量测/抄表/铭牌 | E13: 国家排放因子 | F13: 校准且合格 | G13: =IF(D13="自动连续量测",6,IF(D13="定期量测/抄表/铭牌",3,1)) -> 3 | H13: =IF(E13="量测/质量平衡排放因子",6,IF(E13="制程/设备排放因子",5,IF(E13="制造商提供的排放因子",4,IF(E13="区域排放因子",3,IF(E13="国家排放因子",2,1))))) -> 2 | I13: =IF(F13="校准且合格",6,IF(F13="未校准",1,3)) -> 6 | J13: =AVERAGE(G13:I13) -> 3.6666667 | K13: =表1温室气体盘查表!AM15 -> 0.56 | L13: =K13/$K$96 -> 3.607463e-08 | M13: =J13*L13 -> 1.3227364e-07
A14: 12 | B14: =表1温室气体盘查表!C16 -> CH4逸散 | C14: =表1温室气体盘查表!D16 -> 化粪池 | D14: 定期量测/抄表/铭牌 | E14: 国际排放因子 | F14: 校准且合格 | G14: =IF(D14="自动连续量测",6,IF(D14="定期量测/抄表/铭牌",3,1)) -> 3 | H14: =IF(E14="量测/质量平衡排放因子",6,IF(E14="制程/设备排放因子",5,IF(E14="制造商提供的排放因子",4,IF(E14="区域排放因子",3,IF(E14="国家排放因子",2,1))))) -> 1 | I14: =IF(F14="校准且合格",6,IF(F14="未校准",1,3)) -> 6 | J14: =AVERAGE(G14:I14) -> 3.3333333 | K14: =表1温室气体盘查表!AM16 -> 116.30952 | L14: =K14/$K$96 -> 7.4925409e-06 | M14: =J14*L14 -> 2.4975136e-05
... A27: 25 | B27: =表1温室气体盘查表!C29 -> 焦油 | C27: =表1温室气体盘查表!D29 -> 危废处置 | D27: 定期量测/抄表/铭牌 | E27: 国家排放因子 | F27: 校准且合格 | G27: =IF(D27="自动连续量测",6,IF(D27="定期量测/抄表/铭牌",3,1)) -> 3 | H27: =IF(E27="量测/质量平衡排放因子",6,IF(E27="制程/设备排放因子",5,IF(E27="制造商提供的排放因子",4,IF(E27="区域排放因子",3,IF(E27="国家排放因子",2,1))))) -> 2 | I27: =IF(F27="校准且合格",6,IF(F27="未校准",1,3)) -> 6 | J27: =AVERAGE(G27:I27) -> 3.6666667 | K27: =表1温室气体盘查表!AM29 -> -163466.55 | L27: =K27/$K$96 -> -0.010530349 | M27: =J27*L27 -> -0.03861128
A28: 26 | B28: =表1温室气体盘查表!C31 -> 外购电力（基于市场） | C28: =表1温室气体盘查表!D31 -> 用电设备 | D28: 自动连续量测 | E28: 国家排放因子 | F28: 校准且合格 | G28: =IF(D28="自动连续量测",6,IF(D28="定期量测/抄表/铭牌",3,1)) -> 6 | H28: =IF(E28="量测/质量平衡排放因子",6,IF(E28="制程/设备排放因子",5,IF(E28="制造商提供的排放因子",4,IF(E28="区域排放因子",3,IF(E28="国家排放因子",2,1))))) -> 2 | I28: =IF(F28="校准且合格",6,IF(F28="未校准",1,3)) -> 6 | J28: =AVERAGE(G28:I28) -> 4.6666667 | K28: =表1温室气体盘查表!AM31 -> 1186800.3 | L28: =K28/$K$96 -> 0.076452465 | M28: =J28*L28 -> 0.35677817
A29: 27 | B29: =表1温室气体盘查表!C32 -> 铁矿石生产 | C29: =表1温室气体盘查表!D32 -> 烧结 | D29: 定期量测/抄表/铭牌 | E29: 国家排放因子 | F29: 校准且合格 | G29: =IF(D29="自动连续量测",6,IF(D29="定期量测/抄表/铭牌",3,1)) -> 3 | H29: =IF(E29="量测/质量平衡排放因子",6,IF(E29="制程/设备排放因子",5,IF(E29="制造商提供的排放因子",4,IF(E29="区域排放因子",3,IF(E29="国家排放因子",2,1))))) -> 2 | I29: =IF(F29="校准且合格",6,IF(F29="未校准",1,3)) -> 6 | J29: =AVERAGE(G29:I29) -> 3.6666667 | K29: =表1温室气体盘查表!AM32 -> 479835.37 | L29: =K29/$K$96 -> 0.030910506 | M29: =J29*L29 -> 0.11333852
A30: 28 | B30: =表1温室气体盘查表!C33 -> 生石灰生产 | C30: =表1温室气体盘查表!D33 -> 烧结、转炉、电炉 | D30: 定期量测/抄表/铭牌 | E30: 国际排放因子 | F30: 校准且合格 | G30: =IF(D30="自动连续量测",6,IF(D30="定期量测/抄表/铭牌",3,1)) -> 3 | H30: =IF(E30="量测/质量平衡排放因子",6,IF(E30="制程/设备排放因子",5,IF(E30="制造商提供的排放因子",4,IF(E30="区域排放因子",3,IF(E30="国家排放因子",2,1))))) -> 1 | I30: =IF(F30="校准且合格",6,IF(F30="未校准",1,3)) -> 6 | J30: =AVERAGE(G30:I30) -> 3.3333333 | K30: =表1温室气体盘查表!AM33 -> 236961.26 | L30: =K30/$K$96 -> 0.015264803 | M30: =J30*L30 -> 0.050882678
A31: 29 | B31: =表1温室气体盘查表!C34 -> 白云石生产 | C31: =表1温室气体盘查表!D34 -> 烧结、转炉、电炉 | D31: 定期量测/抄表/铭牌 | E31: 国际排放因子 | F31: 校准且合格 | G31: =IF(D31="自动连续量测",6,IF(D31="定期量测/抄表/铭牌",3,1)) -> 3 | H31: =IF(E31="量测/质量平衡排放因子",6,IF(E31="制程/设备排放因子",5,IF(E31="制造商提供的排放因子",4,IF(E31="区域排放因子",3,IF(E31="国家排放因子",2,1))))) -> 1 | I31: =IF(F31="校准且合格",6,IF(F31="未校准",1,3)) -> 6 | J31: =AVERAGE(G31:I31) -> 3.3333333 | K31: =表1温室气体盘查表!AM34 -> 5039.7894 | L31: =K31/$K$96 -> 0.00032465811 | M31: =J31*L31 -> 0.0010821937
A32: 30 | B32: =表1温室气体盘查表!C35 -> 球团生产 | C32: =表1温室气体盘查表!D35 -> 高炉、转炉 | D32: 定期量测/抄表/铭牌 | E32: 国际排放因子 | F32: 校准且合格 | G32: =IF(D32="自动连续量测",6,IF(D32="定期量测/抄表/铭牌",3,1)) -> 3 | H32: =IF(E32="量测/质量平衡排放因子",6,IF(E32="制程/设备排放因子",5,IF(E32="制造商提供的排放因子",4,IF(E32="区域排放因子",3,IF(E32="国家排放因子",2,1))))) -> 1 | I32: =IF(F32="校准且合格",6,IF(F32="未校准",1,3)) -> 6 | J32: =AVERAGE(G32:I32) -> 3.3333333 | K32: =表1温室气体盘查表!AM35 -> 71241.082 | L32: =K32/$K$96 -> 0.004589278 | M32: =J32*L32 -> 0.015297593
A33: 31 | B33: =表1温室气体盘查表!C36 -> 废钢生产 | C33: =表1温室气体盘查表!D36 -> 转炉、电炉 | D33: 定期量测/抄表/铭牌 | E33: 国际排放因子 | F33: 校准且合格 | G33: =IF(D33="自动连续量测",6,IF(D33="定期量测/抄表/铭牌",3,1)) -> 3 | H33: =IF(E33="量测/质量平衡排放因子",6,IF(E33="制程/设备排放因子",5,IF(E33="制造商提供的排放因子",4,IF(E33="区域排放因子",3,IF(E33="国家排放因子",2,1))))) -> 1 | I33: =IF(F33="校准且合格",6,IF(F33="未校准",1,3)) -> 6 | J33: =AVERAGE(G33:I33) -> 3.3333333 | K33: =表1温室气体盘查表!AM36 -> 83051.97 | L33: =K33/$K$96 -> 0.0053501234 | M33: =J33*L33 -> 0.017833745
A34: 32 | B34: =表1温室气体盘查表!C37 -> 电极生产 | C34: =表1温室气体盘查表!D37 -> 转炉、电炉 | D34: 定期量测/抄表/铭牌 | E34: 国际排放因子 | F34: 校准且合格 | G34: =IF(D34="自动连续量测",6,IF(D34="定期量测/抄表/铭牌",3,1)) -> 3 | H34: =IF(E34="量测/质量平衡排放因子",6,IF(E34="制程/设备排放因子",5,IF(E34="制造商提供的排放因子",4,IF(E34="区域排放因子",3,IF(E34="国家排放因子",2,1))))) -> 1 | I34: =IF(F34="校准且合格",6,IF(F34="未校准",1,3)) -> 6 | J34: =AVERAGE(G34:I34) -> 3.3333333 | K34: =表1温室气体盘查表!AM37 -> 60962.024 | L34: =K34/$K$96 -> 0.0039271116 | M34: =J34*L34 -> 0.013090372
A35: 33 | B35: =表1温室气体盘查表!C38 -> 锰铁生产 | C35: =表1温室气体盘查表!D38 -> 转炉、电炉 | D35: 定期量测/抄表/铭牌 | E35: 国际排放因子 | F35: 校准且合格 | G35: =IF(D35="自动连续量测",6,IF(D35="定期量测/抄表/铭牌",3,1)) -> 3 | H35: =IF(E35="量测/质量平衡排放因子",6,IF(E35="制程/设备排放因子",5,IF(E35="制造商提供的排放因子",4,IF(E35="区域排放因子",3,IF(E35="国家排放因子",2,1))))) -> 1 | I35: =IF(F35="校准且合格",6,IF(F35="未校准",1,3)) -> 6 | J35: =AVERAGE(G35:I35) -> 3.3333333 | K35: =表1温室气体盘查表!AM38 -> 123503.69 | L35: =K35/$K$96 -> 0.0079559823 | M35: =J35*L35 -> 0.026519941
A36: 34 | B36: =表1温室气体盘查表!C39 -> 镍铁生产 | C36: =表1温室气体盘查表!D39 -> 转炉、电炉 | D36: 定期量测/抄表/铭牌 | E36: 国际排放因子 | F36: 校准且合格 | G36: =IF(D36="自动连续量测",6,IF(D36="定期量测/抄表/铭牌",3,1)) -> 3 | H36: =IF(E36="量测/质量平衡排放因子",6,IF(E36="制程/设备排放因子",5,IF(E36="制造商提供的排放因子",4,IF(E36="区域排放因子",3,IF(E36="国家排放因子",2,1))))) -> 1 | I36: =IF(F36="校准且合格",6,IF(F36="未校准",1,3)) -> 6 | J36: =AVERAGE(G36:I36) -> 3.3333333 | K36: =表1温室气体盘查表!AM39 -> 87049.733 | L36: =K36/$K$96 -> 0.0056076552 | M36: =J36*L36 -> 0.018692184
A37: 35 | B37: =表1温室气体盘查表!C40 -> 铬铁生产 | C37: =表1温室气体盘查表!D40 -> 转炉、电炉 | D37: 定期量测/抄表/铭牌 | E37: 国际排放因子 | F37: 校准且合格 | G37: =IF(D37="自动连续量测",6,IF(D37="定期量测/抄表/铭牌",3,1)) -> 3 | H37: =IF(E37="量测/质量平衡排放因子",6,IF(E37="制程/设备排放因子",5,IF(E37="制造商提供的排放因子",4,IF(E37="区域排放因子",3,IF(E37="国家排放因子",2,1))))) -> 1 | I37: =IF(F37="校准且合格",6,IF(F37="未校准",1,3)) -> 6 | J37: =AVERAGE(G37:I37) -> 3.3333333 | K37: =表1温室气体盘查表!AM40 -> 204743.82 | L37: =K37/$K$96 -> 0.013189388 | M37: =J37*L37 -> 0.043964628
A38: 36 | B38: =表1温室气体盘查表!C41 -> 萤石生产 | C38: =表1温室气体盘查表!D41 -> 转炉、电炉 | D38: 定期量测/抄表/铭牌 | E38: 国际排放因子 | F38: 校准且合格 | G38: =IF(D38="自动连续量测",6,IF(D38="定期量测/抄表/铭牌",3,1)) -> 3 | H38: =IF(E38="量测/质量平衡排放因子",6,IF(E38="制程/设备排放因子",5,IF(E38="制造商提供的排放因子",4,IF(E38="区域排放因子",3,IF(E38="国家排放因子",2,1))))) -> 1 | I38: =IF(F38="校准且合格",6,IF(F38="未校准",1,3)) -> 6 | J38: =AVERAGE(G38:I38) -> 3.3333333 | K38: =表1温室气体盘查表!AM41 -> 88473.44 | L38: =K38/$K$96 -> 0.005699369 | M38: =J38*L38 -> 0.018997897
A39: 37 | B39: =表1温室气体盘查表!C42 -> 硅铁生产 | C39: =表1温室气体盘查表!D42 -> 转炉、电炉 | D39: 定期量测/抄表/铭牌 | E39: 国际排放因子 | F39: 校准且合格 | G39: =IF(D39="自动连续量测",6,IF(D39="定期量测/抄表/铭牌",3,1)) -> 3 | H39: =IF(E39="量测/质量平衡排放因子",6,IF(E39="制程/设备排放因子",5,IF(E39="制造商提供的排放因子",4,IF(E39="区域排放因子",3,IF(E39="国家排放因子",2,1))))) -> 1 | I39: =IF(F39="校准且合格",6,IF(F39="未校准",1,3)) -> 6 | J39: =AVERAGE(G39:I39) -> 3.3333333 | K39: =表1温室气体盘查表!AM42 -> 149088.59 | L39: =K39/$K$96 -> 0.009604135 | M39: =J39*L39 -> 0.032013783
... A95: 93 | B95: =表1温室气体盘查表!C98 -> 产品报废 | C95: =表1温室气体盘查表!D98 -> 下游钢铁厂 | D95: 自行推估 | E95: 国际排放因子 | F95: 校准但不合格/未校准但数据可查证 | G95: =IF(D95="自动连续量测",6,IF(D95="定期量测/抄表/铭牌",3,1)) -> 1 | H95: =IF(E95="量测/质量平衡排放因子",6,IF(E95="制程/设备排放因子",5,IF(E95="制造商提供的排放因子",4,IF(E95="区域排放因子",3,IF(E95="国家排放因子",2,1))))) -> 1 | I95: =IF(F95="校准且合格",6,IF(F95="未校准",1,3)) -> 3 | J95: =AVERAGE(G95:I95) -> 1.6666667 | K95: =表1温室气体盘查表!AM98 -> 3589.115 | L95: =K95/$K$96 -> 0.00023120714 | M95: =J95*L95 -> 0.00038534523
K96: =SUM(K3:K95) -> 15523375 | L96: 加权合计 | M96: =SUM(M3:M95) -> 3.6975488 | N96: uncertainty_score_market_based
L97: 加权等级 | M97: =IF(M96<2,"差",IF(M96<3,"一般",IF(M96<4,"良",IF(M96<5,"优","优+")))) -> 良 | N97: uncertainty_level_market_based
A107: 优+ | B107: >=5.0
A108: 优 | B108: <5.0,>=4.0
A109: 良 | B109: <4.0,>=3.0
A110: 一般 | B110: <3.0,>=2.0
A111: 差 | B111: <2.0

Sheet 附表1-GWP TABLE
B2: 工业名称 | C2: 中文名称/化学分子式 | D2: 组成比例（%） | E2: GWP | F2: GWP(HFCs) | G2: GWP(PFCs) | H2: 来源 | I2: 备注
B3: CO2 | C3: 二氧化碳 | E3: 1 | H3: 2021年IPCC第六次评估报告AR6
B4: CH4 | C4: 甲烷 | E4: 27.9 | H4: =H3 -> 2021年IPCC第六次评估报告AR6
B5: N2O | C5: 氧化亚氮 | E5: 273 | H5: =H3 -> 2021年IPCC第六次评估报告AR6
B6: HCFC-22 | C6: R-22，一氟二氯甲烷，CHCl2F | F6: 1960 | H6: =H$3 -> 2021年IPCC第六次评估报告AR6
B7: HFC-23 | C7: R-23，三氟甲烷，CHF3 | F7: 14600 | H7: =H$3 -> 2021年IPCC第六次评估报告AR6
B8: HFC-32 | C8: R-32，二氟甲烷，CH2F2 | F8: 771 | H8: =H$3 -> 2021年IPCC第六次评估报告AR6
B9: HFC-41 | C9: 一氟甲烷，CH3F | F9: 135 | H9: =H$3 -> 2021年IPCC第六次评估报告AR6
B10: HFC-125 | C10: R-125，1,1,1,2,2-五氟乙烷，C2HF5 | F10: 3740 | H10: =H$3 -> 2021年IPCC第六次评估报告AR6
B11: HFC-134 | C11: R-134，1,1,2,2-四氟乙烷，C2H2F4 | F11: 1260 | H11: =H$3 -> 2021年IPCC第六次评估报告AR6
B12: HFC-134a | C12: R-134a，1,1,1,2-四氟乙烷，C2H2F4 | F12: 1530 | H12: =H$3 -> 2021年IPCC第六次评估报告AR6
B13: HFC-143 | C13: R-143，1,1,2-三氟乙烷，CHF2CH2F | F13: 364 | H13: =H$3 -> 2021年IPCC第六次评估报告AR6
B14: HFC-143a | C14: R-143a，1,1,1-三氟乙烷，C2H3F3 | F14: 5810 | H14: =H$3 -> 2021年IPCC第六次评估报告AR6
B15: HFC-152 | C15: R-152，1,2-二氟乙烷，CH2FCH2F | F15: 21.5 | H15: =H$3 -> 2021年IPCC第六次评估报告AR6
B16: HFC-152a | C16: R-152a，1,1-二氟乙烷，C2H4F2 | F16: 164 | H16: =H$3 -> 2021年IPCC第六次评估报告AR6
B17: HFC-161 | C17: R-161，一氟乙烷，CH3CH2F | F17: 4.84 | H17: =H$3 -> 2021年IPCC第六次评估报告AR6
... B25: HFC-43-10mee | C25: R-43-10mee，1,1,1,2,2,3,4,5,5,5-十氟戊烷，CF3CHFCHFCF2CF3 | F25: 1600 | H25: =H$3 -> 2021年IPCC第六次评估报告AR6
B26: R401A | D26: R22/152a/R124（53/13/34） | F26: =F16*13% -> 21.32 | H26: =H$3 -> 2021年IPCC第六次评估报告AR6 | I26: 只考虑了R152a
B27: R401B | D27: R22/152a/R124（61/11/28） | F27: =F16*11% -> 18.04 | H27: =H$3 -> 2021年IPCC第六次评估报告AR6 | I27: 只考虑了R152a
B28: R404A | D28: R125/143a/R134a（44/52/4） | F28: =F10*44%+F14*52%+F12*4% -> 4728 | H28: =H$3 -> 2021年IPCC第六次评估报告AR6
B29: R407A | D29: R32/R125/R134a（20/40/40） | F29: =F8*20%+F10*40%+F12*40% -> 2262.2 | H29: =H$3 -> 2021年IPCC第六次评估报告AR6
B30: R407B | D30: R32/R125/R134a（10/70/20） | F30: =F8*10%+F10*70%+F12*20% -> 3001.1 | H30: =H$3 -> 2021年IPCC第六次评估报告AR6
B31: R407C | D31: R32/R125/R134a（23/25/52） | F31: =F8*23%+F10*25%+F12*52% -> 1907.93 | H31: =H$3 -> 2021年IPCC第六次评估报告AR6
B32: R408A | D32: R125/R143a/R22（7/46/47） | F32: =F10*7%+F14*46% -> 2934.4 | H32: =H$3 -> 2021年IPCC第六次评估报告AR6 | I32: 未考虑R22
B33: R410A | D33: R32/R125（50/50） | F33: =F8*50%+F10*50% -> 2255.5 | H33: =H$3 -> 2021年IPCC第六次评估报告AR6
B34: R413A | D34: R218/R134a/R600a(9/88/3） | F34: =G42*9%+F12*88%+0 -> 2182.5 | H34: =H$3 -> 2021年IPCC第六次评估报告AR6
B35: R417A | D35: R125/R134a/R600a(46.6/50/3.4) | F35: =F10*46.6%+F12*50%+0 -> 2507.84 | H35: =H$3 -> 2021年IPCC第六次评估报告AR6
B36: R503 | D36: R23/R13（40.1/59.9） | F36: =F7*40.1% -> 5854.6 | H36: =H$3 -> 2021年IPCC第六次评估报告AR6 | I36: 只考虑了R23,未考虑R13
B37: R507A | D37: R125/R143a（50.0/50.0） | F37: =F10*50%+F14*50% -> 4775 | H37: =H$3 -> 2021年IPCC第六次评估报告AR6
B38: R508A | D38: R23/R116（39.0/61.0） | F38: =F7*39%+G40*61% -> 13258 | H38: =H$3 -> 2021年IPCC第六次评估报告AR6
B39: R508B | D39: R23/R116（46.0/54.0） | F39: =F7*46%+G40*54% -> 13412 | H39: =H$3 -> 2021年IPCC第六次评估报告AR6
B40: PFC-116 | C40: R-116，六氟乙烷，C2F6 | G40: 12400 | H40: =H$3 -> 2021年IPCC第六次评估报告AR6
B41: PFC-14 | C41: R-14，四氟化碳，CF4 | G41: 7380 | H41: =H$3 -> 2021年IPCC第六次评估报告AR6
B42: PFC-218 | C42: C3F8，全氟丙烷 | G42: 9290 | H42: =H$3 -> 2021年IPCC第六次评估报告AR6
B43: PFC-318 | C43: c-C4F8，八氟环丁烷 | G43: 10200 | H43: =H$3 -> 2021年IPCC第六次评估报告AR6
B44: PFC-31-10 | C44: C4F10，全氟丁烷 | G44: 10000 | H44: =H$3 -> 2021年IPCC第六次评估报告AR6
B45: PFC-41-12 | C45: C5F12，全氟戊烷 | G45: 9220 | H45: =H$3 -> 2021年IPCC第六次评估报告AR6
B46: PFC-51-14 | C46: C6F14，全氟己烷 | G46: 8620 | H46: =H$3 -> 2021年IPCC第六次评估报告AR6
B47: NF3 | C47: 三氟化氮 | E47: 17400 | H47: =H3 -> 2021年IPCC第六次评估报告AR6
B48: SF6 | C48: 六氟化硫 | E48: 24300 | H48: =H3 -> 2021年IPCC第六次评估报告AR6

Sheet 附表2-EF
B2: 编号 | C2: GHG排放类别 | D2: 排放源 | E2: 设施 | F2: 低位发热量 | G2: 单位 | H2: 氧化率 | I2: 基于热值排放系数，t GHG/GJ | L2: 排放因子，t GHG/10000m³
I3: IPCC-2006缺省值 | L3: 计算值
F4: 企业温室气体排放核算与报告指南 钢铁行业 | H4: 企业温室气体排放核算与报告指南 钢铁行业 | I4: CO2 | J4: CH4 | K4: N2O | L4: CO2 | M4: CH4 | N4: N2O
B5: 1 | C5: 范围一 固定燃烧排放 | D5: 天然气燃烧 | E5: 热处理炉 | F5: 389.31 | G5: GJ/104Nm3 | H5: 0.99 | I5: =56100/10^6 -> 0.0561 | J5: =1/10^6 -> 1e-06 | K5: =0.1/10^6 -> 1e-07 | L5: =F5*H5*I5 -> 21.621888 | M5: =F5*H5*J5 -> 0.0003854169 | N5: =F5*H5*K5 -> 3.854169e-05
B6: 2 | C6: 范围一 固定燃烧排放 | D6: 液化石油气燃烧 | E6: 冶钢宾馆 | F6: 50.179 | G6: GJ/t | H6: 0.98 | I6: =63100/10^6 -> 0.0631 | J6: =1/10^6 -> 1e-06 | K6: =0.1/10^6 -> 1e-07 | L6: =F6*H6*I6 -> 3.102969 | M6: =F6*H6*J6 -> 4.917542e-05 | N6: =F6*H6*K6 -> 4.917542e-06
B7: 3 | C7: 范围一 固定燃烧排放 | D7: 烟煤燃烧 | E7: 高炉 | F7: 23.736 | G7: GJ/t | H7: 0.99 | I7: =98300/10^6 -> 0.0983 | J7: =1/10^6 -> 1e-06 | K7: =1.5/10^6 -> 1.5e-06 | L7: =F7*H7*I7 -> 2.3099163 | M7: =F7*H7*J7 -> 2.349864e-05 | N7: =F7*H7*K7 -> 3.524796e-05
B8: 4 | C8: 范围一 固定燃烧排放 | D8: 无烟煤燃烧 | E8: 高炉 | F8: 25.024 | G8: GJ/t | H8: 0.99 | I8: =98300/10^6 -> 0.0983 | J8: =1/10^6 -> 1e-06 | K8: =1.5/10^6 -> 1.5e-06 | L8: =F8*H8*I8 -> 2.4352606 | M8: =F8*H8*J8 -> 2.477376e-05 | N8: =F8*H8*K8 -> 3.716064e-05
B9: 5 | C9: 范围一 固定燃烧排放 | D9: 洗精煤燃烧 | E9: 焦炉 | F9: 26.344 | G9: GJ/t | H9: 0.99 | I9: =94600/10^6 -> 0.0946 | J9: =1/10^6 -> 1e-06 | K9: =1.5/10^6 -> 1.5e-06 | L9: =F9*H9*I9 -> 2.467221 | M9: =F9*H9*J9 -> 2.608056e-05 | N9: =F9*H9*K9 -> 3.912084e-05
B10: 6 | C10: 范围一 固定燃烧排放 | D10: 焦炭燃烧 | E10: 焦炉 | F10: 28.435 | G10: GJ/t | H10: 0.99 | I10: =107000/10^6 -> 0.107 | J10: =1/10^6 -> 1e-06 | K10: =1.5/10^6 -> 1.5e-06 | L10: =F10*H10*I10 -> 3.0121195 | M10: =F10*H10*J10 -> 2.815065e-05 | N10: =F10*H10*K10 -> 4.2225975e-05
B11: 7 | C11: 范围一 固定燃烧排放 | D11: 焦屑燃烧 | E11: 焦炉 | F11: 28.435 | G11: GJ/t | H11: 0.99 | I11: =107000/10^6 -> 0.107 | J11: =1/10^6 -> 1e-06 | K11: =1.5/10^6 -> 1.5e-06 | L11: =F11*H11*I11 -> 3.0121195 | M11: =F11*H11*J11 -> 2.815065e-05 | N11: =F11*H11*K11 -> 4.2225975e-05
B12: 8 | C12: 范围一 固定燃烧排放 | D12: 焦丁燃烧 | E12: 焦炉 | F12: 28.435 | G12: GJ/t | H12: 0.99 | I12: =107000/10^6 -> 0.107 | J12: =1/10^6 -> 1e-06 | K12: =1.5/10^6 -> 1.5e-06 | L12: =F12*H12*I12 -> 3.0121195 | M12: =F12*H12*J12 -> 2.815065e-05 | N12: =F12*H12*K12 -> 4.2225975e-05
B13: 9 | C13: 范围一 固定燃烧排放 | D13: 焦炉煤气燃烧 | E13: 外售 | F13: 173.854 | G13: GJ/104Nm3 | H13: 0.99 | I13: =44400/10^6 -> 0.0444 | J13: =1/10^6 -> 1e-06 | K13: =0.1/10^6 -> 1e-07 | L13: =F13*H13*I13 -> 7.6419264 | M13: =F13*H13*J13 -> 0.00017211546 | N13: =F13*H13*K13 -> 1.7211546e-05
B14: 10 | C14: 范围一 移动燃烧排放 | D14: 柴油燃烧 | E14: 火车/货车 | F14: 42.652 | G14: GJ/t | H14: 0.98 | I14: 0.0741 | J14: =0.0039/10^3 -> 3.9e-06 | K14: =0.0039/10^3 -> 3.9e-06 | L14: =$F$14*$H$14*I14 -> 3.0973029 | M14: =$F$14*$H$14*J14 -> 0.00016301594 | N14: =$F$14*$H$14*K14 -> 0.00016301594
B15: 11 | C15: 范围一 移动燃烧排放 | D15: 汽油燃烧 | E15: 公务车 | F15: 43.07 | G15: GJ/t | H15: 0.98 | I15: 0.0693 | J15: =0.025/10^3 -> 2.5e-05 | K15: =0.008/10^3 -> 8e-06 | L15: =$F$15*$H$15*I15 -> 2.925056 | M15: =$F$15*$H$15*J15 -> 0.001055215 | N15: =$F$15*$H$15*K15 -> 0.0003376688
B17: 编号 | C17: GHG排放类别 | D17: 排放源 | E17: 设施 | F17: CO2排放因子 | G17: 单位
F18: 企业温室气体排放核算与报告指南 钢铁行业
B19: 1 | C19: 范围一 制程排放 | D19: 粗苯 | E19: 外售 | F19: 3.382 | G19: tCO2/t
B20: 2 | C20: 范围一 制程排放 | D20: 焦油 | E20: 外售 | F20: 2.699 | G20: tCO2/t
B21: 3 | C21: 范围一 制程排放 | D21: 石灰石 | E21: 石灰窑 | F21: 0.44 | G21: tCO2/t
B22: 4 | C22: 范围一 制程排放 | D22: 白云石 | E22: 高炉 | F22: 0.476 | G22: tCO2/t
B23: 5 | C23: 范围一 制程排放 | D23: 电极 | E23: 炼钢 | F23: 3.663 | G23: tCO2/t
B24: 6 | C24: 范围一 制程排放 | D24: 镍铁 | E24: 炼钢 | F24: 0.037 | G24: tCO2/t
B25: 7 | C25: 范围一 制程排放 | D25: 高碳铬铁 | E25: 炼钢 | F25: 0.348 | G25: tCO2/t
B26: 8 | C26: 范围一 制程排放 | D26: 钼铁 | E26: 炼钢 | F26: 0.018 | G26: tCO2/t
B27: 9 | C27: 范围一 制程排放 | D27: 硅铁 | E27: 炼钢 | F27: 0.007 | G27: tCO2/t
B28: 10 | C28: 范围一 制程排放 | D28: 高碳锰铁 | E28: 炼钢 | F28: 0.275 | G28: tCO2/t
B29: 11 | C29: 范围一 制程排放 | D29: 微碳锰铁 | E29: 炼钢 | F29: 0.004 | G29: tCO2/t
B30: 12 | C30: 范围一 制程排放 | D30: 锰硅合金 | E30: 炼钢 | F30: 0.092 | G30: tCO2/t
... B32: 14 | C32: 范围一 制程排放 | D32: 粗钢 | E32: 固碳产品 | F32: 0.037 | G32: tCO2/t
B35: 编号 | C35: GHG排放类别 | D35: 排放源 | E35: 设施 | F35: HFCs/PFCs | H35: MCF | I35: Bo | J35: 排放因子 | K35: 单位 | L35: 排放因子引用源
F36: EF估计值 | G36: 单位
B37: 1 | C37: 范围一 逸散排放 | D37: CO2逸散 | E37: 二氧化碳灭火器 | F37: 1 | G37: kgCO2/kg | L37: 质量平衡
B38: 2 | C38: 范围一 逸散排放 | D38: 制冷剂逸散（R32） | E38: 分体式空调 | F38: 1 | G38: kgGHG/kg | L38: 质量平衡
B39: 3 | C39: 范围一 逸散排放 | D39: CH4逸散 | E39: 化粪池 | H39: 0.3 | I39: 0.6 | J39: =H39*I39 -> 0.18 | K39: kgCH4/kgBOD | L39: 2006年IPCC国家温室气体清单指南V5_6_Ch6 Table6.2/6.3;公式6.1/6.2
B40: 4 | C40: 范围一 逸散排放 | D40: CH4逸散 | E40: 厌氧池 | H40: 0.3 | I40: 0.25 | J40: =H40*I40 -> 0.075 | K40: kgCH4/kgCOD | L40: 2006年IPCC国家温室气体清单指南V5_6_Ch6 Table6.2/6.3;公式6.1/6.2
B41: 5 | C41: 范围一 逸散排放 | D41: CH4逸散 | E41: 厌氧池、厕所、下水道等 | J41: 40 | K41: gBOD/人·天 | L41: 2006年IPCC国家温室气体清单指南V5_6_Ch6 Table 6.4;公式6.3
B43: 编号 | C43: GHG排放类别 | D43: 排放源 | E43: 设施 | F43: EF | G43: 单位 | H43: 排放因子引用源
B44: 1 | C44: 范围二 外购能源间接排放 | D44: 电力 | E44: 用电设备 | F44: 0.5306 | G44: tCO2/MWh | H44: 生态环境部、国家能源局发布2023年电力二氧化碳排放因子的公告（2023年全国电力排放因子）
B45: 2 | C45: 范围二 外购能源间接排放 | D45: 电力 | E45: 用电设备 | F45: 0.6096 | G45: tCO2/MWh | H45: 生态环境部、国家能源局发布2023年电力二氧化碳排放因子的公告（2023年全国电力平均二氧化碳排放因子（不包括市场化交易的非化石能源电量））
B47: 编号 | C47: GHG排放类别 | D47: 排放源 | E47: Activity name | F47: Geography | G47: CO2 | I47: 引用源
G48: 排放因子 | H48: 单位 | I48: 缺省排放因子
B49: 1 | C49: 范围三 类别1 外购商品和服务的上游排放 | D49: =表1温室气体盘查表!C32 -> 铁矿石生产 | E49: marker for Iron ore,crude ore,63% Fe | F49: Global (GLO) | G49: 0.098847 | H49: tCO2/t | I49: ecoinvent 3.10-cut off
B50: 2 | C50: 范围三 类别1 外购商品和服务的上游排放 | D50: =表1温室气体盘查表!C33 -> 生石灰生产 | E50: market for quicklime, in pieces, loose | F50: Rest-of-World (RoW) | G50: 1.1896699 | H50: tCO2/t | I50: ecoinvent 3.10-cut off
B51: 3 | C51: 范围三 类别1 外购商品和服务的上游排放 | D51: =表1温室气体盘查表!C34 -> 白云石生产 | E51: marker for dolomite | F51: Rest-of-World (RoW) | G51: 0.13033 | H51: tCO2/t | I51: ecoinvent 3.10-cut off
B52: 4 | C52: 范围三 类别1 外购商品和服务的上游排放 | D52: =表1温室气体盘查表!C35 -> 球团生产 | E52: market for iron pellet | F52: Global (GLO) | G52: 0.10446 | H52: tCO2/t | I52: ecoinvent 3.10-cut off
B53: 5 | C53: 范围三 类别1 外购商品和服务的上游排放 | D53: =表1温室气体盘查表!C36 -> 废钢生产 | E53: market for waste reinforcement steel | F53: Rest-of-World (RoW) | G53: 0.074179 | H53: tCO2/t | I53: ecoinvent 3.10-cut off
B54: 6 | C54: 范围三 类别1 外购商品和服务的上游排放 | D54: =表1温室气体盘查表!C37 -> 电极生产 | E54: market for graphite block | F54: Global (GLO) | G54: 12.17913 | H54: tCO2/t | I54: ecoinvent 3.11-cut off
B55: 7 | C55: 范围三 类别1 外购商品和服务的上游排放 | D55: =表1温室气体盘查表!C38 -> 锰铁生产 | E55: market for ferromanganese,high-coal,74.5% Mn | F55: Global (GLO) | G55: 2.9772 | H55: tCO2/t | I55: ecoinvent 3.10-cut off
B56: 8 | C56: 范围三 类别1 外购商品和服务的上游排放 | D56: =表1温室气体盘查表!C39 -> 镍铁生产 | E56: market for ferronickel | F56: Global (GLO) | G56: 8.7547 | H56: tCO2/t | I56: ecoinvent 3.10-cut off
B57: 9 | C57: 范围三 类别1 外购商品和服务的上游排放 | D57: =表1温室气体盘查表!C40 -> 铬铁生产 | E57: market for ferrochromium,high-carbom.55% Cr | F57: Global (GLO) | G57: 5.0921 | H57: tCO2/t | I57: ecoinvent 3.10-cut off
B58: 10 | C58: 范围三 类别1 外购商品和服务的上游排放 | D58: =表1温室气体盘查表!C41 -> 萤石生产 | E58: market for fluorspar, 97% purity | F58: Global (GLO) | G58: 0.21158 | H58: tCO2/t | I58: ecoinvent 3.10-cut off
B59: 11 | C59: 范围三 类别1 外购商品和服务的上游排放 | D59: =表1温室气体盘查表!C42 -> 硅铁生产 | E59: ferrosilicon production | F59: China (CN) | G59: 10.145 | H59: tCO2/t | I59: ecoinvent 3.10-cut off
B60: 12 | C60: 范围三 类别1 外购商品和服务的上游排放 | D60: =表1温室气体盘查表!C43 -> 钼铁生产 | E60: Ferro-Molybdenum | G60: 8.1 | H60: tCO2/t | I60: USLCI+
B61: 13 | C61: 范围三 类别1 外购商品和服务的上游排放 | D61: =表1温室气体盘查表!C44 -> 铝铁生产 | E61: market for aluminium,cast alloy | F61: global warming potential (GWP100) | G61: 5.7320082 | H61: tCO2/t | I61: ecoinvent 3.10-cut off
B62: 14 | C62: 范围三 类别1 外购商品和服务的上游排放 | D62: =表1温室气体盘查表!C45 -> 铝生产 | E62: market for aluminium,primary,ingot | F62: Rest-of-World (RoW) | G62: 22.290561 | H62: tCO2/t | I62: ecoinvent 3.10-cut off
B63: 15 | C63: 范围三 类别1 外购商品和服务的上游排放 | D63: =表1温室气体盘查表!C46 -> 增碳剂生产 | E63: market for recarburizer | F63: China (CN) | G63: 1.6645335 | H63: tCO2/t | I63: ecoinvent 3.11-cut off
B64: 16 | C64: 范围三 类别1 外购商品和服务的上游排放 | D64: =表1温室气体盘查表!C47 -> 铁鳞生产 | E64: market for iron scrap, unsorted | F64: Global (GLO) | G64: 0.0035231057 | H64: tCO2/t | I64: ecoinvent 3.10-cut off
B65: 17 | C65: 范围三 类别1 外购商品和服务的上游排放 | D65: =表1温室气体盘查表!C48 -> 氨水生产 | E65: market for ammonia, anhydrous, liquid | F65: China (CN) | G65: 5.4368448 | H65: tCO2/t | I65: ecoinvent 3.10-cut off
B66: 18 | C66: 范围三 类别1 外购商品和服务的上游排放 | D66: =表1温室气体盘查表!C49 -> 盐酸生产 | E66: market for hydrochloric acid, without water, in 30% solution state | F66: Rest-of-World (RoW) | G66: 0.97573527 | H66: tCO2/t | I66: ecoinvent 3.10-cut off
B67: 19 | C67: 范围三 类别1 外购商品和服务的上游排放 | D67: =表1温室气体盘查表!C50 -> 氢氧化钠生产 | E67: market for sodium hydroxide, without water, in 50% solution state | F67: Rest-of-World (RoW) | G67: 1.4645659 | H67: tCO2/t | I67: ecoinvent 3.10-cut off
B68: 20 | C68: 范围三 类别1 外购商品和服务的上游排放 | D68: =表1温室气体盘查表!C51 -> 碳化硅生产 | E68: market for silicon carbide | F68: Global (GLO) | G68: 7.2790711 | H68: tCO2/t | I68: ecoinvent 3.10-cut off
B69: 21 | C69: 范围三 类别1 外购商品和服务的上游排放 | D69: =表1温室气体盘查表!C52 -> 镁生产 | E69: market for magnesium | F69: Global (GLO) | G69: 26.345188 | H69: tCO2/t | I69: ecoinvent 3.10-cut off
B70: 22 | C70: 范围三 类别1 外购商品和服务的上游排放 | D70: 所有其他纸制品加工制造 | E70: All Other Converted Paper Product Manufacturing | G70: 0.000343 | H70: t CO2e/2022 USD, purchaser price | I70: SupplyChainGHGEmissionFactors_v1.3.0_NAICS_CO2e_USD2022
B71: 23 | C71: 范围三 类别1 外购商品和服务的上游排放 | D71: =表1温室气体盘查表!C54 -> 办公用品(纸张除外)制造 | E71: Office Supplies (except Paper) Manufacturing | G71: 0.000265 | H71: t CO2e/2022 USD, purchaser price | I71: SupplyChainGHGEmissionFactors_v1.3.0_NAICS_CO2e_USD2022
B72: 24 | C72: 范围三 类别1 外购商品和服务的上游排放 | D72: =表1温室气体盘查表!C55 -> 源水 | E72: market for tap water | F72: Rest-of-World (RoW) | G72: 0.0012784698 | H72: tCO2/t | I72: ecoinvent 3.10-cut off
B74: 编号 | C74: GHG排放类别 | D74: 排放源 | E74: Activity name | F74: CO2 | H74: 引用源
F75: 排放因子 | G75: 单位 | H75: 缺省排放因子
B76: 1 | C76: 范围三 类别2 资本货物 | D76: =表1温室气体盘查表!C56 -> 采购产品空调和暖空气加热设备和商业和工业制冷设备制造 | E76: Warm Air Heating and Air-Conditioning Equipment and Supplies Merchant Wholesalers | F76: =0.108/1000 -> 0.000108 | G76: t CO2e/2022 USD, purchaser price | H76: SupplyChainGHGEmissionFactors_v1.3.0_NAICS_CO2e_USD2022
B77: 2 | C77: 范围三 类别2 资本货物 | D77: =表1温室气体盘查表!C57 -> 电子计算机制造 | E77: Electronic Computer Manufacturing | F77: =0.058/1000 -> 5.8e-05 | G77: t CO2e/2022 USD, purchaser price | H77: SupplyChainGHGEmissionFactors_v1.3.0_NAICS_CO2e_USD2022
B78: 3 | C78: 范围三 类别2 资本货物 | D78: =表1温室气体盘查表!C58 -> 其他工业设备制造 | E78: Other Industrial Machinery Manufacturing | F78: =0.185/1000 -> 0.000185 | G78: t CO2e/2022 USD, purchaser price | H78: SupplyChainGHGEmissionFactors_v1.3.0_NAICS_CO2e_USD2022
B79: 4 | C79: 范围三 类别2 资本货物 | D79: =表1温室气体盘查表!C59 -> 测量和测试电力和电气信号的仪器制造 | E79: Instrument Manufacturing for Measuring and Testing Electricity and Electrical Signals | F79: =0.079/1000 -> 7.9e-05 | G79: t CO2e/2022 USD, purchaser price | H79: SupplyChainGHGEmissionFactors_v1.3.0_NAICS_CO2e_USD2022
B80: 5 | C80: 范围三 类别2 资本货物 | D80: 机械动力传动设备制造 | E80: Mechanical Power Transmission Equipment Manufacturing | F80: =0.209/1000 -> 0.000209 | G80: t CO2e/2022 USD, purchaser price | H80: SupplyChainGHGEmissionFactors_v1.3.0_NAICS_CO2e_USD2022
B81: 6 | C81: 范围三 类别2 资本货物 | D81: 测量、分配及其他泵类设备制造 | E81: Measuring, Dispensing, and Other Pumping Equipment Manufacturing | F81: =0.223/1000 -> 0.000223 | G81: t CO2e/2022 USD, purchaser price | H81: SupplyChainGHGEmissionFactors_v1.3.0_NAICS_CO2e_USD2022
B82: 7 | C82: 范围三 类别2 资本货物 | D82: 用于测量、显示和控制工业过程变量的仪器及相关产品制造 | E82: Instruments and Related Products Manufacturing for Measuring, Displaying, and Controlling Industrial Process Variables | F82: =0.063/1000 -> 6.3e-05 | G82: t CO2e/2022 USD, purchaser price | H82: SupplyChainGHGEmissionFactors_v1.3.0_NAICS_CO2e_USD2022
B83: 8 | C83: 范围三 类别2 资本货物 | D83: =表1温室气体盘查表!C63 -> 所有其他杂项电气设备及元件制造 | E83: All Other Miscellaneous Electrical Equipment and Component Manufacturing | F83: =0.128/1000 -> 0.000128 | G83: t CO2e/2022 USD, purchaser price | H83: SupplyChainGHGEmissionFactors_v1.3.0_NAICS_CO2e_USD2022
B84: 9 | C84: 范围三 类别2 资本货物 | D84: =表1温室气体盘查表!C64 -> 所有其他杂项制造 | E84: All Other Miscellaneous Manufacturing | F84: =0.182/1000 -> 0.000182 | G84: t CO2e/2022 USD, purchaser price | H84: SupplyChainGHGEmissionFactors_v1.3.0_NAICS_CO2e_USD2022
B86: 编号 | C86: GHG排放类别 | D86: 排放源 | E86: Activity name | F86: Geography | G86: CO2 | I86: 引用源
G87: 排放因子 | H87: 单位 | I87: 缺省排放因子
B88: 1 | C88: 范围三 类别3 范围一、二之外燃料和能源相关的活动产生的排放 | D88: =表1温室气体盘查表!C65 -> 液化石油气生产 | E88: market for liquefied petroleum gas | F88: Rest-of-World (RoW) | G88: 1.0062256 | H88: tCO2/t | I88: ecoinvent 3.10-cut off
B89: 2 | C89: 范围三 类别3 范围一、二之外燃料和能源相关的活动产生的排放 | D89: =表1温室气体盘查表!C66 -> 洗精煤生产 | E89: market for hard coal | F89: China (CN) | G89: 0.57555 | H89: tCO2/t | I89: ecoinvent 3.10-cut off
B90: 3 | C90: 范围三 类别3 范围一、二之外燃料和能源相关的活动产生的排放 | D90: =表1温室气体盘查表!C67 -> 柴油生产 | E90: market for diesel | F90: Rest-of-World (RoW) | G90: 0.84212 | H90: tCO2/t | I90: ecoinvent 3.10-cut off
B91: 4 | C91: 范围三 类别3 范围一、二之外燃料和能源相关的活动产生的排放 | D91: =表1温室气体盘查表!C68 -> 汽油生产 | E91: market for petrol, unleaded | F91: Rest-of-World (RoW) | G91: 0.98733031 | H91: tCO2/t | I91: ecoinvent 3.10-cut off
B92: 5 | C92: 范围三 类别3 范围一、二之外燃料和能源相关的活动产生的排放 | D92: =表1温室气体盘查表!C69 -> 焦炭生产 | E92: Metallurgical coke, at plant {RNA} 丨 Metallurgical coke | F92: China (CN) | G92: 0.349 | H92: tCO2/t | I92: USLCI+
B93: 6 | C93: 范围三 类别3 范围一、二之外燃料和能源相关的活动产生的排放 | D93: =表1温室气体盘查表!C70 -> 烟煤生产 | E93: Bituminous coal, at mine {RNA} 丨 Bituminous coal, at mine | F93: China (CN) | G93: 0.179 | H93: tCO2/t | I93: USLCI+
B94: 7 | C94: 范围三 类别3 范围一、二之外燃料和能源相关的活动产生的排放 | D94: =表1温室气体盘查表!C71 -> 无烟煤生产 | E94: Anthracite coal, at mine {RNA} 丨 Anthracite coal, at mine | F94: China (CN) | G94: 0.684 | H94: tCO2/t | I94: USLCI+
B95: 8 | C95: 范围三 类别3 范围一、二之外燃料和能源相关的活动产生的排放 | D95: =表1温室气体盘查表!C72 -> 天然气生产 | E95: market for natural gas, high pressure | F95: China (CN) | G95: 6.19 | H95: tCO2/10000Nm³ | I95: ecoinvent 3.10-cut off
B96: 9 | C96: 范围三 类别3 范围一、二之外燃料和能源相关的活动产生的排放 | D96: =表1温室气体盘查表!C73 -> 外购电力上游排放 | F96: China (CN) | G96: =0.6205-0.5306 -> 0.0899 | H96: tCO2/MWh | I96: 2023年全国电力平均碳足迹因子、2023年全国电力平均排放因子
B98: 编号 | C98: GHG排放类别 | D98: 排放源 | E98: Activity name | F98: Geography | G98: CO2 | I98: 引用源
G99: 排放因子 | H99: 单位 | I99: 缺省排放因子
B100: 1 | C100: 范围三 类别4 上下游运输配送产生的排放 | D100: 船运 | E100: market for transport, freight, inland waterways, barge | F100: Rest-of-World (RoW) | G100: 5.1968558e-05 | H100: tCO2-Eq/tkm | I100: ecoinvent 3.10-cut off
B101: 2 | C101: 范围三 类别4 上下游运输配送产生的排放 | D101: 汽运 | E101: market group for transport, freight, lorry, unspecified | F101: Global (GLO) | G101: 0.00015196288 | H101: tCO2-Eq/tkm | I101: ecoinvent 3.10-cut off
B102: 3 | C102: 范围三 类别4 上下游运输配送产生的排放 | D102: 铁路运输 | E102: market for transport, freight train | F102: China (CN) | G102: 4.8531851e-05 | H102: tCO2-Eq/tkm | I102: ecoinvent 3.10-cut off
B104: 编号 | C104: GHG排放类别 | D104: 排放源 | E104: Activity name | F104: Geography | G104: CO2 | I104: 引用源
G105: 排放因子 | H105: 单位 | I105: 缺省排放因子
B106: 1 | C106: 范围三 类别5 运营中产生的废物排放 | D106: 生活垃圾和厨余垃圾 | E106: market for average incineration residue | F106: Rest-of-World (RoW) | G106: 0.3713343 | H106: tCO2/t | I106: ecoinvent 3.10-cut off
B107: 2 | C107: 范围三 类别5 运营中产生的废物排放 | D107: 废油 | E107: treatment of waste mineral oil, hazardous waste incineration | F107: Rest-of-World (RoW) | G107: 2.849057 | H107: tCO2/t | I107: ecoinvent 3.10-cut off
B108: 3 | C108: 范围三 类别5 运营中产生的废物排放 | D108: 废油水 | E108: treatment of waste mineral oil, hazardous waste incineration | F108: Rest-of-World (RoW) | G108: 2.849057 | H108: tCO2/t | I108: ecoinvent 3.10-cut off
B110: 编号 | C110: GHG排放类别 | D110: 排放源 | E110: Activity name | F110: Geography | G110: CO2 | I110: 引用源
G111: 排放因子 | H111: 单位 | I111: 缺省排放因子
B112: 1 | C112: 范围三 类别6 商务旅行产生的排放 | D112: 航运 | E112: 国内航空客运（中型飞机） | G112: 0.084 | H112: kgCO2/passenger*km | I112: CPCD, China Products Carbon Footprint Factors Database
...

Sheet 减排行动统计
B2: 2024年已实施的节能减排措施
B3: 序号 | C3: 节能实施方案名称 | D3: 方案具体描述 | E3: 责任部门 | F3: 项目实施进度概况 | G3: 节能量预估
B4: 1 | C4: 节电 | D4: 通过选择经济购电套餐、错峰用电、降低计费容量等方式，2024年外购电价同比去年下降0.0784元/kWh（含年度交易电价下降0.0330元/kWh），减少外购电费13263万元，全年减少外购电费15560万元。 | E4: 能源环保部 | F4: 已完成 | G4: 预计全年减少外购电3800万kWh
B5: 2 | C5: 减少天然气外购 | D5: 推进焦气替代天然气项目，减少天然气外购，降低燃气成本。 | E5: 能源环保部 | F5: 已完成 | G5: 预计全年减少采购费用2000万元
B6: 3 | C6: 提升回收转炉煤气量 | D6: 通过改善回收条件、风机提频、管道清灰等措施提升转炉煤气回收量。 | E6: 能源环保部 | F6: 已完成 | G6: 预计全年创效1020万元
B7: 4 | C7: 管理类节能 | D7: 氩气提产降耗、提升转炉煤气回收等。 | E7: 能源环保部 | F7: 已完成 | G7: 吨钢氩气消耗量较去年下降1.3m³/t，转炉煤气回收较去年月均提高16.52m³/t
B9: 2025年计划实施的节能减排措施
B10: 序号 | C10: 节能实施方案名称 | D10: 方案具体描述 | E10: 责任部门 | F10: 项目实施进度概况 | G10: 节能量预估
B11: 1 | C11: 提升绿电消耗量 | D11: 增加自建光伏发电面积，加大外购绿电消耗量 | E11: 能源环保部 | F11: 实施中 | G11: 实现建筑物可利用面积光伏利用率≥90%，力争外购绿电消耗占比达10%
B12: 2 | C12: 提升焦炉煤气外送量 | D12: 按预定计划完成外供逸洋制管能源介质项目 | E12: 能源环保部 | F12: 实施中 | G12: 计划全年外供煤气1800万m³，减少碳排放1.37万吨

Sheet 活动数据汇总表（GHG基于位置）
A1: 各排放源明细
A2: 编号 | B2: GHG排放类别 | C2: 排放源 | D2: 报告边界 | E2: 活动数据 | G2: 排放因子&系数 | AD2: 排放量
G3: CO2 | J3: CH4 | M3: N2O | P3: HFCs | T3: PFCs | X3: SF6 | AA3: NF3 | AD3: =G3 -> CO2 | AE3: =J3 -> CH4 | AF3: =M3 -> N2O | AG3: =P3 -> HFCs | AH3: =T3 -> PFCs | AI3: =X3 -> SF6 | AJ3: =AA3 -> NF3 | AK3: 总量
E4: 数值 | F4: 计量单位 | G4: EF | H4: 计量单位 | I4: GWP | J4: EF | K4: 计量单位 | L4: GWP | M4: EF | N4: 计量单位 | O4: GWP | P4: EF | Q4: 计量单位 | R4: GWP | S4: 型号 | T4: EF | U4: 计量单位 | V4: GWP | W4: 型号 | X4: EF | Y4: 计量单位 | Z4: GWP | AA4: EF | AB4: 计量单位 | AC4: GWP | AD4: tCO2e
A5: 1 | B5: =表1温室气体盘查表!B5 -> 固定燃烧 | C5: =表1温室气体盘查表!C5 -> 天然气燃烧 | D5: =表1温室气体盘查表!E5 -> 范围一 | E5: =表1温室气体盘查表!F5 -> 1454 | F5: =表1温室气体盘查表!G5 -> 10000Nm3 | G5: ='附表2-EF'!K5*10 -> 1e-06 | H5: tCO2/10000Nm3 | I5: ='附表1-GWP TABLE'!E3 -> 1 | AD5: =表1温室气体盘查表!AF5 -> 31438.225 | AE5: =表1温室气体盘查表!AG5 -> 15.635053 | AF5: =表1温室气体盘查表!AH5 -> 15.298816 | AG5: =表1温室气体盘查表!AI5 -> 0 | AH5: =表1温室气体盘查表!AJ5 -> 0 | AI5: =表1温室气体盘查表!AK5 -> 0 | AJ5: =表1温室气体盘查表!AL5 -> 0 | AK5: =表1温室气体盘查表!AM5 -> 31469.159
A6: 2 | B6: =表1温室气体盘查表!B6 -> 固定燃烧 | C6: =表1温室气体盘查表!C6 -> 液化石油气燃烧 | D6: =表1温室气体盘查表!E6 -> 范围一 | E6: =表1温室气体盘查表!F6 -> 9.43 | F6: =表1温室气体盘查表!G6 -> t | G6: ='附表2-EF'!K6*10 -> 1e-06 | H6: tCO2/10000Nm4 | I6: ='附表1-GWP TABLE'!E4 -> 27.9 | AD6: =表1温室气体盘查表!AF6 -> 29.260998 | AE6: =表1温室气体盘查表!AG6 -> 0.012937905 | AF6: =表1温室气体盘查表!AH6 -> 0.012659671 | AG6: =表1温室气体盘查表!AI6 -> 0 | AH6: =表1温室气体盘查表!AJ6 -> 0 | AI6: =表1温室气体盘查表!AK6 -> 0 | AJ6: =表1温室气体盘查表!AL6 -> 0 | AK6: =表1温室气体盘查表!AM6 -> 29.286595
A7: 3 | B7: =表1温室气体盘查表!B7 -> 固定燃烧 | C7: =表1温室气体盘查表!C7 -> 烟煤燃烧 | D7: =表1温室气体盘查表!E7 -> 范围一 | E7: =表1温室气体盘查表!F7 -> 323067.87 | F7: =表1温室气体盘查表!G7 -> t | G7: ='附表2-EF'!K7*10 -> 1.5e-05 | H7: tCO2/10000Nm5 | I7: ='附表1-GWP TABLE'!E5 -> 273 | AD7: =表1温室气体盘查表!AF7 -> 746259.74 | AE7: =表1温室气体盘查表!AG7 -> 211.80719 | AF7: =表1温室气体盘查表!AH7 -> 3108.783 | AG7: =表1温室气体盘查表!AI7 -> 0 | AH7: =表1温室气体盘查表!AJ7 -> 0 | AI7: =表1温室气体盘查表!AK7 -> 0 | AJ7: =表1温室气体盘查表!AL7 -> 0 | AK7: =表1温室气体盘查表!AM7 -> 749580.33
A8: 4 | B8: =表1温室气体盘查表!B8 -> 固定燃烧 | C8: =表1温室气体盘查表!C8 -> 无烟煤燃烧 | D8: =表1温室气体盘查表!E8 -> 范围一 | E8: =表1温室气体盘查表!F8 -> 335482.33 | F8: =表1温室气体盘查表!G8 -> t | G8: ='附表2-EF'!K8*10 -> 1.5e-05 | H8: tCO2/10000Nm6 | I8: ='附表1-GWP TABLE'!E6 -> 0 | AD8: =表1温室气体盘查表!AF8 -> 816986.9 | AE8: =表1温室气体盘查表!AG8 -> 231.88133 | AF8: =表1温室气体盘查表!AH8 -> 3403.4195 | AG8: =表1温室气体盘查表!AI8 -> 0 | AH8: =表1温室气体盘查表!AJ8 -> 0 | AI8: =表1温室气体盘查表!AK8 -> 0 | AJ8: =表1温室气体盘查表!AL8 -> 0 | AK8: =表1温室气体盘查表!AM8 -> 820622.2
A9: 5 | B9: =表1温室气体盘查表!B9 -> 固定燃烧 | C9: =表1温室气体盘查表!C9 -> 洗精煤燃烧 | D9: =表1温室气体盘查表!E9 -> 范围一 | E9: =表1温室气体盘查表!F9 -> 2093622.8 | F9: =表1温室气体盘查表!G9 -> t | G9: ='附表2-EF'!K9*10 -> 1.5e-05 | H9: tCO2/10000Nm7 | I9: ='附表1-GWP TABLE'!E7 -> 0 | AD9: =表1温室气体盘查表!AF9 -> 5165430 | AE9: =表1温室气体盘查表!AG9 -> 1523.4196 | AF9: =表1温室气体盘查表!AH9 -> 22359.869 | AG9: =表1温室气体盘查表!AI9 -> 0 | AH9: =表1温室气体盘查表!AJ9 -> 0 | AI9: =表1温室气体盘查表!AK9 -> 0 | AJ9: =表1温室气体盘查表!AL9 -> 0 | AK9: =表1温室气体盘查表!AM9 -> 5189313.3
A10: 6 | B10: =表1温室气体盘查表!B10 -> 固定燃烧 | C10: =表1温室气体盘查表!C10 -> 焦炭燃烧 | D10: =表1温室气体盘查表!E10 -> 范围一 | E10: =表1温室气体盘查表!F10 -> 221509.17 | F10: =表1温室气体盘查表!G10 -> t | G10: ='附表2-EF'!K10*10 -> 1.5e-05 | H10: tCO2/10000Nm8 | I10: ='附表1-GWP TABLE'!E8 -> 0 | AD10: =表1温室气体盘查表!AF10 -> 667212.1 | AE10: =表1温室气体盘查表!AG10 -> 173.974 | AF10: =表1温室气体盘查表!AH10 -> 2553.4893 | AG10: =表1温室气体盘查表!AI10 -> 0 | AH10: =表1温室气体盘查表!AJ10 -> 0 | AI10: =表1温室气体盘查表!AK10 -> 0 | AJ10: =表1温室气体盘查表!AL10 -> 0 | AK10: =表1温室气体盘查表!AM10 -> 669939.56
A11: 7 | B11: =表1温室气体盘查表!B11 -> 固定燃烧 | C11: =表1温室气体盘查表!C11 -> 焦炉煤气燃烧 | D11: =表1温室气体盘查表!E11 -> 范围一 | E11: =表1温室气体盘查表!F11 -> -788.73 | F11: =表1温室气体盘查表!G11 -> 10000Nm3 | G11: ='附表2-EF'!K12*10 -> 1.5e-05 | H11: tCO2/10000Nm10 | I11: ='附表1-GWP TABLE'!E10 -> 0 | AD11: =表1温室气体盘查表!AF11 -> -6027.4166 | AE11: =表1温室气体盘查表!AG11 -> -3.7874983 | AF11: =表1温室气体盘查表!AH11 -> -3.7060467 | AG11: =表1温室气体盘查表!AI11 -> 0 | AH11: =表1温室气体盘查表!AJ11 -> 0 | AI11: =表1温室气体盘查表!AK11 -> 0 | AJ11: =表1温室气体盘查表!AL11 -> 0 | AK11: =表1温室气体盘查表!AM11 -> -6034.9102
A12: 8 | B12: =表1温室气体盘查表!B12 -> 移动燃烧 | C12: =表1温室气体盘查表!C12 -> 柴油燃烧 | D12: =表1温室气体盘查表!E12 -> 范围一 | E12: =表1温室气体盘查表!F12 -> 1422.69 | F12: =表1温室气体盘查表!G12 -> t | G12: ='附表2-EF'!K13*10 -> 1e-06 | H12: tCO2/10000Nm11 | I12: ='附表1-GWP TABLE'!E11 -> 0 | AD12: =表1温室气体盘查表!AF12 -> 4406.5019 | AE12: =表1温室气体盘查表!AG12 -> 6.4706002 | AF12: =表1温室气体盘查表!AH12 -> 63.314475 | AG12: =表1温室气体盘查表!AI12 -> 0 | AH12: =表1温室气体盘查表!AJ12 -> 0 | AI12: =表1温室气体盘查表!AK12 -> 0 | AJ12: =表1温室气体盘查表!AL12 -> 0 | AK12: =表1温室气体盘查表!AM12 -> 4476.287
A13: 9 | B13: =表1温室气体盘查表!B13 -> 移动燃烧 | C13: =表1温室气体盘查表!C13 -> 汽油燃烧 | D13: =表1温室气体盘查表!E13 -> 范围一 | E13: =表1温室气体盘查表!F13 -> 47.34 | F13: =表1温室气体盘查表!G13 -> t | G13: ='附表2-EF'!K14*10 -> 3.9e-05 | H13: tCO2/10000Nm12 | I13: ='附表1-GWP TABLE'!E12 -> 0 | AD13: =表1温室气体盘查表!AF13 -> 138.47215 | AE13: =表1温室气体盘查表!AG13 -> 1.3937132 | AF13: =表1温室气体盘查表!AH13 -> 4.3639708 | AG13: =表1温室气体盘查表!AI13 -> 0 | AH13: =表1温室气体盘查表!AJ13 -> 0 | AI13: =表1温室气体盘查表!AK13 -> 0 | AJ13: =表1温室气体盘查表!AL13 -> 0 | AK13: =表1温室气体盘查表!AM13 -> 144.22983
A14: 10 | B14: =表1温室气体盘查表!B14 -> 逸散排放 | C14: =表1温室气体盘查表!C14 -> 制冷剂逸散（R32） | D14: =表1温室气体盘查表!E14 -> 范围一 | E14: =表1温室气体盘查表!F14 -> 0.74 | F14: =表1温室气体盘查表!G14 -> t | G14: ='附表2-EF'!K15*10 -> 8e-05 | H14: tCO2/10000Nm13 | I14: ='附表1-GWP TABLE'!E13 -> 0 | AD14: =表1温室气体盘查表!AF14 -> 0 | AE14: =表1温室气体盘查表!AG14 -> 0 | AF14: =表1温室气体盘查表!AH14 -> 0 | AG14: =表1温室气体盘查表!AI14 -> 570.54 | AH14: =表1温室气体盘查表!AJ14 -> 0 | AI14: =表1温室气体盘查表!AK14 -> 0 | AJ14: =表1温室气体盘查表!AL14 -> 0 | AK14: =表1温室气体盘查表!AM14 -> 570.54
A15: 11 | B15: =表1温室气体盘查表!B15 -> 逸散排放 | C15: =表1温室气体盘查表!C15 -> CO2逸散 | D15: =表1温室气体盘查表!E15 -> 范围一 | E15: =表1温室气体盘查表!F15 -> 0.56 | F15: =表1温室气体盘查表!G15 -> t | G15: ='附表2-EF'!K16*10 -> 0 | H15: tCO2/10000Nm14 | I15: ='附表1-GWP TABLE'!E14 -> 0 | AD15: =表1温室气体盘查表!AF15 -> 0.56 | AE15: =表1温室气体盘查表!AG15 -> 0 | AF15: =表1温室气体盘查表!AH15 -> 0 | AG15: =表1温室气体盘查表!AI15 -> 0 | AH15: =表1温室气体盘查表!AJ15 -> 0 | AI15: =表1温室气体盘查表!AK15 -> 0 | AJ15: =表1温室气体盘查表!AL15 -> 0 | AK15: =表1温室气体盘查表!AM15 -> 0.56
A16: 12 | B16: =表1温室气体盘查表!B16 -> 逸散排放 | C16: =表1温室气体盘查表!C16 -> CH4逸散 | D16: =表1温室气体盘查表!E16 -> 范围一 | E16: =表1温室气体盘查表!F16 -> 23.16 | F16: =表1温室气体盘查表!G16 -> tBOD | G16: ='附表2-EF'!K17*10 -> 0 | H16: tCO2/10000Nm15 | I16: ='附表1-GWP TABLE'!E15 -> 0 | AD16: =表1温室气体盘查表!AF16 -> 0 | AE16: =表1温室气体盘查表!AG16 -> 116.30952 | AF16: =表1温室气体盘查表!AH16 -> 0 | AG16: =表1温室气体盘查表!AI16 -> 0 | AH16: =表1温室气体盘查表!AJ16 -> 0 | AI16: =表1温室气体盘查表!AK16 -> 0 | AJ16: =表1温室气体盘查表!AL16 -> 0 | AK16: =表1温室气体盘查表!AM16 -> 116.30952
A17: 13 | B17: =表1温室气体盘查表!B17 -> 逸散排放 | C17: =表1温室气体盘查表!C17 -> CH4逸散 | D17: =表1温室气体盘查表!E17 -> 范围一 | E17: =表1温室气体盘查表!F17 -> 4018.57 | F17: =表1温室气体盘查表!G17 -> tCOD | G17: ='附表2-EF'!K18*10 -> 0 | H17: tCO2/10000Nm16 | I17: ='附表1-GWP TABLE'!E16 -> 0 | AD17: =表1温室气体盘查表!AF17 -> 0 | AE17: =表1温室气体盘查表!AG17 -> 8408.8577 | AF17: =表1温室气体盘查表!AH17 -> 0 | AG17: =表1温室气体盘查表!AI17 -> 0 | AH17: =表1温室气体盘查表!AJ17 -> 0 | AI17: =表1温室气体盘查表!AK17 -> 0 | AJ17: =表1温室气体盘查表!AL17 -> 0 | AK17: =表1温室气体盘查表!AM17 -> 8408.8577
A18: 14 | B18: =表1温室气体盘查表!B18 -> 制程排放 | C18: =表1温室气体盘查表!C18 -> 白云石 | D18: =表1温室气体盘查表!E18 -> 范围一 | E18: =表1温室气体盘查表!F18 -> 38669.45 | F18: =表1温室气体盘查表!G18 -> t | G18: ='附表2-EF'!K19*10 -> 0 | H18: tCO2/10000Nm17 | I18: ='附表1-GWP TABLE'!E17 -> 0 | AD18: =表1温室气体盘查表!AF18 -> 18406.658 | AE18: =表1温室气体盘查表!AG18 -> 0 | AF18: =表1温室气体盘查表!AH18 -> 0 | AG18: =表1温室气体盘查表!AI18 -> 0 | AH18: =表1温室气体盘查表!AJ18 -> 0 | AI18: =表1温室气体盘查表!AK18 -> 0 | AJ18: =表1温室气体盘查表!AL18 -> 0 | AK18: =表1温室气体盘查表!AM18 -> 18406.658
A19: 15 | B19: =表1温室气体盘查表!B19 -> 制程排放 | C19: =表1温室气体盘查表!C19 -> 电极 | D19: =表1温室气体盘查表!E19 -> 范围一 | E19: =表1温室气体盘查表!F19 -> 5005.45 | F19: =表1温室气体盘查表!G19 -> t | G19: ='附表2-EF'!K20*10 -> 0 | H19: tCO2/10000Nm18 | I19: ='附表1-GWP TABLE'!E18 -> 0 | AD19: =表1温室气体盘查表!AF19 -> 18334.963 | AE19: =表1温室气体盘查表!AG19 -> 0 | AF19: =表1温室气体盘查表!AH19 -> 0 | AG19: =表1温室气体盘查表!AI19 -> 0 | AH19: =表1温室气体盘查表!AJ19 -> 0 | AI19: =表1温室气体盘查表!AK19 -> 0 | AJ19: =表1温室气体盘查表!AL19 -> 0 | AK19: =表1温室气体盘查表!AM19 -> 18334.963
A20: 16 | B20: =表1温室气体盘查表!B20 -> 制程排放 | C20: =表1温室气体盘查表!C20 -> 废钢 | D20: =表1温室气体盘查表!E20 -> 范围一 | E20: =表1温室气体盘查表!F20 -> 1119615.7 | F20: =表1温室气体盘查表!G20 -> t | G20: ='附表2-EF'!K21*10 -> 0 | H20: tCO2/10000Nm19 | I20: ='附表1-GWP TABLE'!E19 -> 0 | AD20: =表1温室气体盘查表!AF20 -> 41425.779 | AE20: =表1温室气体盘查表!AG20 -> 0 | AF20: =表1温室气体盘查表!AH20 -> 0 | AG20: =表1温室气体盘查表!AI20 -> 0 | AH20: =表1温室气体盘查表!AJ20 -> 0 | AI20: =表1温室气体盘查表!AK20 -> 0 | AJ20: =表1温室气体盘查表!AL20 -> 0 | AK20: =表1温室气体盘查表!AM20 -> 41425.779
A21: 17 | B21: =表1温室气体盘查表!B21 -> 制程排放 | C21: =表1温室气体盘查表!C21 -> 高碳锰铁 | D21: =表1温室气体盘查表!E21 -> 范围一 | E21: =表1温室气体盘查表!F21 -> 41483.17 | F21: =表1温室气体盘查表!G21 -> t | G21: ='附表2-EF'!K22*10 -> 0 | H21: tCO2/10000Nm20 | I21: ='附表1-GWP TABLE'!E20 -> 0 | AD21: =表1温室气体盘查表!AF21 -> 11407.872 | AE21: =表1温室气体盘查表!AG21 -> 0 | AF21: =表1温室气体盘查表!AH21 -> 0 | AG21: =表1温室气体盘查表!AI21 -> 0 | AH21: =表1温室气体盘查表!AJ21 -> 0 | AI21: =表1温室气体盘查表!AK21 -> 0 | AJ21: =表1温室气体盘查表!AL21 -> 0 | AK21: =表1温室气体盘查表!AM21 -> 11407.872
A22: 18 | B22: =表1温室气体盘查表!B22 -> 制程排放 | C22: =表1温室气体盘查表!C22 -> 锰硅合金 | D22: =表1温室气体盘查表!E22 -> 范围一 | E22: =表1温室气体盘查表!F22 -> 2887.69 | F22: =表1温室气体盘查表!G22 -> t | G22: ='附表2-EF'!K23*10 -> 0 | H22: tCO2/10000Nm21 | I22: ='附表1-GWP TABLE'!E21 -> 0 | AD22: =表1温室气体盘查表!AF22 -> 265.66748 | AE22: =表1温室气体盘查表!AG22 -> 0 | AF22: =表1温室气体盘查表!AH22 -> 0 | AG22: =表1温室气体盘查表!AI22 -> 0 | AH22: =表1温室气体盘查表!AJ22 -> 0 | AI22: =表1温室气体盘查表!AK22 -> 0 | AJ22: =表1温室气体盘查表!AL22 -> 0 | AK22: =表1温室气体盘查表!AM22 -> 265.66748
... A30: 26 | B30: =表1温室气体盘查表!B30 -> 输入能源间接温室气体排放 | C30: =表1温室气体盘查表!C30 -> 外购电力（基于位置） | D30: =表1温室气体盘查表!E30 -> 范围二 | E30: =表1温室气体盘查表!F30 -> 1966850.8 | F30: =表1温室气体盘查表!G30 -> MWh | G30: ='附表2-EF'!K31*10 -> 0 | H30: tCO2/10000Nm29 | I30: ='附表1-GWP TABLE'!E29 -> 0 | AD30: =表1温室气体盘查表!AF30 -> 1043611.1 | AE30: =表1温室气体盘查表!AG30 -> 0 | AF30: =表1温室气体盘查表!AH30 -> 0 | AG30: =表1温室气体盘查表!AI30 -> 0 | AH30: =表1温室气体盘查表!AJ30 -> 0 | AI30: =表1温室气体盘查表!AK30 -> 0 | AJ30: =表1温室气体盘查表!AL30 -> 0 | AK30: =表1温室气体盘查表!AM30 -> 1043611.1
A31: 27 | B31: =表1温室气体盘查表!B32 -> 外购商品和服务的上游排放 | C31: =表1温室气体盘查表!C32 -> 铁矿石生产 | D31: =表1温室气体盘查表!E32 -> 范围三 类别1 | E31: =表1温室气体盘查表!F32 -> 4854324.1 | F31: =表1温室气体盘查表!G32 -> t | G31: ='附表2-EF'!K33*10 -> 0 | H31: tCO2/10000Nm31 | I31: ='附表1-GWP TABLE'!E31 -> 0 | AD31: =表1温室气体盘查表!AF32 -> 479835.37 | AE31: =表1温室气体盘查表!AG32 -> 0 | AF31: =表1温室气体盘查表!AH32 -> 0 | AG31: =表1温室气体盘查表!AI32 -> 0 | AH31: =表1温室气体盘查表!AJ32 -> 0 | AI31: =表1温室气体盘查表!AK32 -> 0 | AJ31: =表1温室气体盘查表!AL32 -> 0 | AK31: =表1温室气体盘查表!AM32 -> 479835.37
A32: 28 | B32: =表1温室气体盘查表!B33 -> 外购商品和服务的上游排放 | C32: =表1温室气体盘查表!C33 -> 生石灰生产 | D32: =表1温室气体盘查表!E33 -> 范围三 类别1 | E32: =表1温室气体盘查表!F33 -> 199182.36 | F32: =表1温室气体盘查表!G33 -> t | G32: ='附表2-EF'!K34*10 -> 0 | H32: tCO2/10000Nm32 | I32: ='附表1-GWP TABLE'!E32 -> 0 | AD32: =表1温室气体盘查表!AF33 -> 236961.26 | AE32: =表1温室气体盘查表!AG33 -> 0 | AF32: =表1温室气体盘查表!AH33 -> 0 | AG32: =表1温室气体盘查表!AI33 -> 0 | AH32: =表1温室气体盘查表!AJ33 -> 0 | AI32: =表1温室气体盘查表!AK33 -> 0 | AJ32: =表1温室气体盘查表!AL33 -> 0 | AK32: =表1温室气体盘查表!AM33 -> 236961.26
A33: 29 | B33: =表1温室气体盘查表!B34 -> 外购商品和服务的上游排放 | C33: =表1温室气体盘查表!C34 -> 白云石生产 | D33: =表1温室气体盘查表!E34 -> 范围三 类别1 | E33: =表1温室气体盘查表!F34 -> 38669.45 | F33: =表1温室气体盘查表!G34 -> t | G33: ='附表2-EF'!K35*10 -> #VALUE! | H33: tCO2/10000Nm33 | I33: ='附表1-GWP TABLE'!E33 -> 0 | AD33: =表1温室气体盘查表!AF34 -> 5039.7894 | AE33: =表1温室气体盘查表!AG34 -> 0 | AF33: =表1温室气体盘查表!AH34 -> 0 | AG33: =表1温室气体盘查表!AI34 -> 0 | AH33: =表1温室气体盘查表!AJ34 -> 0 | AI33: =表1温室气体盘查表!AK34 -> 0 | AJ33: =表1温室气体盘查表!AL34 -> 0 | AK33: =表1温室气体盘查表!AM34 -> 5039.7894
A34: 30 | B34: =表1温室气体盘查表!B35 -> 外购商品和服务的上游排放 | C34: =表1温室气体盘查表!C35 -> 球团生产 | D34: =表1温室气体盘查表!E35 -> 范围三 类别1 | E34: =表1温室气体盘查表!F35 -> 681993.89 | F34: =表1温室气体盘查表!G35 -> t | G34: ='附表2-EF'!K36*10 -> 0 | H34: tCO2/10000Nm34 | I34: ='附表1-GWP TABLE'!E34 -> 0 | AD34: =表1温室气体盘查表!AF35 -> 71241.082 | AE34: =表1温室气体盘查表!AG35 -> 0 | AF34: =表1温室气体盘查表!AH35 -> 0 | AG34: =表1温室气体盘查表!AI35 -> 0 | AH34: =表1温室气体盘查表!AJ35 -> 0 | AI34: =表1温室气体盘查表!AK35 -> 0 | AJ34: =表1温室气体盘查表!AL35 -> 0 | AK34: =表1温室气体盘查表!AM35 -> 71241.082
A35: 31 | B35: =表1温室气体盘查表!B36 -> 外购商品和服务的上游排放 | C35: =表1温室气体盘查表!C36 -> 废钢生产 | D35: =表1温室气体盘查表!E36 -> 范围三 类别1 | E35: =表1温室气体盘查表!F36 -> 1119615.7 | F35: =表1温室气体盘查表!G36 -> t | G35: ='附表2-EF'!K37*10 -> 0 | H35: tCO2/10000Nm35 | I35: ='附表1-GWP TABLE'!E35 -> 0 | AD35: =表1温室气体盘查表!AF36 -> 83051.97 | AE35: =表1温室气体盘查表!AG36 -> 0 | AF35: =表1温室气体盘查表!AH36 -> 0 | AG35: =表1温室气体盘查表!AI36 -> 0 | AH35: =表1温室气体盘查表!AJ36 -> 0 | AI35: =表1温室气体盘查表!AK36 -> 0 | AJ35: =表1温室气体盘查表!AL36 -> 0 | AK35: =表1温室气体盘查表!AM36 -> 83051.97
A36: 32 | B36: =表1温室气体盘查表!B37 -> 外购商品和服务的上游排放 | C36: =表1温室气体盘查表!C37 -> 电极生产 | D36: =表1温室气体盘查表!E37 -> 范围三 类别1 | E36: =表1温室气体盘查表!F37 -> 5005.45 | F36: =表1温室气体盘查表!G37 -> t | G36: ='附表2-EF'!K38*10 -> 0 | H36: tCO2/10000Nm36 | I36: ='附表1-GWP TABLE'!E36 -> 0 | AD36: =表1温室气体盘查表!AF37 -> 60962.024 | AE36: =表1温室气体盘查表!AG37 -> 0 | AF36: =表1温室气体盘查表!AH37 -> 0 | AG36: =表1温室气体盘查表!AI37 -> 0 | AH36: =表1温室气体盘查表!AJ37 -> 0 | AI36: =表1温室气体盘查表!AK37 -> 0 | AJ36: =表1温室气体盘查表!AL37 -> 0 | AK36: =表1温室气体盘查表!AM37 -> 60962.024
A37: 33 | B37: =表1温室气体盘查表!B38 -> 外购商品和服务的上游排放 | C37: =表1温室气体盘查表!C38 -> 锰铁生产 | D37: =表1温室气体盘查表!E38 -> 范围三 类别1 | E37: =表1温室气体盘查表!F38 -> 41483.17 | F37: =表1温室气体盘查表!G38 -> t | G37: ='附表2-EF'!K39*10 -> #VALUE! | H37: tCO2/10000Nm37 | I37: ='附表1-GWP TABLE'!E37 -> 0 | AD37: =表1温室气体盘查表!AF38 -> 123503.69 | AE37: =表1温室气体盘查表!AG38 -> 0 | AF37: =表1温室气体盘查表!AH38 -> 0 | AG37: =表1温室气体盘查表!AI38 -> 0 | AH37: =表1温室气体盘查表!AJ38 -> 0 | AI37: =表1温室气体盘查表!AK38 -> 0 | AJ37: =表1温室气体盘查表!AL38 -> 0 | AK37: =表1温室气体盘查表!AM38 -> 123503.69
A38: 34 | B38: =表1温室气体盘查表!B39 -> 外购商品和服务的上游排放 | C38: =表1温室气体盘查表!C39 -> 镍铁生产 | D38: =表1温室气体盘查表!E39 -> 范围三 类别1 | E38: =表1温室气体盘查表!F39 -> 9943.2 | F38: =表1温室气体盘查表!G39 -> t | G38: ='附表2-EF'!K40*10 -> #VALUE! | H38: tCO2/10000Nm38 | I38: ='附表1-GWP TABLE'!E38 -> 0 | AD38: =表1温室气体盘查表!AF39 -> 87049.733 | AE38: =表1温室气体盘查表!AG39 -> 0 | AF38: =表1温室气体盘查表!AH39 -> 0 | AG38: =表1温室气体盘查表!AI39 -> 0 | AH38: =表1温室气体盘查表!AJ39 -> 0 | AI38: =表1温室气体盘查表!AK39 -> 0 | AJ38: =表1温室气体盘查表!AL39 -> 0 | AK38: =表1温室气体盘查表!AM39 -> 87049.733
A39: 35 | B39: =表1温室气体盘查表!B40 -> 外购商品和服务的上游排放 | C39: =表1温室气体盘查表!C40 -> 铬铁生产 | D39: =表1温室气体盘查表!E40 -> 范围三 类别1 | E39: =表1温室气体盘查表!F40 -> 40208.13 | F39: =表1温室气体盘查表!G40 -> t | G39: ='附表2-EF'!K41*10 -> #VALUE! | H39: tCO2/10000Nm39 | I39: ='附表1-GWP TABLE'!E39 -> 0 | AD39: =表1温室气体盘查表!AF40 -> 204743.82 | AE39: =表1温室气体盘查表!AG40 -> 0 | AF39: =表1温室气体盘查表!AH40 -> 0 | AG39: =表1温室气体盘查表!AI40 -> 0 | AH39: =表1温室气体盘查表!AJ40 -> 0 | AI39: =表1温室气体盘查表!AK40 -> 0 | AJ39: =表1温室气体盘查表!AL40 -> 0 | AK39: =表1温室气体盘查表!AM40 -> 204743.82
A40: 36 | B40: =表1温室气体盘查表!B41 -> 外购商品和服务的上游排放 | C40: =表1温室气体盘查表!C41 -> 萤石生产 | D40: =表1温室气体盘查表!E41 -> 范围三 类别1 | E40: =表1温室气体盘查表!F41 -> 418155.97 | F40: =表1温室气体盘查表!G41 -> t | G40: ='附表2-EF'!K42*10 -> 0 | H40: tCO2/10000Nm40 | I40: ='附表1-GWP TABLE'!E40 -> 0 | AD40: =表1温室气体盘查表!AF41 -> 88473.44 | AE40: =表1温室气体盘查表!AG41 -> 0 | AF40: =表1温室气体盘查表!AH41 -> 0 | AG40: =表1温室气体盘查表!AI41 -> 0 | AH40: =表1温室气体盘查表!AJ41 -> 0 | AI40: =表1温室气体盘查表!AK41 -> 0 | AJ40: =表1温室气体盘查表!AL41 -> 0 | AK40: =表1温室气体盘查表!AM41 -> 88473.44
A41: 37 | B41: =表1温室气体盘查表!B42 -> 外购商品和服务的上游排放 | C41: =表1温室气体盘查表!C42 -> 硅铁生产 | D41: =表1温室气体盘查表!E42 -> 范围三 类别1 | E41: =表1温室气体盘查表!F42 -> 14695.77 | F41: =表1温室气体盘查表!G42 -> t | G41: ='附表2-EF'!K43*10 -> 0 | H41: tCO2/10000Nm41 | I41: ='附表1-GWP TABLE'!E41 -> 0 | AD41: =表1温室气体盘查表!AF42 -> 149088.59 | AE41: =表1温室气体盘查表!AG42 -> 0 | AF41: =表1温室气体盘查表!AH42 -> 0 | AG41: =表1温室气体盘查表!AI42 -> 0 | AH41: =表1温室气体盘查表!AJ42 -> 0 | AI41: =表1温室气体盘查表!AK42 -> 0 | AJ41: =表1温室气体盘查表!AL42 -> 0 | AK41: =表1温室气体盘查表!AM42 -> 149088.59
A42: 38 | B42: =表1温室气体盘查表!B43 -> 外购商品和服务的上游排放 | C42: =表1温室气体盘查表!C43 -> 钼铁生产 | D42: =表1温室气体盘查表!E43 -> 范围三 类别1 | E42: =表1温室气体盘查表!F43 -> 7268.72 | F42: =表1温室气体盘查表!G43 -> t | G42: ='附表2-EF'!K44*10 -> 0 | H42: tCO2/10000Nm42 | I42: ='附表1-GWP TABLE'!E42 -> 0 | AD42: =表1温室气体盘查表!AF43 -> 58876.632 | AE42: =表1温室气体盘查表!AG43 -> 0 | AF42: =表1温室气体盘查表!AH43 -> 0 | AG42: =表1温室气体盘查表!AI43 -> 0 | AH42: =表1温室气体盘查表!AJ43 -> 0 | AI42: =表1温室气体盘查表!AK43 -> 0 | AJ42: =表1温室气体盘查表!AL43 -> 0 | AK42: =表1温室气体盘查表!AM43 -> 58876.632
... A49: 45 | B49: =表1温室气体盘查表!B50 -> 外购商品和服务的上游排放 | C49: =表1温室气体盘查表!C50 -> 氢氧化钠生产 | D49: =表1温室气体盘查表!E50 -> 范围三 类别1 | E49: =表1温室气体盘查表!F50 -> 2.24 | F49: =表1温室气体盘查表!G50 -> t | G49: ='附表2-EF'!K51*10 -> 0 | H49: tCO2/10000Nm49 | I49: ='附表1-GWP TABLE'!E49 -> 0 | AD49: =表1温室气体盘查表!AF50 -> 3.2806275 | AE49: =表1温室气体盘查表!AG50 -> 0 | AF49: =表1温室气体盘查表!AH50 -> 0 | AG49: =表1温室气体盘查表!AI50 -> 0 | AH49: =表1温室气体盘查表!AJ50 -> 0 | AI49: =表1温室气体盘查表!AK50 -> 0 | AJ49: =表1温室气体盘查表!AL50 -> 0 | AK49: =表1温室气体盘查表!AM50 -> 3.2806275
A50: 46 | B50: =表1温室气体盘查表!B51 -> 外购商品和服务的上游排放 | C50: =表1温室气体盘查表!C51 -> 碳化硅生产 | D50: =表1温室气体盘查表!E51 -> 范围三 类别1 | E50: =表1温室气体盘查表!F51 -> 3676.387 | F50: =表1温室气体盘查表!G51 -> t | G50: ='附表2-EF'!K50*10 -> 0 | H50: tCO2/10000Nm48 | I50: ='附表1-GWP TABLE'!E48 -> 24300 | AD50: =表1温室气体盘查表!AF51 -> 26760.682 | AE50: =表1温室气体盘查表!AG51 -> 0 | AF50: =表1温室气体盘查表!AH51 -> 0 | AG50: =表1温室气体盘查表!AI51 -> 0 | AH50: =表1温室气体盘查表!AJ51 -> 0 | AI50: =表1温室气体盘查表!AK51 -> 0 | AJ50: =表1温室气体盘查表!AL51 -> 0 | AK50: =表1温室气体盘查表!AM51 -> 26760.682
A51: 47 | B51: =表1温室气体盘查表!B52 -> 外购商品和服务的上游排放 | C51: =表1温室气体盘查表!C52 -> 镁生产 | D51: =表1温室气体盘查表!E52 -> 范围三 类别1 | E51: =表1温室气体盘查表!F52 -> 9749.982 | F51: =表1温室气体盘查表!G52 -> t | G51: ='附表2-EF'!K51*10 -> 0 | H51: tCO2/10000Nm49 | I51: ='附表1-GWP TABLE'!E49 -> 0 | AD51: =表1温室气体盘查表!AF52 -> 256865.11 | AE51: =表1温室气体盘查表!AG52 -> 0 | AF51: =表1温室气体盘查表!AH52 -> 0 | AG51: =表1温室气体盘查表!AI52 -> 0 | AH51: =表1温室气体盘查表!AJ52 -> 0 | AI51: =表1温室气体盘查表!AK52 -> 0 | AJ51: =表1温室气体盘查表!AL52 -> 0 | AK51: =表1温室气体盘查表!AM52 -> 256865.11
A52: 48 | B52: =表1温室气体盘查表!B53 -> 外购商品和服务的上游排放 | C52: =表1温室气体盘查表!C53 -> 所有其他纸制品加工制造 | D52: =表1温室气体盘查表!E53 -> 范围三 类别1 | E52: =表1温室气体盘查表!F53 -> 15287.09 | F52: =表1温室气体盘查表!G53 -> $ | G52: ='附表2-EF'!K52*10 -> 0 | H52: tCO2/10000Nm50 | I52: ='附表1-GWP TABLE'!E50 -> 0 | AD52: =表1温室气体盘查表!AF53 -> 5.2434719 | AE52: =表1温室气体盘查表!AG53 -> 0 | AF52: =表1温室气体盘查表!AH53 -> 0 | AG52: =表1温室气体盘查表!AI53 -> 0 | AH52: =表1温室气体盘查表!AJ53 -> 0 | AI52: =表1温室气体盘查表!AK53 -> 0 | AJ52: =表1温室气体盘查表!AL53 -> 0 | AK52: =表1温室气体盘查表!AM53 -> 5.2434719
A53: 49 | B53: =表1温室气体盘查表!B54 -> 外购商品和服务的上游排放 | C53: =表1温室气体盘查表!C54 -> 办公用品(纸张除外)制造 | D53: =表1温室气体盘查表!E54 -> 范围三 类别1 | E53: =表1温室气体盘查表!F54 -> 272877.67 | F53: =表1温室气体盘查表!G54 -> $ | G53: ='附表2-EF'!K53*10 -> 0 | H53: tCO2/10000Nm51 | I53: ='附表1-GWP TABLE'!E51 -> 0 | AD53: =表1温室气体盘查表!AF54 -> 72.312583 | AE53: =表1温室气体盘查表!AG54 -> 0 | AF53: =表1温室气体盘查表!AH54 -> 0 | AG53: =表1温室气体盘查表!AI54 -> 0 | AH53: =表1温室气体盘查表!AJ54 -> 0 | AI53: =表1温室气体盘查表!AK54 -> 0 | AJ53: =表1温室气体盘查表!AL54 -> 0 | AK53: =表1温室气体盘查表!AM54 -> 72.312583
A54: 50 | B54: =表1温室气体盘查表!B55 -> 外购商品和服务的上游排放 | C54: =表1温室气体盘查表!C55 -> 源水 | D54: =表1温室气体盘查表!E55 -> 范围三 类别1 | E54: =表1温室气体盘查表!F55 -> 20647661 | F54: =表1温室气体盘查表!G55 -> t | G54: ='附表2-EF'!K54*10 -> 0 | H54: tCO2/10000Nm52 | I54: ='附表1-GWP TABLE'!E52 -> 0 | AD54: =表1温室气体盘查表!AF55 -> 26397.412 | AE54: =表1温室气体盘查表!AG55 -> 0 | AF54: =表1温室气体盘查表!AH55 -> 0 | AG54: =表1温室气体盘查表!AI55 -> 0 | AH54: =表1温室气体盘查表!AJ55 -> 0 | AI54: =表1温室气体盘查表!AK55 -> 0 | AJ54: =表1温室气体盘查表!AL55 -> 0 | AK54: =表1温室气体盘查表!AM55 -> 26397.412
A55: 51 | B55: =表1温室气体盘查表!B56 -> 资本货物 | C55: =表1温室气体盘查表!C56 -> 采购产品空调和暖空气加热设备和商业和工业制冷设备制造 | D55: =表1温室气体盘查表!E56 -> 范围三 类别2 | E55: =表1温室气体盘查表!F56 -> 1112205.8 | F55: =表1温室气体盘查表!G56 -> $ | G55: ='附表2-EF'!K55*10 -> 0 | H55: tCO2/10000Nm53 | I55: ='附表1-GWP TABLE'!E53 -> 0 | AD55: =表1温室气体盘查表!AF56 -> 120.11822 | AE55: =表1温室气体盘查表!AG56 -> 0 | AF55: =表1温室气体盘查表!AH56 -> 0 | AG55: =表1温室气体盘查表!AI56 -> 0 | AH55: =表1温室气体盘查表!AJ56 -> 0 | AI55: =表1温室气体盘查表!AK56 -> 0 | AJ55: =表1温室气体盘查表!AL56 -> 0 | AK55: =表1温室气体盘查表!AM56 -> 120.11822
A56: 52 | B56: =表1温室气体盘查表!B57 -> 资本货物 | C56: =表1温室气体盘查表!C57 -> 电子计算机制造 | D56: =表1温室气体盘查表!E57 -> 范围三 类别2 | E56: =表1温室气体盘查表!F57 -> 445501.57 | F56: =表1温室气体盘查表!G57 -> $ | G56: ='附表2-EF'!K56*10 -> 0 | H56: tCO2/10000Nm54 | I56: ='附表1-GWP TABLE'!E54 -> 0 | AD56: =表1温室气体盘查表!AF57 -> 25.839091 | AE56: =表1温室气体盘查表!AG57 -> 0 | AF56: =表1温室气体盘查表!AH57 -> 0 | AG56: =表1温室气体盘查表!AI57 -> 0 | AH56: =表1温室气体盘查表!AJ57 -> 0 | AI56: =表1温室气体盘查表!AK57 -> 0 | AJ56: =表1温室气体盘查表!AL57 -> 0 | AK56: =表1温室气体盘查表!AM57 -> 25.839091
A57: 53 | B57: =表1温室气体盘查表!B58 -> 资本货物 | C57: =表1温室气体盘查表!C58 -> 其他工业设备制造 | D57: =表1温室气体盘查表!E58 -> 范围三 类别2 | E57: =表1温室气体盘查表!F58 -> 2803779.7 | F57: =表1温室气体盘查表!G58 -> $ | G57: ='附表2-EF'!K57*10 -> 0 | H57: tCO2/10000Nm55 | I57: ='附表1-GWP TABLE'!E55 -> 0 | AD57: =表1温室气体盘查表!AF58 -> 518.69925 | AE57: =表1温室气体盘查表!AG58 -> 0 | AF57: =表1温室气体盘查表!AH58 -> 0 | AG57: =表1温室气体盘查表!AI58 -> 0 | AH57: =表1温室气体盘查表!AJ58 -> 0 | AI57: =表1温室气体盘查表!AK58 -> 0 | AJ57: =表1温室气体盘查表!AL58 -> 0 | AK57: =表1温室气体盘查表!AM58 -> 518.69925
A58: 54 | B58: =表1温室气体盘查表!B59 -> 资本货物 | C58: =表1温室气体盘查表!C59 -> 测量和测试电力和电气信号的仪器制造 | D58: =表1温室气体盘查表!E59 -> 范围三 类别2 | E58: =表1温室气体盘查表!F59 -> 2788670.8 | F58: =表1温室气体盘查表!G59 -> $ | G58: ='附表2-EF'!K58*10 -> 0 | H58: tCO2/10000Nm56 | I58: ='附表1-GWP TABLE'!E56 -> 0 | AD58: =表1温室气体盘查表!AF59 -> 220.30499 | AE58: =表1温室气体盘查表!AG59 -> 0 | AF58: =表1温室气体盘查表!AH59 -> 0 | AG58: =表1温室气体盘查表!AI59 -> 0 | AH58: =表1温室气体盘查表!AJ59 -> 0 | AI58: =表1温室气体盘查表!AK59 -> 0 | AJ58: =表1温室气体盘查表!AL59 -> 0 | AK58: =表1温室气体盘查表!AM59 -> 220.30499
A59: 55 | B59: =表1温室气体盘查表!B60 -> 资本货物 | C59: =表1温室气体盘查表!C60 -> 机械动力传动设备制造 | D59: =表1温室气体盘查表!E60 -> 范围三 类别2 | E59: =表1温室气体盘查表!F60 -> 5368992.6 | F59: =表1温室气体盘查表!G60 -> $ | G59: ='附表2-EF'!K59*10 -> 0 | H59: tCO2/10000Nm57 | I59: ='附表1-GWP TABLE'!E57 -> 0 | AD59: =表1温室气体盘查表!AF60 -> 1122.1195 | AE59: =表1温室气体盘查表!AG60 -> 0 | AF59: =表1温室气体盘查表!AH60 -> 0 | AG59: =表1温室气体盘查表!AI60 -> 0 | AH59: =表1温室气体盘查表!AJ60 -> 0 | AI59: =表1温室气体盘查表!AK60 -> 0 | AJ59: =表1温室气体盘查表!AL60 -> 0 | AK59: =表1温室气体盘查表!AM60 -> 1122.1195
A60: 56 | B60: =表1温室气体盘查表!B61 -> 资本货物 | C60: =表1温室气体盘查表!C61 -> 测量、分配及其他泵类设备制造 | D60: =表1温室气体盘查表!E61 -> 范围三 类别2 | E60: =表1温室气体盘查表!F61 -> 2709414.4 | F60: =表1温室气体盘查表!G61 -> $ | G60: ='附表2-EF'!K60*10 -> 0 | H60: tCO2/10000Nm58 | I60: ='附表1-GWP TABLE'!E58 -> 0 | AD60: =表1温室气体盘查表!AF61 -> 604.1994 | AE60: =表1温室气体盘查表!AG61 -> 0 | AF60: =表1温室气体盘查表!AH61 -> 0 | AG60: =表1温室气体盘查表!AI61 -> 0 | AH60: =表1温室气体盘查表!AJ61 -> 0 | AI60: =表1温室气体盘查表!AK61 -> 0 | AJ60: =表1温室气体盘查表!AL61 -> 0 | AK60: =表1温室气体盘查表!AM61 -> 604.1994
A61: 57 | B61: =表1温室气体盘查表!B62 -> 资本货物 | C61: =表1温室气体盘查表!C62 -> 用于测量、显示和控制工业过程变量的仪器及相关产品制造 | D61: =表1温室气体盘查表!E62 -> 范围三 类别2 | E61: =表1温室气体盘查表!F62 -> 2228829.7 | F61: =表1温室气体盘查表!G62 -> $ | G61: ='附表2-EF'!K61*10 -> 0 | H61: tCO2/10000Nm59 | I61: ='附表1-GWP TABLE'!E59 -> 0 | AD61: =表1温室气体盘查表!AF62 -> 140.41627 | AE61: =表1温室气体盘查表!AG62 -> 0 | AF61: =表1温室气体盘查表!AH62 -> 0 | AG61: =表1温室气体盘查表!AI62 -> 0 | AH61: =表1温室气体盘查表!AJ62 -> 0 | AI61: =表1温室气体盘查表!AK62 -> 0 | AJ61: =表1温室气体盘查表!AL62 -> 0 | AK61: =表1温室气体盘查表!AM62 -> 140.41627
... A65: 61 | B65: =表1温室气体盘查表!B66 -> 范围一、二相关燃料和能源相关的活动产生的排放 | C65: =表1温室气体盘查表!C66 -> 洗精煤生产 | D65: =表1温室气体盘查表!E66 -> 范围三 类别3 | E65: =表1温室气体盘查表!F66 -> 2093622.8 | F65: =表1温室气体盘查表!G66 -> t | G65: ='附表2-EF'!K65*10 -> 0 | H65: tCO2/10000Nm63 | I65: ='附表1-GWP TABLE'!E63 -> 0 | AD65: =表1温室气体盘查表!AF66 -> 1204984.6 | AE65: =表1温室气体盘查表!AG66 -> 0 | AF65: =表1温室气体盘查表!AH66 -> 0 | AG65: =表1温室气体盘查表!AI66 -> 0 | AH65: =表1温室气体盘查表!AJ66 -> 0 | AI65: =表1温室气体盘查表!AK66 -> 0 | AJ65: =表1温室气体盘查表!AL66 -> 0 | AK65: =表1温室气体盘查表!AM66 -> 1204984.6
A66: 62 | B66: =表1温室气体盘查表!B67 -> 范围一、二相关燃料和能源相关的活动产生的排放 | C66: =表1温室气体盘查表!C67 -> 柴油生产 | D66: =表1温室气体盘查表!E67 -> 范围三 类别3 | E66: =表1温室气体盘查表!F67 -> 1422.69 | F66: =表1温室气体盘查表!G67 -> t | G66: ='附表2-EF'!K68*10 -> 0 | H66: tCO2/10000Nm64 | I66: ='附表1-GWP TABLE'!E64 -> 0 | AD66: =表1温室气体盘查表!AF67 -> 1198.0757 | AE66: =表1温室气体盘查表!AG67 -> 0 | AF66: =表1温室气体盘查表!AH67 -> 0 | AG66: =表1温室气体盘查表!AI67 -> 0 | AH66: =表1温室气体盘查表!AJ67 -> 0 | AI66: =表1温室气体盘查表!AK67 -> 0 | AJ66: =表1温室气体盘查表!AL67 -> 0 | AK66: =表1温室气体盘查表!AM67 -> 1198.0757
A67: 63 | B67: =表1温室气体盘查表!B68 -> 范围一、二相关燃料和能源相关的活动产生的排放 | C67: =表1温室气体盘查表!C68 -> 汽油生产 | D67: =表1温室气体盘查表!E68 -> 范围三 类别3 | E67: =表1温室气体盘查表!F68 -> 47.34 | F67: =表1温室气体盘查表!G68 -> t | G67: ='附表2-EF'!K69*10 -> 0 | H67: tCO2/10000Nm65 | I67: ='附表1-GWP TABLE'!E65 -> 0 | AD67: =表1温室气体盘查表!AF68 -> 46.740217 | AE67: =表1温室气体盘查表!AG68 -> 0 | AF67: =表1温室气体盘查表!AH68 -> 0 | AG67: =表1温室气体盘查表!AI68 -> 0 | AH67: =表1温室气体盘查表!AJ68 -> 0 | AI67: =表1温室气体盘查表!AK68 -> 0 | AJ67: =表1温室气体盘查表!AL68 -> 0 | AK67: =表1温室气体盘查表!AM68 -> 46.740217
A68: 64 | B68: =表1温室气体盘查表!B69 -> 范围一、二相关燃料和能源相关的活动产生的排放 | C68: =表1温室气体盘查表!C69 -> 焦炭生产 | D68: =表1温室气体盘查表!E69 -> 范围三 类别3 | E68: =表1温室气体盘查表!F69 -> 221509.17 | F68: =表1温室气体盘查表!G69 -> t | G68: ='附表2-EF'!K70*10 -> 0 | H68: tCO2/10000Nm66 | I68: ='附表1-GWP TABLE'!E66 -> 0 | AD68: =表1温室气体盘查表!AF69 -> 77306.7 | AE68: =表1温室气体盘查表!AG69 -> 0 | AF68: =表1温室气体盘查表!AH69 -> 0 | AG68: =表1温室气体盘查表!AI69 -> 0 | AH68: =表1温室气体盘查表!AJ69 -> 0 | AI68: =表1温室气体盘查表!AK69 -> 0 | AJ68: =表1温室气体盘查表!AL69 -> 0 | AK68: =表1温室气体盘查表!AM69 -> 77306.7
A69: 65 | B69: =表1温室气体盘查表!B70 -> 范围一、二相关燃料和能源相关的活动产生的排放 | C69: =表1温室气体盘查表!C70 -> 烟煤生产 | D69: =表1温室气体盘查表!E70 -> 范围三 类别3 | E69: =表1温室气体盘查表!F70 -> 323067.87 | F69: =表1温室气体盘查表!G70 -> t | G69: ='附表2-EF'!K72*10 -> 0 | H69: tCO2/10000Nm68 | I69: ='附表1-GWP TABLE'!E68 -> 0 | AD69: =表1温室气体盘查表!AF70 -> 57829.149 | AE69: =表1温室气体盘查表!AG70 -> 0 | AF69: =表1温室气体盘查表!AH70 -> 0 | AG69: =表1温室气体盘查表!AI70 -> 0 | AH69: =表1温室气体盘查表!AJ70 -> 0 | AI69: =表1温室气体盘查表!AK70 -> 0 | AJ69: =表1温室气体盘查表!AL70 -> 0 | AK69: =表1温室气体盘查表!AM70 -> 57829.149
A70: 66 | B70: =表1温室气体盘查表!B71 -> 范围一、二相关燃料和能源相关的活动产生的排放 | C70: =表1温室气体盘查表!C71 -> 无烟煤生产 | D70: =表1温室气体盘查表!E71 -> 范围三 类别3 | E70: =表1温室气体盘查表!F71 -> 335482.33 | F70: =表1温室气体盘查表!G71 -> t | G70: ='附表2-EF'!K73*10 -> 0 | H70: tCO2/10000Nm69 | I70: ='附表1-GWP TABLE'!E69 -> 0 | AD70: =表1温室气体盘查表!AF71 -> 229469.91 | AE70: =表1温室气体盘查表!AG71 -> 0 | AF70: =表1温室气体盘查表!AH71 -> 0 | AG70: =表1温室气体盘查表!AI71 -> 0 | AH70: =表1温室气体盘查表!AJ71 -> 0 | AI70: =表1温室气体盘查表!AK71 -> 0 | AJ70: =表1温室气体盘查表!AL71 -> 0 | AK70: =表1温室气体盘查表!AM71 -> 229469.91
A71: 67 | B71: =表1温室气体盘查表!B72 -> 范围一、二相关燃料和能源相关的活动产生的排放 | C71: =表1温室气体盘查表!C72 -> 天然气生产 | D71: =表1温室气体盘查表!E72 -> 范围三 类别3 | E71: =表1温室气体盘查表!F72 -> 1454 | F71: =表1温室气体盘查表!G72 -> 10000Nm3 | G71: ='附表2-EF'!#REF!*10 -> #REF! | H71: tCO2/10000Nm70 | I71: ='附表1-GWP TABLE'!E70 -> 0 | AD71: =表1温室气体盘查表!AF72 -> 9000.26 | AE71: =表1温室气体盘查表!AG72 -> 0 | AF71: =表1温室气体盘查表!AH72 -> 0 | AG71: =表1温室气体盘查表!AI72 -> 0 | AH71: =表1温室气体盘查表!AJ72 -> 0 | AI71: =表1温室气体盘查表!AK72 -> 0 | AJ71: =表1温室气体盘查表!AL72 -> 0 | AK71: =表1温室气体盘查表!AM72 -> 9000.26
A72: 68 | B72: =表1温室气体盘查表!B73 -> 范围一、二相关燃料和能源相关的活动产生的排放 | C72: =表1温室气体盘查表!C73 -> 外购电力上游排放 | D72: =表1温室气体盘查表!E73 -> 范围三 类别3 | E72: =表1温室气体盘查表!F73 -> 1966850.8 | F72: =表1温室气体盘查表!G73 -> MWh | G72: ='附表2-EF'!K74*10 -> 0 | H72: tCO2/10000Nm71 | I72: ='附表1-GWP TABLE'!E71 -> 0 | AD72: =表1温室气体盘查表!AF73 -> 176819.89 | AE72: =表1温室气体盘查表!AG73 -> 0 | AF72: =表1温室气体盘查表!AH73 -> 0 | AG72: =表1温室气体盘查表!AI73 -> 0 | AH72: =表1温室气体盘查表!AJ73 -> 0 | AI72: =表1温室气体盘查表!AK73 -> 0 | AJ72: =表1温室气体盘查表!AL73 -> 0 | AK72: =表1温室气体盘查表!AM73 -> 176819.89
A73: 69 | B73: =表1温室气体盘查表!B74 -> 上游运输配送产生的排放 | C73: =表1温室气体盘查表!C74 -> 船运 | D73: =表1温室气体盘查表!E74 -> 范围三 类别4 | E73: =表1温室气体盘查表!F74 -> 4.8219087e+09 | F73: =表1温室气体盘查表!G74 -> tkm | G73: ='附表2-EF'!K75*10 -> 0 | H73: tCO2/10000Nm72 | I73: ='附表1-GWP TABLE'!E72 -> 0 | AD73: =表1温室气体盘查表!AF74 -> 250587.64 | AE73: =表1温室气体盘查表!AG74 -> 0 | AF73: =表1温室气体盘查表!AH74 -> 0 | AG73: =表1温室气体盘查表!AI74 -> 0 | AH73: =表1温室气体盘查表!AJ74 -> 0 | AI73: =表1温室气体盘查表!AK74 -> 0 | AJ73: =表1温室气体盘查表!AL74 -> 0 | AK73: =表1温室气体盘查表!AM74 -> 250587.64
A74: 70 | B74: =表1温室气体盘查表!B75 -> 上游运输配送产生的排放 | C74: =表1温室气体盘查表!C75 -> 汽运 | D74: =表1温室气体盘查表!E75 -> 范围三 类别4 | E74: =表1温室气体盘查表!F75 -> 4.9114048e+08 | F74: =表1温室气体盘查表!G75 -> tkm | G74: ='附表2-EF'!K76*10 -> 0 | H74: tCO2/10000Nm73 | I74: ='附表1-GWP TABLE'!E73 -> 0 | AD74: =表1温室气体盘查表!AF75 -> 74635.121 | AE74: =表1温室气体盘查表!AG75 -> 0 | AF74: =表1温室气体盘查表!AH75 -> 0 | AG74: =表1温室气体盘查表!AI75 -> 0 | AH74: =表1温室气体盘查表!AJ75 -> 0 | AI74: =表1温室气体盘查表!AK75 -> 0 | AJ74: =表1温室气体盘查表!AL75 -> 0 | AK74: =表1温室气体盘查表!AM75 -> 74635.121
A75: 71 | B75: =表1温室气体盘查表!B76 -> 上游运输配送产生的排放 | C75: =表1温室气体盘查表!C76 -> 铁路运输 | D75: =表1温室气体盘查表!E76 -> 范围三 类别4 | E75: =表1温室气体盘查表!F76 -> 1.5557672e+09 | F75: =表1温室气体盘查表!G76 -> tkm | G75: ='附表2-EF'!K77*10 -> 0 | H75: tCO2/10000Nm74 | I75: ='附表1-GWP TABLE'!E74 -> 0 | AD75: =表1温室气体盘查表!AF76 -> 75504.264 | AE75: =表1温室气体盘查表!AG76 -> 0 | AF75: =表1温室气体盘查表!AH76 -> 0 | AG75: =表1温室气体盘查表!AI76 -> 0 | AH75: =表1温室气体盘查表!AJ76 -> 0 | AI75: =表1温室气体盘查表!AK76 -> 0 | AJ75: =表1温室气体盘查表!AL76 -> 0 | AK75: =表1温室气体盘查表!AM76 -> 75504.264
A76: 72 | B76: =表1温室气体盘查表!B77 -> 运营中产生的废物排放 | C76: =表1温室气体盘查表!C77 -> 生活垃圾和厨余垃圾 | D76: =表1温室气体盘查表!E77 -> 范围三 类别5 | E76: =表1温室气体盘查表!F77 -> 2801.4 | F76: =表1温室气体盘查表!G77 -> t | G76: ='附表2-EF'!K78*10 -> 0 | H76: tCO2/10000Nm75 | I76: ='附表1-GWP TABLE'!E75 -> 0 | AD76: =表1温室气体盘查表!AF77 -> 1040.2559 | AE76: =表1温室气体盘查表!AG77 -> 0 | AF76: =表1温室气体盘查表!AH77 -> 0 | AG76: =表1温室气体盘查表!AI77 -> 0 | AH76: =表1温室气体盘查表!AJ77 -> 0 | AI76: =表1温室气体盘查表!AK77 -> 0 | AJ76: =表1温室气体盘查表!AL77 -> 0 | AK76: =表1温室气体盘查表!AM77 -> 1040.2559
A77: 73 | B77: =表1温室气体盘查表!B78 -> 运营中产生的废物排放 | C77: =表1温室气体盘查表!C78 -> 废油 | D77: =表1温室气体盘查表!E78 -> 范围三 类别5 | E77: =表1温室气体盘查表!F78 -> 1719.05 | F77: =表1温室气体盘查表!G78 -> t | G77: ='附表2-EF'!K79*10 -> 0 | H77: tCO2/10000Nm76 | I77: ='附表1-GWP TABLE'!E76 -> 0 | AD77: =表1温室气体盘查表!AF78 -> 4897.6715 | AE77: =表1温室气体盘查表!AG78 -> 0 | AF77: =表1温室气体盘查表!AH78 -> 0 | AG77: =表1温室气体盘查表!AI78 -> 0 | AH77: =表1温室气体盘查表!AJ78 -> 0 | AI77: =表1温室气体盘查表!AK78 -> 0 | AJ77: =表1温室气体盘查表!AL78 -> 0 | AK77: =表1温室气体盘查表!AM78 -> 4897.6715
A78: 74 | B78: =表1温室气体盘查表!B79 -> 运营中产生的废物排放 | C78: =表1温室气体盘查表!C79 -> 废油水 | D78: =表1温室气体盘查表!E79 -> 范围三 类别5 | E78: =表1温室气体盘查表!F79 -> 5203.3 | F78: =表1温室气体盘查表!G79 -> t | G78: ='附表2-EF'!K80*10 -> 0 | H78: tCO2/10000Nm77 | I78: ='附表1-GWP TABLE'!E77 -> 0 | AD78: =表1温室气体盘查表!AF79 -> 14824.498 | AE78: =表1温室气体盘查表!AG79 -> 0 | AF78: =表1温室气体盘查表!AH79 -> 0 | AG78: =表1温室气体盘查表!AI79 -> 0 | AH78: =表1温室气体盘查表!AJ79 -> 0 | AI78: =表1温室气体盘查表!AK79 -> 0 | AJ78: =表1温室气体盘查表!AL79 -> 0 | AK78: =表1温室气体盘查表!AM79 -> 14824.498
A79: 75 | B79: =表1温室气体盘查表!B80 -> 运营中产生的废物排放 | C79: =表1温室气体盘查表!C80 -> 废弃物运输 | D79: =表1温室气体盘查表!E80 -> 范围三 类别5 | E79: =表1温室气体盘查表!F80 -> 67053170 | F79: =表1温室气体盘查表!G80 -> tkm | G79: ='附表2-EF'!K82*10 -> 0 | H79: tCO2/10000Nm79 | I79: ='附表1-GWP TABLE'!E79 -> 0 | AD79: =表1温室气体盘查表!AF80 -> 10189.593 | AE79: =表1温室气体盘查表!AG80 -> 0 | AF79: =表1温室气体盘查表!AH80 -> 0 | AG79: =表1温室气体盘查表!AI80 -> 0 | AH79: =表1温室气体盘查表!AJ80 -> 0 | AI79: =表1温室气体盘查表!AK80 -> 0 | AJ79: =表1温室气体盘查表!AL80 -> 0 | AK79: =表1温室气体盘查表!AM80 -> 10189.593
A80: 76 | B80: =表1温室气体盘查表!B81 -> 商务旅行产生的排放 | C80: =表1温室气体盘查表!C81 -> 航运 | D80: =表1温室气体盘查表!E81 -> 范围三 类别6 | E80: =表1温室气体盘查表!F81 -> 3709585 | F80: =表1温室气体盘查表!G81 -> passenger*km | G80: ='附表2-EF'!K83*10 -> 0 | H80: tCO2/10000Nm80 | I80: ='附表1-GWP TABLE'!E80 -> 0 | AD80: =表1温室气体盘查表!AF81 -> 311.60514 | AE80: =表1温室气体盘查表!AG81 -> 0 | AF80: =表1温室气体盘查表!AH81 -> 0 | AG80: =表1温室气体盘查表!AI81 -> 0 | AH80: =表1温室气体盘查表!AJ81 -> 0 | AI80: =表1温室气体盘查表!AK81 -> 0 | AJ80: =表1温室气体盘查表!AL81 -> 0 | AK80: =表1温室气体盘查表!AM81 -> 311.60514
A81: 77 | B81: =表1温室气体盘查表!B82 -> 商务旅行产生的排放 | C81: =表1温室气体盘查表!C82 -> 铁路运输 | D81: =表1温室气体盘查表!E82 -> 范围三 类别6 | E81: =表1温室气体盘查表!F82 -> 9687112 | F81: =表1温室气体盘查表!G82 -> passenger*km | G81: ='附表2-EF'!K84*10 -> 0 | H81: tCO2/10000Nm81 | I81: ='附表1-GWP TABLE'!E81 -> 0 | AD81: =表1温室气体盘查表!AF82 -> 725.30841 | AE81: =表1温室气体盘查表!AG82 -> 0 | AF81: =表1温室气体盘查表!AH82 -> 0 | AG81: =表1温室气体盘查表!AI82 -> 0 | AH81: =表1温室气体盘查表!AJ82 -> 0 | AI81: =表1温室气体盘查表!AK82 -> 0 | AJ81: =表1温室气体盘查表!AL82 -> 0 | AK81: =表1温室气体盘查表!AM82 -> 725.30841
A82: 78 | B82: =表1温室气体盘查表!B83 -> 商务旅行产生的排放 | C82: =表1温室气体盘查表!C83 -> 员工差旅住宿 | D82: =表1温室气体盘查表!E83 -> 范围三 类别6 | E82: =表1温室气体盘查表!F83 -> 14352 | F82: =表1温室气体盘查表!G83 -> 总间*晚 | G82: ='附表2-EF'!K85*10 -> 0 | H82: tCO2/10000Nm82 | I82: ='附表1-GWP TABLE'!E82 -> 0 | AD82: =表1温室气体盘查表!AF83 -> 767.832 | AE82: =表1温室气体盘查表!AG83 -> 0 | AF82: =表1温室气体盘查表!AH83 -> 0 | AG82: =表1温室气体盘查表!AI83 -> 0 | AH82: =表1温室气体盘查表!AJ83 -> 0 | AI82: =表1温室气体盘查表!AK83 -> 0 | AJ82: =表1温室气体盘查表!AL83 -> 0 | AK82: =表1温室气体盘查表!AM83 -> 767.832
A83: 79 | B83: =表1温室气体盘查表!B84 -> 员工通勤产生的排放 | C83: =表1温室气体盘查表!C84 -> 通勤车 | D83: =表1温室气体盘查表!E84 -> 范围三 类别7 | E83: =表1温室气体盘查表!F84 -> 6808531.3 | F83: =表1温室气体盘查表!G84 -> passenger*km | G83: ='附表2-EF'!K86*10 -> 0 | H83: tCO2/10000Nm83 | I83: ='附表1-GWP TABLE'!E83 -> 0 | AD83: =表1温室气体盘查表!AF84 -> 59.915075 | AE83: =表1温室气体盘查表!AG84 -> 0 | AF83: =表1温室气体盘查表!AH84 -> 0 | AG83: =表1温室气体盘查表!AI84 -> 0 | AH83: =表1温室气体盘查表!AJ84 -> 0 | AI83: =表1温室气体盘查表!AK84 -> 0 | AJ83: =表1温室气体盘查表!AL84 -> 0 | AK83: =表1温室气体盘查表!AM84 -> 59.915075
A84: 80 | B84: =表1温室气体盘查表!B85 -> 员工通勤产生的排放 | C84: =表1温室气体盘查表!C85 -> 电力公交 | D84: =表1温室气体盘查表!E85 -> 范围三 类别7 | E84: =表1温室气体盘查表!F85 -> 316087.41 | F84: =表1温室气体盘查表!G85 -> passenger*km | G84: ='附表2-EF'!K87*10 -> 0 | H84: tCO2/10000Nm84 | I84: ='附表1-GWP TABLE'!E84 -> 0 | AD84: =表1温室气体盘查表!AF85 -> 2.7815692 | AE84: =表1温室气体盘查表!AG85 -> 0 | AF84: =表1温室气体盘查表!AH85 -> 0 | AG84: =表1温室气体盘查表!AI85 -> 0 | AH84: =表1温室气体盘查表!AJ85 -> 0 | AI84: =表1温室气体盘查表!AK85 -> 0 | AJ84: =表1温室气体盘查表!AL85 -> 0 | AK84: =表1温室气体盘查表!AM85 -> 2.7815692
A85: 81 | B85: =表1温室气体盘查表!B86 -> 员工通勤产生的排放 | C85: =表1温室气体盘查表!C86 -> 电瓶车 | D85: =表1温室气体盘查表!E86 -> 范围三 类别7 | E85: =表1温室气体盘查表!F86 -> 10595750 | F85: =表1温室气体盘查表!G86 -> passenger*km | G85: ='附表2-EF'!K88*10 -> 0 | H85: tCO2/10000Nm85 | I85: ='附表1-GWP TABLE'!E85 -> 0 | AD85: =表1温室气体盘查表!AF86 -> 286.29993 | AE85: =表1温室气体盘查表!AG86 -> 0 | AF85: =表1温室气体盘查表!AH86 -> 0 | AG85: =表1温室气体盘查表!AI86 -> 0 | AH85: =表1温室气体盘查表!AJ86 -> 0 | AI85: =表1温室气体盘查表!AK86 -> 0 | AJ85: =表1温室气体盘查表!AL86 -> 0 | AK85: =表1温室气体盘查表!AM86 -> 286.29993
A86: 82 | B86: =表1温室气体盘查表!B87 -> 员工通勤产生的排放 | C86: =表1温室气体盘查表!C87 -> 自驾油车 | D86: =表1温室气体盘查表!E87 -> 范围三 类别7 | E86: =表1温室气体盘查表!F87 -> 12199616 | F86: =表1温室气体盘查表!G87 -> km | G86: ='附表2-EF'!K89*10 -> 0 | H86: tCO2/10000Nm86 | I86: ='附表1-GWP TABLE'!E86 -> 0 | AD86: =表1温室气体盘查表!AF87 -> 4531.2743 | AE86: =表1温室气体盘查表!AG87 -> 0 | AF86: =表1温室气体盘查表!AH87 -> 0 | AG86: =表1温室气体盘查表!AI87 -> 0 | AH86: =表1温室气体盘查表!AJ87 -> 0 | AI86: =表1温室气体盘查表!AK87 -> 0 | AJ86: =表1温室气体盘查表!AL87 -> 0 | AK86: =表1温室气体盘查表!AM87 -> 4531.2743
A87: 83 | B87: =表1温室气体盘查表!B88 -> 员工通勤产生的排放 | C87: =表1温室气体盘查表!C88 -> 自驾电车 | D87: =表1温室气体盘查表!E88 -> 范围三 类别7 | E87: =表1温室气体盘查表!F88 -> 1527084.8 | F87: =表1温室气体盘查表!G88 -> km | G87: ='附表2-EF'!K90*10 -> 0 | H87: tCO2/10000Nm87 | I87: ='附表1-GWP TABLE'!E87 -> 0 | AD87: =表1温室气体盘查表!AF88 -> 567.20147 | AE87: =表1温室气体盘查表!AG88 -> 0 | AF87: =表1温室气体盘查表!AH88 -> 0 | AG87: =表1温室气体盘查表!AI88 -> 0 | AH87: =表1温室气体盘查表!AJ88 -> 0 | AI87: =表1温室气体盘查表!AK88 -> 0 | AJ87: =表1温室气体盘查表!AL88 -> 0 | AK87: =表1温室气体盘查表!AM88 -> 567.20147
A88: 84 | B88: =表1温室气体盘查表!B89 -> 下游运输配送产生的排放 | C88: =表1温室气体盘查表!C89 -> 船运 | D88: =表1温室气体盘查表!E89 -> 范围三 类别9 | E88: =表1温室气体盘查表!F89 -> 9.6547784e+08 | F88: =表1温室气体盘查表!G89 -> tkm | G88: ='附表2-EF'!K91*10 -> 0 | H88: tCO2/10000Nm88 | I88: ='附表1-GWP TABLE'!E88 -> 0 | AD88: =表1温室气体盘查表!AF89 -> 50174.491 | AE88: =表1温室气体盘查表!AG89 -> 0 | AF88: =表1温室气体盘查表!AH89 -> 0 | AG88: =表1温室气体盘查表!AI89 -> 0 | AH88: =表1温室气体盘查表!AJ89 -> 0 | AI88: =表1温室气体盘查表!AK89 -> 0 | AJ88: =表1温室气体盘查表!AL89 -> 0 | AK88: =表1温室气体盘查表!AM89 -> 50174.491
A89: 85 | B89: =表1温室气体盘查表!B90 -> 下游运输配送产生的排放 | C89: =表1温室气体盘查表!C90 -> 汽运 | D89: =表1温室气体盘查表!E90 -> 范围三 类别9 | E89: =表1温室气体盘查表!F90 -> 1.3667586e+09 | F89: =表1温室气体盘查表!G90 -> tkm | G89: ='附表2-EF'!K92*10 -> 0 | H89: tCO2/10000Nm89 | I89: ='附表1-GWP TABLE'!E89 -> 0 | AD89: =表1温室气体盘查表!AF90 -> 207696.58 | AE89: =表1温室气体盘查表!AG90 -> 0 | AF89: =表1温室气体盘查表!AH90 -> 0 | AG89: =表1温室气体盘查表!AI90 -> 0 | AH89: =表1温室气体盘查表!AJ90 -> 0 | AI89: =表1温室气体盘查表!AK90 -> 0 | AJ89: =表1温室气体盘查表!AL90 -> 0 | AK89: =表1温室气体盘查表!AM90 -> 207696.58
A90: 86 | B90: =表1温室气体盘查表!B91 -> 下游运输配送产生的排放 | C90: =表1温室气体盘查表!C91 -> 铁路运输 | D90: =表1温室气体盘查表!E91 -> 范围三 类别9 | E90: =表1温室气体盘查表!F91 -> 3.4351903e+08 | F90: =表1温室气体盘查表!G91 -> tkm | G90: ='附表2-EF'!#REF!*10 -> #REF! | H90: tCO2/10000Nm90 | I90: ='附表1-GWP TABLE'!E90 -> 0 | AD90: =表1温室气体盘查表!AF91 -> 16671.614 | AE90: =表1温室气体盘查表!AG91 -> 0 | AF90: =表1温室气体盘查表!AH91 -> 0 | AG90: =表1温室气体盘查表!AI91 -> 0 | AH90: =表1温室气体盘查表!AJ91 -> 0 | AI90: =表1温室气体盘查表!AK91 -> 0 | AJ90: =表1温室气体盘查表!AL91 -> 0 | AK90: =表1温室气体盘查表!AM91 -> 16671.614
A91: 87 | B91: =表1温室气体盘查表!B92 -> 下游运输配送产生的排放 | C91: =表1温室气体盘查表!C92 -> 汽运-副产品 | D91: =表1温室气体盘查表!E92 -> 范围三 类别9 | E91: =表1温室气体盘查表!F92 -> 43030612 | F91: =表1温室气体盘查表!G92 -> tkm | G91: ='附表2-EF'!K93*10 -> 0 | H91: tCO2/10000Nm91 | I91: ='附表1-GWP TABLE'!E91 -> 0 | AD91: =表1温室气体盘查表!AF92 -> 6539.0557 | AE91: =表1温室气体盘查表!AG92 -> 0 | AF91: =表1温室气体盘查表!AH92 -> 0 | AG91: =表1温室气体盘查表!AI92 -> 0 | AH91: =表1温室气体盘查表!AJ92 -> 0 | AI91: =表1温室气体盘查表!AK92 -> 0 | AJ91: =表1温室气体盘查表!AL92 -> 0 | AK91: =表1温室气体盘查表!AM92 -> 6539.0557
A92: 88 | B92: =表1温室气体盘查表!B93 -> 外销产品加工产生的排放 | C92: =表1温室气体盘查表!C93 -> 锻材加工 | D92: =表1温室气体盘查表!E93 -> 范围三 类别10 | E92: =表1温室气体盘查表!F93 -> 172270 | F92: =表1温室气体盘查表!G93 -> t | G92: ='附表2-EF'!K94*10 -> 0 | H92: tCO2/10000Nm92 | I92: ='附表1-GWP TABLE'!E92 -> 0 | AD92: =表1温室气体盘查表!AF93 -> 135333.27 | AE92: =表1温室气体盘查表!AG93 -> 0 | AF92: =表1温室气体盘查表!AH93 -> 0 | AG92: =表1温室气体盘查表!AI93 -> 0 | AH92: =表1温室气体盘查表!AJ93 -> 0 | AI92: =表1温室气体盘查表!AK93 -> 0 | AJ92: =表1温室气体盘查表!AL93 -> 0 | AK92: =表1温室气体盘查表!AM93 -> 135333.27
A93: 89 | B93: =表1温室气体盘查表!B94 -> 外销产品加工产生的排放 | C93: =表1温室气体盘查表!C94 -> 棒材加工 | D93: =表1温室气体盘查表!E94 -> 范围三 类别10 | E93: =表1温室气体盘查表!F94 -> 2063196.5 | F93: =表1温室气体盘查表!G94 -> t | G93: ='附表2-EF'!K95*10 -> 0 | H93: tCO2/10000Nm93 | I93: ='附表1-GWP TABLE'!E93 -> 0 | AD93: =表1温室气体盘查表!AF94 -> 2075519.7 | AE93: =表1温室气体盘查表!AG94 -> 0 | AF93: =表1温室气体盘查表!AH94 -> 0 | AG93: =表1温室气体盘查表!AI94 -> 0 | AH93: =表1温室气体盘查表!AJ94 -> 0 | AI93: =表1温室气体盘查表!AK94 -> 0 | AJ93: =表1温室气体盘查表!AL94 -> 0 | AK93: =表1温室气体盘查表!AM94 -> 2075519.7
A94: 90 | B94: =表1温室气体盘查表!B95 -> 外销产品加工产生的排放 | C94: =表1温室气体盘查表!C95 -> 钢管加工 | D94: =表1温室气体盘查表!E95 -> 范围三 类别10 | E94: =表1温室气体盘查表!F95 -> 649008.66 | F94: =表1温室气体盘查表!G95 -> t | G94: ='附表2-EF'!K96*10 -> 0 | H94: tCO2/10000Nm94 | I94: ='附表1-GWP TABLE'!E94 -> 0 | AD94: =表1温室气体盘查表!AF95 -> 61948.696 | AE94: =表1温室气体盘查表!AG95 -> 0 | AF94: =表1温室气体盘查表!AH95 -> 0 | AG94: =表1温室气体盘查表!AI95 -> 0 | AH94: =表1温室气体盘查表!AJ95 -> 0 | AI94: =表1温室气体盘查表!AK95 -> 0 | AJ94: =表1温室气体盘查表!AL95 -> 0 | AK94: =表1温室气体盘查表!AM95 -> 61948.696
A95: 91 | B95: =表1温室气体盘查表!B96 -> 外销产品加工产生的排放 | C95: =表1温室气体盘查表!C96 -> 钢坯加工 | D95: =表1温室气体盘查表!E96 -> 范围三 类别10 | E95: =表1温室气体盘查表!F96 -> 608494.2 | F95: =表1温室气体盘查表!G96 -> t | G95: ='附表2-EF'!K97*10 -> 0 | H95: tCO2/10000Nm95 | I95: ='附表1-GWP TABLE'!E95 -> 0 | AD95: =表1温室气体盘查表!AF96 -> 176591.21 | AE95: =表1温室气体盘查表!AG96 -> 0 | AF95: =表1温室气体盘查表!AH96 -> 0 | AG95: =表1温室气体盘查表!AI96 -> 0 | AH95: =表1温室气体盘查表!AJ96 -> 0 | AI95: =表1温室气体盘查表!AK96 -> 0 | AJ95: =表1温室气体盘查表!AL96 -> 0 | AK95: =表1温室气体盘查表!AM96 -> 176591.21
A96: 92 | B96: =表1温室气体盘查表!B97 -> 外销产品使用产生的排放 | C96: =表1温室气体盘查表!C97 -> 外售焦炉煤气燃烧 | D96: =表1温室气体盘查表!E97 -> 范围三 类别11 | E96: =表1温室气体盘查表!F97 -> 788.73 | F96: =表1温室气体盘查表!G97 -> 10000Nm3 | G96: ='附表2-EF'!K98*10 -> 0 | H96: tCO2/10000Nm96 | I96: ='附表1-GWP TABLE'!E96 -> 0 | AD96: =表1温室气体盘查表!AF97 -> 6027.4166 | AE96: =表1温室气体盘查表!AG97 -> 3.7874983 | AF96: =表1温室气体盘查表!AH97 -> 3.7060467 | AG96: =表1温室气体盘查表!AI97 -> 0 | AH96: =表1温室气体盘查表!AJ97 -> 0 | AI96: =表1温室气体盘查表!AK97 -> 0 | AJ96: =表1温室气体盘查表!AL97 -> 0 | AK96: =表1温室气体盘查表!AM97 -> 6034.9102
A97: 93 | B97: =表1温室气体盘查表!B98 -> 外售产品报废产生的排放 | C97: =表1温室气体盘查表!C98 -> 产品报废 | D97: =表1温室气体盘查表!E98 -> 范围三 类别12 | E97: =表1温室气体盘查表!F98 -> 573065.29 | F97: =表1温室气体盘查表!G98 -> t | G97: ='附表2-EF'!K99*10 -> 0 | H97: tCO2/10000Nm97 | I97: ='附表1-GWP TABLE'!E97 -> 0 | AD97: =表1温室气体盘查表!AF98 -> 3589.115 | AE97: =表1温室气体盘查表!AG98 -> 0 | AF97: =表1温室气体盘查表!AH98 -> 0 | AG97: =表1温室气体盘查表!AI98 -> 0 | AH97: =表1温室气体盘查表!AJ98 -> 0 | AI97: =表1温室气体盘查表!AK98 -> 0 | AJ97: =表1温室气体盘查表!AL98 -> 0 | AK97: =表1温室气体盘查表!AM98 -> 3589.115
AD98: =SUM(AD5:AD97) -> 15337417 | AE98: =SUM(AE5:AE97) -> 10689.762 | AF98: =SUM(AF5:AF97) -> 31508.551 | AG98: =SUM(AG5:AG97) -> 570.54 | AH98: =SUM(AH5:AH97) -> 0 | AI98: =SUM(AI5:AI97) -> 0 | AJ98: =SUM(AJ5:AJ97) -> 0 | AK98: =SUM(AK5:AK97) -> 15380185

Sheet 活动数据汇总表（GHG基于市场）
A1: 各排放源明细
A2: 编号 | B2: GHG排放类别 | C2: 排放源 | D2: 报告边界 | E2: 活动数据 | G2: 排放因子&系数 | AD2: 排放量
G3: CO2 | J3: CH4 | M3: N2O | P3: HFCs | T3: PFCs | X3: SF6 | AA3: NF3 | AD3: =G3 -> CO2 | AE3: =J3 -> CH4 | AF3: =M3 -> N2O | AG3: =P3 -> HFCs | AH3: =T3 -> PFCs | AI3: =X3 -> SF6 | AJ3: =AA3 -> NF3 | AK3: 总量
E4: 数值 | F4: 计量单位 | G4: EF | H4: 计量单位 | I4: GWP | J4: EF | K4: 计量单位 | L4: GWP | M4: EF | N4: 计量单位 | O4: GWP | P4: EF | Q4: 计量单位 | R4: GWP | S4: 型号 | T4: EF | U4: 计量单位 | V4: GWP | W4: 型号 | X4: EF | Y4: 计量单位 | Z4: GWP | AA4: EF | AB4: 计量单位 | AC4: GWP | AD4: tCO2e
A5: 1 | B5: =表1温室气体盘查表!B5 -> 固定燃烧 | C5: =表1温室气体盘查表!C5 -> 天然气燃烧 | D5: =表1温室气体盘查表!E5 -> 范围一 | E5: =表1温室气体盘查表!F5 -> 1454 | F5: =表1温室气体盘查表!G5 -> 10000Nm3 | G5: ='附表2-EF'!K5*10 -> 1e-06 | H5: tCO2/10000Nm3 | I5: ='附表1-GWP TABLE'!E3 -> 1 | AD5: =表1温室气体盘查表!AF5 -> 31438.225 | AE5: =表1温室气体盘查表!AG5 -> 15.635053 | AF5: =表1温室气体盘查表!AH5 -> 15.298816 | AG5: =表1温室气体盘查表!AI5 -> 0 | AH5: =表1温室气体盘查表!AJ5 -> 0 | AI5: =表1温室气体盘查表!AK5 -> 0 | AJ5: =表1温室气体盘查表!AL5 -> 0 | AK5: =表1温室气体盘查表!AM5 -> 31469.159
A6: 2 | B6: =表1温室气体盘查表!B6 -> 固定燃烧 | C6: =表1温室气体盘查表!C6 -> 液化石油气燃烧 | D6: =表1温室气体盘查表!E6 -> 范围一 | E6: =表1温室气体盘查表!F6 -> 9.43 | F6: =表1温室气体盘查表!G6 -> t | G6: ='附表2-EF'!K6*10 -> 1e-06 | H6: tCO2/10000Nm4 | I6: ='附表1-GWP TABLE'!E4 -> 27.9 | AD6: =表1温室气体盘查表!AF6 -> 29.260998 | AE6: =表1温室气体盘查表!AG6 -> 0.012937905 | AF6: =表1温室气体盘查表!AH6 -> 0.012659671 | AG6: =表1温室气体盘查表!AI6 -> 0 | AH6: =表1温室气体盘查表!AJ6 -> 0 | AI6: =表1温室气体盘查表!AK6 -> 0 | AJ6: =表1温室气体盘查表!AL6 -> 0 | AK6: =表1温室气体盘查表!AM6 -> 29.286595
A7: 3 | B7: =表1温室气体盘查表!B7 -> 固定燃烧 | C7: =表1温室气体盘查表!C7 -> 烟煤燃烧 | D7: =表1温室气体盘查表!E7 -> 范围一 | E7: =表1温室气体盘查表!F7 -> 323067.87 | F7: =表1温室气体盘查表!G7 -> t | G7: ='附表2-EF'!K7*10 -> 1.5e-05 | H7: tCO2/10000Nm5 | I7: ='附表1-GWP TABLE'!E5 -> 273 | AD7: =表1温室气体盘查表!AF7 -> 746259.74 | AE7: =表1温室气体盘查表!AG7 -> 211.80719 | AF7: =表1温室气体盘查表!AH7 -> 3108.783 | AG7: =表1温室气体盘查表!AI7 -> 0 | AH7: =表1温室气体盘查表!AJ7 -> 0 | AI7: =表1温室气体盘查表!AK7 -> 0 | AJ7: =表1温室气体盘查表!AL7 -> 0 | AK7: =表1温室气体盘查表!AM7 -> 749580.33
A8: 4 | B8: =表1温室气体盘查表!B8 -> 固定燃烧 | C8: =表1温室气体盘查表!C8 -> 无烟煤燃烧 | D8: =表1温室气体盘查表!E8 -> 范围一 | E8: =表1温室气体盘查表!F8 -> 335482.33 | F8: =表1温室气体盘查表!G8 -> t | G8: ='附表2-EF'!K8*10 -> 1.5e-05 | H8: tCO2/10000Nm6 | I8: ='附表1-GWP TABLE'!E6 -> 0 | AD8: =表1温室气体盘查表!AF8 -> 816986.9 | AE8: =表1温室气体盘查表!AG8 -> 231.88133 | AF8: =表1温室气体盘查表!AH8 -> 3403.4195 | AG8: =表1温室气体盘查表!AI8 -> 0 | AH8: =表1温室气体盘查表!AJ8 -> 0 | AI8: =表1温室气体盘查表!AK8 -> 0 | AJ8: =表1温室气体盘查表!AL8 -> 0 | AK8: =表1温室气体盘查表!AM8 -> 820622.2
A9: 5 | B9: =表1温室气体盘查表!B9 -> 固定燃烧 | C9: =表1温室气体盘查表!C9 -> 洗精煤燃烧 | D9: =表1温室气体盘查表!E9 -> 范围一 | E9: =表1温室气体盘查表!F9 -> 2093622.8 | F9: =表1温室气体盘查表!G9 -> t | G9: ='附表2-EF'!K9*10 -> 1.5e-05 | H9: tCO2/10000Nm7 | I9: ='附表1-GWP TABLE'!E7 -> 0 | AD9: =表1温室气体盘查表!AF9 -> 5165430 | AE9: =表1温室气体盘查表!AG9 -> 1523.4196 | AF9: =表1温室气体盘查表!AH9 -> 22359.869 | AG9: =表1温室气体盘查表!AI9 -> 0 | AH9: =表1温室气体盘查表!AJ9 -> 0 | AI9: =表1温室气体盘查表!AK9 -> 0 | AJ9: =表1温室气体盘查表!AL9 -> 0 | AK9: =表1温室气体盘查表!AM9 -> 5189313.3
A10: 6 | B10: =表1温室气体盘查表!B10 -> 固定燃烧 | C10: =表1温室气体盘查表!C10 -> 焦炭燃烧 | D10: =表1温室气体盘查表!E10 -> 范围一 | E10: =表1温室气体盘查表!F10 -> 221509.17 | F10: =表1温室气体盘查表!G10 -> t | G10: ='附表2-EF'!K10*10 -> 1.5e-05 | H10: tCO2/10000Nm8 | I10: ='附表1-GWP TABLE'!E8 -> 0 | AD10: =表1温室气体盘查表!AF10 -> 667212.1 | AE10: =表1温室气体盘查表!AG10 -> 173.974 | AF10: =表1温室气体盘查表!AH10 -> 2553.4893 | AG10: =表1温室气体盘查表!AI10 -> 0 | AH10: =表1温室气体盘查表!AJ10 -> 0 | AI10: =表1温室气体盘查表!AK10 -> 0 | AJ10: =表1温室气体盘查表!AL10 -> 0 | AK10: =表1温室气体盘查表!AM10 -> 669939.56
