Workbook
Name CONST_CNTR_TotProd: #REF!
Name CONST_ElecConsumption: #REF!

Sheet 温室气体盘查清册 (2)
B1: 温室气体盘查清册 | L1: 编号：DY-GHG-2025-01
L2: 版本/版次：A/1
L3: 日期：2025/7/3
B4: 组织名称： | C4: 大冶特殊钢有限公司
B5: 组织边界： | C5: 湖北省黄石市黄石大道316号
B6: 盘查覆盖周期: | C6: 2024年1月1日至2024年12月31日
B7: 编制 ： | E7: 审核： | K7: 核准：
B8: 报告边界 | C8: 运营控制权 | E8: 范围一排放量： | F8: =F14 -> 7122248.8 | K8: 单位：tCO2e
E9: 范围二（基于位置）排放量： | F9: =F47 -> 1069378.7
E10: 范围二（基于市场）排放量： | F10: =F48 -> 1161900.3
B11: 排放 | E11: 范围三排放量： | F11: =SUM(F50,F76,F89,F101,F106,F113,F118,F124,F130,F136) -> 7328574.6
B12: 编号 | C12: 排放源 | D12: 排放设施 | E12: 备注 | F12: 总排放量 | G12: CO2 | H12: CH4 | I12: N2O | J12: HFCs | K12: PFCs | L12: SF6 | M12: NF3
G13: tCO2e
B14: 范围一 直接排放 | F14: =F15+F24+F27+F33 -> 7122248.8 | G14: =G15+G24+G27+G33 -> 7086080.3 | H14: =H15+H24+H27+H33 -> 2569.6835 | I14: =I15+I24+I27+I33 -> 30422.615 | J14: =J15+J24+J27+J33 -> 717.03 | K14: =K15+K24+K27+K33 -> 0 | L14: =L15+L24+L27+L33 -> 2459.16 | M14: =M15+M24+M27+M33 -> 0
B15: 1.1 | C15: 固定源燃烧直接排放 | F15: =SUM(G15:M15) -> 7227644.2 | G15: =SUM(G16:G23) -> 7195204.6 | H15: =SUM(H16:H23) -> 2083.9816 | I15: =SUM(I16:I23) -> 30355.616 | J15: =SUM(J16:J23) -> 0 | K15: =SUM(K16:K23) -> 0 | L15: =SUM(L16:L23) -> 0 | M15: =SUM(M16:M23) -> 0
B16: 1.1.1 | C16: =表1温室气体盘查表!C5 -> 天然气燃烧 | D16: =表1温室气体盘查表!D5 -> 热处理炉（加热炉） | F16: =SUM(G16:M16) -> 38881.726 | G16: =表1温室气体盘查表!AE5 -> 38843.506 | H16: =表1温室气体盘查表!AF5 -> 19.317893 | I16: =表1温室气体盘查表!AG5 -> 18.902455 | J16: =表1温室气体盘查表!AH5 -> 0 | K16: =表1温室气体盘查表!AI5 -> 0 | L16: =表1温室气体盘查表!AJ5 -> 0 | M16: =表1温室气体盘查表!AK5 -> 0
B17: 1.1.2 | C17: =表1温室气体盘查表!C6 -> 液化石油气燃烧 | D17: =表1温室气体盘查表!D6 -> 冶钢宾馆 | F17: =SUM(G17:M17) -> 29.162368 | G17: =表1温室气体盘查表!AE6 -> 29.136879 | H17: =表1温室气体盘查表!AF6 -> 0.012883026 | I17: =表1温室气体盘查表!AG6 -> 0.012605971 | J17: =表1温室气体盘查表!AH6 -> 0 | K17: =表1温室气体盘查表!AI6 -> 0 | L17: =表1温室气体盘查表!AJ6 -> 0 | M17: =表1温室气体盘查表!AK6 -> 0
B18: 1.1.3 | C18: =表1温室气体盘查表!C7 -> 烟煤燃烧 | D18: =表1温室气体盘查表!D7 -> 高炉 | F18: =SUM(G18:M18) -> 925941.32 | G18: =表1温室气体盘查表!AE7 -> 921839.46 | H18: =表1温室气体盘查表!AF7 -> 261.64111 | I18: =表1温室气体盘查表!AG7 -> 3840.2163 | J18: =表1温室气体盘查表!AH7 -> 0 | K18: =表1温室气体盘查表!AI7 -> 0 | L18: =表1温室气体盘查表!AJ7 -> 0 | M18: =表1温室气体盘查表!AK7 -> 0
B19: 1.1.4 | C19: =表1温室气体盘查表!C8 -> 无烟煤燃烧 | D19: =表1温室气体盘查表!D8 -> 高炉、烧结 | F19: =SUM(G19:M19) -> 637282.39 | G19: =表1温室气体盘查表!AE8 -> 634459.27 | H19: =表1温室气体盘查表!AF8 -> 180.07542 | I19: =表1温室气体盘查表!AG8 -> 2643.0424 | J19: =表1温室气体盘查表!AH8 -> 0 | K19: =表1温室气体盘查表!AI8 -> 0 | L19: =表1温室气体盘查表!AJ8 -> 0 | M19: =表1温室气体盘查表!AK8 -> 0
B20: 1.1.5 | C20: =表1温室气体盘查表!C9 -> 洗精煤燃烧 | D20: =表1温室气体盘查表!D9 -> 焦炉 | F20: =SUM(G20:M20) -> 4824841.6 | G20: =表1温室气体盘查表!AE9 -> 4802635.7 | H20: =表1温室气体盘查表!AF9 -> 1416.4222 | I20: =表1温室气体盘查表!AG9 -> 20789.422 | J20: =表1温室气体盘查表!AH9 -> 0 | K20: =表1温室气体盘查表!AI9 -> 0 | L20: =表1温室气体盘查表!AJ9 -> 0 | M20: =表1温室气体盘查表!AK9 -> 0
B21: 1.1.6 | C21: =表1温室气体盘查表!C10 -> 焦炭燃烧 | D21: =表1温室气体盘查表!D10 -> 高炉 | F21: =SUM(G21:M21) -> 439843.84 | G21: =表1温室气体盘查表!AE10 -> 438053.15 | H21: =表1温室气体盘查表!AF10 -> 114.22134 | I21: =表1温室气体盘查表!AG10 -> 1676.4744 | J21: =表1温室气体盘查表!AH10 -> 0 | K21: =表1温室气体盘查表!AI10 -> 0 | L21: =表1温室气体盘查表!AJ10 -> 0 | M21: =表1温室气体盘查表!AK10 -> 0
B22: 1.1.7 | C22: =表1温室气体盘查表!C11 -> 焦屑燃烧 | D22: =表1温室气体盘查表!D11 -> 烧结、高炉 | F22: =SUM(G22:M22) -> 364657.36 | G22: =表1温室气体盘查表!AE11 -> 363172.76 | H22: =表1温室气体盘查表!AF11 -> 94.696449 | I22: =表1温室气体盘查表!AG11 -> 1389.8995 | J22: =表1温室气体盘查表!AH11 -> 0 | K22: =表1温室气体盘查表!AI11 -> 0 | L22: =表1温室气体盘查表!AJ11 -> 0 | M22: =表1温室气体盘查表!AK11 -> 0
B23: 1.1.8 | C23: =表1温室气体盘查表!C12 -> 焦炉煤气燃烧 | D23: =表1温室气体盘查表!D12 -> 外售 | F23: =SUM(G23:M23) -> -3833.1355 | G23: =表1温室气体盘查表!AE12 -> -3828.3759 | H23: =表1温室气体盘查表!AF12 -> -2.4056686 | I23: =表1温室气体盘查表!AG12 -> -2.3539338 | J23: =表1温室气体盘查表!AH12 -> 0 | K23: =表1温室气体盘查表!AI12 -> 0 | L23: =表1温室气体盘查表!AJ12 -> 0 | M23: =表1温室气体盘查表!AK12 -> 0
B24: 1.2 | C24: 移动源燃烧直接排放 | F24: =SUM(G24:M24) -> 4566.5427 | G24: =SUM(G25:G26) -> 4491.7139 | H24: =SUM(H25:H26) -> 7.8293549 | I24: =SUM(I25:I26) -> 66.999448 | J24: =SUM(J25:J26) -> 0 | K24: =SUM(K25:K26) -> 0 | L24: =SUM(L25:L26) -> 0 | M24: =SUM(M25:M26) -> 0
B25: 1.2.1 | C25: =表1温室气体盘查表!C13 -> 0#柴油燃烧 | D25: =表1温室气体盘查表!D13 -> 场内运输 | F25: =SUM(G25:M25) -> 4417.0726 | G25: =表1温室气体盘查表!AE13 -> 4348.2107 | H25: =表1温室气体盘查表!AF13 -> 6.3850041 | I25: =表1温室气体盘查表!AG13 -> 62.476922 | J25: =表1温室气体盘查表!AH13 -> 0 | K25: =表1温室气体盘查表!AI13 -> 0 | L25: =表1温室气体盘查表!AJ13 -> 0 | M25: =表1温室气体盘查表!AK13 -> 0
B26: 1.2.2 | C26: =表1温室气体盘查表!C14 -> 92#汽油燃烧 | D26: =表1温室气体盘查表!D14 -> 公务车 | F26: =SUM(G26:M26) -> 149.47012 | G26: =表1温室气体盘查表!AE14 -> 143.50325 | H26: =表1温室气体盘查表!AF14 -> 1.4443509 | I26: =表1温室气体盘查表!AG14 -> 4.5225266 | J26: =表1温室气体盘查表!AH14 -> 0 | K26: =表1温室气体盘查表!AI14 -> 0 | L26: =表1温室气体盘查表!AJ14 -> 0 | M26: =表1温室气体盘查表!AK14 -> 0
B27: 1.3 | C27: 逸散源直接排放 | F27: =SUM(G27:M27) -> 3654.7226 | G27: =SUM(G28:G32) -> 0.66 | H27: =SUM(H28:H32) -> 477.87259 | I27: =SUM(I28:I32) -> 0 | J27: =SUM(J28:J32) -> 717.03 | K27: =SUM(K28:K32) -> 0 | L27: =SUM(L28:L32) -> 2459.16 | M27: =SUM(M28:M32) -> 0
B28: 1.3.1 | C28: =表1温室气体盘查表!C15 -> 制冷剂逸散（R32） | D28: =表1温室气体盘查表!D15 -> 分体式空调 | F28: =SUM(G28:M28) -> 717.03 | G28: =表1温室气体盘查表!AE15 -> 0 | H28: =表1温室气体盘查表!AF15 -> 0 | I28: =表1温室气体盘查表!AG15 -> 0 | J28: =表1温室气体盘查表!AH15 -> 717.03 | K28: =表1温室气体盘查表!AI15 -> 0 | L28: =表1温室气体盘查表!AJ15 -> 0 | M28: =表1温室气体盘查表!AK15 -> 0
B29: 1.3.2 | C29: =表1温室气体盘查表!C16 -> CO2逸散 | D29: =表1温室气体盘查表!D16 -> 二氧化碳灭火器 | F29: =SUM(G29:M29) -> 0.66 | G29: =表1温室气体盘查表!AE16 -> 0.66 | H29: =表1温室气体盘查表!AF16 -> 0 | I29: =表1温室气体盘查表!AG16 -> 0 | J29: =表1温室气体盘查表!AH16 -> 0 | K29: =表1温室气体盘查表!AI16 -> 0 | L29: =表1温室气体盘查表!AJ16 -> 0 | M29: =表1温室气体盘查表!AK16 -> 0
B30: 1.3.3 | C30: =表1温室气体盘查表!C17 -> CH4逸散 | D30: =表1温室气体盘查表!D17 -> 化粪池 | F30: =SUM(G30:M30) -> 112.29192 | G30: =表1温室气体盘查表!AE17 -> 0 | H30: =表1温室气体盘查表!AF17 -> 112.29192 | I30: =表1温室气体盘查表!AG17 -> 0 | J30: =表1温室气体盘查表!AH17 -> 0 | K30: =表1温室气体盘查表!AI17 -> 0 | L30: =表1温室气体盘查表!AJ17 -> 0 | M30: =表1温室气体盘查表!AK17 -> 0
B31: 1.3.4 | C31: =表1温室气体盘查表!C18 -> CH4逸散 | D31: =表1温室气体盘查表!D18 -> 耗氧池 | F31: =SUM(G31:M31) -> 365.58067 | G31: =表1温室气体盘查表!AE18 -> 0 | H31: =表1温室气体盘查表!AF18 -> 365.58067 | I31: =表1温室气体盘查表!AG18 -> 0 | J31: =表1温室气体盘查表!AH18 -> 0 | K31: =表1温室气体盘查表!AI18 -> 0 | L31: =表1温室气体盘查表!AJ18 -> 0 | M31: =表1温室气体盘查表!AK18 -> 0
B32: 1.3.5 | C32: =表1温室气体盘查表!C19 -> SF6逸散 | D32: =表1温室气体盘查表!D19 -> 高压开关 | F32: =SUM(G32:M32) -> 2459.16 | G32: =表1温室气体盘查表!AE19 -> 0 | H32: =表1温室气体盘查表!AF19 -> 0 | I32: =表1温室气体盘查表!AG19 -> 0 | J32: =表1温室气体盘查表!AH19 -> 0 | K32: =表1温室气体盘查表!AI19 -> 0 | L32: =表1温室气体盘查表!AJ19 -> 2459.16 | M32: =表1温室气体盘查表!AK19 -> 0
B33: 1.4 | C33: 制程排放 | F33: =SUM(G33:M33) -> -113616.67 | G33: =SUM(G34:G45) -> -113616.67 | H33: =SUM(H34:H45) -> 0 | I33: =SUM(I34:I45) -> 0 | J33: =SUM(J34:J45) -> 0 | K33: =SUM(K34:K45) -> 0 | L33: =SUM(L34:L45) -> 0 | M33: =SUM(M34:M45) -> 0
B34: 1.4.1 | C34: =表1温室气体盘查表!C20 -> 石灰石 | D34: =表1温室气体盘查表!D20 -> 石灰窑 | F34: =SUM(G34:M34) -> 8520.9388 | G34: =表1温室气体盘查表!AE20 -> 8520.9388 | H34: =表1温室气体盘查表!AF20 -> 0 | I34: =表1温室气体盘查表!AG20 -> 0 | J34: =表1温室气体盘查表!AH20 -> 0 | K34: =表1温室气体盘查表!AI20 -> 0 | L34: =表1温室气体盘查表!AJ20 -> 0 | M34: =表1温室气体盘查表!AK20 -> 0
B35: 1.4.2 | C35: =表1温室气体盘查表!C21 -> 白云石 | D35: =表1温室气体盘查表!D21 -> 高炉 | F35: =SUM(G35:M35) -> 169593.75 | G35: =表1温室气体盘查表!AE21 -> 169593.75 | H35: =表1温室气体盘查表!AF21 -> 0 | I35: =表1温室气体盘查表!AG21 -> 0 | J35: =表1温室气体盘查表!AH21 -> 0 | K35: =表1温室气体盘查表!AI21 -> 0 | L35: =表1温室气体盘查表!AJ21 -> 0 | M35: =表1温室气体盘查表!AK21 -> 0
B36: 1.4.3 | C36: =表1温室气体盘查表!C22 -> 电极 | D36: =表1温室气体盘查表!D22 -> 炼钢 | F36: =SUM(G36:M36) -> 17447.125 | G36: =表1温室气体盘查表!AE22 -> 17447.125 | H36: =表1温室气体盘查表!AF22 -> 0 | I36: =表1温室气体盘查表!AG22 -> 0 | J36: =表1温室气体盘查表!AH22 -> 0 | K36: =表1温室气体盘查表!AI22 -> 0 | L36: =表1温室气体盘查表!AJ22 -> 0 | M36: =表1温室气体盘查表!AK22 -> 0
B37: 1.4.4 | C37: =表1温室气体盘查表!C23 -> 废钢 | D37: =表1温室气体盘查表!D23 -> 炼钢 | F37: =SUM(G37:M37) -> 39875.738 | G37: =表1温室气体盘查表!AE23 -> 39875.738 | H37: =表1温室气体盘查表!AF23 -> 0 | I37: =表1温室气体盘查表!AG23 -> 0 | J37: =表1温室气体盘查表!AH23 -> 0 | K37: =表1温室气体盘查表!AI23 -> 0 | L37: =表1温室气体盘查表!AJ23 -> 0 | M37: =表1温室气体盘查表!AK23 -> 0
B38: 1.4.5 | C38: =表1温室气体盘查表!C24 -> 锰铁 | D38: =表1温室气体盘查表!D24 -> 炼钢 | F38: =SUM(G38:M38) -> 13114.101 | G38: =表1温室气体盘查表!AE24 -> 13114.101 | H38: =表1温室气体盘查表!AF24 -> 0 | I38: =表1温室气体盘查表!AG24 -> 0 | J38: =表1温室气体盘查表!AH24 -> 0 | K38: =表1温室气体盘查表!AI24 -> 0 | L38: =表1温室气体盘查表!AJ24 -> 0 | M38: =表1温室气体盘查表!AK24 -> 0
B39: 1.4.6 | C39: =表1温室气体盘查表!C25 -> 镍铁 | D39: =表1温室气体盘查表!D25 -> 炼钢 | F39: =SUM(G39:M39) -> 349.46907 | G39: =表1温室气体盘查表!AE25 -> 349.46907 | H39: =表1温室气体盘查表!AF25 -> 0 | I39: =表1温室气体盘查表!AG25 -> 0 | J39: =表1温室气体盘查表!AH25 -> 0 | K39: =表1温室气体盘查表!AI25 -> 0 | L39: =表1温室气体盘查表!AJ25 -> 0 | M39: =表1温室气体盘查表!AK25 -> 0
B40: 1.4.7 | C40: =表1温室气体盘查表!C26 -> 铬铁 | D40: =表1温室气体盘查表!D26 -> 炼钢 | F40: =SUM(G40:M40) -> 22918.907 | G40: =表1温室气体盘查表!AE26 -> 22918.907 | H40: =表1温室气体盘查表!AF26 -> 0 | I40: =表1温室气体盘查表!AG26 -> 0 | J40: =表1温室气体盘查表!AH26 -> 0 | K40: =表1温室气体盘查表!AI26 -> 0 | L40: =表1温室气体盘查表!AJ26 -> 0 | M40: =表1温室气体盘查表!AK26 -> 0
B41: 1.4.8 | C41: =表1温室气体盘查表!C27 -> 硅铁 | D41: =表1温室气体盘查表!D27 -> 炼钢 | F41: =SUM(G41:M41) -> 74.70736 | G41: =表1温室气体盘查表!AE27 -> 74.70736 | H41: =表1温室气体盘查表!AF27 -> 0 | I41: =表1温室气体盘查表!AG27 -> 0 | J41: =表1温室气体盘查表!AH27 -> 0 | K41: =表1温室气体盘查表!AI27 -> 0 | L41: =表1温室气体盘查表!AJ27 -> 0 | M41: =表1温室气体盘查表!AK27 -> 0
B42: 1.4.9 | C42: =表1温室气体盘查表!C28 -> 钼铁 | D42: =表1温室气体盘查表!D28 -> 炼钢 | F42: =SUM(G42:M42) -> 143.01295 | G42: =表1温室气体盘查表!AE28 -> 143.01295 | H42: =表1温室气体盘查表!AF28 -> 0 | I42: =表1温室气体盘查表!AG28 -> 0 | J42: =表1温室气体盘查表!AH28 -> 0 | K42: =表1温室气体盘查表!AI28 -> 0 | L42: =表1温室气体盘查表!AJ28 -> 0 | M42: =表1温室气体盘查表!AK28 -> 0
B43: 1.4.10 | C43: =表1温室气体盘查表!C29 -> 钢坯 | D43: =表1温室气体盘查表!D29 -> 固碳产品 | F43: =SUM(G43:M43) -> -160314.41 | G43: =表1温室气体盘查表!AE29 -> -160314.41 | H43: =表1温室气体盘查表!AF29 -> 0 | I43: =表1温室气体盘查表!AG29 -> 0 | J43: =表1温室气体盘查表!AH29 -> 0 | K43: =表1温室气体盘查表!AI29 -> 0 | L43: =表1温室气体盘查表!AJ29 -> 0 | M43: =表1温室气体盘查表!AK29 -> 0
B44: 1.4.11 | C44: =表1温室气体盘查表!C30 -> 粗苯 | D44: =表1温室气体盘查表!D30 -> 外售 | F44: =SUM(G44:M44) -> -65952.991 | G44: =表1温室气体盘查表!AE30 -> -65952.991 | H44: =表1温室气体盘查表!AF30 -> 0 | I44: =表1温室气体盘查表!AG30 -> 0 | J44: =表1温室气体盘查表!AH30 -> 0 | K44: =表1温室气体盘查表!AI30 -> 0 | L44: =表1温室气体盘查表!AJ30 -> 0 | M44: =表1温室气体盘查表!AK30 -> 0
B45: 1.4.12 | C45: =表1温室气体盘查表!C31 -> 煤焦油 | D45: =表1温室气体盘查表!D31 -> 危废处置 | F45: =SUM(G45:M45) -> -159387.02 | G45: =表1温室气体盘查表!AE31 -> -159387.02 | H45: =表1温室气体盘查表!AF31 -> 0 | I45: =表1温室气体盘查表!AG31 -> 0 | J45: =表1温室气体盘查表!AH31 -> 0 | K45: =表1温室气体盘查表!AI31 -> 0 | L45: =表1温室气体盘查表!AJ31 -> 0 | M45: =表1温室气体盘查表!AK31 -> 0
B46: 范围二 外购电间接排放
B47: 2.1 | C47: =表1温室气体盘查表!C32 -> 外购电力（基于位置） | D47: =表1温室气体盘查表!D32 -> 用电设备 | F47: =SUM(G47:M47) -> 1069378.7 | G47: =表1温室气体盘查表!AE32 -> 1069378.7 | H47: =表1温室气体盘查表!AF32 -> 0 | I47: =表1温室气体盘查表!AG32 -> 0 | J47: =表1温室气体盘查表!AH32 -> 0 | K47: =表1温室气体盘查表!AI32 -> 0 | L47: =表1温室气体盘查表!AJ32 -> 0 | M47: =表1温室气体盘查表!AK32 -> 0
B48: 2.2 | C48: =表1温室气体盘查表!C33 -> 外购电力（基于市场） | D48: =表1温室气体盘查表!D33 -> 用电设备 | F48: =SUM(G48:M48) -> 1161900.3 | G48: =表1温室气体盘查表!AE33 -> 1161900.3 | H48: =表1温室气体盘查表!AF33 -> 0 | I48: =表1温室气体盘查表!AG33 -> 0 | J48: =表1温室气体盘查表!AH33 -> 0 | K48: =表1温室气体盘查表!AI33 -> 0 | L48: =表1温室气体盘查表!AJ33 -> 0 | M48: =表1温室气体盘查表!AK33 -> 0
B50: 范围三 类别1 | C50: 外购商品和服务的上游排放 | F50: =SUM(G50:M50) -> 2710165.6 | G50: =SUM(G51:G74) -> 2710165.6 | H50: =SUM(H51:H69) -> 0 | I50: =SUM(I51:I69) -> 0 | J50: =SUM(J51:J69) -> 0 | K50: =SUM(K51:K69) -> 0 | L50: =SUM(L51:L69) -> 0 | M50: =SUM(M51:M69) -> 0
B51: 3.1.1 | C51: =表1温室气体盘查表!C34 -> 铁矿石生产 | D51: =表1温室气体盘查表!D34 -> 烧结 | F51: =表1温室气体盘查表!AL34 -> 448588.58 | G51: =表1温室气体盘查表!AE34 -> 448588.58 | H51: =表1温室气体盘查表!AF34 -> 0 | I51: =表1温室气体盘查表!AG34 -> 0 | J51: =表1温室气体盘查表!AH34 -> 0 | K51: =表1温室气体盘查表!AI34 -> 0 | L51: =表1温室气体盘查表!AJ34 -> 0 | M51: =表1温室气体盘查表!AK34 -> 0
B52: 3.1.2 | C52: =表1温室气体盘查表!C35 -> 生石灰生产 | D52: =表1温室气体盘查表!D35 -> 烧结、转炉、电炉 | F52: =表1温室气体盘查表!AL35 -> 727500.38 | G52: =表1温室气体盘查表!AE35 -> 727500.38 | H52: =表1温室气体盘查表!AF35 -> 0 | I52: =表1温室气体盘查表!AG35 -> 0 | J52: =表1温室气体盘查表!AH35 -> 0 | K52: =表1温室气体盘查表!AI35 -> 0 | L52: =表1温室气体盘查表!AJ35 -> 0 | M52: =表1温室气体盘查表!AK35 -> 0
B53: 3.1.3 | C53: =表1温室气体盘查表!C36 -> 石灰石生产 | D53: =表1温室气体盘查表!D36 -> 转炉 | F53: =表1温室气体盘查表!AL36 -> 58.676347 | G53: =表1温室气体盘查表!AE36 -> 58.676347 | H53: =表1温室气体盘查表!AF36 -> 0 | I53: =表1温室气体盘查表!AG36 -> 0 | J53: =表1温室气体盘查表!AH36 -> 0 | K53: =表1温室气体盘查表!AI36 -> 0 | L53: =表1温室气体盘查表!AJ36 -> 0 | M53: =表1温室气体盘查表!AK36 -> 0
B54: 3.1.4 | C54: =表1温室气体盘查表!C37 -> 白云石生产 | D54: =表1温室气体盘查表!D37 -> 烧结、转炉、电炉 | F54: =表1温室气体盘查表!AL37 -> 46435.196 | G54: =表1温室气体盘查表!AE37 -> 46435.196 | H54: =表1温室气体盘查表!AF37 -> 0 | I54: =表1温室气体盘查表!AG37 -> 0 | J54: =表1温室气体盘查表!AH37 -> 0 | K54: =表1温室气体盘查表!AI37 -> 0 | L54: =表1温室气体盘查表!AJ37 -> 0 | M54: =表1温室气体盘查表!AK37 -> 0
B55: 3.1.5 | C55: =表1温室气体盘查表!C38 -> 轻烧白云石生产 | D55: =表1温室气体盘查表!D39 -> 高炉、转炉 | F55: =表1温室气体盘查表!AL38 -> 363.20886 | G55: =表1温室气体盘查表!AE38 -> 363.20886 | H55: =表1温室气体盘查表!AF38 -> 0 | I55: =表1温室气体盘查表!AG38 -> 0 | J55: =表1温室气体盘查表!AH38 -> 0 | K55: =表1温室气体盘查表!AI38 -> 0 | L55: =表1温室气体盘查表!AJ38 -> 0 | M55: =表1温室气体盘查表!AK38 -> 0
B56: 3.1.6 | C56: =表1温室气体盘查表!C39 -> 球团生产 | D56: =表1温室气体盘查表!D40 -> 转炉、电炉 | F56: =表1温室气体盘查表!AL39 -> 71601.051 | G56: =表1温室气体盘查表!AE39 -> 71601.051 | H56: =表1温室气体盘查表!AF39 -> 0 | I56: =表1温室气体盘查表!AG39 -> 0 | J56: =表1温室气体盘查表!AH39 -> 0 | K56: =表1温室气体盘查表!AI39 -> 0 | L56: =表1温室气体盘查表!AJ39 -> 0 | M56: =表1温室气体盘查表!AK39 -> 0
B57: 3.1.7 | C57: =表1温室气体盘查表!C40 -> 废钢生产 | D57: =表1温室气体盘查表!D41 -> 转炉、电炉 | F57: =表1温室气体盘查表!AL40 -> 79944.388 | G57: =表1温室气体盘查表!AE40 -> 79944.388 | H57: =表1温室气体盘查表!AF40 -> 0 | I57: =表1温室气体盘查表!AG40 -> 0 | J57: =表1温室气体盘查表!AH40 -> 0 | K57: =表1温室气体盘查表!AI40 -> 0 | L57: =表1温室气体盘查表!AJ40 -> 0 | M57: =表1温室气体盘查表!AK40 -> 0
B58: 3.1.8 | C58: =表1温室气体盘查表!C41 -> 电极生产 | D58: =表1温室气体盘查表!D42 -> 转炉、电炉 | F58: =表1温室气体盘查表!AL41 -> 37742.812 | G58: =表1温室气体盘查表!AE41 -> 37742.812 | H58: =表1温室气体盘查表!AF41 -> 0 | I58: =表1温室气体盘查表!AG41 -> 0 | J58: =表1温室气体盘查表!AH41 -> 0 | K58: =表1温室气体盘查表!AI41 -> 0 | L58: =表1温室气体盘查表!AJ41 -> 0 | M58: =表1温室气体盘查表!AK41 -> 0
B59: 3.1.9 | C59: =表1温室气体盘查表!C42 -> 锰铁生产 | D59: =表1温室气体盘查表!D43 -> 转炉、电炉 | F59: =表1温室气体盘查表!AL42 -> 141868.58 | G59: =表1温室气体盘查表!AE42 -> 141868.58 | H59: =表1温室气体盘查表!AF42 -> 0 | I59: =表1温室气体盘查表!AG42 -> 0 | J59: =表1温室气体盘查表!AH42 -> 0 | K59: =表1温室气体盘查表!AI42 -> 0 | L59: =表1温室气体盘查表!AJ42 -> 0 | M59: =表1温室气体盘查表!AK42 -> 0
B60: 3.1.10 | C60: =表1温室气体盘查表!C43 -> 镍铁生产 | D60: =表1温室气体盘查表!D44 -> 转炉、电炉 | F60: =表1温室气体盘查表!AL43 -> 84819.123 | G60: =表1温室气体盘查表!AE43 -> 84819.123 | H60: =表1温室气体盘查表!AF43 -> 0 | I60: =表1温室气体盘查表!AG43 -> 0 | J60: =表1温室气体盘查表!AH43 -> 0 | K60: =表1温室气体盘查表!AI43 -> 0 | L60: =表1温室气体盘查表!AJ43 -> 0 | M60: =表1温室气体盘查表!AK43 -> 0
B61: 3.1.11 | C61: =表1温室气体盘查表!C44 -> 铬铁生产 | D61: =表1温室气体盘查表!D45 -> 转炉、电炉 | F61: =表1温室气体盘查表!AL44 -> 345101.44 | G61: =表1温室气体盘查表!AE44 -> 345101.44 | H61: =表1温室气体盘查表!AF44 -> 0 | I61: =表1温室气体盘查表!AG44 -> 0 | J61: =表1温室气体盘查表!AH44 -> 0 | K61: =表1温室气体盘查表!AI44 -> 0 | L61: =表1温室气体盘查表!AJ44 -> 0 | M61: =表1温室气体盘查表!AK44 -> 0
B62: 3.1.12 | C62: =表1温室气体盘查表!C45 -> 萤石生产 | D62: =表1温室气体盘查表!D46 -> 转炉、电炉 | F62: =表1温室气体盘查表!AL45 -> 685.06219 | G62: =表1温室气体盘查表!AE45 -> 685.06219 | H62: =表1温室气体盘查表!AF45 -> 0 | I62: =表1温室气体盘查表!AG45 -> 0 | J62: =表1温室气体盘查表!AH45 -> 0 | K62: =表1温室气体盘查表!AI45 -> 0 | L62: =表1温室气体盘查表!AJ45 -> 0 | M62: =表1温室气体盘查表!AK45 -> 0
B63: 3.1.13 | C63: =表1温室气体盘查表!C46 -> 硅铁生产 | D63: =表1温室气体盘查表!D47 -> 转炉、电炉 | F63: =表1温室气体盘查表!AL46 -> 103575.78 | G63: =表1温室气体盘查表!AE46 -> 103575.78 | H63: =表1温室气体盘查表!AF46 -> 0 | I63: =表1温室气体盘查表!AG46 -> 0 | J63: =表1温室气体盘查表!AH46 -> 0 | K63: =表1温室气体盘查表!AI46 -> 0 | L63: =表1温室气体盘查表!AJ46 -> 0 | M63: =表1温室气体盘查表!AK46 -> 0
B64: 3.1.14 | C64: =表1温室气体盘查表!C47 -> 钼铁生产 | D64: =表1温室气体盘查表!D48 -> 转炉、电炉 | F64: =表1温室气体盘查表!AL47 -> 66065.4 | G64: =表1温室气体盘查表!AE47 -> 66065.4 | H64: =表1温室气体盘查表!AF47 -> 0 | I64: =表1温室气体盘查表!AG47 -> 0 | J64: =表1温室气体盘查表!AH47 -> 0 | K64: =表1温室气体盘查表!AI47 -> 0 | L64: =表1温室气体盘查表!AJ47 -> 0 | M64: =表1温室气体盘查表!AK47 -> 0
B65: 3.1.15 | C65: =表1温室气体盘查表!C48 -> 铝铁生产 | D65: =表1温室气体盘查表!D49 -> 转炉、电炉 | F65: =表1温室气体盘查表!AL48 -> 63158.19 | G65: =表1温室气体盘查表!AE48 -> 63158.19 | H65: =表1温室气体盘查表!AF48 -> 0 | I65: =表1温室气体盘查表!AG48 -> 0 | J65: =表1温室气体盘查表!AH48 -> 0 | K65: =表1温室气体盘查表!AI48 -> 0 | L65: =表1温室气体盘查表!AJ48 -> 0 | M65: =表1温室气体盘查表!AK48 -> 0
B66: 3.1.16 | C66: =表1温室气体盘查表!C49 -> 铝生产 | D66: =表1温室气体盘查表!D50 -> 转炉、电炉 | F66: =表1温室气体盘查表!AL49 -> 63342.195 | G66: =表1温室气体盘查表!AE49 -> 63342.195 | H66: =表1温室气体盘查表!AF49 -> 0 | I66: =表1温室气体盘查表!AG49 -> 0 | J66: =表1温室气体盘查表!AH49 -> 0 | K66: =表1温室气体盘查表!AI49 -> 0 | L66: =表1温室气体盘查表!AJ49 -> 0 | M66: =表1温室气体盘查表!AK49 -> 0
B67: 3.1.17 | C67: =表1温室气体盘查表!C50 -> 增碳剂生产 | D67: =表1温室气体盘查表!D50 -> 转炉、电炉 | F67: =表1温室气体盘查表!AL50 -> 17778.323 | G67: =表1温室气体盘查表!AE50 -> 17778.323 | H67: =表1温室气体盘查表!AF50 -> 0 | I67: =表1温室气体盘查表!AG50 -> 0 | J67: =表1温室气体盘查表!AH50 -> 0 | K67: =表1温室气体盘查表!AI50 -> 0 | L67: =表1温室气体盘查表!AJ50 -> 0 | M67: =表1温室气体盘查表!AK50 -> 0
B68: 3.1.18 | C68: =表1温室气体盘查表!C51 -> 铁鳞生产 | D68: =表1温室气体盘查表!D51 -> 炼钢 | F68: =表1温室气体盘查表!AL51 -> 608.38394 | G68: =表1温室气体盘查表!AE51 -> 608.38394 | H68: =表1温室气体盘查表!AF51 -> 0 | I68: =表1温室气体盘查表!AG51 -> 0 | J68: =表1温室气体盘查表!AH51 -> 0 | K68: =表1温室气体盘查表!AI51 -> 0 | L68: =表1温室气体盘查表!AJ51 -> 0 | M68: =表1温室气体盘查表!AK51 -> 0
B69: 3.1.19 | C69: =表1温室气体盘查表!C52 -> 氨水生产 | D69: =表1温室气体盘查表!D52 -> 烧结 | F69: =表1温室气体盘查表!AL52 -> 24444.815 | G69: =表1温室气体盘查表!AE52 -> 24444.815 | H69: =表1温室气体盘查表!AF52 -> 0 | I69: =表1温室气体盘查表!AG52 -> 0 | J69: =表1温室气体盘查表!AH52 -> 0 | K69: =表1温室气体盘查表!AI52 -> 0 | L69: =表1温室气体盘查表!AJ52 -> 0 | M69: =表1温室气体盘查表!AK52 -> 0
B70: 3.1.20 | C70: =表1温室气体盘查表!C53 -> 碳化硅生产 | D70: =表1温室气体盘查表!D53 -> - | F70: =表1温室气体盘查表!AL53 -> 48149.585 | G70: =表1温室气体盘查表!AE53 -> 48149.585 | H70: =表1温室气体盘查表!AF53 -> 0 | I70: =表1温室气体盘查表!AG53 -> 0 | J70: =表1温室气体盘查表!AH53 -> 0 | K70: =表1温室气体盘查表!AI53 -> 0 | L70: =表1温室气体盘查表!AJ53 -> 0 | M70: =表1温室气体盘查表!AK53 -> 0
B71: 3.1.21 | C71: =表1温室气体盘查表!C54 -> 镁生产 | D71: =表1温室气体盘查表!D54 -> - | F71: =表1温室气体盘查表!AL54 -> 308520.83 | G71: =表1温室气体盘查表!AE54 -> 308520.83 | H71: =表1温室气体盘查表!AF54 -> 0 | I71: =表1温室气体盘查表!AG54 -> 0 | J71: =表1温室气体盘查表!AH54 -> 0 | K71: =表1温室气体盘查表!AI54 -> 0 | L71: =表1温室气体盘查表!AJ54 -> 0 | M71: =表1温室气体盘查表!AK54 -> 0
B72: 3.1.22 | C72: =表1温室气体盘查表!C55 -> 所有其他纸制品加工制造 | D72: =表1温室气体盘查表!D55 -> 办公室 | F72: =表1温室气体盘查表!AL55 -> 5.5436243 | G72: =表1温室气体盘查表!AE55 -> 5.5436243 | H72: =表1温室气体盘查表!AF55 -> 0 | I72: =表1温室气体盘查表!AG55 -> 0 | J72: =表1温室气体盘查表!AH55 -> 0 | K72: =表1温室气体盘查表!AI55 -> 0 | L72: =表1温室气体盘查表!AJ55 -> 0 | M72: =表1温室气体盘查表!AK55 -> 0
B73: 3.1.23 | C73: =表1温室气体盘查表!C56 -> 办公用品(纸张除外)制造 | D73: =表1温室气体盘查表!D56 -> 办公室 | F73: =表1温室气体盘查表!AL56 -> 47.034256 | G73: =表1温室气体盘查表!AE56 -> 47.034256 | H73: =表1温室气体盘查表!AF56 -> 0 | I73: =表1温室气体盘查表!AG56 -> 0 | J73: =表1温室气体盘查表!AH56 -> 0 | K73: =表1温室气体盘查表!AI56 -> 0 | L73: =表1温室气体盘查表!AJ56 -> 0 | M73: =表1温室气体盘查表!AK56 -> 0
B74: 3.1.24 | C74: =表1温室气体盘查表!C57 -> 源水 | D74: =表1温室气体盘查表!D57 -> 水处理工序 | F74: =表1温室气体盘查表!AL57 -> 29761.031 | G74: =表1温室气体盘查表!AE57 -> 29761.031 | H74: =表1温室气体盘查表!AF57 -> 0 | I74: =表1温室气体盘查表!AG57 -> 0 | J74: =表1温室气体盘查表!AH57 -> 0 | K74: =表1温室气体盘查表!AI57 -> 0 | L74: =表1温室气体盘查表!AJ57 -> 0 | M74: =表1温室气体盘查表!AK57 -> 0
B76: 范围三 类别2 | C76: =表1温室气体盘查表!B58 -> 资本货物 | F76: =SUM(G76:M76) -> 51806.97 | G76: =SUM(G77:G87) -> 51806.97 | H76: =SUM(H77:H87) -> 0 | I76: =SUM(I77:I87) -> 0 | J76: =SUM(J77:J87) -> 0 | K76: =SUM(K77:K87) -> 0 | L76: =SUM(L77:L87) -> 0 | M76: =SUM(M77:M87) -> 0
B77: 3.2.1 | C77: =表1温室气体盘查表!C58 -> 采购产品空调和暖空气加热设备和商业和工业制冷设备制造 | D77: =表1温室气体盘查表!D58 -> 办公室、各工序 | F77: =表1温室气体盘查表!AL58 -> 14.832439 | G77: =表1温室气体盘查表!AE58 -> 14.832439 | H77: =表1温室气体盘查表!AF58 -> 0 | I77: =表1温室气体盘查表!AG58 -> 0 | J77: =表1温室气体盘查表!AH58 -> 0 | K77: =表1温室气体盘查表!AI58 -> 0 | L77: =表1温室气体盘查表!AJ58 -> 0 | M77: =表1温室气体盘查表!AK58 -> 0
B78: 3.2.2 | C78: =表1温室气体盘查表!C59 -> 电子计算机制造 | D78: =表1温室气体盘查表!D59 -> 办公室、各工序 | F78: =表1温室气体盘查表!AL59 -> 3.7880397 | G78: =表1温室气体盘查表!AE59 -> 3.7880397 | H78: =表1温室气体盘查表!AF59 -> 0 | I78: =表1温室气体盘查表!AG59 -> 0 | J78: =表1温室气体盘查表!AH59 -> 0 | K78: =表1温室气体盘查表!AI59 -> 0 | L78: =表1温室气体盘查表!AJ59 -> 0 | M78: =表1温室气体盘查表!AK59 -> 0
B79: 3.2.3 | C79: =表1温室气体盘查表!C60 -> 焊接及焊接设备制造 | D79: =表1温室气体盘查表!D60 -> 各工序 | F79: =表1温室气体盘查表!AL60 -> 216.41133 | G79: =表1温室气体盘查表!AE60 -> 216.41133 | H79: =表1温室气体盘查表!AF60 -> 0 | I79: =表1温室气体盘查表!AG60 -> 0 | J79: =表1温室气体盘查表!AH60 -> 0 | K79: =表1温室气体盘查表!AI60 -> 0 | L79: =表1温室气体盘查表!AJ60 -> 0 | M79: =表1温室气体盘查表!AK60 -> 0
B80: 3.2.4 | C80: =表1温室气体盘查表!C61 -> 其他工业设备制造 | D80: =表1温室气体盘查表!D61 -> 各工序 | F80: =表1温室气体盘查表!AL61 -> 1153.4664 | G80: =表1温室气体盘查表!AE61 -> 1153.4664 | H80: =表1温室气体盘查表!AF61 -> 0 | I80: =表1温室气体盘查表!AG61 -> 0 | J80: =表1温室气体盘查表!AH61 -> 0 | K80: =表1温室气体盘查表!AI61 -> 0 | L80: =表1温室气体盘查表!AJ61 -> 0 | M80: =表1温室气体盘查表!AK61 -> 0
B81: 3.2.5 | C81: =表1温室气体盘查表!C62 -> 测量和测试电力和电气信号的仪器制造 | D81: =表1温室气体盘查表!D62 -> 各工序 | F81: =表1温室气体盘查表!AL62 -> 44.316302 | G81: =表1温室气体盘查表!AE62 -> 44.316302 | H81: =表1温室气体盘查表!AF62 -> 0 | I81: =表1温室气体盘查表!AG62 -> 0 | J81: =表1温室气体盘查表!AH62 -> 0 | K81: =表1温室气体盘查表!AI62 -> 0 | L81: =表1温室气体盘查表!AJ62 -> 0 | M81: =表1温室气体盘查表!AK62 -> 0
B82: 3.2.6 | C82: =表1温室气体盘查表!C63 -> 计算机系统设计服务 | D82: =表1温室气体盘查表!D63 -> 各工序 | F82: =表1温室气体盘查表!AL63 -> 56.221168 | G82: =表1温室气体盘查表!AE63 -> 56.221168 | H82: =表1温室气体盘查表!AF63 -> 0 | I82: =表1温室气体盘查表!AG63 -> 0 | J82: =表1温室气体盘查表!AH63 -> 0 | K82: =表1温室气体盘查表!AI63 -> 0 | L82: =表1温室气体盘查表!AJ63 -> 0 | M82: =表1温室气体盘查表!AK63 -> 0
B83: 3.2.7 | C83: =表1温室气体盘查表!C64 -> 机械动力传动设备制造 | D83: =表1温室气体盘查表!D64 -> 各工序 | F83: =表1温室气体盘查表!AL64 -> 35.304052 | G83: =表1温室气体盘查表!AE64 -> 35.304052 | H83: =表1温室气体盘查表!AF64 -> 0 | I83: =表1温室气体盘查表!AG64 -> 0 | J83: =表1温室气体盘查表!AH64 -> 0 | K83: =表1温室气体盘查表!AI64 -> 0 | L83: =表1温室气体盘查表!AJ64 -> 0 | M83: =表1温室气体盘查表!AK64 -> 0
B84: 3.2.8 | C84: =表1温室气体盘查表!C65 -> 测量、分配及其他泵类设备制造 | D84: =表1温室气体盘查表!D65 -> 各工序 | F84: =表1温室气体盘查表!AL65 -> 432.06182 | G84: =表1温室气体盘查表!AE65 -> 432.06182 | H84: =表1温室气体盘查表!AF65 -> 0 | I84: =表1温室气体盘查表!AG65 -> 0 | J84: =表1温室气体盘查表!AH65 -> 0 | K84: =表1温室气体盘查表!AI65 -> 0 | L84: =表1温室气体盘查表!AJ65 -> 0 | M84: =表1温室气体盘查表!AK65 -> 0
B85: 3.2.9 | C85: =表1温室气体盘查表!C66 -> 用于测量、显示和控制工业过程变量的仪器及相关产品制造 | D85: =表1温室气体盘查表!D66 -> 各工序 | F85: =表1温室气体盘查表!AL66 -> 11.184553 | G85: =表1温室气体盘查表!AE66 -> 11.184553 | H85: =表1温室气体盘查表!AF66 -> 0 | I85: =表1温室气体盘查表!AG66 -> 0 | J85: =表1温室气体盘查表!AH66 -> 0 | K85: =表1温室气体盘查表!AI66 -> 0 | L85: =表1温室气体盘查表!AJ66 -> 0 | M85: =表1温室气体盘查表!AK66 -> 0
B86: 3.2.10 | C86: =表1温室气体盘查表!C67 -> 所有其他杂项电气设备及元件制造 | D86: =表1温室气体盘查表!D67 -> 各工序 | F86: =表1温室气体盘查表!AL67 -> 555.0722 | G86: =表1温室气体盘查表!AE67 -> 555.0722 | H86: =表1温室气体盘查表!AF67 -> 0 | I86: =表1温室气体盘查表!AG67 -> 0 | J86: =表1温室气体盘查表!AH67 -> 0 | K86: =表1温室气体盘查表!AI67 -> 0 | L86: =表1温室气体盘查表!AJ67 -> 0 | M86: =表1温室气体盘查表!AK67 -> 0
B87: 3.2.11 | C87: =表1温室气体盘查表!C68 -> 所有其他杂项制造 | D87: =表1温室气体盘查表!D68 -> 各工序 | F87: =表1温室气体盘查表!AL68 -> 49284.312 | G87: =表1温室气体盘查表!AE68 -> 49284.312 | H87: =表1温室气体盘查表!AF68 -> 0 | I87: =表1温室气体盘查表!AG68 -> 0 | J87: =表1温室气体盘查表!AH68 -> 0 | K87: =表1温室气体盘查表!AI68 -> 0 | L87: =表1温室气体盘查表!AJ68 -> 0 | M87: =表1温室气体盘查表!AK68 -> 0
B89: 范围三 类别3 | C89: =表1温室气体盘查表!B70 -> 范围一、二相关燃料和能源相关的活动产生的排放 | F89: =SUM(G89:M89) -> 2016736.1 | G89: =SUM(G90:G99) -> 2016736.1 | H89: =SUM(H91:H98) -> 0 | I89: =SUM(I91:I98) -> 0 | J89: =SUM(J91:J98) -> 0 | K89: =SUM(K91:K98) -> 0 | L89: =SUM(L91:L98) -> 0 | M89: =SUM(M91:M98) -> 0
B90: 3.3.1 | C90: =表1温室气体盘查表!C69 -> 液化石油气生产 | D90: =表1温室气体盘查表!D69 -> 冶钢宾馆 | F90: =表1温室气体盘查表!AL69 -> 9.448458 | G90: =表1温室气体盘查表!AE69 -> 9.448458 | H90: =表1温室气体盘查表!AF69 -> 0 | I90: =表1温室气体盘查表!AG69 -> 0 | J90: =表1温室气体盘查表!AH69 -> 0 | K90: =表1温室气体盘查表!AI69 -> 0 | L90: =表1温室气体盘查表!AJ69 -> 0 | M90: =表1温室气体盘查表!AK69 -> 0
B91: 3.3.2 | C91: =表1温室气体盘查表!C70 -> 洗精煤生产 | D91: =表1温室气体盘查表!D70 -> 焦化 | F91: =表1温室气体盘查表!AL70 -> 1120352.4 | G91: =表1温室气体盘查表!AE70 -> 1120352.4 | H91: =表1温室气体盘查表!AF70 -> 0 | I91: =表1温室气体盘查表!AG70 -> 0 | J91: =表1温室气体盘查表!AH70 -> 0 | K91: =表1温室气体盘查表!AI70 -> 0 | L91: =表1温室气体盘查表!AJ70 -> 0 | M91: =表1温室气体盘查表!AK70 -> 0
B92: 3.3.3 | C92: =表1温室气体盘查表!C71 -> 柴油生产 | D92: =表1温室气体盘查表!D71 -> 各工序 | F92: =表1温室气体盘查表!AL71 -> 1182.227 | G92: =表1温室气体盘查表!AE71 -> 1182.227 | H92: =表1温室气体盘查表!AF71 -> 0 | I92: =表1温室气体盘查表!AG71 -> 0 | J92: =表1温室气体盘查表!AH71 -> 0 | K92: =表1温室气体盘查表!AI71 -> 0 | L92: =表1温室气体盘查表!AJ71 -> 0 | M92: =表1温室气体盘查表!AK71 -> 0
B93: 3.3.4 | C93: =表1温室气体盘查表!C72 -> 汽油生产 | D93: =表1温室气体盘查表!D72 -> 车队 | F93: =表1温室气体盘查表!AL72 -> 48.438425 | G93: =表1温室气体盘查表!AE72 -> 48.438425 | H93: =表1温室气体盘查表!AF72 -> 0 | I93: =表1温室气体盘查表!AG72 -> 0 | J93: =表1温室气体盘查表!AH72 -> 0 | K93: =表1温室气体盘查表!AI72 -> 0 | L93: =表1温室气体盘查表!AJ72 -> 0 | M93: =表1温室气体盘查表!AK72 -> 0
B94: 3.3.5 | C94: =表1温室气体盘查表!C73 -> 焦炭生产 | D94: =表1温室气体盘查表!D73 -> 烧结、高炉 | F94: =表1温室气体盘查表!AL73 -> 184347.32 | G94: =表1温室气体盘查表!AE73 -> 184347.32 | H94: =表1温室气体盘查表!AF73 -> 0 | I94: =表1温室气体盘查表!AG73 -> 0 | J94: =表1温室气体盘查表!AH73 -> 0 | K94: =表1温室气体盘查表!AI73 -> 0 | L94: =表1温室气体盘查表!AJ73 -> 0 | M94: =表1温室气体盘查表!AK73 -> 0
B95: 3.3.6 | C95: =表1温室气体盘查表!C74 -> 焦屑生产 | D95: =表1温室气体盘查表!D74 -> 烧结、高炉 | F95: =表1温室气体盘查表!AL74 -> 152835.17 | G95: =表1温室气体盘查表!AE74 -> 152835.17 | H95: =表1温室气体盘查表!AF74 -> 0 | I95: =表1温室气体盘查表!AG74 -> 0 | J95: =表1温室气体盘查表!AH74 -> 0 | K95: =表1温室气体盘查表!AI74 -> 0 | L95: =表1温室气体盘查表!AJ74 -> 0 | M95: =表1温室气体盘查表!AK74 -> 0
B96: 3.3.7 | C96: =表1温室气体盘查表!C75 -> 烟煤生产 | D96: =表1温室气体盘查表!D75 -> 高炉 | F96: =表1温室气体盘查表!AL75 -> 229690.01 | G96: =表1温室气体盘查表!AE75 -> 229690.01 | H96: =表1温室气体盘查表!AF75 -> 0 | I96: =表1温室气体盘查表!AG75 -> 0 | J96: =表1温室气体盘查表!AH75 -> 0 | K96: =表1温室气体盘查表!AI75 -> 0 | L96: =表1温室气体盘查表!AJ75 -> 0 | M96: =表1温室气体盘查表!AK75 -> 0
B97: 3.3.8 | C97: =表1温室气体盘查表!C76 -> 无烟煤生产 | D97: =表1温室气体盘查表!D76 -> 烧结、高炉 | F97: =表1温室气体盘查表!AL76 -> 149948.24 | G97: =表1温室气体盘查表!AE76 -> 149948.24 | H97: =表1温室气体盘查表!AF76 -> 0 | I97: =表1温室气体盘查表!AG76 -> 0 | J97: =表1温室气体盘查表!AH76 -> 0 | K97: =表1温室气体盘查表!AI76 -> 0 | L97: =表1温室气体盘查表!AJ76 -> 0 | M97: =表1温室气体盘查表!AK76 -> 0
B98: 3.3.9 | C98: =表1温室气体盘查表!C77 -> 天然气生产 | D98: =表1温室气体盘查表!D77 -> 转炉、电炉、锻造、热处理 | F98: =表1温室气体盘查表!AL77 -> 11120.273 | G98: =表1温室气体盘查表!AE77 -> 11120.273 | H98: =表1温室气体盘查表!AF77 -> 0 | I98: =表1温室气体盘查表!AG77 -> 0 | J98: =表1温室气体盘查表!AH77 -> 0 | K98: =表1温室气体盘查表!AI77 -> 0 | L98: =表1温室气体盘查表!AJ77 -> 0 | M98: =表1温室气体盘查表!AK77 -> 0
B99: 3.3.10 | C99: =表1温室气体盘查表!C78 -> 外购电力上游排放 | D99: =表1温室气体盘查表!D78 -> 各工序 | F99: =表1温室气体盘查表!AL78 -> 167202.53 | G99: =表1温室气体盘查表!AE78 -> 167202.53 | H99: =表1温室气体盘查表!AF78 -> 0 | I99: =表1温室气体盘查表!AG78 -> 0 | J99: =表1温室气体盘查表!AH78 -> 0 | K99: =表1温室气体盘查表!AI78 -> 0 | L99: =表1温室气体盘查表!AJ78 -> 0 | M99: =表1温室气体盘查表!AK78 -> 0
B101: 范围三 类别4 | C101: =表1温室气体盘查表!B79 -> 上游运输配送产生的排放 | F101: =SUM(G101:M101) -> 362284.25 | G101: =SUM(G102:G104) -> 362284.25 | H101: =SUM(H102:H104) -> 0 | I101: =SUM(I102:I104) -> 0 | J101: =SUM(J102:J104) -> 0 | K101: =SUM(K102:K104) -> 0 | L101: =SUM(L102:L104) -> 0 | M101: =SUM(M102:M104) -> 0
B102: 3.4.1 | C102: =表1温室气体盘查表!C79 -> 船运 | D102: =表1温室气体盘查表!D79 -> - | F102: =表1温室气体盘查表!AL79 -> 256608.97 | G102: =表1温室气体盘查表!AE79 -> 256608.97 | H102: =表1温室气体盘查表!AF79 -> 0 | I102: =表1温室气体盘查表!AG79 -> 0 | J102: =表1温室气体盘查表!AH79 -> 0 | K102: =表1温室气体盘查表!AI79 -> 0 | L102: =表1温室气体盘查表!AJ79 -> 0 | M102: =表1温室气体盘查表!AK79 -> 0
B103: 3.4.2 | C103: =表1温室气体盘查表!C80 -> 汽运 | D103: =表1温室气体盘查表!D80 -> - | F103: =表1温室气体盘查表!AL80 -> 46150.512 | G103: =表1温室气体盘查表!AE80 -> 46150.512 | H103: =表1温室气体盘查表!AF80 -> 0 | I103: =表1温室气体盘查表!AG80 -> 0 | J103: =表1温室气体盘查表!AH80 -> 0 | K103: =表1温室气体盘查表!AI80 -> 0 | L103: =表1温室气体盘查表!AJ80 -> 0 | M103: =表1温室气体盘查表!AK80 -> 0
B104: 3.4.3 | C104: =表1温室气体盘查表!C81 -> 铁路运输 | D104: =表1温室气体盘查表!D81 -> - | F104: =表1温室气体盘查表!AL81 -> 59524.772 | G104: =表1温室气体盘查表!AE81 -> 59524.772 | H104: =表1温室气体盘查表!AF81 -> 0 | I104: =表1温室气体盘查表!AG81 -> 0 | J104: =表1温室气体盘查表!AH81 -> 0 | K104: =表1温室气体盘查表!AI81 -> 0 | L104: =表1温室气体盘查表!AJ81 -> 0 | M104: =表1温室气体盘查表!AK81 -> 0
...

Sheet 基本信息
A1: 变量名 | B1: 变量名 | C1: 值
A2: 公司名称 | B2: company_name | C2: 大冶特殊钢有限公司
A3: 报告周期 | B3: reporting_period | C3: 2024年1月1日至2024年12月31日
A4: 报告编号 | B4: document_number | C4: DY-GHG-2025-02
A5: 生成日期 | B5: posted_time | C5: 45841
A6: 统一社会信用代码 | B6: Unified_Social_Credit_Identifier | C6: 91420000798750168P
A7: 法人代表 | B7: legal_person | C7: 蒋乔
A8: 注册资金 | B8: registered_capital | C8: 207218.53万元
A9: 注册日期 | B9: date_of_establishment | C9: 39150
A10: 注册地址 | B10: registered_address | C10: 湖北省黄石市黄石大道316号
A11: 生产地址 | B11: production_address | C11: 湖北省黄石市黄石大道316号
A12: 经营范围 | B12: scope_of_business | C12: 大冶特殊钢有限公司成立于2007年03月09日，注册地位于湖北省黄石市黄石大道316号，法定代表人为蒋乔。经营范围包括黑色、有色金属冶炼、压延加工；生产、销售高温合金材料、耐蚀合金材料、铁矿石、钢坯、钢锭、钢材、金属制品、钢管及管件和相应的工业辅助材料及承接来料加工业务；钢铁和合金材料检测；再生资源回收经营；货物或技术进出口（国家限定公司经营或禁止进出口的商品和技术除外）；机械零件、汽车零部件制造和加工；机械、仪表、电器制造和修理；化工产品（不含危险品和限制类产品）制造；港口码头建设及经营；煤气、热力、自来水、工业用水生产和供应；餐饮经营与管理。（涉及许可经营项目，应取得相关部门许可后方可经营）。
A13: 公司简介 | B13: company_profile | C13: 大冶特殊钢有限公司（简称：大冶特钢）是中国近代“钢铁摇篮”，地处中国矿冶之都、先进制造业基地湖北省黄石市。隶属中信泰富特钢集团，是其沿海沿江产业链的战略布局中的重要一环。 大冶特钢是国家高新技术企业、全国首批两化融合示范企业、全国首批绿色制造示范企业、全国绿化模范单位。拥有国家认定企业技术中心、院士专家工作站、博士后科研工作站、高品质特殊钢湖北省重点实验室，先后承担国家多项冶金课题的项目攻关，主持或参与起草修订了多项国家和行业技术标准。先后荣获“全国质量奖”、“全国质量标杆”、“中国工业大奖表彰奖”，多项产品荣获国家冶金产品实物质量“金杯奖”、“国家科学技术进步一等奖、二等奖”、“冶金科学技术奖一等奖”、“国家知识产权优势企业”、“中国航天突出贡献供应商”、“中国工模具行业最具影响力钢厂品牌”等奖项。 大冶特钢是中国品种规格最齐全的高品质棒材、高端中厚壁无缝钢管、高合金锻材三大特钢生产基地，工艺技术和装备具备世界先进水平。主要产品有轴承钢、汽车用钢、能源用钢、工程机械用钢、航空航天用钢等。主要服务于航天航空、海洋、核电、风电、交通、火电、油气、工程机械、重燃、船舶、石化、汽车、高铁等关键领域。 从中国第一炉电渣钢到第一根极薄壁高温合金旋压管，从第一个飞机用高温合金涡轮盘，到第一根轧制的飞机大梁(毛坯)，从中国第一颗人造地球卫星，到神舟系列飞船的上天，到“嫦娥”奔月，再到“天宫”“北斗”发射升空，大冶特钢均提供了关键部件的用钢。工程机械用无缝钢管已连续13年产销量全国第一、13年全球第一，石油工具及装备用中厚壁无缝钢管连续10年产销量全国第一，大口径厚壁高压锅炉用管连续5年产销量全国第一。 大冶特钢秉承“诚信、创新、融合、卓越”的理念，牢记为客户创造价值，为员工创造幸福，为股东创造效益，为社会创造财富的企业使命，致力于为客户提供多规格、多品种、高品质的特殊钢产品及整体服务方案，致力于“创建全球最具竞争力的特钢企业集团”。
A14: DDL | B14: deadline | C14: 2025年6月底前
A15: 规则文件 | B15: rule_file | C15: 《大冶特殊钢温室气体盘查控制程序（DY-GHG-2023）》
A16: GWP值来源文件 | B16: GWP_Value_Reference_Document | C16: IPCC 2021年出具的《第六次评估报告AR6》
B17: source_file | C17: 《温室气体盘查清册》-表2 不确定性评估
A18: 制作 | B18: producer | C18: 杨春英
A19: 审核 | B19: auditor
A20: 核准 | B20: approver
A21: 报告年 | B21: reporting_year | C21: 2024
A22: 下一年 | B22: next_year | C22: 2025

Sheet Sheet1
A1: {%tr for item in act_summary_loc %}
A2: {{item.number}} | B2: {{item.emission_source_type_loc}} | C2: {{item.emission_source_loc}} | D2: {{item. report_boundary_loc}} | E2: {{item.act_summary_loc}} | F2: {{item.act_summary_loc_unit}} | G2: {{item.CO2_emissions}} | H2: {{item.CH4_emissions}} | I2: {{item.N2O_emissions}} | J2: {{item.HFCs_emissions}} | K2: {{item.PFCs_emissions}} | L2: {{item.SF6_emissions}} | M2: {{item.NF3_emissions}} | N2: {{item.total_green_house_gas_emissions}}
A3: {%tr endfor %}
G4: {{loc_CO2_emissions_sum_formatted}} | H4: {{loc_CH4_emissions_sum_formatted}} | I4: {{loc_N2O_emissions_sum_formatted}} | J4: {{loc_HFCs_emissions_sum_formatted}} | K4: {{loc_PFCs_emissions_sum_formatted}} | L4: {{loc_SF6_emissions_sum_formatted}} | M4: {{loc_NF3_emissions_sum_formatted}} | N4: {{loc_total_green_house_gas_emissions_sum_formatted}}
A7: {%tr for item in act_summary_mar %}
A8: {{item.number}} | B8: {{item.emission_source_type_mar}} | C8: {{item.emission_source_mar}} | D8: {{item. report_boundary_mar}} | E8: {{item.act_summary_mar}} | F8: {{item.act_summary_mar_unit}} | G8: {{item.CO2_emissions}} | H8: {{item.CH4_emissions}} | I8: {{item.N2O_emissions}} | J8: {{item.HFCs_emissions}} | K8: {{item.PFCs_emissions}} | L8: {{item.SF6_emissions}} | M8: {{item.NF3_emissions}} | N8: {{item.total_green_house_gas_emissions}}
A9: {%tr endfor %}
G10: {{mar_CO2_emissions_sum_formatted}} | H10: {{mar_CH4_emissions_sum_formatted}} | I10: {{mar_N2O_emissions_sum_formatted}} | J10: {{mar_HFCs_emissions_sum_formatted}} | K10: {{mar_PFCs_emissions_sum_formatted}} | L10: {{mar_SF6_emissions_sum_formatted}} | M10: {{mar_NF3_emissions_sum_formatted}} | N10: {{mar_total_green_house_gas_emissions_sum_formatted}}
A14: 编号 | B14: GHG排放类别 | C14: 排放源 | D14: 设施 | E14: 低位发热量 | F14: 单位 | G14: 氧化率 | H14: 基于热值排放系数，t GHG/GJ | K14: 排放因子，t GHG/10000m³
H15: IPCC-2006缺省值 | K15: 计算值
E16: 企业温室气体排放核算与报告指南 钢铁行业 | G16: 企业温室气体排放核算与报告指南 钢铁行业 | H16: CO2 | I16: CH4 | J16: N2O | K16: CO2 | L16: CH4 | M16: N2O
A17: {%tr for item in com_ef_items %}
A18: {{item.number}} | B18: {{item.emission_source_type_dir}} | C18: {{item.emission_source_dir}} | D18: {{item.emission_facilities_dir}} | E18: {{item.ncv_dir}} | F18: {{item.emission_unit_dir}} | G18: {{item.emission_oa_dir}} | H18: {{item.CO2_emission_cv_factor}} | I18: {{item.CH4_emission_cv_factor}} | J18: {{item.N2O_emission_cv_factor}} | K18: {{item.CO2_emission_factor}} | L18: {{item.CH4_emission_factor}} | M18: {{item.N2O_emission_factor}}
A19: {%tr endfor %}
A22: 编号 | B22: GHG排放类别 | C22: 排放源 | D22: 设施 | E22: CO2排放因子 | F22: 单位
E23: 企业温室气体排放核算与报告指南 钢铁行业
A24: {%tr for item in pro_ef_items %}
A25: {{item.number}} | B25: {{item.emission_source_type_dir}} | C25: {{item.emission_source_dir}} | D25: {{item.emission_facilities_dir}} | E25: {{item.CO2_emission_factor}} | F25: {{item.emission_unit_dir}}
A26: {%tr endfor %}
A28: 编号 | B28: GHG排放类别 | C28: 排放源 | D28: 设施 | E28: HFCs/PFCs | G28: MCF | H28: Bo | I28: 排放因子 | J28: 单位 | K28: 排放因子引用源
E29: EF估计值 | F29: 单位
A30: {%tr for item in fug_ef_items %}
A31: {{item.number}} | B31: {{item.emission_source_type_dir}} | C31: {{item.emission_source_dir}} | D31: {{item.emission_facilities_dir}} | E31: {{item.HFCs_PCFs_emission_factor}} | F31: {{item.emission_unit_dir}} | G31: {{item.MCF}} | H31: {{item.Bo}} | I31: {{item.emission_factor}} | J31: {{item.emission_unit_dir}} | K31: {{item.emission_source_dir}}
A32: {%tr endfor %}
A34: 编号 | B34: GHG排放类别 | C34: 排放源 | D34: 设施 | E34: EF | F34: 单位 | G34: 排放因子引用源
A35: {%tr for item in indir_ef_items %}
A36: {{item.number}} | B36: {{item.emission_source_type_indir}} | C36: {{item.emission_source_indir}} | D36: {{item.emission_facilities_indir}} | E36: {{item.elec_emission_factor}} | F36: {{item.elec_emission_unit}} | G36: {{item.elec_emission_source}}
A37: {%tr endfor %}
A39: 编号 | B39: GHG排放类别 | C39: 排放源 | D39: Activity name | E39: Geography | F39: CO2 | H39: 引用源
F40: 排放因子 | G40: 单位 | H40: 缺省排放因子
A41: {%tr for item in cat1_ef_items %}
A42: {{item.number}} | B42: {{item.emission_source_type_cat1}} | C42: {{item.emission_source_cat1}} | D42: {{item.emission_name_cat1}} | E42: {{item.emission_geo_cat1}} | F42: {{item.cat1_emission_factor}} | G42: {{item.cat1_emission_unit}} | H42: {{item.cat1_emission_source}}
A43: {%tr endfor %}
A45: 编号 | B45: GHG排放类别 | C45: 排放源 | D45: Activity name | E45: CO2 | G45: 引用源
E46: 排放因子 | F46: 单位 | G46: 缺省排放因子
A47: {%tr for item in cat2_ef_items %}
A48: {{item.number}} | B48: {{item.emission_source_type_cat2}} | C48: {{item.emission_source_cat2}} | D48: {{item.emission_name_cat2}} | E48: {{item.cat2_emission_factor}} | F48: {{item.cat2_emission_unit}} | G48: {{item.cat2_emission_source}}
A49: {%tr endfor %}
A51: 编号 | B51: GHG排放类别 | C51: 排放源 | D51: Activity name | E51: Geography | F51: CO2 | H51: 引用源
F52: 排放因子 | G52: 单位 | H52: 缺省排放因子
A53: {%tr for item in cat3_ef_items %}
A54: {{item.number}} | B54: {{item.emission_source_type_cat3}} | C54: {{item.emission_source_cat3}} | D54: {{item.emission_name_cat3}} | E54: {{item.emission_geo_cat3}} | F54: {{item.cat3_emission_factor}} | G54: {{item.cat3_emission_unit}} | H54: {{item.cat3_emission_source}}
A55: {%tr endfor %}
A57: 编号 | B57: GHG排放类别 | C57: 排放源 | D57: Activity name | E57: Geography | F57: CO2 | H57: 引用源
F58: 排放因子 | G58: 单位 | H58: 缺省排放因子
A59: {%tr for item in cat4_ef_items %}
A60: {{item.number}} | B60: {{item.emission_source_type_cat4}} | C60: {{item.emission_source_cat4}} | D60: {{item.emission_name_cat4}} | E60: {{item.emission_geo_cat4}} | F60: {{item.cat4_emission_factor}} | G60: {{item.cat4_emission_unit}} | H60: {{item.cat4_emission_source}}
A61: {%tr endfor %}
A63: 编号 | B63: GHG排放类别 | C63: 排放源 | D63: Activity name | E63: Geography | F63: CO2 | H63: 引用源
F64: 排放因子 | G64: 单位 | H64: 缺省排放因子
A65: {%tr for item in cat5_ef_items %}
A66: {{item.number}} | B66: {{item.emission_source_type_cat5}} | C66: {{item.emission_source_cat5}} | D66: {{item.emission_name_cat5}} | E66: {{item.emission_geo_cat5}} | F66: {{item.cat5_emission_factor}} | G66: {{item.cat5_emission_unit}} | H66: {{item.cat5_emission_source}}
A67: {%tr endfor %}
A69: 编号 | B69: GHG排放类别 | C69: 排放源 | D69: Activity name | E69: Geography | F69: CO2 | H69: 引用源
F70: 排放因子 | G70: 单位 | H70: 缺省排放因子
A71: {%tr for item in cat6_ef_items %}
A72: {{item.number}} | B72: {{item.emission_source_type_cat6}} | C72: {{item.emission_source_cat6}} | D72: {{item.emission_name_cat6}} | E72: {{item.emission_geo_cat6}} | F72: {{item.cat6_emission_factor}} | G72: {{item.cat6_emission_unit}} | H72: {{item.cat6_emission_source}}
A73: {%tr endfor %}
A75: 编号 | B75: GHG排放类别 | C75: 排放源 | D75: Activity name | E75: Geography | F75: CO2 | H75: 引用源
F76: 排放因子 | G76: 单位 | H76: 缺省排放因子
A77: {%tr for item in cat7_ef_items %}
A78: {{item.number}} | B78: {{item.emission_source_type_cat7}} | C78: {{item.emission_source_cat7}} | D78: {{item.emission_name_cat7}} | E78: {{item.emission_geo_cat7}} | F78: {{item.cat7_emission_factor}} | G78: {{item.cat7_emission_unit}} | H78: {{item.cat7_emission_source}}
A79: {%tr endfor %}
A81: 编号 | B81: GHG排放类别 | C81: 排放源 | D81: Activity name | E81: CO2 | G81: 引用源 | H81: 备注
E82: 排放因子 | F82: 单位
A83: {%tr for item in cat9_ef_items %}
A84: {{item.number}} | B84: {{item.emission_source_type_cat9}} | C84: {{item.emission_source_cat9}} | D84: {{item.emission_name_cat9}} | E84: {{item.cat9_emission_factor}} | F84: {{item.cat9_emission_unit}} | G84: {{item.cat9_emission_source}} | H84: {{item.cat9_emission_remark}}
A85: {%tr endfor %}
A87: 编号 | B87: GHG排放类别 | C87: 排放源 | D87: 设施 | E87: 低位发热量 | F87: 单位 | G87: 氧化率 | H87: 基于热值排放系数，t GHG/GJ | K87: 排放因子，t GHG/10000m³
H88: IPCC-2006缺省值 | K88: 计算值
E89: 企业温室气体排放核算与报告指南 钢铁行业 | G89: 企业温室气体排放核算与报告指南 钢铁行业 | H89: CO2 | I89: CH4 | J89: N2O | K89: CO2 | L89: CH4 | M89: N2O
A90: {%tr for item in cat11_ef_items %}
A91: {{item.number}} | B91: {{item.emission_source_type_cat11}} | C91: {{item.emission_source_cat11}} | D91: {{item.emission_name_cat11}} | E91: {{item.ncv_cat11}} | F91: {{item.emission_unit_cat11}} | G91: {{item.emission_oa_cat11}} | H91: {{item.CO2_emission_cv_factor}} | I91: {{item.CH4_emission_cv_factor}} | J91: {{item.N2O_emission_cv_factor}} | K91: {{item.CO2_emission_factor}} | L91: {{item.CH4_emission_factor}} | M91: {{item.N2O_emission_factor}}
A92: {%tr endfor %}
A94: 编号 | B94: GHG排放类别 | C94: 排放源 | D94: Activity name | E94: Geography | F94: CO2 | H94: 引用源
F95: 排放因子 | G95: 单位 | H95: 缺省排放因子
A96: {%tr for item in cat12_ef_items %}
A97: {{item.number}} | B97: {{item.emission_source_type_cat12}} | C97: {{item.emission_source_cat12}} | D97: {{item.emission_name_cat12}} | E97: {{item.emission_geo_cat12}} | F97: {{item.cat12_emission_factor}} | G97: {{item.cat12_emission_unit}} | H97: {{item.cat12_emission_source}}
A98: {%tr endfor %}

Sheet 温室气体盘查清册
B1: 温室气体盘查清册 | L1: 编号：DY-GHG-2025-01
L2: 版本/版次：A/1
L3: 日期：2025/7/3
B4: 组织名称： | C4: 大冶特殊钢有限公司
B5: 组织边界： | C5: 湖北省黄石市黄石大道316号
B6: 盘查覆盖周期: | C6: 2024年1月1日至2024年12月31日
B7: 编制 ： | E7: 审核： | K7: 核准：
B8: 报告边界 | C8: 运营控制权 | E8: 范围一排放量： | F8: =F14 -> 7122248.8 | K8: 单位：tCO2e
E9: 范围二（基于位置）排放量： | F9: =F47 -> 1069378.7
E10: 范围二（基于市场）排放量： | F10: =F48 -> 1161900.3
B11: 排放 | E11: 范围三排放量： | F11: =SUM(F50,F76,F89,F101,F106,F113,F118,F124,F130,F139,F136) -> 7332407.7
B12: 编号 | C12: 排放源 | D12: 排放设施 | E12: 备注 | F12: 总排放量 | G12: CO2 | H12: CH4 | I12: N2O | J12: HFCs | K12: PFCs | L12: SF6 | M12: NF3
G13: tCO2e
B14: 范围一 直接排放 | F14: =F15+F24+F27+F33 -> 7122248.8 | G14: =G15+G24+G27+G33 -> 7086080.3 | H14: =H15+H24+H27+H33 -> 2569.6835 | I14: =I15+I24+I27+I33 -> 30422.615 | J14: =J15+J24+J27+J33 -> 717.03 | K14: =K15+K24+K27+K33 -> 0 | L14: =L15+L24+L27+L33 -> 2459.16 | M14: =M15+M24+M27+M33 -> 0
B15: 1.1 | C15: 固定源燃烧直接排放 | F15: =SUM(G15:M15) -> 7227644.2 | G15: =SUM(G16:G23) -> 7195204.6 | H15: =SUM(H16:H23) -> 2083.9816 | I15: =SUM(I16:I23) -> 30355.616 | J15: =SUM(J16:J23) -> 0 | K15: =SUM(K16:K23) -> 0 | L15: =SUM(L16:L23) -> 0 | M15: =SUM(M16:M23) -> 0
B16: 1.1.1 | C16: =表1温室气体盘查表!C5 -> 天然气燃烧 | D16: =表1温室气体盘查表!D5 -> 热处理炉（加热炉） | F16: =SUM(G16:M16) -> 38881.726 | G16: =表1温室气体盘查表!AE5 -> 38843.506 | H16: =表1温室气体盘查表!AF5 -> 19.317893 | I16: =表1温室气体盘查表!AG5 -> 18.902455 | J16: =表1温室气体盘查表!AH5 -> 0 | K16: =表1温室气体盘查表!AI5 -> 0 | L16: =表1温室气体盘查表!AJ5 -> 0 | M16: =表1温室气体盘查表!AK5 -> 0
B17: 1.1.2 | C17: =表1温室气体盘查表!C6 -> 液化石油气燃烧 | D17: =表1温室气体盘查表!D6 -> 冶钢宾馆 | F17: =SUM(G17:M17) -> 29.162368 | G17: =表1温室气体盘查表!AE6 -> 29.136879 | H17: =表1温室气体盘查表!AF6 -> 0.012883026 | I17: =表1温室气体盘查表!AG6 -> 0.012605971 | J17: =表1温室气体盘查表!AH6 -> 0 | K17: =表1温室气体盘查表!AI6 -> 0 | L17: =表1温室气体盘查表!AJ6 -> 0 | M17: =表1温室气体盘查表!AK6 -> 0
B18: 1.1.3 | C18: =表1温室气体盘查表!C7 -> 烟煤燃烧 | D18: =表1温室气体盘查表!D7 -> 高炉 | F18: =SUM(G18:M18) -> 925941.32 | G18: =表1温室气体盘查表!AE7 -> 921839.46 | H18: =表1温室气体盘查表!AF7 -> 261.64111 | I18: =表1温室气体盘查表!AG7 -> 3840.2163 | J18: =表1温室气体盘查表!AH7 -> 0 | K18: =表1温室气体盘查表!AI7 -> 0 | L18: =表1温室气体盘查表!AJ7 -> 0 | M18: =表1温室气体盘查表!AK7 -> 0
B19: 1.1.4 | C19: =表1温室气体盘查表!C8 -> 无烟煤燃烧 | D19: =表1温室气体盘查表!D8 -> 高炉、烧结 | F19: =SUM(G19:M19) -> 637282.39 | G19: =表1温室气体盘查表!AE8 -> 634459.27 | H19: =表1温室气体盘查表!AF8 -> 180.07542 | I19: =表1温室气体盘查表!AG8 -> 2643.0424 | J19: =表1温室气体盘查表!AH8 -> 0 | K19: =表1温室气体盘查表!AI8 -> 0 | L19: =表1温室气体盘查表!AJ8 -> 0 | M19: =表1温室气体盘查表!AK8 -> 0
B20: 1.1.5 | C20: =表1温室气体盘查表!C9 -> 洗精煤燃烧 | D20: =表1温室气体盘查表!D9 -> 焦炉 | F20: =SUM(G20:M20) -> 4824841.6 | G20: =表1温室气体盘查表!AE9 -> 4802635.7 | H20: =表1温室气体盘查表!AF9 -> 1416.4222 | I20: =表1温室气体盘查表!AG9 -> 20789.422 | J20: =表1温室气体盘查表!AH9 -> 0 | K20: =表1温室气体盘查表!AI9 -> 0 | L20: =表1温室气体盘查表!AJ9 -> 0 | M20: =表1温室气体盘查表!AK9 -> 0
B21: 1.1.6 | C21: =表1温室气体盘查表!C10 -> 焦炭燃烧 | D21: =表1温室气体盘查表!D10 -> 高炉 | F21: =SUM(G21:M21) -> 439843.84 | G21: =表1温室气体盘查表!AE10 -> 438053.15 | H21: =表1温室气体盘查表!AF10 -> 114.22134 | I21: =表1温室气体盘查表!AG10 -> 1676.4744 | J21: =表1温室气体盘查表!AH10 -> 0 | K21: =表1温室气体盘查表!AI10 -> 0 | L21: =表1温室气体盘查表!AJ10 -> 0 | M21: =表1温室气体盘查表!AK10 -> 0
B22: 1.1.7 | C22: =表1温室气体盘查表!C11 -> 焦屑燃烧 | D22: =表1温室气体盘查表!D11 -> 烧结、高炉 | F22: =SUM(G22:M22) -> 364657.36 | G22: =表1温室气体盘查表!AE11 -> 363172.76 | H22: =表1温室气体盘查表!AF11 -> 94.696449 | I22: =表1温室气体盘查表!AG11 -> 1389.8995 | J22: =表1温室气体盘查表!AH11 -> 0 | K22: =表1温室气体盘查表!AI11 -> 0 | L22: =表1温室气体盘查表!AJ11 -> 0 | M22: =表1温室气体盘查表!AK11 -> 0
B23: 1.1.8 | C23: =表1温室气体盘查表!C12 -> 焦炉煤气燃烧 | D23: =表1温室气体盘查表!D12 -> 外售 | F23: =SUM(G23:M23) -> -3833.1355 | G23: =表1温室气体盘查表!AE12 -> -3828.3759 | H23: =表1温室气体盘查表!AF12 -> -2.4056686 | I23: =表1温室气体盘查表!AG12 -> -2.3539338 | J23: =表1温室气体盘查表!AH12 -> 0 | K23: =表1温室气体盘查表!AI12 -> 0 | L23: =表1温室气体盘查表!AJ12 -> 0 | M23: =表1温室气体盘查表!AK12 -> 0
B24: 1.2 | C24: 移动源燃烧直接排放 | F24: =SUM(G24:M24) -> 4566.5427 | G24: =SUM(G25:G26) -> 4491.7139 | H24: =SUM(H25:H26) -> 7.8293549 | I24: =SUM(I25:I26) -> 66.999448 | J24: =SUM(J25:J26) -> 0 | K24: =SUM(K25:K26) -> 0 | L24: =SUM(L25:L26) -> 0 | M24: =SUM(M25:M26) -> 0
B25: 1.2.1 | C25: =表1温室气体盘查表!C13 -> 0#柴油燃烧 | D25: =表1温室气体盘查表!D13 -> 场内运输 | F25: =SUM(G25:M25) -> 4417.0726 | G25: =表1温室气体盘查表!AE13 -> 4348.2107 | H25: =表1温室气体盘查表!AF13 -> 6.3850041 | I25: =表1温室气体盘查表!AG13 -> 62.476922 | J25: =表1温室气体盘查表!AH13 -> 0 | K25: =表1温室气体盘查表!AI13 -> 0 | L25: =表1温室气体盘查表!AJ13 -> 0 | M25: =表1温室气体盘查表!AK13 -> 0
B26: 1.2.2 | C26: =表1温室气体盘查表!C14 -> 92#汽油燃烧 | D26: =表1温室气体盘查表!D14 -> 公务车 | F26: =SUM(G26:M26) -> 149.47012 | G26: =表1温室气体盘查表!AE14 -> 143.50325 | H26: =表1温室气体盘查表!AF14 -> 1.4443509 | I26: =表1温室气体盘查表!AG14 -> 4.5225266 | J26: =表1温室气体盘查表!AH14 -> 0 | K26: =表1温室气体盘查表!AI14 -> 0 | L26: =表1温室气体盘查表!AJ14 -> 0 | M26: =表1温室气体盘查表!AK14 -> 0
B27: 1.3 | C27: 逸散源直接排放 | F27: =SUM(G27:M27) -> 3654.7226 | G27: =SUM(G28:G32) -> 0.66 | H27: =SUM(H28:H32) -> 477.87259 | I27: =SUM(I28:I32) -> 0 | J27: =SUM(J28:J32) -> 717.03 | K27: =SUM(K28:K32) -> 0 | L27: =SUM(L28:L32) -> 2459.16 | M27: =SUM(M28:M32) -> 0
B28: 1.3.1 | C28: =表1温室气体盘查表!C15 -> 制冷剂逸散（R32） | D28: =表1温室气体盘查表!D15 -> 分体式空调 | F28: =SUM(G28:M28) -> 717.03 | G28: =表1温室气体盘查表!AE15 -> 0 | H28: =表1温室气体盘查表!AF15 -> 0 | I28: =表1温室气体盘查表!AG15 -> 0 | J28: =表1温室气体盘查表!AH15 -> 717.03 | K28: =表1温室气体盘查表!AI15 -> 0 | L28: =表1温室气体盘查表!AJ15 -> 0 | M28: =表1温室气体盘查表!AK15 -> 0
B29: 1.3.2 | C29: =表1温室气体盘查表!C16 -> CO2逸散 | D29: =表1温室气体盘查表!D16 -> 二氧化碳灭火器 | F29: =SUM(G29:M29) -> 0.66 | G29: =表1温室气体盘查表!AE16 -> 0.66 | H29: =表1温室气体盘查表!AF16 -> 0 | I29: =表1温室气体盘查表!AG16 -> 0 | J29: =表1温室气体盘查表!AH16 -> 0 | K29: =表1温室气体盘查表!AI16 -> 0 | L29: =表1温室气体盘查表!AJ16 -> 0 | M29: =表1温室气体盘查表!AK16 -> 0
B30: 1.3.3 | C30: =表1温室气体盘查表!C17 -> CH4逸散 | D30: =表1温室气体盘查表!D17 -> 化粪池 | F30: =SUM(G30:M30) -> 112.29192 | G30: =表1温室气体盘查表!AE17 -> 0 | H30: =表1温室气体盘查表!AF17 -> 112.29192 | I30: =表1温室气体盘查表!AG17 -> 0 | J30: =表1温室气体盘查表!AH17 -> 0 | K30: =表1温室气体盘查表!AI17 -> 0 | L30: =表1温室气体盘查表!AJ17 -> 0 | M30: =表1温室气体盘查表!AK17 -> 0
B31: 1.3.4 | C31: =表1温室气体盘查表!C18 -> CH4逸散 | D31: =表1温室气体盘查表!D18 -> 耗氧池 | F31: =SUM(G31:M31) -> 365.58067 | G31: =表1温室气体盘查表!AE18 -> 0 | H31: =表1温室气体盘查表!AF18 -> 365.58067 | I31: =表1温室气体盘查表!AG18 -> 0 | J31: =表1温室气体盘查表!AH18 -> 0 | K31: =表1温室气体盘查表!AI18 -> 0 | L31: =表1温室气体盘查表!AJ18 -> 0 | M31: =表1温室气体盘查表!AK18 -> 0
B32: 1.3.5 | C32: =表1温室气体盘查表!C19 -> SF6逸散 | D32: =表1温室气体盘查表!D19 -> 高压开关 | F32: =SUM(G32:M32) -> 2459.16 | G32: =表1温室气体盘查表!AE19 -> 0 | H32: =表1温室气体盘查表!AF19 -> 0 | I32: =表1温室气体盘查表!AG19 -> 0 | J32: =表1温室气体盘查表!AH19 -> 0 | K32: =表1温室气体盘查表!AI19 -> 0 | L32: =表1温室气体盘查表!AJ19 -> 2459.16 | M32: =表1温室气体盘查表!AK19 -> 0
B33: 1.4 | C33: 制程排放 | F33: =SUM(G33:M33) -> -113616.67 | G33: =SUM(G34:G45) -> -113616.67 | H33: =SUM(H34:H45) -> 0 | I33: =SUM(I34:I45) -> 0 | J33: =SUM(J34:J45) -> 0 | K33: =SUM(K34:K45) -> 0 | L33: =SUM(L34:L45) -> 0 | M33: =SUM(M34:M45) -> 0
B34: 1.4.1 | C34: =表1温室气体盘查表!C20 -> 石灰石 | D34: =表1温室气体盘查表!D20 -> 石灰窑 | F34: =SUM(G34:M34) -> 8520.9388 | G34: =表1温室气体盘查表!AE20 -> 8520.9388 | H34: =表1温室气体盘查表!AF20 -> 0 | I34: =表1温室气体盘查表!AG20 -> 0 | J34: =表1温室气体盘查表!AH20 -> 0 | K34: =表1温室气体盘查表!AI20 -> 0 | L34: =表1温室气体盘查表!AJ20 -> 0 | M34: =表1温室气体盘查表!AK20 -> 0
B35: 1.4.2 | C35: =表1温室气体盘查表!C21 -> 白云石 | D35: =表1温室气体盘查表!D21 -> 高炉 | F35: =SUM(G35:M35) -> 169593.75 | G35: =表1温室气体盘查表!AE21 -> 169593.75 | H35: =表1温室气体盘查表!AF21 -> 0 | I35: =表1温室气体盘查表!AG21 -> 0 | J35: =表1温室气体盘查表!AH21 -> 0 | K35: =表1温室气体盘查表!AI21 -> 0 | L35: =表1温室气体盘查表!AJ21 -> 0 | M35: =表1温室气体盘查表!AK21 -> 0
B36: 1.4.3 | C36: =表1温室气体盘查表!C22 -> 电极 | D36: =表1温室气体盘查表!D22 -> 炼钢 | F36: =SUM(G36:M36) -> 17447.125 | G36: =表1温室气体盘查表!AE22 -> 17447.125 | H36: =表1温室气体盘查表!AF22 -> 0 | I36: =表1温室气体盘查表!AG22 -> 0 | J36: =表1温室气体盘查表!AH22 -> 0 | K36: =表1温室气体盘查表!AI22 -> 0 | L36: =表1温室气体盘查表!AJ22 -> 0 | M36: =表1温室气体盘查表!AK22 -> 0
B37: 1.4.4 | C37: =表1温室气体盘查表!C23 -> 废钢 | D37: =表1温室气体盘查表!D23 -> 炼钢 | F37: =SUM(G37:M37) -> 39875.738 | G37: =表1温室气体盘查表!AE23 -> 39875.738 | H37: =表1温室气体盘查表!AF23 -> 0 | I37: =表1温室气体盘查表!AG23 -> 0 | J37: =表1温室气体盘查表!AH23 -> 0 | K37: =表1温室气体盘查表!AI23 -> 0 | L37: =表1温室气体盘查表!AJ23 -> 0 | M37: =表1温室气体盘查表!AK23 -> 0
B38: 1.4.5 | C38: =表1温室气体盘查表!C24 -> 锰铁 | D38: =表1温室气体盘查表!D24 -> 炼钢 | F38: =SUM(G38:M38) -> 13114.101 | G38: =表1温室气体盘查表!AE24 -> 13114.101 | H38: =表1温室气体盘查表!AF24 -> 0 | I38: =表1温室气体盘查表!AG24 -> 0 | J38: =表1温室气体盘查表!AH24 -> 0 | K38: =表1温室气体盘查表!AI24 -> 0 | L38: =表1温室气体盘查表!AJ24 -> 0 | M38: =表1温室气体盘查表!AK24 -> 0
B39: 1.4.6 | C39: =表1温室气体盘查表!C25 -> 镍铁 | D39: =表1温室气体盘查表!D25 -> 炼钢 | F39: =SUM(G39:M39) -> 349.46907 | G39: =表1温室气体盘查表!AE25 -> 349.46907 | H39: =表1温室气体盘查表!AF25 -> 0 | I39: =表1温室气体盘查表!AG25 -> 0 | J39: =表1温室气体盘查表!AH25 -> 0 | K39: =表1温室气体盘查表!AI25 -> 0 | L39: =表1温室气体盘查表!AJ25 -> 0 | M39: =表1温室气体盘查表!AK25 -> 0
B40: 1.4.7 | C40: =表1温室气体盘查表!C26 -> 铬铁 | D40: =表1温室气体盘查表!D26 -> 炼钢 | F40: =SUM(G40:M40) -> 22918.907 | G40: =表1温室气体盘查表!AE26 -> 22918.907 | H40: =表1温室气体盘查表!AF26 -> 0 | I40: =表1温室气体盘查表!AG26 -> 0 | J40: =表1温室气体盘查表!AH26 -> 0 | K40: =表1温室气体盘查表!AI26 -> 0 | L40: =表1温室气体盘查表!AJ26 -> 0 | M40: =表1温室气体盘查表!AK26 -> 0
B41: 1.4.8 | C41: =表1温室气体盘查表!C27 -> 硅铁 | D41: =表1温室气体盘查表!D27 -> 炼钢 | F41: =SUM(G41:M41) -> 74.70736 | G41: =表1温室气体盘查表!AE27 -> 74.70736 | H41: =表1温室气体盘查表!AF27 -> 0 | I41: =表1温室气体盘查表!AG27 -> 0 | J41: =表1温室气体盘查表!AH27 -> 0 | K41: =表1温室气体盘查表!AI27 -> 0 | L41: =表1温室气体盘查表!AJ27 -> 0 | M41: =表1温室气体盘查表!AK27 -> 0
B42: 1.4.9 | C42: =表1温室气体盘查表!C28 -> 钼铁 | D42: =表1温室气体盘查表!D28 -> 炼钢 | F42: =SUM(G42:M42) -> 143.01295 | G42: =表1温室气体盘查表!AE28 -> 143.01295 | H42: =表1温室气体盘查表!AF28 -> 0 | I42: =表1温室气体盘查表!AG28 -> 0 | J42: =表1温室气体盘查表!AH28 -> 0 | K42: =表1温室气体盘查表!AI28 -> 0 | L42: =表1温室气体盘查表!AJ28 -> 0 | M42: =表1温室气体盘查表!AK28 -> 0
B43: 1.4.10 | C43: =表1温室气体盘查表!C29 -> 钢坯 | D43: =表1温室气体盘查表!D29 -> 固碳产品 | F43: =SUM(G43:M43) -> -160314.41 | G43: =表1温室气体盘查表!AE29 -> -160314.41 | H43: =表1温室气体盘查表!AF29 -> 0 | I43: =表1温室气体盘查表!AG29 -> 0 | J43: =表1温室气体盘查表!AH29 -> 0 | K43: =表1温室气体盘查表!AI29 -> 0 | L43: =表1温室气体盘查表!AJ29 -> 0 | M43: =表1温室气体盘查表!AK29 -> 0
B44: 1.4.11 | C44: =表1温室气体盘查表!C30 -> 粗苯 | D44: =表1温室气体盘查表!D30 -> 外售 | F44: =SUM(G44:M44) -> -65952.991 | G44: =表1温室气体盘查表!AE30 -> -65952.991 | H44: =表1温室气体盘查表!AF30 -> 0 | I44: =表1温室气体盘查表!AG30 -> 0 | J44: =表1温室气体盘查表!AH30 -> 0 | K44: =表1温室气体盘查表!AI30 -> 0 | L44: =表1温室气体盘查表!AJ30 -> 0 | M44: =表1温室气体盘查表!AK30 -> 0
B45: 1.4.12 | C45: =表1温室气体盘查表!C31 -> 煤焦油 | D45: =表1温室气体盘查表!D31 -> 危废处置 | F45: =SUM(G45:M45) -> -159387.02 | G45: =表1温室气体盘查表!AE31 -> -159387.02 | H45: =表1温室气体盘查表!AF31 -> 0 | I45: =表1温室气体盘查表!AG31 -> 0 | J45: =表1温室气体盘查表!AH31 -> 0 | K45: =表1温室气体盘查表!AI31 -> 0 | L45: =表1温室气体盘查表!AJ31 -> 0 | M45: =表1温室气体盘查表!AK31 -> 0
B46: 范围二 外购电间接排放
B47: 2.1 | C47: =表1温室气体盘查表!C32 -> 外购电力（基于位置） | D47: =表1温室气体盘查表!D32 -> 用电设备 | F47: =SUM(G47:M47) -> 1069378.7 | G47: =表1温室气体盘查表!AE32 -> 1069378.7 | H47: =表1温室气体盘查表!AF32 -> 0 | I47: =表1温室气体盘查表!AG32 -> 0 | J47: =表1温室气体盘查表!AH32 -> 0 | K47: =表1温室气体盘查表!AI32 -> 0 | L47: =表1温室气体盘查表!AJ32 -> 0 | M47: =表1温室气体盘查表!AK32 -> 0
B48: 2.2 | C48: =表1温室气体盘查表!C33 -> 外购电力（基于市场） | D48: =表1温室气体盘查表!D33 -> 用电设备 | F48: =SUM(G48:M48) -> 1161900.3 | G48: =表1温室气体盘查表!AE33 -> 1161900.3 | H48: =表1温室气体盘查表!AF33 -> 0 | I48: =表1温室气体盘查表!AG33 -> 0 | J48: =表1温室气体盘查表!AH33 -> 0 | K48: =表1温室气体盘查表!AI33 -> 0 | L48: =表1温室气体盘查表!AJ33 -> 0 | M48: =表1温室气体盘查表!AK33 -> 0
B50: 范围三 类别1 | C50: 外购商品和服务的上游排放 | F50: =SUM(G50:M50) -> 2710165.6 | G50: =SUM(G51:G74) -> 2710165.6 | H50: =SUM(H51:H69) -> 0 | I50: =SUM(I51:I69) -> 0 | J50: =SUM(J51:J69) -> 0 | K50: =SUM(K51:K69) -> 0 | L50: =SUM(L51:L69) -> 0 | M50: =SUM(M51:M69) -> 0
B51: 3.1.1 | C51: =表1温室气体盘查表!C34 -> 铁矿石生产 | D51: =表1温室气体盘查表!D34 -> 烧结 | F51: =表1温室气体盘查表!AL34 -> 448588.58 | G51: =表1温室气体盘查表!AE34 -> 448588.58 | H51: =表1温室气体盘查表!AF34 -> 0 | I51: =表1温室气体盘查表!AG34 -> 0 | J51: =表1温室气体盘查表!AH34 -> 0 | K51: =表1温室气体盘查表!AI34 -> 0 | L51: =表1温室气体盘查表!AJ34 -> 0 | M51: =表1温室气体盘查表!AK34 -> 0
B52: 3.1.2 | C52: =表1温室气体盘查表!C35 -> 生石灰生产 | D52: =表1温室气体盘查表!D35 -> 烧结、转炉、电炉 | F52: =表1温室气体盘查表!AL35 -> 727500.38 | G52: =表1温室气体盘查表!AE35 -> 727500.38 | H52: =表1温室气体盘查表!AF35 -> 0 | I52: =表1温室气体盘查表!AG35 -> 0 | J52: =表1温室气体盘查表!AH35 -> 0 | K52: =表1温室气体盘查表!AI35 -> 0 | L52: =表1温室气体盘查表!AJ35 -> 0 | M52: =表1温室气体盘查表!AK35 -> 0
B53: 3.1.3 | C53: =表1温室气体盘查表!C36 -> 石灰石生产 | D53: =表1温室气体盘查表!D36 -> 转炉 | F53: =表1温室气体盘查表!AL36 -> 58.676347 | G53: =表1温室气体盘查表!AE36 -> 58.676347 | H53: =表1温室气体盘查表!AF36 -> 0 | I53: =表1温室气体盘查表!AG36 -> 0 | J53: =表1温室气体盘查表!AH36 -> 0 | K53: =表1温室气体盘查表!AI36 -> 0 | L53: =表1温室气体盘查表!AJ36 -> 0 | M53: =表1温室气体盘查表!AK36 -> 0
B54: 3.1.4 | C54: =表1温室气体盘查表!C37 -> 白云石生产 | D54: =表1温室气体盘查表!D37 -> 烧结、转炉、电炉 | F54: =表1温室气体盘查表!AL37 -> 46435.196 | G54: =表1温室气体盘查表!AE37 -> 46435.196 | H54: =表1温室气体盘查表!AF37 -> 0 | I54: =表1温室气体盘查表!AG37 -> 0 | J54: =表1温室气体盘查表!AH37 -> 0 | K54: =表1温室气体盘查表!AI37 -> 0 | L54: =表1温室气体盘查表!AJ37 -> 0 | M54: =表1温室气体盘查表!AK37 -> 0
B55: 3.1.5 | C55: =表1温室气体盘查表!C38 -> 轻烧白云石生产 | D55: =表1温室气体盘查表!D39 -> 高炉、转炉 | F55: =表1温室气体盘查表!AL38 -> 363.20886 | G55: =表1温室气体盘查表!AE38 -> 363.20886 | H55: =表1温室气体盘查表!AF38 -> 0 | I55: =表1温室气体盘查表!AG38 -> 0 | J55: =表1温室气体盘查表!AH38 -> 0 | K55: =表1温室气体盘查表!AI38 -> 0 | L55: =表1温室气体盘查表!AJ38 -> 0 | M55: =表1温室气体盘查表!AK38 -> 0
B56: 3.1.6 | C56: =表1温室气体盘查表!C39 -> 球团生产 | D56: =表1温室气体盘查表!D40 -> 转炉、电炉 | F56: =表1温室气体盘查表!AL39 -> 71601.051 | G56: =表1温室气体盘查表!AE39 -> 71601.051 | H56: =表1温室气体盘查表!AF39 -> 0 | I56: =表1温室气体盘查表!AG39 -> 0 | J56: =表1温室气体盘查表!AH39 -> 0 | K56: =表1温室气体盘查表!AI39 -> 0 | L56: =表1温室气体盘查表!AJ39 -> 0 | M56: =表1温室气体盘查表!AK39 -> 0
B57: 3.1.7 | C57: =表1温室气体盘查表!C40 -> 废钢生产 | D57: =表1温室气体盘查表!D41 -> 转炉、电炉 | F57: =表1温室气体盘查表!AL40 -> 79944.388 | G57: =表1温室气体盘查表!AE40 -> 79944.388 | H57: =表1温室气体盘查表!AF40 -> 0 | I57: =表1温室气体盘查表!AG40 -> 0 | J57: =表1温室气体盘查表!AH40 -> 0 | K57: =表1温室气体盘查表!AI40 -> 0 | L57: =表1温室气体盘查表!AJ40 -> 0 | M57: =表1温室气体盘查表!AK40 -> 0
B58: 3.1.8 | C58: =表1温室气体盘查表!C41 -> 电极生产 | D58: =表1温室气体盘查表!D42 -> 转炉、电炉 | F58: =表1温室气体盘查表!AL41 -> 37742.812 | G58: =表1温室气体盘查表!AE41 -> 37742.812 | H58: =表1温室气体盘查表!AF41 -> 0 | I58: =表1温室气体盘查表!AG41 -> 0 | J58: =表1温室气体盘查表!AH41 -> 0 | K58: =表1温室气体盘查表!AI41 -> 0 | L58: =表1温室气体盘查表!AJ41 -> 0 | M58: =表1温室气体盘查表!AK41 -> 0
B59: 3.1.9 | C59: =表1温室气体盘查表!C42 -> 锰铁生产 | D59: =表1温室气体盘查表!D43 -> 转炉、电炉 | F59: =表1温室气体盘查表!AL42 -> 141868.58 | G59: =表1温室气体盘查表!AE42 -> 141868.58 | H59: =表1温室气体盘查表!AF42 -> 0 | I59: =表1温室气体盘查表!AG42 -> 0 | J59: =表1温室气体盘查表!AH42 -> 0 | K59: =表1温室气体盘查表!AI42 -> 0 | L59: =表1温室气体盘查表!AJ42 -> 0 | M59: =表1温室气体盘查表!AK42 -> 0
B60: 3.1.10 | C60: =表1温室气体盘查表!C43 -> 镍铁生产 | D60: =表1温室气体盘查表!D44 -> 转炉、电炉 | F60: =表1温室气体盘查表!AL43 -> 84819.123 | G60: =表1温室气体盘查表!AE43 -> 84819.123 | H60: =表1温室气体盘查表!AF43 -> 0 | I60: =表1温室气体盘查表!AG43 -> 0 | J60: =表1温室气体盘查表!AH43 -> 0 | K60: =表1温室气体盘查表!AI43 -> 0 | L60: =表1温室气体盘查表!AJ43 -> 0 | M60: =表1温室气体盘查表!AK43 -> 0
B61: 3.1.11 | C61: =表1温室气体盘查表!C44 -> 铬铁生产 | D61: =表1温室气体盘查表!D45 -> 转炉、电炉 | F61: =表1温室气体盘查表!AL44 -> 345101.44 | G61: =表1温室气体盘查表!AE44 -> 345101.44 | H61: =表1温室气体盘查表!AF44 -> 0 | I61: =表1温室气体盘查表!AG44 -> 0 | J61: =表1温室气体盘查表!AH44 -> 0 | K61: =表1温室气体盘查表!AI44 -> 0 | L61: =表1温室气体盘查表!AJ44 -> 0 | M61: =表1温室气体盘查表!AK44 -> 0
B62: 3.1.12 | C62: =表1温室气体盘查表!C45 -> 萤石生产 | D62: =表1温室气体盘查表!D46 -> 转炉、电炉 | F62: =表1温室气体盘查表!AL45 -> 685.06219 | G62: =表1温室气体盘查表!AE45 -> 685.06219 | H62: =表1温室气体盘查表!AF45 -> 0 | I62: =表1温室气体盘查表!AG45 -> 0 | J62: =表1温室气体盘查表!AH45 -> 0 | K62: =表1温室气体盘查表!AI45 -> 0 | L62: =表1温室气体盘查表!AJ45 -> 0 | M62: =表1温室气体盘查表!AK45 -> 0
B63: 3.1.13 | C63: =表1温室气体盘查表!C46 -> 硅铁生产 | D63: =表1温室气体盘查表!D47 -> 转炉、电炉 | F63: =表1温室气体盘查表!AL46 -> 103575.78 | G63: =表1温室气体盘查表!AE46 -> 103575.78 | H63: =表1温室气体盘查表!AF46 -> 0 | I63: =表1温室气体盘查表!AG46 -> 0 | J63: =表1温室气体盘查表!AH46 -> 0 | K63: =表1温室气体盘查表!AI46 -> 0 | L63: =表1温室气体盘查表!AJ46 -> 0 | M63: =表1温室气体盘查表!AK46 -> 0
B64: 3.1.14 | C64: =表1温室气体盘查表!C47 -> 钼铁生产 | D64: =表1温室气体盘查表!D48 -> 转炉、电炉 | F64: =表1温室气体盘查表!AL47 -> 66065.4 | G64: =表1温室气体盘查表!AE47 -> 66065.4 | H64: =表1温室气体盘查表!AF47 -> 0 | I64: =表1温室气体盘查表!AG47 -> 0 | J64: =表1温室气体盘查表!AH47 -> 0 | K64: =表1温室气体盘查表!AI47 -> 0 | L64: =表1温室气体盘查表!AJ47 -> 0 | M64: =表1温室气体盘查表!AK47 -> 0
B65: 3.1.15 | C65: =表1温室气体盘查表!C48 -> 铝铁生产 | D65: =表1温室气体盘查表!D49 -> 转炉、电炉 | F65: =表1温室气体盘查表!AL48 -> 63158.19 | G65: =表1温室气体盘查表!AE48 -> 63158.19 | H65: =表1温室气体盘查表!AF48 -> 0 | I65: =表1温室气体盘查表!AG48 -> 0 | J65: =表1温室气体盘查表!AH48 -> 0 | K65: =表1温室气体盘查表!AI48 -> 0 | L65: =表1温室气体盘查表!AJ48 -> 0 | M65: =表1温室气体盘查表!AK48 -> 0
B66: 3.1.16 | C66: =表1温室气体盘查表!C49 -> 铝生产 | D66: =表1温室气体盘查表!D50 -> 转炉、电炉 | F66: =表1温室气体盘查表!AL49 -> 63342.195 | G66: =表1温室气体盘查表!AE49 -> 63342.195 | H66: =表1温室气体盘查表!AF49 -> 0 | I66: =表1温室气体盘查表!AG49 -> 0 | J66: =表1温室气体盘查表!AH49 -> 0 | K66: =表1温室气体盘查表!AI49 -> 0 | L66: =表1温室气体盘查表!AJ49 -> 0 | M66: =表1温室气体盘查表!AK49 -> 0
B67: 3.1.17 | C67: =表1温室气体盘查表!C50 -> 增碳剂生产 | D67: =表1温室气体盘查表!D50 -> 转炉、电炉 | F67: =表1温室气体盘查表!AL50 -> 17778.323 | G67: =表1温室气体盘查表!AE50 -> 17778.323 | H67: =表1温室气体盘查表!AF50 -> 0 | I67: =表1温室气体盘查表!AG50 -> 0 | J67: =表1温室气体盘查表!AH50 -> 0 | K67: =表1温室气体盘查表!AI50 -> 0 | L67: =表1温室气体盘查表!AJ50 -> 0 | M67: =表1温室气体盘查表!AK50 -> 0
B68: 3.1.18 | C68: =表1温室气体盘查表!C51 -> 铁鳞生产 | D68: =表1温室气体盘查表!D51 -> 炼钢 | F68: =表1温室气体盘查表!AL51 -> 608.38394 | G68: =表1温室气体盘查表!AE51 -> 608.38394 | H68: =表1温室气体盘查表!AF51 -> 0 | I68: =表1温室气体盘查表!AG51 -> 0 | J68: =表1温室气体盘查表!AH51 -> 0 | K68: =表1温室气体盘查表!AI51 -> 0 | L68: =表1温室气体盘查表!AJ51 -> 0 | M68: =表1温室气体盘查表!AK51 -> 0
B69: 3.1.19 | C69: =表1温室气体盘查表!C52 -> 氨水生产 | D69: =表1温室气体盘查表!D52 -> 烧结 | F69: =表1温室气体盘查表!AL52 -> 24444.815 | G69: =表1温室气体盘查表!AE52 -> 24444.815 | H69: =表1温室气体盘查表!AF52 -> 0 | I69: =表1温室气体盘查表!AG52 -> 0 | J69: =表1温室气体盘查表!AH52 -> 0 | K69: =表1温室气体盘查表!AI52 -> 0 | L69: =表1温室气体盘查表!AJ52 -> 0 | M69: =表1温室气体盘查表!AK52 -> 0
B70: 3.1.20 | C70: =表1温室气体盘查表!C53 -> 碳化硅生产 | D70: =表1温室气体盘查表!D53 -> - | F70: =表1温室气体盘查表!AL53 -> 48149.585 | G70: =表1温室气体盘查表!AE53 -> 48149.585 | H70: =表1温室气体盘查表!AF53 -> 0 | I70: =表1温室气体盘查表!AG53 -> 0 | J70: =表1温室气体盘查表!AH53 -> 0 | K70: =表1温室气体盘查表!AI53 -> 0 | L70: =表1温室气体盘查表!AJ53 -> 0 | M70: =表1温室气体盘查表!AK53 -> 0
B71: 3.1.21 | C71: =表1温室气体盘查表!C54 -> 镁生产 | D71: =表1温室气体盘查表!D54 -> - | F71: =表1温室气体盘查表!AL54 -> 308520.83 | G71: =表1温室气体盘查表!AE54 -> 308520.83 | H71: =表1温室气体盘查表!AF54 -> 0 | I71: =表1温室气体盘查表!AG54 -> 0 | J71: =表1温室气体盘查表!AH54 -> 0 | K71: =表1温室气体盘查表!AI54 -> 0 | L71: =表1温室气体盘查表!AJ54 -> 0 | M71: =表1温室气体盘查表!AK54 -> 0
B72: 3.1.22 | C72: =表1温室气体盘查表!C55 -> 所有其他纸制品加工制造 | D72: =表1温室气体盘查表!D55 -> 办公室 | F72: =表1温室气体盘查表!AL55 -> 5.5436243 | G72: =表1温室气体盘查表!AE55 -> 5.5436243 | H72: =表1温室气体盘查表!AF55 -> 0 | I72: =表1温室气体盘查表!AG55 -> 0 | J72: =表1温室气体盘查表!AH55 -> 0 | K72: =表1温室气体盘查表!AI55 -> 0 | L72: =表1温室气体盘查表!AJ55 -> 0 | M72: =表1温室气体盘查表!AK55 -> 0
B73: 3.1.23 | C73: =表1温室气体盘查表!C56 -> 办公用品(纸张除外)制造 | D73: =表1温室气体盘查表!D56 -> 办公室 | F73: =表1温室气体盘查表!AL56 -> 47.034256 | G73: =表1温室气体盘查表!AE56 -> 47.034256 | H73: =表1温室气体盘查表!AF56 -> 0 | I73: =表1温室气体盘查表!AG56 -> 0 | J73: =表1温室气体盘查表!AH56 -> 0 | K73: =表1温室气体盘查表!AI56 -> 0 | L73: =表1温室气体盘查表!AJ56 -> 0 | M73: =表1温室气体盘查表!AK56 -> 0
B74: 3.1.24 | C74: =表1温室气体盘查表!C57 -> 源水 | D74: =表1温室气体盘查表!D57 -> 水处理工序 | F74: =表1温室气体盘查表!AL57 -> 29761.031 | G74: =表1温室气体盘查表!AE57 -> 29761.031 | H74: =表1温室气体盘查表!AF57 -> 0 | I74: =表1温室气体盘查表!AG57 -> 0 | J74: =表1温室气体盘查表!AH57 -> 0 | K74: =表1温室气体盘查表!AI57 -> 0 | L74: =表1温室气体盘查表!AJ57 -> 0 | M74: =表1温室气体盘查表!AK57 -> 0
B76: 范围三 类别2 | C76: =表1温室气体盘查表!B58 -> 资本货物 | F76: =SUM(G76:M76) -> 51806.97 | G76: =SUM(G77:G87) -> 51806.97 | H76: =SUM(H77:H87) -> 0 | I76: =SUM(I77:I87) -> 0 | J76: =SUM(J77:J87) -> 0 | K76: =SUM(K77:K87) -> 0 | L76: =SUM(L77:L87) -> 0 | M76: =SUM(M77:M87) -> 0
B77: 3.2.1 | C77: =表1温室气体盘查表!C58 -> 采购产品空调和暖空气加热设备和商业和工业制冷设备制造 | D77: =表1温室气体盘查表!D58 -> 办公室、各工序 | F77: =表1温室气体盘查表!AL58 -> 14.832439 | G77: =表1温室气体盘查表!AE58 -> 14.832439 | H77: =表1温室气体盘查表!AF58 -> 0 | I77: =表1温室气体盘查表!AG58 -> 0 | J77: =表1温室气体盘查表!AH58 -> 0 | K77: =表1温室气体盘查表!AI58 -> 0 | L77: =表1温室气体盘查表!AJ58 -> 0 | M77: =表1温室气体盘查表!AK58 -> 0
B78: 3.2.2 | C78: =表1温室气体盘查表!C59 -> 电子计算机制造 | D78: =表1温室气体盘查表!D59 -> 办公室、各工序 | F78: =表1温室气体盘查表!AL59 -> 3.7880397 | G78: =表1温室气体盘查表!AE59 -> 3.7880397 | H78: =表1温室气体盘查表!AF59 -> 0 | I78: =表1温室气体盘查表!AG59 -> 0 | J78: =表1温室气体盘查表!AH59 -> 0 | K78: =表1温室气体盘查表!AI59 -> 0 | L78: =表1温室气体盘查表!AJ59 -> 0 | M78: =表1温室气体盘查表!AK59 -> 0
B79: 3.2.3 | C79: =表1温室气体盘查表!C60 -> 焊接及焊接设备制造 | D79: =表1温室气体盘查表!D60 -> 各工序 | F79: =表1温室气体盘查表!AL60 -> 216.41133 | G79: =表1温室气体盘查表!AE60 -> 216.41133 | H79: =表1温室气体盘查表!AF60 -> 0 | I79: =表1温室气体盘查表!AG60 -> 0 | J79: =表1温室气体盘查表!AH60 -> 0 | K79: =表1温室气体盘查表!AI60 -> 0 | L79: =表1温室气体盘查表!AJ60 -> 0 | M79: =表1温室气体盘查表!AK60 -> 0
B80: 3.2.4 | C80: =表1温室气体盘查表!C61 -> 其他工业设备制造 | D80: =表1温室气体盘查表!D61 -> 各工序 | F80: =表1温室气体盘查表!AL61 -> 1153.4664 | G80: =表1温室气体盘查表!AE61 -> 1153.4664 | H80: =表1温室气体盘查表!AF61 -> 0 | I80: =表1温室气体盘查表!AG61 -> 0 | J80: =表1温室气体盘查表!AH61 -> 0 | K80: =表1温室气体盘查表!AI61 -> 0 | L80: =表1温室气体盘查表!AJ61 -> 0 | M80: =表1温室气体盘查表!AK61 -> 0
B81: 3.2.5 | C81: =表1温室气体盘查表!C62 -> 测量和测试电力和电气信号的仪器制造 | D81: =表1温室气体盘查表!D62 -> 各工序 | F81: =表1温室气体盘查表!AL62 -> 44.316302 | G81: =表1温室气体盘查表!AE62 -> 44.316302 | H81: =表1温室气体盘查表!AF62 -> 0 | I81: =表1温室气体盘查表!AG62 -> 0 | J81: =表1温室气体盘查表!AH62 -> 0 | K81: =表1温室气体盘查表!AI62 -> 0 | L81: =表1温室气体盘查表!AJ62 -> 0 | M81: =表1温室气体盘查表!AK62 -> 0
B82: 3.2.6 | C82: =表1温室气体盘查表!C63 -> 计算机系统设计服务 | D82: =表1温室气体盘查表!D63 -> 各工序 | F82: =表1温室气体盘查表!AL63 -> 56.221168 | G82: =表1温室气体盘查表!AE63 -> 56.221168 | H82: =表1温室气体盘查表!AF63 -> 0 | I82: =表1温室气体盘查表!AG63 -> 0 | J82: =表1温室气体盘查表!AH63 -> 0 | K82: =表1温室气体盘查表!AI63 -> 0 | L82: =表1温室气体盘查表!AJ63 -> 0 | M82: =表1温室气体盘查表!AK63 -> 0
B83: 3.2.7 | C83: =表1温室气体盘查表!C64 -> 机械动力传动设备制造 | D83: =表1温室气体盘查表!D64 -> 各工序 | F83: =表1温室气体盘查表!AL64 -> 35.304052 | G83: =表1温室气体盘查表!AE64 -> 35.304052 | H83: =表1温室气体盘查表!AF64 -> 0 | I83: =表1温室气体盘查表!AG64 -> 0 | J83: =表1温室气体盘查表!AH64 -> 0 | K83: =表1温室气体盘查表!AI64 -> 0 | L83: =表1温室气体盘查表!AJ64 -> 0 | M83: =表1温室气体盘查表!AK64 -> 0
B84: 3.2.8 | C84: =表1温室气体盘查表!C65 -> 测量、分配及其他泵类设备制造 | D84: =表1温室气体盘查表!D65 -> 各工序 | F84: =表1温室气体盘查表!AL65 -> 432.06182 | G84: =表1温室气体盘查表!AE65 -> 432.06182 | H84: =表1温室气体盘查表!AF65 -> 0 | I84: =表1温室气体盘查表!AG65 -> 0 | J84: =表1温室气体盘查表!AH65 -> 0 | K84: =表1温室气体盘查表!AI65 -> 0 | L84: =表1温室气体盘查表!AJ65 -> 0 | M84: =表1温室气体盘查表!AK65 -> 0
B85: 3.2.9 | C85: =表1温室气体盘查表!C66 -> 用于测量、显示和控制工业过程变量的仪器及相关产品制造 | D85: =表1温室气体盘查表!D66 -> 各工序 | F85: =表1温室气体盘查表!AL66 -> 11.184553 | G85: =表1温室气体盘查表!AE66 -> 11.184553 | H85: =表1温室气体盘查表!AF66 -> 0 | I85: =表1温室气体盘查表!AG66 -> 0 | J85: =表1温室气体盘查表!AH66 -> 0 | K85: =表1温室气体盘查表!AI66 -> 0 | L85: =表1温室气体盘查表!AJ66 -> 0 | M85: =表1温室气体盘查表!AK66 -> 0
B86: 3.2.10 | C86: =表1温室气体盘查表!C67 -> 所有其他杂项电气设备及元件制造 | D86: =表1温室气体盘查表!D67 -> 各工序 | F86: =表1温室气体盘查表!AL67 -> 555.0722 | G86: =表1温室气体盘查表!AE67 -> 555.0722 | H86: =表1温室气体盘查表!AF67 -> 0 | I86: =表1温室气体盘查表!AG67 -> 0 | J86: =表1温室气体盘查表!AH67 -> 0 | K86: =表1温室气体盘查表!AI67 -> 0 | L86: =表1温室气体盘查表!AJ67 -> 0 | M86: =表1温室气体盘查表!AK67 -> 0
B87: 3.2.11 | C87: =表1温室气体盘查表!C68 -> 所有其他杂项制造 | D87: =表1温室气体盘查表!D68 -> 各工序 | F87: =表1温室气体盘查表!AL68 -> 49284.312 | G87: =表1温室气体盘查表!AE68 -> 49284.312 | H87: =表1温室气体盘查表!AF68 -> 0 | I87: =表1温室气体盘查表!AG68 -> 0 | J87: =表1温室气体盘查表!AH68 -> 0 | K87: =表1温室气体盘查表!AI68 -> 0 | L87: =表1温室气体盘查表!AJ68 -> 0 | M87: =表1温室气体盘查表!AK68 -> 0
B89: 范围三 类别3 | C89: =表1温室气体盘查表!B70 -> 范围一、二相关燃料和能源相关的活动产生的排放 | F89: =SUM(G89:M89) -> 2016736.1 | G89: =SUM(G90:G99) -> 2016736.1 | H89: =SUM(H91:H98) -> 0 | I89: =SUM(I91:I98) -> 0 | J89: =SUM(J91:J98) -> 0 | K89: =SUM(K91:K98) -> 0 | L89: =SUM(L91:L98) -> 0 | M89: =SUM(M91:M98) -> 0
B90: 3.3.1 | C90: =表1温室气体盘查表!C69 -> 液化石油气生产 | D90: =表1温室气体盘查表!D69 -> 冶钢宾馆 | F90: =表1温室气体盘查表!AL69 -> 9.448458 | G90: =表1温室气体盘查表!AE69 -> 9.448458 | H90: =表1温室气体盘查表!AF69 -> 0 | I90: =表1温室气体盘查表!AG69 -> 0 | J90: =表1温室气体盘查表!AH69 -> 0 | K90: =表1温室气体盘查表!AI69 -> 0 | L90: =表1温室气体盘查表!AJ69 -> 0 | M90: =表1温室气体盘查表!AK69 -> 0
B91: 3.3.2 | C91: =表1温室气体盘查表!C70 -> 洗精煤生产 | D91: =表1温室气体盘查表!D70 -> 焦化 | F91: =表1温室气体盘查表!AL70 -> 1120352.4 | G91: =表1温室气体盘查表!AE70 -> 1120352.4 | H91: =表1温室气体盘查表!AF70 -> 0 | I91: =表1温室气体盘查表!AG70 -> 0 | J91: =表1温室气体盘查表!AH70 -> 0 | K91: =表1温室气体盘查表!AI70 -> 0 | L91: =表1温室气体盘查表!AJ70 -> 0 | M91: =表1温室气体盘查表!AK70 -> 0
B92: 3.3.3 | C92: =表1温室气体盘查表!C71 -> 柴油生产 | D92: =表1温室气体盘查表!D71 -> 各工序 | F92: =表1温室气体盘查表!AL71 -> 1182.227 | G92: =表1温室气体盘查表!AE71 -> 1182.227 | H92: =表1温室气体盘查表!AF71 -> 0 | I92: =表1温室气体盘查表!AG71 -> 0 | J92: =表1温室气体盘查表!AH71 -> 0 | K92: =表1温室气体盘查表!AI71 -> 0 | L92: =表1温室气体盘查表!AJ71 -> 0 | M92: =表1温室气体盘查表!AK71 -> 0
B93: 3.3.4 | C93: =表1温室气体盘查表!C72 -> 汽油生产 | D93: =表1温室气体盘查表!D72 -> 车队 | F93: =表1温室气体盘查表!AL72 -> 48.438425 | G93: =表1温室气体盘查表!AE72 -> 48.438425 | H93: =表1温室气体盘查表!AF72 -> 0 | I93: =表1温室气体盘查表!AG72 -> 0 | J93: =表1温室气体盘查表!AH72 -> 0 | K93: =表1温室气体盘查表!AI72 -> 0 | L93: =表1温室气体盘查表!AJ72 -> 0 | M93: =表1温室气体盘查表!AK72 -> 0
B94: 3.3.5 | C94: =表1温室气体盘查表!C73 -> 焦炭生产 | D94: =表1温室气体盘查表!D73 -> 烧结、高炉 | F94: =表1温室气体盘查表!AL73 -> 184347.32 | G94: =表1温室气体盘查表!AE73 -> 184347.32 | H94: =表1温室气体盘查表!AF73 -> 0 | I94: =表1温室气体盘查表!AG73 -> 0 | J94: =表1温室气体盘查表!AH73 -> 0 | K94: =表1温室气体盘查表!AI73 -> 0 | L94: =表1温室气体盘查表!AJ73 -> 0 | M94: =表1温室气体盘查表!AK73 -> 0
B95: 3.3.6 | C95: =表1温室气体盘查表!C74 -> 焦屑生产 | D95: =表1温室气体盘查表!D74 -> 烧结、高炉 | F95: =表1温室气体盘查表!AL74 -> 152835.17 | G95: =表1温室气体盘查表!AE74 -> 152835.17 | H95: =表1温室气体盘查表!AF74 -> 0 | I95: =表1温室气体盘查表!AG74 -> 0 | J95: =表1温室气体盘查表!AH74 -> 0 | K95: =表1温室气体盘查表!AI74 -> 0 | L95: =表1温室气体盘查表!AJ74 -> 0 | M95: =表1温室气体盘查表!AK74 -> 0
B96: 3.3.7 | C96: =表1温室气体盘查表!C75 -> 烟煤生产 | D96: =表1温室气体盘查表!D75 -> 高炉 | F96: =表1温室气体盘查表!AL75 -> 229690.01 | G96: =表1温室气体盘查表!AE75 -> 229690.01 | H96: =表1温室气体盘查表!AF75 -> 0 | I96: =表1温室气体盘查表!AG75 -> 0 | J96: =表1温室气体盘查表!AH75 -> 0 | K96: =表1温室气体盘查表!AI75 -> 0 | L96: =表1温室气体盘查表!AJ75 -> 0 | M96: =表1温室气体盘查表!AK75 -> 0
B97: 3.3.8 | C97: =表1温室气体盘查表!C76 -> 无烟煤生产 | D97: =表1温室气体盘查表!D76 -> 烧结、高炉 | F97: =表1温室气体盘查表!AL76 -> 149948.24 | G97: =表1温室气体盘查表!AE76 -> 149948.24 | H97: =表1温室气体盘查表!AF76 -> 0 | I97: =表1温室气体盘查表!AG76 -> 0 | J97: =表1温室气体盘查表!AH76 -> 0 | K97: =表1温室气体盘查表!AI76 -> 0 | L97: =表1温室气体盘查表!AJ76 -> 0 | M97: =表1温室气体盘查表!AK76 -> 0
B98: 3.3.9 | C98: =表1温室气体盘查表!C77 -> 天然气生产 | D98: =表1温室气体盘查表!D77 -> 转炉、电炉、锻造、热处理 | F98: =表1温室气体盘查表!AL77 -> 11120.273 | G98: =表1温室气体盘查表!AE77 -> 11120.273 | H98: =表1温室气体盘查表!AF77 -> 0 | I98: =表1温室气体盘查表!AG77 -> 0 | J98: =表1温室气体盘查表!AH77 -> 0 | K98: =表1温室气体盘查表!AI77 -> 0 | L98: =表1温室气体盘查表!AJ77 -> 0 | M98: =表1温室气体盘查表!AK77 -> 0
B99: 3.3.10 | C99: =表1温室气体盘查表!C78 -> 外购电力上游排放 | D99: =表1温室气体盘查表!D78 -> 各工序 | F99: =表1温室气体盘查表!AL78 -> 167202.53 | G99: =表1温室气体盘查表!AE78 -> 167202.53 | H99: =表1温室气体盘查表!AF78 -> 0 | I99: =表1温室气体盘查表!AG78 -> 0 | J99: =表1温室气体盘查表!AH78 -> 0 | K99: =表1温室气体盘查表!AI78 -> 0 | L99: =表1温室气体盘查表!AJ78 -> 0 | M99: =表1温室气体盘查表!AK78 -> 0
B101: 范围三 类别4 | C101: =表1温室气体盘查表!B79 -> 上游运输配送产生的排放 | F101: =SUM(G101:M101) -> 362284.25 | G101: =SUM(G102:G104) -> 362284.25 | H101: =SUM(H102:H104) -> 0 | I101: =SUM(I102:I104) -> 0 | J101: =SUM(J102:J104) -> 0 | K101: =SUM(K102:K104) -> 0 | L101: =SUM(L102:L104) -> 0 | M101: =SUM(M102:M104) -> 0
B102: 3.4.1 | C102: =表1温室气体盘查表!C79 -> 船运 | D102: =表1温室气体盘查表!D79 -> - | F102: =表1温室气体盘查表!AL79 -> 256608.97 | G102: =表1温室气体盘查表!AE79 -> 256608.97 | H102: =表1温室气体盘查表!AF79 -> 0 | I102: =表1温室气体盘查表!AG79 -> 0 | J102: =表1温室气体盘查表!AH79 -> 0 | K102: =表1温室气体盘查表!AI79 -> 0 | L102: =表1温室气体盘查表!AJ79 -> 0 | M102: =表1温室气体盘查表!AK79 -> 0
B103: 3.4.2 | C103: =表1温室气体盘查表!C80 -> 汽运 | D103: =表1温室气体盘查表!D80 -> - | F103: =表1温室气体盘查表!AL80 -> 46150.512 | G103: =表1温室气体盘查表!AE80 -> 46150.512 | H103: =表1温室气体盘查表!AF80 -> 0 | I103: =表1温室气体盘查表!AG80 -> 0 | J103: =表1温室气体盘查表!AH80 -> 0 | K103: =表1温室气体盘查表!AI80 -> 0 | L103: =表1温室气体盘查表!AJ80 -> 0 | M103: =表1温室气体盘查表!AK80 -> 0
B104: 3.4.3 | C104: =表1温室气体盘查表!C81 -> 铁路运输 | D104: =表1温室气体盘查表!D81 -> - | F104: =表1温室气体盘查表!AL81 -> 59524.772 | G104: =表1温室气体盘查表!AE81 -> 59524.772 | H104: =表1温室气体盘查表!AF81 -> 0 | I104: =表1温室气体盘查表!AG81 -> 0 | J104: =表1温室气体盘查表!AH81 -> 0 | K104: =表1温室气体盘查表!AI81 -> 0 | L104: =表1温室气体盘查表!AJ81 -> 0 | M104: =表1温室气体盘查表!AK81 -> 0
...

Sheet 表1温室气体盘查表
A1: 温室气体盘查表
A2: 编号 | B2: GHG排放类别 | C2: 排放源 | D2: 设施 | E2: 报告边界 | F2: 活动数据 | H2: 排放因子&系数 | AE2: 排放量
H3: CO2 | K3: CH4 | N3: N2O | Q3: HFCs | U3: PFCs | Y3: SF6 | AB3: NF3 | AE3: =H3 -> CO2 | AF3: =K3 -> CH4 | AG3: =N3 -> N2O | AH3: =Q3 -> HFCs | AI3: =U3 -> PFCs | AJ3: =Y3 -> SF6 | AK3: =AB3 -> NF3 | AL3: 总量
F4: 数值 | G4: 计量单位 | H4: EF | I4: 计量单位 | J4: GWP | K4: EF | L4: 计量单位 | M4: GWP | N4: EF | O4: 计量单位 | P4: GWP | Q4: EF | R4: 计量单位 | S4: GWP | T4: 型号 | U4: EF | V4: 计量单位 | W4: GWP | X4: 型号 | Y4: EF | Z4: 计量单位 | AA4: GWP | AB4: EF | AC4: 计量单位 | AD4: GWP | AE4: tCO2e
A5: 1 | B5: 固定燃烧 | C5: 天然气燃烧 | D5: 热处理炉（加热炉） | E5: 范围一 | F5: 1796.49 | G5: 10000Nm3 | H5: ='附表2-EF'!L5 -> 21.621888 | I5: tCO2/10000Nm3 | J5: ='附表1-GWP TABLE'!E3 -> 1 | K5: ='附表2-EF'!M5 -> 0.0003854169 | M5: ='附表1-GWP TABLE'!E4 -> 27.9 | N5: ='附表2-EF'!N5 -> 3.854169e-05 | P5: ='附表1-GWP TABLE'!E5 -> 273 | AE5: =F5*H5*J5 -> 38843.506 | AF5: =F5*K5*M5 -> 19.317893 | AG5: =F5*N5*P5 -> 18.902455 | AH5: =F5*Q5*S5 -> 0 | AI5: =F5*U5*W5 -> 0 | AJ5: =F5*Y5*AA5 -> 0 | AK5: =F5*AB5*AD5 -> 0 | AL5: =SUM(AE5:AK5) -> 38881.726
A6: 2 | B6: 固定燃烧 | C6: 液化石油气燃烧 | D6: 冶钢宾馆 | E6: 范围一 | F6: =ROUND(9.391,2) -> 9.39 | G6: t | H6: ='附表2-EF'!L6 -> 3.102969 | I6: tCO2/t | J6: 1 | K6: ='附表2-EF'!M6 -> 4.917542e-05 | M6: ='附表1-GWP TABLE'!E4 -> 27.9 | N6: ='附表2-EF'!N6 -> 4.917542e-06 | P6: ='附表1-GWP TABLE'!E5 -> 273 | AE6: =F6*H6*J6 -> 29.136879 | AF6: =F6*K6*M6 -> 0.012883026 | AG6: =F6*N6*P6 -> 0.012605971 | AH6: =F6*Q6*S6 -> 0 | AI6: =F6*U6*W6 -> 0 | AJ6: =F6*Y6*AA6 -> 0 | AK6: =F6*AB6*AD6 -> 0 | AL6: =SUM(AE6:AK6) -> 29.162368
A7: 3 | B7: 固定燃烧 | C7: 烟煤燃烧 | D7: 高炉 | E7: 范围一 | F7: =ROUND(333590.27/(1-0.1641),2) -> 399079.16 | G7: t | H7: ='附表2-EF'!L7 -> 2.3099163 | I7: tCO2/t | J7: ='附表1-GWP TABLE'!E3 -> 1 | K7: ='附表2-EF'!M7 -> 2.349864e-05 | M7: ='附表1-GWP TABLE'!E4 -> 27.9 | N7: ='附表2-EF'!N7 -> 3.524796e-05 | P7: ='附表1-GWP TABLE'!E5 -> 273 | AE7: =F7*H7*J7 -> 921839.46 | AF7: =F7*K7*M7 -> 261.64111 | AG7: =F7*N7*P7 -> 3840.2163 | AH7: =F7*Q7*S7 -> 0 | AI7: =F7*U7*W7 -> 0 | AJ7: =F7*Y7*AA7 -> 0 | AK7: =F7*AB7*AD7 -> 0 | AL7: =SUM(AE7:AK7) -> 925941.32
A8: 4 | B8: 固定燃烧 | C8: 无烟煤燃烧 | D8: 高炉、烧结 | E8: 范围一 | F8: =ROUND(235649.69/(1-0.0955),2) -> 260530.34 | G8: t | H8: ='附表2-EF'!L8 -> 2.4352606 | I8: tCO2/t | J8: ='附表1-GWP TABLE'!E3 -> 1 | K8: ='附表2-EF'!M8 -> 2.477376e-05 | M8: ='附表1-GWP TABLE'!E4 -> 27.9 | N8: ='附表2-EF'!N8 -> 3.716064e-05 | P8: ='附表1-GWP TABLE'!E5 -> 273 | AE8: =F8*H8*J8 -> 634459.27 | AF8: =F8*K8*M8 -> 180.07542 | AG8: =F8*N8*P8 -> 2643.0424 | AH8: =F8*Q8*S8 -> 0 | AI8: =F8*U8*W8 -> 0 | AJ8: =F8*Y8*AA8 -> 0 | AK8: =F8*AB8*AD8 -> 0 | AL8: =SUM(AE8:AK8) -> 637282.39
A9: 5 | B9: 固定燃烧 | C9: 洗精煤燃烧 | D9: 焦炉 | E9: 范围一 | F9: =ROUND(1790850.884/(1-0.08),2) -> 1946577.1 | G9: t | H9: ='附表2-EF'!L9 -> 2.467221 | I9: tCO2/t | J9: ='附表1-GWP TABLE'!E3 -> 1 | K9: ='附表2-EF'!M9 -> 2.608056e-05 | M9: ='附表1-GWP TABLE'!E4 -> 27.9 | N9: ='附表2-EF'!N9 -> 3.912084e-05 | P9: ='附表1-GWP TABLE'!E5 -> 273 | AE9: =F9*H9*J9 -> 4802635.7 | AF9: =F9*K9*M9 -> 1416.4222 | AG9: =F9*N9*P9 -> 20789.422 | AH9: =F9*Q9*S9 -> 0 | AI9: =F9*U9*W9 -> 0 | AJ9: =F9*Y9*AA9 -> 0 | AK9: =F9*AB9*AD9 -> 0 | AL9: =SUM(AE9:AK9) -> 4824841.6
A10: 6 | B10: 固定燃烧 | C10: 焦炭燃烧 | D10: 高炉 | E10: 范围一 | F10: =ROUND(141299.98/(1-0.0284),2) -> 145430.2 | G10: t | H10: ='附表2-EF'!L10 -> 3.0121195 | I10: tCO2/t | J10: ='附表1-GWP TABLE'!E3 -> 1 | K10: ='附表2-EF'!M10 -> 2.815065e-05 | M10: ='附表1-GWP TABLE'!E4 -> 27.9 | N10: ='附表2-EF'!N10 -> 4.2225975e-05 | P10: ='附表1-GWP TABLE'!E5 -> 273 | AE10: =F10*H10*J10 -> 438053.15 | AF10: =F10*K10*M10 -> 114.22134 | AG10: =F10*N10*P10 -> 1676.4744 | AH10: =F10*Q10*S10 -> 0 | AI10: =F10*U10*W10 -> 0 | AJ10: =F10*Y10*AA10 -> 0 | AK10: =F10*AB10*AD10 -> 0 | AL10: =SUM(AE10:AK10) -> 439843.84
A11: 7 | B11: 固定燃烧 | C11: 焦屑燃烧 | D11: 烧结、高炉 | E11: 范围一 | F11: =ROUND(109912.07/(1-0.0884),2) -> 120570.5 | G11: t | H11: ='附表2-EF'!L10 -> 3.0121195 | I11: tCO2/t | J11: ='附表1-GWP TABLE'!E3 -> 1 | K11: ='附表2-EF'!M10 -> 2.815065e-05 | M11: ='附表1-GWP TABLE'!E4 -> 27.9 | N11: ='附表2-EF'!N10 -> 4.2225975e-05 | P11: ='附表1-GWP TABLE'!E5 -> 273 | AE11: =F11*H11*J11 -> 363172.76 | AF11: =F11*K11*M11 -> 94.696449 | AG11: =F11*N11*P11 -> 1389.8995 | AH11: =F11*Q11*S11 -> 0 | AI11: =F11*U11*W11 -> 0 | AJ11: =F11*Y11*AA11 -> 0 | AK11: =F11*AB11*AD11 -> 0 | AL11: =SUM(AE11:AK11) -> 364657.36
A12: 8 | B12: 固定燃烧 | C12: 焦炉煤气燃烧 | D12: 外售 | E12: 范围一 | F12: =ROUND(-500.973085,2) -> -500.97 | G12: 10000Nm3 | H12: ='附表2-EF'!L11 -> 7.6419264 | I12: tCO2/10000Nm3 | J12: 1 | K12: ='附表2-EF'!M11 -> 0.00017211546 | M12: ='附表1-GWP TABLE'!E4 -> 27.9 | N12: ='附表2-EF'!N11 -> 1.7211546e-05 | P12: ='附表1-GWP TABLE'!E5 -> 273 | AE12: =F12*H12*J12 -> -3828.3759 | AF12: =F12*K12*M12 -> -2.4056686 | AG12: =F12*N12*P12 -> -2.3539338 | AH12: =F12*Q12*S12 -> 0 | AI12: =F12*U12*W12 -> 0 | AJ12: =F12*Y12*AA12 -> 0 | AK12: =F12*AB12*AD12 -> 0 | AL12: =SUM(AE12:AK12) -> -3833.1355
A13: 9 | B13: 移动燃烧 | C13: 0#柴油燃烧 | D13: 场内运输 | E13: 范围一 | F13: =ROUND(1403.865,2) -> 1403.87 | G13: t | H13: ='附表2-EF'!L12 -> 3.0973029 | I13: tCO2/t | J13: 1 | K13: ='附表2-EF'!M12 -> 0.00016301594 | M13: ='附表1-GWP TABLE'!E4 -> 27.9 | N13: ='附表2-EF'!N12 -> 0.00016301594 | P13: ='附表1-GWP TABLE'!E5 -> 273 | AE13: =F13*H13*J13 -> 4348.2107 | AF13: =F13*K13*M13 -> 6.3850041 | AG13: =F13*N13*P13 -> 62.476922 | AH13: =F13*Q13*S13 -> 0 | AI13: =F13*U13*W13 -> 0 | AJ13: =F13*Y13*AA13 -> 0 | AK13: =F13*AB13*AD13 -> 0 | AL13: =SUM(AE13:AK13) -> 4417.0726
A14: 10 | B14: 移动燃烧 | C14: 92#汽油燃烧 | D14: 公务车 | E14: 范围一 | F14: =ROUND(63298.77*0.775/10^3,2) -> 49.06 | G14: t | H14: ='附表2-EF'!L13 -> 2.925056 | I14: tCO2/t | J14: 1 | K14: ='附表2-EF'!M13 -> 0.001055215 | M14: ='附表1-GWP TABLE'!E4 -> 27.9 | N14: ='附表2-EF'!N13 -> 0.0003376688 | P14: ='附表1-GWP TABLE'!E5 -> 273 | AE14: =F14*H14*J14 -> 143.50325 | AF14: =F14*K14*M14 -> 1.4443509 | AG14: =F14*N14*P14 -> 4.5225266 | AH14: =F14*Q14*S14 -> 0 | AI14: =F14*U14*W14 -> 0 | AJ14: =F14*Y14*AA14 -> 0 | AK14: =F14*AB14*AD14 -> 0 | AL14: =SUM(AE14:AK14) -> 149.47012
A15: 11 | B15: 逸散排放 | C15: 制冷剂逸散（R32） | D15: 分体式空调 | E15: 范围一 | F15: =ROUND(0.9274,2) -> 0.93 | G15: t | Q15: 1 | R15: tHFCs/t | S15: ='附表1-GWP TABLE'!F8 -> 771 | T15: HFC-32 | AE15: =F15*H15*J15 -> 0 | AF15: =F15*K15*M15 -> 0 | AG15: =F15*N15*P15 -> 0 | AH15: =F15*Q15*S15 -> 717.03 | AI15: =F15*U15*W15 -> 0 | AJ15: =F15*Y15*AA15 -> 0 | AK15: =F15*AB15*AD15 -> 0 | AL15: =SUM(AE15:AK15) -> 717.03
A16: 12 | B16: 逸散排放 | C16: CO2逸散 | D16: 二氧化碳灭火器 | E16: 范围一 | F16: =ROUND((127*3+56*5)/1000,2) -> 0.66 | G16: t | H16: ='附表2-EF'!F34 -> 1 | I16: tCO2/t | J16: 1 | AE16: =F16*H16*J16 -> 0.66 | AF16: =F16*K16*M16 -> 0 | AG16: =F16*N16*P16 -> 0 | AH16: =F16*Q16*S16 -> 0 | AI16: =F16*U16*W16 -> 0 | AJ16: =F16*Y16*AA16 -> 0 | AK16: =F16*AB16*AD16 -> 0 | AL16: =SUM(AE16:AK16) -> 0.66
A17: 13 | B17: 逸散排放 | C17: CH4逸散 | D17: 化粪池 | E17: 范围一 | F17: =ROUND(6680*'附表2-EF'!J38*251/10^6*8/24,2) -> 22.36 | G17: tBOD | K17: ='附表2-EF'!J36 -> 0.18 | L17: tCH4/tBOD | M17: ='附表1-GWP TABLE'!E4 -> 27.9 | AE17: =F17*H17*J17 -> 0 | AF17: =F17*K17*M17 -> 112.29192 | AG17: =F17*N17*P17 -> 0 | AH17: =F17*Q17*S17 -> 0 | AI17: =F17*U17*W17 -> 0 | AJ17: =F17*Y17*AA17 -> 0 | AK17: =F17*AB17*AD17 -> 0 | AL17: =SUM(AE17:AK17) -> 112.29192
A18: 14 | B18: 逸散排放 | C18: CH4逸散 | D18: 耗氧池 | E18: 范围一 | F18: =ROUND((21.7-7.3)/10^6*9700672+(27.5-8.5)/10^6*1843418,2) -> 174.71 | G18: tCOD | K18: ='附表2-EF'!J37 -> 0.075 | L18: tCH4/tCOD | M18: ='附表1-GWP TABLE'!E4 -> 27.9 | AE18: =F18*H18*J18 -> 0 | AF18: =F18*K18*M18 -> 365.58067 | AG18: =F18*N18*P18 -> 0 | AH18: =F18*Q18*S18 -> 0 | AI18: =F18*U18*W18 -> 0 | AJ18: =F18*Y18*AA18 -> 0 | AK18: =F18*AB18*AD18 -> 0 | AL18: =SUM(AE18:AK18) -> 365.58067
A19: 15 | B19: 逸散排放 | C19: SF6逸散 | D19: 高压开关 | E19: 范围一 | F19: =ROUND((56*24+63*300)/1000,2) -> 20.24 | G19: t | Y19: ='附表2-EF'!F33 -> 0.005 | Z19: tSF6/t | AA19: ='附表1-GWP TABLE'!E48 -> 24300 | AE19: =F19*H19*J19 -> 0 | AF19: =F19*K19*M19 -> 0 | AG19: =F19*N19*P19 -> 0 | AH19: =F19*Q19*S19 -> 0 | AI19: =F19*U19*W19 -> 0 | AJ19: =F19*Y19*AA19 -> 2459.16 | AK19: =F19*AB19*AD19 -> 0 | AL19: =SUM(AE19:AK19) -> 2459.16
A20: 16 | B20: 制程排放 | C20: 石灰石 | D20: 石灰窑 | E20: 范围一 | F20: =ROUND(4595.368+7694.12+7076.28,2) -> 19365.77 | G20: t | H20: ='附表2-EF'!F19 -> 0.44 | I20: tCO2/t | J20: 1 | AE20: =F20*H20*J20 -> 8520.9388 | AF20: =F20*K20*M20 -> 0 | AG20: =F20*N20*P20 -> 0 | AH20: =F20*Q20*S20 -> 0 | AI20: =F20*U20*W20 -> 0 | AJ20: =F20*Y20*AA20 -> 0 | AK20: =F20*AB20*AD20 -> 0 | AL20: =SUM(AE20:AK20) -> 8520.9388
A21: 17 | B21: 制程排放 | C21: 白云石 | D21: 高炉 | E21: 范围一 | F21: =ROUND(356289.39,2) -> 356289.39 | G21: t | H21: ='附表2-EF'!F20 -> 0.476 | I21: tCO2/t | J21: 1 | AE21: =F21*H21*J21 -> 169593.75 | AF21: =F21*K21*M21 -> 0 | AG21: =F21*N21*P21 -> 0 | AH21: =F21*Q21*S21 -> 0 | AI21: =F21*U21*W21 -> 0 | AJ21: =F21*Y21*AA21 -> 0 | AK21: =F21*AB21*AD21 -> 0 | AL21: =SUM(AE21:AK21) -> 169593.75
A22: 18 | B22: 制程排放 | C22: 电极 | D22: 炼钢 | E22: 范围一 | F22: =ROUND(4763.07,2) -> 4763.07 | G22: t | H22: ='附表2-EF'!F21 -> 3.663 | I22: tCO2/t | J22: 1 | AE22: =F22*H22*J22 -> 17447.125 | AF22: =F22*K22*M22 -> 0 | AG22: =F22*N22*P22 -> 0 | AH22: =F22*Q22*S22 -> 0 | AI22: =F22*U22*W22 -> 0 | AJ22: =F22*Y22*AA22 -> 0 | AK22: =F22*AB22*AD22 -> 0 | AL22: =SUM(AE22:AK22) -> 17447.125
A23: 19 | B23: 制程排放 | C23: 废钢 | D23: 炼钢 | E23: 范围一 | F23: 1077722.6 | G23: t | H23: ='附表2-EF'!F27 -> 0.037 | I23: tCO2/t | J23: 1 | AE23: =F23*H23*J23 -> 39875.738 | AF23: =F23*K23*M23 -> 0 | AG23: =F23*N23*P23 -> 0 | AH23: =F23*Q23*S23 -> 0 | AI23: =F23*U23*W23 -> 0 | AJ23: =F23*Y23*AA23 -> 0 | AK23: =F23*AB23*AD23 -> 0 | AL23: =SUM(AE23:AK23) -> 39875.738
A24: 20 | B24: 制程排放 | C24: 锰铁 | D24: 炼钢 | E24: 范围一 | F24: =ROUND(47687.636,2) -> 47687.64 | G24: t | H24: ='附表2-EF'!F26 -> 0.275 | I24: tCO2/t | J24: 1 | AE24: =F24*H24*J24 -> 13114.101 | AF24: =F24*K24*M24 -> 0 | AG24: =F24*N24*P24 -> 0 | AH24: =F24*Q24*S24 -> 0 | AI24: =F24*U24*W24 -> 0 | AJ24: =F24*Y24*AA24 -> 0 | AK24: =F24*AB24*AD24 -> 0 | AL24: =SUM(AE24:AK24) -> 13114.101
A25: 21 | B25: 制程排放 | C25: 镍铁 | D25: 炼钢 | E25: 范围一 | F25: =ROUND(9445.106,2) -> 9445.11 | G25: t | H25: ='附表2-EF'!F22 -> 0.037 | I25: tCO2/t | J25: 1 | AE25: =F25*H25*J25 -> 349.46907 | AF25: =F25*K25*M25 -> 0 | AG25: =F25*N25*P25 -> 0 | AH25: =F25*Q25*S25 -> 0 | AI25: =F25*U25*W25 -> 0 | AJ25: =F25*Y25*AA25 -> 0 | AK25: =F25*AB25*AD25 -> 0 | AL25: =SUM(AE25:AK25) -> 349.46907
A26: 22 | B26: 制程排放 | C26: 铬铁 | D26: 炼钢 | E26: 范围一 | F26: 65858.929 | G26: t | H26: ='附表2-EF'!F23 -> 0.348 | I26: tCO2/t | J26: 1 | AE26: =F26*H26*J26 -> 22918.907 | AF26: =F26*K26*M26 -> 0 | AG26: =F26*N26*P26 -> 0 | AH26: =F26*Q26*S26 -> 0 | AI26: =F26*U26*W26 -> 0 | AJ26: =F26*Y26*AA26 -> 0 | AK26: =F26*AB26*AD26 -> 0 | AL26: =SUM(AE26:AK26) -> 22918.907
A27: 23 | B27: 制程排放 | C27: 硅铁 | D27: 炼钢 | E27: 范围一 | F27: =ROUND(10672.477,2) -> 10672.48 | G27: t | H27: ='附表2-EF'!F25 -> 0.007 | I27: tCO2/t | J27: 1 | AE27: =F27*H27*J27 -> 74.70736 | AF27: =F27*K27*M27 -> 0 | AG27: =F27*N27*P27 -> 0 | AH27: =F27*Q27*S27 -> 0 | AI27: =F27*U27*W27 -> 0 | AJ27: =F27*Y27*AA27 -> 0 | AK27: =F27*AB27*AD27 -> 0 | AL27: =SUM(AE27:AK27) -> 74.70736
A28: 24 | B28: 制程排放 | C28: 钼铁 | D28: 炼钢 | E28: 范围一 | F28: 7945.164 | G28: t | H28: ='附表2-EF'!F24 -> 0.018 | I28: tCO2/t | J28: 1 | AE28: =F28*H28*J28 -> 143.01295 | AF28: =F28*K28*M28 -> 0 | AG28: =F28*N28*P28 -> 0 | AH28: =F28*Q28*S28 -> 0 | AI28: =F28*U28*W28 -> 0 | AJ28: =F28*Y28*AA28 -> 0 | AK28: =F28*AB28*AD28 -> 0 | AL28: =SUM(AE28:AK28) -> 143.01295
A29: 25 | B29: 制程排放 | C29: 钢坯 | D29: 固碳产品 | E29: 范围一 | F29: -4332821.9 | G29: t | H29: ='附表2-EF'!F28 -> 0.037 | I29: tCO2/t | J29: 1 | AE29: =F29*H29*J29 -> -160314.41 | AF29: =F29*K29*M29 -> 0 | AG29: =F29*N29*P29 -> 0 | AH29: =F29*Q29*S29 -> 0 | AI29: =F29*U29*W29 -> 0 | AJ29: =F29*Y29*AA29 -> 0 | AK29: =F29*AB29*AD29 -> 0 | AL29: =SUM(AE29:AK29) -> -160314.41
A30: 26 | B30: 制程排放 | C30: 粗苯 | D30: 外售 | E30: 范围一 | F30: -19501.18 | G30: t | H30: ='附表2-EF'!F17 -> 3.382 | I30: tCO2/t | J30: 1 | AE30: =F30*H30*J30 -> -65952.991 | AF30: =F30*K30*M30 -> 0 | AG30: =F30*N30*P30 -> 0 | AH30: =F30*Q30*S30 -> 0 | AI30: =F30*U30*W30 -> 0 | AJ30: =F30*Y30*AA30 -> 0 | AK30: =F30*AB30*AD30 -> 0 | AL30: =SUM(AE30:AK30) -> -65952.991
A31: 27 | B31: 制程排放 | C31: 煤焦油 | D31: 危废处置 | E31: 范围一 | F31: -59054.1 | G31: t | H31: ='附表2-EF'!F18 -> 2.699 | I31: tCO2/t | J31: 1 | AE31: =F31*H31*J31 -> -159387.02 | AF31: =F31*K31*M31 -> 0 | AG31: =F31*N31*P31 -> 0 | AH31: =F31*Q31*S31 -> 0 | AI31: =F31*U31*W31 -> 0 | AJ31: =F31*Y31*AA31 -> 0 | AK31: =F31*AB31*AD31 -> 0 | AL31: =SUM(AE31:AK31) -> -159387.02
A32: 28 | B32: 输入能源间接温室气体排放 | C32: 外购电力（基于位置） | D32: 用电设备 | E32: 范围二 | F32: =ROUND(1992878.77,2) -> 1992878.8 | G32: MWh | H32: ='附表2-EF'!F41 -> 0.5366 | I32: tCO2/MWh | J32: 1 | AE32: =F32*H32*J32 -> 1069378.7 | AF32: =F32*K32*M32 -> 0 | AG32: =F32*N32*P32 -> 0 | AH32: =F32*Q32*S32 -> 0 | AI32: =F32*U32*W32 -> 0 | AJ32: =F32*Y32*AA32 -> 0 | AK32: =F32*AB32*AD32 -> 0 | AL32: =SUM(AE32:AK32) -> 1069378.7
A33: 29 | B33: 输入能源间接温室气体排放 | C33: 外购电力（基于市场） | D33: 用电设备 | E33: 范围二 | F33: =ROUND(1992878.77-8759.35,2) -> 1984119.4 | G33: MWh | H33: ='附表2-EF'!F42 -> 0.5856 | I33: tCO2/MWh | J33: 1 | AE33: =F33*H33*J33 -> 1161900.3 | AF33: =F33*K33*M33 -> 0 | AG33: =F33*N33*P33 -> 0 | AH33: =F33*Q33*S33 -> 0 | AI33: =F33*U33*W33 -> 0 | AJ33: =F33*Y33*AA33 -> 0 | AK33: =F33*AB33*AD33 -> 0 | AL33: =SUM(AE33:AK33) -> 1161900.3
A34: 30 | B34: 外购商品和服务的上游排放 | C34: 铁矿石生产 | D34: 烧结 | E34: 范围三 类别1 | F34: =ROUND(4538211.339,2) -> 4538211.3 | G34: t | H34: ='附表2-EF'!G46 -> 0.098847 | I34: tCO2/t | J34: 1 | AE34: =F34*H34*J34 -> 448588.58 | AF34: =F34*K34*M34 -> 0 | AG34: =F34*N34*P34 -> 0 | AH34: =F34*Q34*S34 -> 0 | AI34: =F34*U34*W34 -> 0 | AJ34: =F34*Y34*AA34 -> 0 | AK34: =F34*AB34*AD34 -> 0 | AL34: =SUM(AE34:AK34) -> 448588.58
A35: 31 | B35: 外购商品和服务的上游排放 | C35: 生石灰生产 | D35: 烧结、转炉、电炉 | E35: 范围三 类别1 | F35: =ROUND(611514.48,2) -> 611514.48 | G35: t | H35: ='附表2-EF'!G47 -> 1.1896699 | I35: tCO2/t | J35: 1 | AE35: =F35*H35*J35 -> 727500.38 | AF35: =F35*K35*M35 -> 0 | AG35: =F35*N35*P35 -> 0 | AH35: =F35*Q35*S35 -> 0 | AI35: =F35*U35*W35 -> 0 | AJ35: =F35*Y35*AA35 -> 0 | AK35: =F35*AB35*AD35 -> 0 | AL35: =SUM(AE35:AK35) -> 727500.38
A36: 32 | B36: 外购商品和服务的上游排放 | C36: 石灰石生产 | D36: 转炉 | E36: 范围三 类别1 | F36: =F20 -> 19365.77 | G36: t | H36: ='附表2-EF'!G48 -> 0.0030299 | I36: tCO2/t | J36: 1 | AE36: =F36*H36*J36 -> 58.676347 | AF36: =F36*K36*M36 -> 0 | AG36: =F36*N36*P36 -> 0 | AH36: =F36*Q36*S36 -> 0 | AI36: =F36*U36*W36 -> 0 | AJ36: =F36*Y36*AA36 -> 0 | AK36: =F36*AB36*AD36 -> 0 | AL36: =SUM(AE36:AK36) -> 58.676347
A37: 33 | B37: 外购商品和服务的上游排放 | C37: 白云石生产 | D37: 烧结、转炉、电炉 | E37: 范围三 类别1 | F37: =F21 -> 356289.39 | G37: t | H37: ='附表2-EF'!G49 -> 0.13033 | I37: tCO2/t | J37: 1 | AE37: =F37*H37*J37 -> 46435.196 | AF37: =F37*K37*M37 -> 0 | AG37: =F37*N37*P37 -> 0 | AH37: =F37*Q37*S37 -> 0 | AI37: =F37*U37*W37 -> 0 | AJ37: =F37*Y37*AA37 -> 0 | AK37: =F37*AB37*AD37 -> 0 | AL37: =SUM(AE37:AK37) -> 46435.196
A38: 34 | B38: 外购商品和服务的上游排放 | C38: 轻烧白云石生产 | D38: 转炉、电炉 | E38: 范围三 类别1 | F38: =ROUND(2786.84,2) -> 2786.84 | G38: t | H38: =H37 -> 0.13033 | I38: tCO2/t | J38: 1 | AE38: =F38*H38*J38 -> 363.20886 | AF38: =F38*K38*M38 -> 0 | AG38: =F38*N38*P38 -> 0 | AH38: =F38*Q38*S38 -> 0 | AI38: =F38*U38*W38 -> 0 | AJ38: =F38*Y38*AA38 -> 0 | AK38: =F38*AB38*AD38 -> 0 | AL38: =SUM(AE38:AK38) -> 363.20886
A39: 35 | B39: 外购商品和服务的上游排放 | C39: 球团生产 | D39: 高炉、转炉 | E39: 范围三 类别1 | F39: =ROUND(685439.89,2) -> 685439.89 | G39: t | H39: ='附表2-EF'!G50 -> 0.10446 | I39: tCO2/t | J39: 1 | AE39: =F39*H39*J39 -> 71601.051 | AF39: =F39*K39*M39 -> 0 | AG39: =F39*N39*P39 -> 0 | AH39: =F39*Q39*S39 -> 0 | AI39: =F39*U39*W39 -> 0 | AJ39: =F39*Y39*AA39 -> 0 | AK39: =F39*AB39*AD39 -> 0 | AL39: =SUM(AE39:AK39) -> 71601.051
A40: 36 | B40: 外购商品和服务的上游排放 | C40: 废钢生产 | D40: 转炉、电炉 | E40: 范围三 类别1 | F40: =F23 -> 1077722.6 | G40: t | H40: ='附表2-EF'!G51 -> 0.074179 | I40: tCO2/t | J40: 1 | AE40: =F40*H40*J40 -> 79944.388 | AF40: =F40*K40*M40 -> 0 | AG40: =F40*N40*P40 -> 0 | AH40: =F40*Q40*S40 -> 0 | AI40: =F40*U40*W40 -> 0 | AJ40: =F40*Y40*AA40 -> 0 | AK40: =F40*AB40*AD40 -> 0 | AL40: =SUM(AE40:AK40) -> 79944.388
A41: 37 | B41: 外购商品和服务的上游排放 | C41: 电极生产 | D41: 转炉、电炉 | E41: 范围三 类别1 | F41: =ROUND(4473.457,2) -> 4473.46 | G41: t | H41: ='附表2-EF'!G52 -> 8.4370514 | I41: tCO2/t | J41: 1 | AE41: =F41*H41*J41 -> 37742.812 | AF41: =F41*K41*M41 -> 0 | AG41: =F41*N41*P41 -> 0 | AH41: =F41*Q41*S41 -> 0 | AI41: =F41*U41*W41 -> 0 | AJ41: =F41*Y41*AA41 -> 0 | AK41: =F41*AB41*AD41 -> 0 | AL41: =SUM(AE41:AK41) -> 37742.812
A42: 38 | B42: 外购商品和服务的上游排放 | C42: 锰铁生产 | D42: 转炉、电炉 | E42: 范围三 类别1 | F42: =ROUND(47651.68,2) -> 47651.68 | G42: t | H42: ='附表2-EF'!G53 -> 2.9772 | I42: tCO2/t | J42: 1 | AE42: =F42*H42*J42 -> 141868.58 | AF42: =F42*K42*M42 -> 0 | AG42: =F42*N42*P42 -> 0 | AH42: =F42*Q42*S42 -> 0 | AI42: =F42*U42*W42 -> 0 | AJ42: =F42*Y42*AA42 -> 0 | AK42: =F42*AB42*AD42 -> 0 | AL42: =SUM(AE42:AK42) -> 141868.58
A43: 39 | B43: 外购商品和服务的上游排放 | C43: 镍铁生产 | D43: 转炉、电炉 | E43: 范围三 类别1 | F43: =ROUND(9688.407,2) -> 9688.41 | G43: t | H43: ='附表2-EF'!G54 -> 8.7547 | I43: tCO2/t | J43: 1 | AE43: =F43*H43*J43 -> 84819.123 | AF43: =F43*K43*M43 -> 0 | AG43: =F43*N43*P43 -> 0 | AH43: =F43*Q43*S43 -> 0 | AI43: =F43*U43*W43 -> 0 | AJ43: =F43*Y43*AA43 -> 0 | AK43: =F43*AB43*AD43 -> 0 | AL43: =SUM(AE43:AK43) -> 84819.123
A44: 40 | B44: 外购商品和服务的上游排放 | C44: 铬铁生产 | D44: 转炉、电炉 | E44: 范围三 类别1 | F44: =ROUND(67771.928,2) -> 67771.93 | G44: t | H44: ='附表2-EF'!G55 -> 5.0921 | I44: tCO2/t | J44: 1 | AE44: =F44*H44*J44 -> 345101.44 | AF44: =F44*K44*M44 -> 0 | AG44: =F44*N44*P44 -> 0 | AH44: =F44*Q44*S44 -> 0 | AI44: =F44*U44*W44 -> 0 | AJ44: =F44*Y44*AA44 -> 0 | AK44: =F44*AB44*AD44 -> 0 | AL44: =SUM(AE44:AK44) -> 345101.44
A45: 41 | B45: 外购商品和服务的上游排放 | C45: 萤石生产 | D45: 转炉、电炉 | E45: 范围三 类别1 | F45: =ROUND(3237.84,2) -> 3237.84 | G45: t | H45: ='附表2-EF'!G56 -> 0.21158 | I45: tCO2/t | J45: 1 | AE45: =F45*H45*J45 -> 685.06219 | AF45: =F45*K45*M45 -> 0 | AG45: =F45*N45*P45 -> 0 | AH45: =F45*Q45*S45 -> 0 | AI45: =F45*U45*W45 -> 0 | AJ45: =F45*Y45*AA45 -> 0 | AK45: =F45*AB45*AD45 -> 0 | AL45: =SUM(AE45:AK45) -> 685.06219
A46: 42 | B46: 外购商品和服务的上游排放 | C46: 硅铁生产 | D46: 转炉、电炉 | E46: 范围三 类别1 | F46: =ROUND(10209.54,2) -> 10209.54 | G46: t | H46: ='附表2-EF'!G57 -> 10.145 | I46: tCO2/t | J46: 1 | AE46: =F46*H46*J46 -> 103575.78 | AF46: =F46*K46*M46 -> 0 | AG46: =F46*N46*P46 -> 0 | AH46: =F46*Q46*S46 -> 0 | AI46: =F46*U46*W46 -> 0 | AJ46: =F46*Y46*AA46 -> 0 | AK46: =F46*AB46*AD46 -> 0 | AL46: =SUM(AE46:AK46) -> 103575.78
A47: 43 | B47: 外购商品和服务的上游排放 | C47: 钼铁生产 | D47: 转炉、电炉 | E47: 范围三 类别1 | F47: =ROUND(7772.398,2) -> 7772.4 | G47: t | H47: ='附表2-EF'!G58 -> 8.5 | I47: tCO2/t | J47: 1 | AE47: =F47*H47*J47 -> 66065.4 | AF47: =F47*K47*M47 -> 0 | AG47: =F47*N47*P47 -> 0 | AH47: =F47*Q47*S47 -> 0 | AI47: =F47*U47*W47 -> 0 | AJ47: =F47*Y47*AA47 -> 0 | AK47: =F47*AB47*AD47 -> 0 | AL47: =SUM(AE47:AK47) -> 66065.4
A48: 44 | B48: 外购商品和服务的上游排放 | C48: 铝铁生产 | D48: 转炉、电炉 | E48: 范围三 类别1 | F48: =ROUND(11018.506,2) -> 11018.51 | G48: t | H48: ='附表2-EF'!G59 -> 5.7320082 | I48: tCO2/t | J48: 1 | AE48: =F48*H48*J48 -> 63158.19 | AF48: =F48*K48*M48 -> 0 | AG48: =F48*N48*P48 -> 0 | AH48: =F48*Q48*S48 -> 0 | AI48: =F48*U48*W48 -> 0 | AJ48: =F48*Y48*AA48 -> 0 | AK48: =F48*AB48*AD48 -> 0 | AL48: =SUM(AE48:AK48) -> 63158.19
A49: 45 | B49: 外购商品和服务的上游排放 | C49: 铝生产 | D49: 转炉、电炉 | E49: 范围三 类别1 | F49: =ROUND(2841.662,2) -> 2841.66 | G49: t | H49: ='附表2-EF'!G60 -> 22.290561 | I49: tCO2/t | J49: 1 | AE49: =F49*H49*J49 -> 63342.195 | AF49: =F49*K49*M49 -> 0 | AG49: =F49*N49*P49 -> 0 | AH49: =F49*Q49*S49 -> 0 | AI49: =F49*U49*W49 -> 0 | AJ49: =F49*Y49*AA49 -> 0 | AK49: =F49*AB49*AD49 -> 0 | AL49: =SUM(AE49:AK49) -> 63342.195
A50: 46 | B50: 外购商品和服务的上游排放 | C50: 增碳剂生产 | D50: 转炉、电炉 | E50: 范围三 类别1 | F50: 10680.664 | G50: t | H50: ='附表2-EF'!G61 -> 1.6645335 | I50: tCO2/t | J50: 1 | AE50: =F50*H50*J50 -> 17778.323 | AF50: =F50*K50*M50 -> 0 | AG50: =F50*N50*P50 -> 0 | AH50: =F50*Q50*S50 -> 0 | AI50: =F50*U50*W50 -> 0 | AJ50: =F50*Y50*AA50 -> 0 | AK50: =F50*AB50*AD50 -> 0 | AL50: =SUM(AE50:AK50) -> 17778.323
A51: 47 | B51: 外购商品和服务的上游排放 | C51: 铁鳞生产 | D51: 炼钢 | E51: 范围三 类别1 | F51: =ROUND(172683.992,2) -> 172683.99 | G51: t | H51: ='附表2-EF'!G62 -> 0.0035231057 | I51: tCO2/t | J51: 1 | AE51: =F51*H51*J51 -> 608.38394 | AF51: =F51*K51*M51 -> 0 | AG51: =F51*N51*P51 -> 0 | AH51: =F51*Q51*S51 -> 0 | AI51: =F51*U51*W51 -> 0 | AJ51: =F51*Y51*AA51 -> 0 | AK51: =F51*AB51*AD51 -> 0 | AL51: =SUM(AE51:AK51) -> 608.38394
A52: 48 | B52: 外购商品和服务的上游排放 | C52: 氨水生产 | D52: 烧结 | E52: 范围三 类别1 | F52: =ROUND(3219.1+1277.04,2) -> 4496.14 | G52: t | H52: ='附表2-EF'!G63 -> 5.4368448 | I52: tCO2/t | J52: 1 | AE52: =F52*H52*J52 -> 24444.815 | AF52: =F52*K52*M52 -> 0 | AG52: =F52*N52*P52 -> 0 | AH52: =F52*Q52*S52 -> 0 | AI52: =F52*U52*W52 -> 0 | AJ52: =F52*Y52*AA52 -> 0 | AK52: =F52*AB52*AD52 -> 0 | AL52: =SUM(AE52:AK52) -> 24444.815
A53: 49 | B53: 外购商品和服务的上游排放 | C53: 碳化硅生产 | D53: - | E53: 范围三 类别1 | F53: 6614.798 | G53: t | H53: ='附表2-EF'!G64 -> 7.2790711 | I53: tCO2/t | J53: 1 | AE53: =F53*H53*J53 -> 48149.585 | AF53: =F53*K53*M53 -> 0 | AG53: =F53*N53*P53 -> 0 | AH53: =F53*Q53*S53 -> 0 | AI53: =F53*U53*W53 -> 0 | AJ53: =F53*Y53*AA53 -> 0 | AK53: =F53*AB53*AD53 -> 0 | AL53: =SUM(AE53:AK53) -> 48149.585
A54: 50 | B54: 外购商品和服务的上游排放 | C54: 镁生产 | D54: - | E54: 范围三 类别1 | F54: 11710.709 | G54: t | H54: ='附表2-EF'!G65 -> 26.345188 | I54: tCO2/t | J54: 1 | AE54: =F54*H54*J54 -> 308520.83 | AF54: =F54*K54*M54 -> 0 | AG54: =F54*N54*P54 -> 0 | AH54: =F54*Q54*S54 -> 0 | AI54: =F54*U54*W54 -> 0 | AJ54: =F54*Y54*AA54 -> 0 | AK54: =F54*AB54*AD54 -> 0 | AL54: =SUM(AE54:AK54) -> 308520.83
A55: 51 | B55: 外购商品和服务的上游排放 | C55: 所有其他纸制品加工制造 | D55: 办公室 | E55: 范围三 类别1 | F55: =ROUND(16162.1742168567,2) -> 16162.17 | G55: $ | H55: ='附表2-EF'!G66 -> 0.000343 | I55: t CO2e/2022 USD, purchaser price | J55: 1 | AE55: =F55*H55*J55 -> 5.5436243 | AF55: =F55*K55*M55 -> 0 | AG55: =F55*N55*P55 -> 0 | AH55: =F55*Q55*S55 -> 0 | AI55: =F55*U55*W55 -> 0 | AJ55: =F55*Y55*AA55 -> 0 | AK55: =F55*AB55*AD55 -> 0 | AL55: =SUM(AE55:AK55) -> 5.5436243
A56: 52 | B56: 外购商品和服务的上游排放 | C56: 办公用品(纸张除外)制造 | D56: 办公室 | E56: 范围三 类别1 | F56: =ROUND(177487.755162724,2) -> 177487.76 | G56: $ | H56: ='附表2-EF'!G67 -> 0.000265 | I56: t CO2e/2022 USD, purchaser price | J56: 1 | AE56: =F56*H56*J56 -> 47.034256 | AF56: =F56*K56*M56 -> 0 | AG56: =F56*N56*P56 -> 0 | AH56: =F56*Q56*S56 -> 0 | AI56: =F56*U56*W56 -> 0 | AJ56: =F56*Y56*AA56 -> 0 | AK56: =F56*AB56*AD56 -> 0 | AL56: =SUM(AE56:AK56) -> 47.034256
A57: 53 | B57: 外购商品和服务的上游排放 | C57: 源水 | D57: 水处理工序 | E57: 范围三 类别1 | F57: =ROUND(23278634,2) -> 23278634 | G57: t | H57: ='附表2-EF'!G68 -> 0.0012784698 | I57: tCO2/t | J57: 1 | AE57: =F57*H57*J57 -> 29761.031 | AF57: =F57*K57*M57 -> 0 | AG57: =F57*N57*P57 -> 0 | AH57: =F57*Q57*S57 -> 0 | AI57: =F57*U57*W57 -> 0 | AJ57: =F57*Y57*AA57 -> 0 | AK57: =F57*AB57*AD57 -> 0 | AL57: =SUM(AE57:AK57) -> 29761.031
A58: 54 | B58: 资本货物 | C58: 采购产品空调和暖空气加热设备和商业和工业制冷设备制造 | D58: 办公室、各工序 | E58: 范围三 类别2 | F58: =ROUND(137337.400573884,2) -> 137337.4 | G58: $ | H58: ='附表2-EF'!F73 -> 0.000108 | I58: t CO2e/2022 USD, purchaser price | J58: 1 | AE58: =F58*H58*J58 -> 14.832439 | AF58: =F58*K58*M58 -> 0 | AG58: =F58*N58*P58 -> 0 | AH58: =F58*Q58*S58 -> 0 | AI58: =F58*U58*W58 -> 0 | AJ58: =F58*Y58*AA58 -> 0 | AK58: =F58*AB58*AD58 -> 0 | AL58: =SUM(AE58:AK58) -> 14.832439
A59: 55 | B59: 资本货物 | C59: 电子计算机制造 | D59: 办公室、各工序 | E59: 范围三 类别2 | F59: =ROUND(65311.0316528152,2) -> 65311.03 | G59: $ | H59: ='附表2-EF'!F74 -> 5.8e-05 | I59: t CO2e/2022 USD, purchaser price | J59: 1 | AE59: =F59*H59*J59 -> 3.7880397 | AF59: =F59*K59*M59 -> 0 | AG59: =F59*N59*P59 -> 0 | AH59: =F59*Q59*S59 -> 0 | AI59: =F59*U59*W59 -> 0 | AJ59: =F59*Y59*AA59 -> 0 | AK59: =F59*AB59*AD59 -> 0 | AL59: =SUM(AE59:AK59) -> 3.7880397
A60: 56 | B60: 资本货物 | C60: 焊接及焊接设备制造 | D60: 各工序 | E60: 范围三 类别2 | F60: =ROUND(869121.797178157,2) -> 869121.8 | G60: $ | H60: ='附表2-EF'!F75 -> 0.000249 | I60: t CO2e/2022 USD, purchaser price | J60: 1 | AE60: =F60*H60*J60 -> 216.41133 | AF60: =F60*K60*M60 -> 0 | AG60: =F60*N60*P60 -> 0 | AH60: =F60*Q60*S60 -> 0 | AI60: =F60*U60*W60 -> 0 | AJ60: =F60*Y60*AA60 -> 0 | AK60: =F60*AB60*AD60 -> 0 | AL60: =SUM(AE60:AK60) -> 216.41133
A61: 57 | B61: 资本货物 | C61: 其他工业设备制造 | D61: 各工序 | E61: 范围三 类别2 | F61: =ROUND(6234953.43066562,2) -> 6234953.4 | G61: $ | H61: ='附表2-EF'!F76 -> 0.000185 | I61: t CO2e/2022 USD, purchaser price | J61: 1 | AE61: =F61*H61*J61 -> 1153.4664 | AF61: =F61*K61*M61 -> 0 | AG61: =F61*N61*P61 -> 0 | AH61: =F61*Q61*S61 -> 0 | AI61: =F61*U61*W61 -> 0 | AJ61: =F61*Y61*AA61 -> 0 | AK61: =F61*AB61*AD61 -> 0 | AL61: =SUM(AE61:AK61) -> 1153.4664
A62: 58 | B62: 资本货物 | C62: 测量和测试电力和电气信号的仪器制造 | D62: 各工序 | E62: 范围三 类别2 | F62: =ROUND(560965.846478643,2) -> 560965.85 | G62: $ | H62: ='附表2-EF'!F77 -> 7.9e-05 | I62: t CO2e/2022 USD, purchaser price | J62: 1 | AE62: =F62*H62*J62 -> 44.316302 | AF62: =F62*K62*M62 -> 0 | AG62: =F62*N62*P62 -> 0 | AH62: =F62*Q62*S62 -> 0 | AI62: =F62*U62*W62 -> 0 | AJ62: =F62*Y62*AA62 -> 0 | AK62: =F62*AB62*AD62 -> 0 | AL62: =SUM(AE62:AK62) -> 44.316302
A63: 59 | B63: 资本货物 | C63: 计算机系统设计服务 | D63: 各工序 | E63: 范围三 类别2 | F63: =ROUND(631698.520688066,2) -> 631698.52 | G63: $ | H63: ='附表2-EF'!F78 -> 8.9e-05 | I63: t CO2e/2022 USD, purchaser price | J63: 1 | AE63: =F63*H63*J63 -> 56.221168 | AF63: =F63*K63*M63 -> 0 | AG63: =F63*N63*P63 -> 0 | AH63: =F63*Q63*S63 -> 0 | AI63: =F63*U63*W63 -> 0 | AJ63: =F63*Y63*AA63 -> 0 | AK63: =F63*AB63*AD63 -> 0 | AL63: =SUM(AE63:AK63) -> 56.221168
A64: 60 | B64: 资本货物 | C64: 机械动力传动设备制造 | D64: 各工序 | E64: 范围三 类别2 | F64: =ROUND(168918.914378317,2) -> 168918.91 | G64: $ | H64: ='附表2-EF'!F79 -> 0.000209 | I64: t CO2e/2022 USD, purchaser price | J64: 1 | AE64: =F64*H64*J64 -> 35.304052 | AF64: =F64*K64*M64 -> 0 | AG64: =F64*N64*P64 -> 0 | AH64: =F64*Q64*S64 -> 0 | AI64: =F64*U64*W64 -> 0 | AJ64: =F64*Y64*AA64 -> 0 | AK64: =F64*AB64*AD64 -> 0 | AL64: =SUM(AE64:AK64) -> 35.304052
A65: 61 | B65: 资本货物 | C65: 测量、分配及其他泵类设备制造 | D65: 各工序 | E65: 范围三 类别2 | F65: =ROUND(1937496.9491979,2) -> 1937496.9 | G65: $ | H65: ='附表2-EF'!F80 -> 0.000223 | I65: t CO2e/2022 USD, purchaser price | J65: 1 | AE65: =F65*H65*J65 -> 432.06182 | AF65: =F65*K65*M65 -> 0 | AG65: =F65*N65*P65 -> 0 | AH65: =F65*Q65*S65 -> 0 | AI65: =F65*U65*W65 -> 0 | AJ65: =F65*Y65*AA65 -> 0 | AK65: =F65*AB65*AD65 -> 0 | AL65: =SUM(AE65:AK65) -> 432.06182
A66: 62 | B66: 资本货物 | C66: 用于测量、显示和控制工业过程变量的仪器及相关产品制造 | D66: 各工序 | E66: 范围三 类别2 | F66: =ROUND(177532.576084209,2) -> 177532.58 | G66: $ | H66: ='附表2-EF'!F81 -> 6.3e-05 | I66: t CO2e/2022 USD, purchaser price | J66: 1 | AE66: =F66*H66*J66 -> 11.184553 | AF66: =F66*K66*M66 -> 0 | AG66: =F66*N66*P66 -> 0 | AH66: =F66*Q66*S66 -> 0 | AI66: =F66*U66*W66 -> 0 | AJ66: =F66*Y66*AA66 -> 0 | AK66: =F66*AB66*AD66 -> 0 | AL66: =SUM(AE66:AK66) -> 11.184553
A67: 63 | B67: 资本货物 | C67: 所有其他杂项电气设备及元件制造 | D67: 各工序 | E67: 范围三 类别2 | F67: =ROUND(4336501.56405644,2) -> 4336501.6 | G67: $ | H67: ='附表2-EF'!F82 -> 0.000128 | I67: t CO2e/2022 USD, purchaser price | J67: 1 | AE67: =F67*H67*J67 -> 555.0722 | AF67: =F67*K67*M67 -> 0 | AG67: =F67*N67*P67 -> 0 | AH67: =F67*Q67*S67 -> 0 | AI67: =F67*U67*W67 -> 0 | AJ67: =F67*Y67*AA67 -> 0 | AK67: =F67*AB67*AD67 -> 0 | AL67: =SUM(AE67:AK67) -> 555.0722
A68: 64 | B68: 资本货物 | C68: 所有其他杂项制造 | D68: 各工序 | E68: 范围三 类别2 | F68: =ROUND(270792923.38651,2) -> 2.7079292e+08 | G68: $ | H68: ='附表2-EF'!F83 -> 0.000182 | I68: t CO2e/2022 USD, purchaser price | J68: 1 | AE68: =F68*H68*J68 -> 49284.312 | AF68: =F68*K68*M68 -> 0 | AG68: =F68*N68*P68 -> 0 | AH68: =F68*Q68*S68 -> 0 | AI68: =F68*U68*W68 -> 0 | AJ68: =F68*Y68*AA68 -> 0 | AK68: =F68*AB68*AD68 -> 0 | AL68: =SUM(AE68:AK68) -> 49284.312
A69: 65 | B69: 范围一、二相关燃料和能源相关的活动产生的排放 | C69: 液化石油气生产 | D69: 冶钢宾馆 | E69: 范围三 类别3 | F69: =F6 -> 9.39 | G69: t | H69: ='附表2-EF'!G87 -> 1.0062256 | I69: tCO2/t | J69: 1 | AE69: =F69*H69*J69 -> 9.448458 | AF69: =F69*K69*M69 -> 0 | AG69: =F69*N69*P69 -> 0 | AH69: =F69*Q69*S69 -> 0 | AI69: =F69*U69*W69 -> 0 | AJ69: =F69*Y69*AA69 -> 0 | AK69: =F69*AB69*AD69 -> 0 | AL69: =SUM(AE69:AK69) -> 9.448458
A70: 66 | B70: 范围一、二相关燃料和能源相关的活动产生的排放 | C70: 洗精煤生产 | D70: 焦化 | E70: 范围三 类别3 | F70: =F9 -> 1946577.1 | G70: t | H70: ='附表2-EF'!G88 -> 0.57555 | I70: tCO2/t | J70: 1 | AE70: =F70*H70*J70 -> 1120352.4 | AF70: =F70*K70*M70 -> 0 | AG70: =F70*N70*P70 -> 0 | AH70: =F70*Q70*S70 -> 0 | AI70: =F70*U70*W70 -> 0 | AJ70: =F70*Y70*AA70 -> 0 | AK70: =F70*AB70*AD70 -> 0 | AL70: =SUM(AE70:AK70) -> 1120352.4
A71: 67 | B71: 范围一、二相关燃料和能源相关的活动产生的排放 | C71: 柴油生产 | D71: 各工序 | E71: 范围三 类别3 | F71: =F13 -> 1403.87 | G71: t | H71: ='附表2-EF'!G89 -> 0.84212 | I71: tCO2/t | J71: 1 | AE71: =F71*H71*J71 -> 1182.227 | AF71: =F71*K71*M71 -> 0 | AG71: =F71*N71*P71 -> 0 | AH71: =F71*Q71*S71 -> 0 | AI71: =F71*U71*W71 -> 0 | AJ71: =F71*Y71*AA71 -> 0 | AK71: =F71*AB71*AD71 -> 0 | AL71: =SUM(AE71:AK71) -> 1182.227
A72: 68 | B72: 范围一、二相关燃料和能源相关的活动产生的排放 | C72: 汽油生产 | D72: 车队 | E72: 范围三 类别3 | F72: =F14 -> 49.06 | G72: t | H72: ='附表2-EF'!G90 -> 0.98733031 | I72: tCO2/t | J72: 1 | AE72: =F72*H72*J72 -> 48.438425 | AF72: =F72*K72*M72 -> 0 | AG72: =F72*N72*P72 -> 0 | AH72: =F72*Q72*S72 -> 0 | AI72: =F72*U72*W72 -> 0 | AJ72: =F72*Y72*AA72 -> 0 | AK72: =F72*AB72*AD72 -> 0 | AL72: =SUM(AE72:AK72) -> 48.438425
A73: 69 | B73: 范围一、二相关燃料和能源相关的活动产生的排放 | C73: 焦炭生产 | D73: 烧结、高炉 | E73: 范围三 类别3 | F73: =F10 -> 145430.2 | G73: t | H73: ='附表2-EF'!G91 -> 1.2676 | I73: tCO2/t | J73: 1 | AE73: =F73*H73*J73 -> 184347.32 | AF73: =F73*K73*M73 -> 0 | AG73: =F73*N73*P73 -> 0 | AH73: =F73*Q73*S73 -> 0 | AI73: =F73*U73*W73 -> 0 | AJ73: =F73*Y73*AA73 -> 0 | AK73: =F73*AB73*AD73 -> 0 | AL73: =SUM(AE73:AK73) -> 184347.32
A74: 70 | B74: 范围一、二相关燃料和能源相关的活动产生的排放 | C74: 焦屑生产 | D74: 烧结、高炉 | E74: 范围三 类别3 | F74: =F11 -> 120570.5 | G74: t | H74: ='附表2-EF'!G92 -> 1.2676 | I74: tCO2/t | J74: 1 | AE74: =F74*H74*J74 -> 152835.17 | AF74: =F74*K74*M74 -> 0 | AG74: =F74*N74*P74 -> 0 | AH74: =F74*Q74*S74 -> 0 | AI74: =F74*U74*W74 -> 0 | AJ74: =F74*Y74*AA74 -> 0 | AK74: =F74*AB74*AD74 -> 0 | AL74: =SUM(AE74:AK74) -> 152835.17
A75: 71 | B75: 范围一、二相关燃料和能源相关的活动产生的排放 | C75: 烟煤生产 | D75: 高炉 | E75: 范围三 类别3 | F75: =F7 -> 399079.16 | G75: t | H75: ='附表2-EF'!G93 -> 0.57555 | I75: tCO2/t | J75: 1 | AE75: =F75*H75*J75 -> 229690.01 | AF75: =F75*K75*M75 -> 0 | AG75: =F75*N75*P75 -> 0 | AH75: =F75*Q75*S75 -> 0 | AI75: =F75*U75*W75 -> 0 | AJ75: =F75*Y75*AA75 -> 0 | AK75: =F75*AB75*AD75 -> 0 | AL75: =SUM(AE75:AK75) -> 229690.01
A76: 72 | B76: 范围一、二相关燃料和能源相关的活动产生的排放 | C76: 无烟煤生产 | D76: 烧结、高炉 | E76: 范围三 类别3 | F76: =F8 -> 260530.34 | G76: t | H76: ='附表2-EF'!G94 -> 0.57555 | I76: tCO2/t | J76: 1 | AE76: =F76*H76*J76 -> 149948.24 | AF76: =F76*K76*M76 -> 0 | AG76: =F76*N76*P76 -> 0 | AH76: =F76*Q76*S76 -> 0 | AI76: =F76*U76*W76 -> 0 | AJ76: =F76*Y76*AA76 -> 0 | AK76: =F76*AB76*AD76 -> 0 | AL76: =SUM(AE76:AK76) -> 149948.24
A77: 73 | B77: 范围一、二相关燃料和能源相关的活动产生的排放 | C77: 天然气生产 | D77: 转炉、电炉、锻造、热处理 | E77: 范围三 类别3 | F77: =F5 -> 1796.49 | G77: 10000Nm3 | H77: ='附表2-EF'!G95 -> 6.19 | I77: tCO2/t | J77: 1 | AE77: =F77*H77*J77 -> 11120.273 | AF77: =F77*K77*M77 -> 0 | AG77: =F77*N77*P77 -> 0 | AH77: =F77*Q77*S77 -> 0 | AI77: =F77*U77*W77 -> 0 | AJ77: =F77*Y77*AA77 -> 0 | AK77: =F77*AB77*AD77 -> 0 | AL77: =SUM(AE77:AK77) -> 11120.273
A78: 74 | B78: 范围一、二相关燃料和能源相关的活动产生的排放 | C78: 外购电力上游排放 | D78: 各工序 | E78: 范围三 类别3 | F78: =F32 -> 1992878.8 | G78: MWh | H78: ='附表2-EF'!G96 -> 0.0839 | I78: tCO2/MWh | J78: 1 | AE78: =F78*H78*J78 -> 167202.53 | AF78: =F78*K78*M78 -> 0 | AG78: =F78*N78*P78 -> 0 | AH78: =F78*Q78*S78 -> 0 | AI78: =F78*U78*W78 -> 0 | AJ78: =F78*Y78*AA78 -> 0 | AK78: =F78*AB78*AD78 -> 0 | AL78: =SUM(AE78:AK78) -> 167202.53
A79: 75 | B79: 上游运输配送产生的排放 | C79: 船运 | D79: - | E79: 范围三 类别4 | F79: 4.9377735e+09 | G79: tkm | H79: ='附表2-EF'!G100 -> 5.1968558e-05 | I79: ='附表2-EF'!H100 -> tCO2-Eq/tkm | J79: 1 | AE79: =F79*H79*J79 -> 256608.97 | AF79: =F79*K79*M79 -> 0 | AG79: =F79*N79*P79 -> 0 | AH79: =F79*Q79*S79 -> 0 | AI79: =F79*U79*W79 -> 0 | AJ79: =F79*Y79*AA79 -> 0 | AK79: =F79*AB79*AD79 -> 0 | AL79: =SUM(AE79:AK79) -> 256608.97
A80: 76 | B80: 上游运输配送产生的排放 | C80: 汽运 | D80: - | E80: 范围三 类别4 | F80: 3.0369596e+08 | G80: tkm | H80: ='附表2-EF'!G101 -> 0.00015196288 | I80: ='附表2-EF'!H101 -> tCO2-Eq/tkm | J80: 1 | AE80: =F80*H80*J80 -> 46150.512 | AF80: =F80*K80*M80 -> 0 | AG80: =F80*N80*P80 -> 0 | AH80: =F80*Q80*S80 -> 0 | AI80: =F80*U80*W80 -> 0 | AJ80: =F80*Y80*AA80 -> 0 | AK80: =F80*AB80*AD80 -> 0 | AL80: =SUM(AE80:AK80) -> 46150.512
A81: 77 | B81: 上游运输配送产生的排放 | C81: 铁路运输 | D81: - | E81: 范围三 类别4 | F81: 1.2265094e+09 | G81: tkm | H81: ='附表2-EF'!G102 -> 4.8531851e-05 | I81: ='附表2-EF'!H102 -> tCO2-Eq/tkm | J81: 1 | AE81: =F81*H81*J81 -> 59524.772 | AF81: =F81*K81*M81 -> 0 | AG81: =F81*N81*P81 -> 0 | AH81: =F81*Q81*S81 -> 0 | AI81: =F81*U81*W81 -> 0 | AJ81: =F81*Y81*AA81 -> 0 | AK81: =F81*AB81*AD81 -> 0 | AL81: =SUM(AE81:AK81) -> 59524.772
A82: 78 | B82: 运营中产生的废物排放 | C82: 生活垃圾和厨余垃圾 | D82: 垃圾站 | E82: 范围三 类别5 | F82: =ROUND(205.51+2404.65,2) -> 2610.16 | G82: t | H82: ='附表2-EF'!G106 -> 0.3713343 | I82: tCO2/t | J82: 1 | AE82: =F82*H82*J82 -> 969.24193 | AF82: =F82*K82*M82 -> 0 | AG82: =F82*N82*P82 -> 0 | AH82: =F82*Q82*S82 -> 0 | AI82: =F82*U82*W82 -> 0 | AJ82: =F82*Y82*AA82 -> 0 | AK82: =F82*AB82*AD82 -> 0 | AL82: =SUM(AE82:AK82) -> 969.24193
A83: 79 | B83: 运营中产生的废物排放 | C83: 废油 | D83: - | E83: 范围三 类别5 | F83: =ROUND(36.746,2) -> 36.75 | G83: t | H83: ='附表2-EF'!G107 -> 2.849057 | I83: tCO2/t | J83: 1 | AE83: =F83*H83*J83 -> 104.70285 | AF83: =F83*K83*M83 -> 0 | AG83: =F83*N83*P83 -> 0 | AH83: =F83*Q83*S83 -> 0 | AI83: =F83*U83*W83 -> 0 | AJ83: =F83*Y83*AA83 -> 0 | AK83: =F83*AB83*AD83 -> 0 | AL83: =SUM(AE83:AK83) -> 104.70285
A84: 80 | B84: 运营中产生的废物排放 | C84: 废油水 | D84: - | E84: 范围三 类别5 | F84: 229.5 | G84: t | H84: ='附表2-EF'!G108 -> 2.849057 | I84: tCO2/t | J84: 1 | AE84: =F84*H84*J84 -> 653.85859 | AF84: =F84*K84*M84 -> 0 | AG84: =F84*N84*P84 -> 0 | AH84: =F84*Q84*S84 -> 0 | AI84: =F84*U84*W84 -> 0 | AJ84: =F84*Y84*AA84 -> 0 | AK84: =F84*AB84*AD84 -> 0 | AL84: =SUM(AE84:AK84) -> 653.85859
A85: 81 | B85: 运营中产生的废物排放 | C85: 煤焦油 | D85: - | E85: 范围三 类别5 | F85: 57478.34 | G85: t | H85: ='附表2-EF'!G109 -> 2.5237125 | I85: tCO2/t | J85: 1 | AE85: =F85*H85*J85 -> 145058.8 | AF85: =F85*K85*M85 -> 0 | AG85: =F85*N85*P85 -> 0 | AH85: =F85*Q85*S85 -> 0 | AI85: =F85*U85*W85 -> 0 | AJ85: =F85*Y85*AA85 -> 0 | AK85: =F85*AB85*AD85 -> 0 | AL85: =SUM(AE85:AK85) -> 145058.8
A86: 82 | B86: 运营中产生的废物排放 | C86: 废弃物运输 | D86: - | E86: 范围三 类别5 | F86: 5589690 | G86: tkm | H86: ='附表2-EF'!G101 -> 0.00015196288 | I86: ='附表2-EF'!H93 -> tCO2/t | J86: 1 | AE86: =F86*H86*J86 -> 849.42539 | AF86: =F86*K86*M86 -> 0 | AG86: =F86*N86*P86 -> 0 | AH86: =F86*Q86*S86 -> 0 | AI86: =F86*U86*W86 -> 0 | AJ86: =F86*Y86*AA86 -> 0 | AK86: =F86*AB86*AD86 -> 0 | AL86: =SUM(AE86:AK86) -> 849.42539
A87: 83 | B87: 商务旅行产生的排放 | C87: 航运 | D87: - | E87: 范围三 类别6 | F87: =ROUND(3901916.53046595,2) -> 3901916.5 | G87: passenger*km | H87: ='附表2-EF'!G113 -> 0.084 | I87: ='附表2-EF'!H113 -> kgCO2/passenger*km | J87: 1 | AE87: =F87*H87*J87/1000 -> 327.76099 | AF87: =F87*K87*M87 -> 0 | AG87: =F87*N87*P87 -> 0 | AH87: =F87*Q87*S87 -> 0 | AI87: =F87*U87*W87 -> 0 | AJ87: =F87*Y87*AA87 -> 0 | AK87: =F87*AB87*AD87 -> 0 | AL87: =SUM(AE87:AK87) -> 327.76099
A88: 84 | B88: 商务旅行产生的排放 | C88: 铁路运输 | D88: - | E88: 范围三 类别6 | F88: =ROUND(8277796.53044579,2) -> 8277796.5 | G88: passenger*km | H88: ='附表2-EF'!G114 -> 0.074873544 | I88: ='附表2-EF'!H114 -> kgCO2/passenger*km | J88: 1 | AE88: =F88*H88*J88/1000 -> 619.78797 | AF88: =F88*K88*M88 -> 0 | AG88: =F88*N88*P88 -> 0 | AH88: =F88*Q88*S88 -> 0 | AI88: =F88*U88*W88 -> 0 | AJ88: =F88*Y88*AA88 -> 0 | AK88: =F88*AB88*AD88 -> 0 | AL88: =SUM(AE88:AK88) -> 619.78797
A89: 85 | B89: 商务旅行产生的排放 | C89: 员工差旅住宿 | D89: - | E89: 范围三 类别6 | F89: =ROUND(13507,2) -> 13507 | G89: 总间*晚 | H89: ='附表2-EF'!G115 -> 0.0535 | I89: tCO2/间*晚 | J89: 1 | AE89: =F89*H89*J89 -> 722.6245 | AF89: =F89*K89*M89 -> 0 | AG89: =F89*N89*P89 -> 0 | AH89: =F89*Q89*S89 -> 0 | AI89: =F89*U89*W89 -> 0 | AJ89: =F89*Y89*AA89 -> 0 | AK89: =F89*AB89*AD89 -> 0 | AL89: =SUM(AE89:AK89) -> 722.6245
A90: 86 | B90: 员工通勤产生的排放 | C90: 通勤车 | D90: - | E90: 范围三 类别7 | F90: =ROUND(12637097,2) -> 12637097 | G90: passenger*km | H90: ='附表2-EF'!G119 -> 0.0088 | I90: ='附表2-EF'!H119 -> kgCO2/passenger*km | J90: 1 | AE90: =F90*H90*J90/1000 -> 111.20645 | AF90: =F90*K90*M90 -> 0 | AG90: =F90*N90*P90 -> 0 | AH90: =F90*Q90*S90 -> 0 | AI90: =F90*U90*W90 -> 0 | AJ90: =F90*Y90*AA90 -> 0 | AK90: =F90*AB90*AD90 -> 0 | AL90: =SUM(AE90:AK90) -> 111.20645
A91: 87 | B91: 员工通勤产生的排放 | C91: 电动车 | D91: - | E91: 范围三 类别7 | F91: =ROUND(17561466,2) -> 17561466 | G91: passenger*km | H91: ='附表2-EF'!G120 -> 0.02702026 | I91: ='附表2-EF'!H120 -> kgCO2/passenger*km | J91: 1 | AE91: =F91*H91*J91/1000 -> 474.51538 | AF91: =F91*K91*M91 -> 0 | AG91: =F91*N91*P91 -> 0 | AH91: =F91*Q91*S91 -> 0 | AI91: =F91*U91*W91 -> 0 | AJ91: =F91*Y91*AA91 -> 0 | AK91: =F91*AB91*AD91 -> 0 | AL91: =SUM(AE91:AK91) -> 474.51538
A92: 88 | B92: 员工通勤产生的排放 | C92: 自驾油车 | D92: - | E92: 范围三 类别7 | F92: =ROUND(31405120,2) -> 31405120 | G92: km | H92: ='附表2-EF'!G121 -> 0.37142762 | I92: ='附表2-EF'!H121 -> kgCO2/km | J92: 1 | AE92: =F92*H92*J92/1000 -> 11664.729 | AF92: =F92*K92*M92 -> 0 | AG92: =F92*N92*P92 -> 0 | AH92: =F92*Q92*S92 -> 0 | AI92: =F92*U92*W92 -> 0 | AJ92: =F92*Y92*AA92 -> 0 | AK92: =F92*AB92*AD92 -> 0 | AL92: =SUM(AE92:AK92) -> 11664.729
A93: 89 | B93: 员工通勤产生的排放 | C93: 自驾电车 | D93: - | E93: 范围三 类别7 | F93: =ROUND(2886500,2) -> 2886500 | G93: km | H93: ='附表2-EF'!G122 -> 0.37142762 | I93: ='附表2-EF'!H122 -> kgCO2/km | J93: 1 | AE93: =F93*H93*J93/1000 -> 1072.1258 | AF93: =F93*K93*M93 -> 0 | AG93: =F93*N93*P93 -> 0 | AH93: =F93*Q93*S93 -> 0 | AI93: =F93*U93*W93 -> 0 | AJ93: =F93*Y93*AA93 -> 0 | AK93: =F93*AB93*AD93 -> 0 | AL93: =SUM(AE93:AK93) -> 1072.1258
A94: 90 | B94: 下游运输配送产生的排放 | C94: 船运 | D94: - | E94: 范围三 类别9 | F94: 1.0290483e+09 | G94: tkm | H94: ='附表2-EF'!G100 -> 5.1968558e-05 | I94: ='附表2-EF'!H100 -> tCO2-Eq/tkm | J94: 1 | AE94: =F94*H94*J94 -> 53478.156 | AF94: =F94*K94*M94 -> 0 | AG94: =F94*N94*P94 -> 0 | AH94: =F94*Q94*S94 -> 0 | AI94: =F94*U94*W94 -> 0 | AJ94: =F94*Y94*AA94 -> 0 | AK94: =F94*AB94*AD94 -> 0 | AL94: =SUM(AE94:AK94) -> 53478.156
A95: 91 | B95: 下游运输配送产生的排放 | C95: 汽运 | D95: - | E95: 范围三 类别9 | F95: 1.369081e+09 | G95: tkm | H95: ='附表2-EF'!G101 -> 0.00015196288 | I95: ='附表2-EF'!H101 -> tCO2-Eq/tkm | J95: 1 | AE95: =F95*H95*J95 -> 208049.49 | AF95: =F95*K95*M95 -> 0 | AG95: =F95*N95*P95 -> 0 | AH95: =F95*Q95*S95 -> 0 | AI95: =F95*U95*W95 -> 0 | AJ95: =F95*Y95*AA95 -> 0 | AK95: =F95*AB95*AD95 -> 0 | AL95: =SUM(AE95:AK95) -> 208049.49
A96: 92 | B96: 下游运输配送产生的排放 | C96: 铁路运输 | D96: - | E96: 范围三 类别9 | F96: 2.2843703e+08 | G96: tkm | H96: ='附表2-EF'!G102 -> 4.8531851e-05 | I96: ='附表2-EF'!H102 -> tCO2-Eq/tkm | J96: 1 | AE96: =F96*H96*J96 -> 11086.472 | AF96: =F96*K96*M96 -> 0 | AG96: =F96*N96*P96 -> 0 | AH96: =F96*Q96*S96 -> 0 | AI96: =F96*U96*W96 -> 0 | AJ96: =F96*Y96*AA96 -> 0 | AK96: =F96*AB96*AD96 -> 0 | AL96: =SUM(AE96:AK96) -> 11086.472
A97: 93 | B97: 下游运输配送产生的排放 | C97: 汽运-副产品 | D97: - | E97: 范围三 类别9 | F97: =ROUND(12973524,2) -> 12973524 | G97: tkm | H97: ='附表2-EF'!G101 -> 0.00015196288 | I97: ='附表2-EF'!H101 -> tCO2-Eq/tkm | J97: 1 | AE97: =F97*H97*J97 -> 1971.494 | AF97: =F97*K97*M97 -> 0 | AG97: =F97*N97*P97 -> 0 | AH97: =F97*Q97*S97 -> 0 | AI97: =F97*U97*W97 -> 0 | AJ97: =F97*Y97*AA97 -> 0 | AK97: =F97*AB97*AD97 -> 0 | AL97: =SUM(AE97:AK97) -> 1971.494
A98: 94 | B98: 外销产品加工产生的排放 | C98: 锻材加工 | D98: 下游钢铁厂 | E98: 范围三 类别10 | F98: =ROUND(149966,2) -> 149966 | G98: t | H98: ='附表2-EF'!F126 -> 0.75534229 | I98: ='附表2-EF'!G126 -> kgCO2/kg | J98: 1 | AE98: =F98*H98*J98 -> 113275.66 | AF98: =F98*K98*M98 -> 0 | AG98: =F98*N98*P98 -> 0 | AH98: =F98*Q98*S98 -> 0 | AI98: =F98*U98*W98 -> 0 | AJ98: =F98*Y98*AA98 -> 0 | AK98: =F98*AB98*AD98 -> 0 | AL98: =SUM(AE98:AK98) -> 113275.66
A99: 95 | B99: 外销产品加工产生的排放 | C99: 棒材加工 | D99: 下游钢铁厂 | E99: 范围三 类别10 | F99: =ROUND(2033971,2) -> 2033971 | G99: t | H99: ='附表2-EF'!F127 -> 0.6672638 | I99: ='附表2-EF'!G127 -> kgCO2/kg | J99: 1 | AE99: =F99*H99*J99 -> 1357195.2 | AF99: =F99*K99*M99 -> 0 | AG99: =F99*N99*P99 -> 0 | AH99: =F99*Q99*S99 -> 0 | AI99: =F99*U99*W99 -> 0 | AJ99: =F99*Y99*AA99 -> 0 | AK99: =F99*AB99*AD99 -> 0 | AL99: =SUM(AE99:AK99) -> 1357195.2
A100: 96 | B100: 外销产品加工产生的排放 | C100: 钢管加工 | D100: 下游钢铁厂 | E100: 范围三 类别10 | F100: =ROUND(760435.743,2) -> 760435.74 | G100: t | H100: ='附表2-EF'!F128 -> 0.095011763 | I100: ='附表2-EF'!G128 -> kgCO2/kg | J100: 1 | AE100: =F100*H100*J100 -> 72250.341 | AF100: =F100*K100*M100 -> 0 | AG100: =F100*N100*P100 -> 0 | AH100: =F100*Q100*S100 -> 0 | AI100: =F100*U100*W100 -> 0 | AJ100: =F100*Y100*AA100 -> 0 | AK100: =F100*AB100*AD100 -> 0 | AL100: =SUM(AE100:AK100) -> 72250.341
...

Sheet 表2.1不确定性评估——基于位置
A1: 不确定性评估表
A2: 编号 | B2: 排放源 | C2: 设施 | D2: 活动数据类别 | E2: 排放因子类别 | F2: 校准频率 | G2: 活动数据级别 | H2: 排放因子级别 | I2: 校准级别 | J2: 平均得分 | K2: 排放量(tCO2e) | L2: 排放量占比 | M2: 加权平均积分
A3: 1 | B3: =表1温室气体盘查表!C5 -> 天然气燃烧 | C3: =表1温室气体盘查表!D5 -> 热处理炉（加热炉） | D3: 自动连续量测 | E3: 国际排放因子 | F3: 校准且合格 | G3: =IF(D3="自动连续量测",6,IF(D3="定期量测/抄表/铭牌",3,1)) -> 6 | H3: =IF(E3="量测/质量平衡排放因子",6,IF(E3="制程/设备排放因子",5,IF(E3="制造商提供的排放因子",4,IF(E3="区域排放因子",3,IF(E3="国家排放因子",2,1))))) -> 1 | I3: =IF(F3="校准且合格",6,IF(F3="未校准",1,3)) -> 6 | J3: =AVERAGE(G3:I3) -> 4.3333333 | K3: =表1温室气体盘查表!AL5 -> 38881.726 | L3: =K3/$K$101 -> 0.0025046146 | M3: =J3*L3 -> 0.01085333
A4: 2 | B4: =表1温室气体盘查表!C6 -> 液化石油气燃烧 | C4: =表1温室气体盘查表!D6 -> 冶钢宾馆 | D4: 定期量测/抄表/铭牌 | E4: 国际排放因子 | F4: 校准且合格 | G4: =IF(D4="自动连续量测",6,IF(D4="定期量测/抄表/铭牌",3,1)) -> 3 | H4: =IF(E4="量测/质量平衡排放因子",6,IF(E4="制程/设备排放因子",5,IF(E4="制造商提供的排放因子",4,IF(E4="区域排放因子",3,IF(E4="国家排放因子",2,1))))) -> 1 | I4: =IF(F4="校准且合格",6,IF(F4="未校准",1,3)) -> 6 | J4: =AVERAGE(G4:I4) -> 3.3333333 | K4: =表1温室气体盘查表!AL6 -> 29.162368 | L4: =K4/$K$101 -> 1.8785301e-06 | M4: =J4*L4 -> 6.2617671e-06
A5: 3 | B5: =表1温室气体盘查表!C7 -> 烟煤燃烧 | C5: =表1温室气体盘查表!D7 -> 高炉 | D5: 自动连续量测 | E5: 国际排放因子 | F5: 校准且合格 | G5: =IF(D5="自动连续量测",6,IF(D5="定期量测/抄表/铭牌",3,1)) -> 6 | H5: =IF(E5="量测/质量平衡排放因子",6,IF(E5="制程/设备排放因子",5,IF(E5="制造商提供的排放因子",4,IF(E5="区域排放因子",3,IF(E5="国家排放因子",2,1))))) -> 1 | I5: =IF(F5="校准且合格",6,IF(F5="未校准",1,3)) -> 6 | J5: =AVERAGE(G5:I5) -> 4.3333333 | K5: =表1温室气体盘查表!AL7 -> 925941.32 | L5: =K5/$K$101 -> 0.059645659 | M5: =J5*L5 -> 0.25846452
A6: 4 | B6: =表1温室气体盘查表!C8 -> 无烟煤燃烧 | C6: =表1温室气体盘查表!D8 -> 高炉、烧结 | D6: 自动连续量测 | E6: 国际排放因子 | F6: 校准且合格 | G6: =IF(D6="自动连续量测",6,IF(D6="定期量测/抄表/铭牌",3,1)) -> 6 | H6: =IF(E6="量测/质量平衡排放因子",6,IF(E6="制程/设备排放因子",5,IF(E6="制造商提供的排放因子",4,IF(E6="区域排放因子",3,IF(E6="国家排放因子",2,1))))) -> 1 | I6: =IF(F6="校准且合格",6,IF(F6="未校准",1,3)) -> 6 | J6: =AVERAGE(G6:I6) -> 4.3333333 | K6: =表1温室气体盘查表!AL8 -> 637282.39 | L6: =K6/$K$101 -> 0.041051336 | M6: =J6*L6 -> 0.17788912
A7: 5 | B7: =表1温室气体盘查表!C9 -> 洗精煤燃烧 | C7: =表1温室气体盘查表!D9 -> 焦炉 | D7: 自动连续量测 | E7: 国际排放因子 | F7: 校准且合格 | G7: =IF(D7="自动连续量测",6,IF(D7="定期量测/抄表/铭牌",3,1)) -> 6 | H7: =IF(E7="量测/质量平衡排放因子",6,IF(E7="制程/设备排放因子",5,IF(E7="制造商提供的排放因子",4,IF(E7="区域排放因子",3,IF(E7="国家排放因子",2,1))))) -> 1 | I7: =IF(F7="校准且合格",6,IF(F7="未校准",1,3)) -> 6 | J7: =AVERAGE(G7:I7) -> 4.3333333 | K7: =表1温室气体盘查表!AL9 -> 4824841.6 | L7: =K7/$K$101 -> 0.31079816 | M7: =J7*L7 -> 1.346792
A8: 6 | B8: =表1温室气体盘查表!C10 -> 焦炭燃烧 | C8: =表1温室气体盘查表!D10 -> 高炉 | D8: 自动连续量测 | E8: 国际排放因子 | F8: 校准且合格 | G8: =IF(D8="自动连续量测",6,IF(D8="定期量测/抄表/铭牌",3,1)) -> 6 | H8: =IF(E8="量测/质量平衡排放因子",6,IF(E8="制程/设备排放因子",5,IF(E8="制造商提供的排放因子",4,IF(E8="区域排放因子",3,IF(E8="国家排放因子",2,1))))) -> 1 | I8: =IF(F8="校准且合格",6,IF(F8="未校准",1,3)) -> 6 | J8: =AVERAGE(G8:I8) -> 4.3333333 | K8: =表1温室气体盘查表!AL10 -> 439843.84 | L8: =K8/$K$101 -> 0.028333087 | M8: =J8*L8 -> 0.12277671
A9: 7 | B9: =表1温室气体盘查表!C11 -> 焦屑燃烧 | C9: =表1温室气体盘查表!D11 -> 烧结、高炉 | D9: 自动连续量测 | E9: 国际排放因子 | F9: 校准且合格 | G9: =IF(D9="自动连续量测",6,IF(D9="定期量测/抄表/铭牌",3,1)) -> 6 | H9: =IF(E9="量测/质量平衡排放因子",6,IF(E9="制程/设备排放因子",5,IF(E9="制造商提供的排放因子",4,IF(E9="区域排放因子",3,IF(E9="国家排放因子",2,1))))) -> 1 | I9: =IF(F9="校准且合格",6,IF(F9="未校准",1,3)) -> 6 | J9: =AVERAGE(G9:I9) -> 4.3333333 | K9: =表1温室气体盘查表!AL11 -> 364657.36 | L9: =K9/$K$101 -> 0.023489856 | M9: =J9*L9 -> 0.10178938
A10: 8 | B10: =表1温室气体盘查表!C12 -> 焦炉煤气燃烧 | C10: =表1温室气体盘查表!D12 -> 外售 | D10: 自动连续量测 | E10: 国际排放因子 | F10: 校准且合格 | G10: =IF(D10="自动连续量测",6,IF(D10="定期量测/抄表/铭牌",3,1)) -> 6 | H10: =IF(E10="量测/质量平衡排放因子",6,IF(E10="制程/设备排放因子",5,IF(E10="制造商提供的排放因子",4,IF(E10="区域排放因子",3,IF(E10="国家排放因子",2,1))))) -> 1 | I10: =IF(F10="校准且合格",6,IF(F10="未校准",1,3)) -> 6 | J10: =AVERAGE(G10:I10) -> 4.3333333 | K10: =表1温室气体盘查表!AL12 -> -3833.1355 | L10: =K10/$K$101 -> -0.00024691618 | M10: =J10*L10 -> -0.0010699701
A11: 9 | B11: =表1温室气体盘查表!C13 -> 0#柴油燃烧 | C11: =表1温室气体盘查表!D13 -> 场内运输 | D11: 定期量测/抄表/铭牌 | E11: 国际排放因子 | F11: 校准但不合格/未校准但数据可查证 | G11: =IF(D11="自动连续量测",6,IF(D11="定期量测/抄表/铭牌",3,1)) -> 3 | H11: =IF(E11="量测/质量平衡排放因子",6,IF(E11="制程/设备排放因子",5,IF(E11="制造商提供的排放因子",4,IF(E11="区域排放因子",3,IF(E11="国家排放因子",2,1))))) -> 1 | I11: =IF(F11="校准且合格",6,IF(F11="未校准",1,3)) -> 3 | J11: =AVERAGE(G11:I11) -> 2.3333333 | K11: =表1温室气体盘查表!AL13 -> 4417.0726 | L11: =K11/$K$101 -> 0.00028453121 | M11: =J11*L11 -> 0.00066390616
A12: 10 | B12: =表1温室气体盘查表!C14 -> 92#汽油燃烧 | C12: =表1温室气体盘查表!D14 -> 公务车 | D12: 定期量测/抄表/铭牌 | E12: 国际排放因子 | F12: 校准但不合格/未校准但数据可查证 | G12: =IF(D12="自动连续量测",6,IF(D12="定期量测/抄表/铭牌",3,1)) -> 3 | H12: =IF(E12="量测/质量平衡排放因子",6,IF(E12="制程/设备排放因子",5,IF(E12="制造商提供的排放因子",4,IF(E12="区域排放因子",3,IF(E12="国家排放因子",2,1))))) -> 1 | I12: =IF(F12="校准且合格",6,IF(F12="未校准",1,3)) -> 3 | J12: =AVERAGE(G12:I12) -> 2.3333333 | K12: =表1温室气体盘查表!AL14 -> 149.47012 | L12: =K12/$K$101 -> 9.6283035e-06 | M12: =J12*L12 -> 2.2466042e-05
A13: 11 | B13: =表1温室气体盘查表!C15 -> 制冷剂逸散（R32） | C13: =表1温室气体盘查表!D15 -> 分体式空调 | D13: 定期量测/抄表/铭牌 | E13: 国家排放因子 | F13: 校准且合格 | G13: =IF(D13="自动连续量测",6,IF(D13="定期量测/抄表/铭牌",3,1)) -> 3 | H13: =IF(E13="量测/质量平衡排放因子",6,IF(E13="制程/设备排放因子",5,IF(E13="制造商提供的排放因子",4,IF(E13="区域排放因子",3,IF(E13="国家排放因子",2,1))))) -> 2 | I13: =IF(F13="校准且合格",6,IF(F13="未校准",1,3)) -> 6 | J13: =AVERAGE(G13:I13) -> 3.6666667 | K13: =表1温室气体盘查表!AL15 -> 717.03 | L13: =K13/$K$101 -> 4.6188377e-05 | M13: =J13*L13 -> 0.00016935738
A14: 12 | B14: =表1温室气体盘查表!C16 -> CO2逸散 | C14: =表1温室气体盘查表!D16 -> 二氧化碳灭火器 | D14: 定期量测/抄表/铭牌 | E14: 国家排放因子 | F14: 校准且合格 | G14: =IF(D14="自动连续量测",6,IF(D14="定期量测/抄表/铭牌",3,1)) -> 3 | H14: =IF(E14="量测/质量平衡排放因子",6,IF(E14="制程/设备排放因子",5,IF(E14="制造商提供的排放因子",4,IF(E14="区域排放因子",3,IF(E14="国家排放因子",2,1))))) -> 2 | I14: =IF(F14="校准且合格",6,IF(F14="未校准",1,3)) -> 6 | J14: =AVERAGE(G14:I14) -> 3.6666667 | K14: =表1温室气体盘查表!AL16 -> 0.66 | L14: =K14/$K$101 -> 4.2514719e-08 | M14: =J14*L14 -> 1.558873e-07
... A30: 28 | B30: =表1温室气体盘查表!C32 -> 外购电力（基于位置） | C30: =表1温室气体盘查表!D32 -> 用电设备 | D30: 自动连续量测 | E30: 国家排放因子 | F30: 校准且合格 | G30: =IF(D30="自动连续量测",6,IF(D30="定期量测/抄表/铭牌",3,1)) -> 6 | H30: =IF(E30="量测/质量平衡排放因子",6,IF(E30="制程/设备排放因子",5,IF(E30="制造商提供的排放因子",4,IF(E30="区域排放因子",3,IF(E30="国家排放因子",2,1))))) -> 2 | I30: =IF(F30="校准且合格",6,IF(F30="未校准",1,3)) -> 6 | J30: =AVERAGE(G30:I30) -> 4.6666667 | K30: =表1温室气体盘查表!AL32 -> 1069378.7 | L30: =K30/$K$101 -> 0.068885359 | M30: =J30*L30 -> 0.32146501
A31: 29 | B31: =表1温室气体盘查表!C34 -> 铁矿石生产 | C31: =表1温室气体盘查表!D34 -> 烧结 | D31: 定期量测/抄表/铭牌 | E31: 国家排放因子 | F31: 校准且合格 | G31: =IF(D31="自动连续量测",6,IF(D31="定期量测/抄表/铭牌",3,1)) -> 3 | H31: =IF(E31="量测/质量平衡排放因子",6,IF(E31="制程/设备排放因子",5,IF(E31="制造商提供的排放因子",4,IF(E31="区域排放因子",3,IF(E31="国家排放因子",2,1))))) -> 2 | I31: =IF(F31="校准且合格",6,IF(F31="未校准",1,3)) -> 6 | J31: =AVERAGE(G31:I31) -> 3.6666667 | K31: =表1温室气体盘查表!AL34 -> 448588.58 | L31: =K31/$K$101 -> 0.02889639 | M31: =J31*L31 -> 0.10595343
A32: 30 | B32: =表1温室气体盘查表!C35 -> 生石灰生产 | C32: =表1温室气体盘查表!D35 -> 烧结、转炉、电炉 | D32: 定期量测/抄表/铭牌 | E32: 国际排放因子 | F32: 校准且合格 | G32: =IF(D32="自动连续量测",6,IF(D32="定期量测/抄表/铭牌",3,1)) -> 3 | H32: =IF(E32="量测/质量平衡排放因子",6,IF(E32="制程/设备排放因子",5,IF(E32="制造商提供的排放因子",4,IF(E32="区域排放因子",3,IF(E32="国家排放因子",2,1))))) -> 1 | I32: =IF(F32="校准且合格",6,IF(F32="未校准",1,3)) -> 6 | J32: =AVERAGE(G32:I32) -> 3.3333333 | K32: =表1温室气体盘查表!AL35 -> 727500.38 | L32: =K32/$K$101 -> 0.04686284 | M32: =J32*L32 -> 0.15620947
A33: 31 | B33: =表1温室气体盘查表!C36 -> 石灰石生产 | C33: =表1温室气体盘查表!D36 -> 转炉 | D33: 定期量测/抄表/铭牌 | E33: 国际排放因子 | F33: 校准且合格 | G33: =IF(D33="自动连续量测",6,IF(D33="定期量测/抄表/铭牌",3,1)) -> 3 | H33: =IF(E33="量测/质量平衡排放因子",6,IF(E33="制程/设备排放因子",5,IF(E33="制造商提供的排放因子",4,IF(E33="区域排放因子",3,IF(E33="国家排放因子",2,1))))) -> 1 | I33: =IF(F33="校准且合格",6,IF(F33="未校准",1,3)) -> 6 | J33: =AVERAGE(G33:I33) -> 3.3333333 | K33: =表1温室气体盘查表!AL36 -> 58.676347 | L33: =K33/$K$101 -> 3.7797097e-06 | M33: =J33*L33 -> 1.2599032e-05
A34: 32 | B34: =表1温室气体盘查表!C37 -> 白云石生产 | C34: =表1温室气体盘查表!D37 -> 烧结、转炉、电炉 | D34: 定期量测/抄表/铭牌 | E34: 国际排放因子 | F34: 校准且合格 | G34: =IF(D34="自动连续量测",6,IF(D34="定期量测/抄表/铭牌",3,1)) -> 3 | H34: =IF(E34="量测/质量平衡排放因子",6,IF(E34="制程/设备排放因子",5,IF(E34="制造商提供的排放因子",4,IF(E34="区域排放因子",3,IF(E34="国家排放因子",2,1))))) -> 1 | I34: =IF(F34="校准且合格",6,IF(F34="未校准",1,3)) -> 6 | J34: =AVERAGE(G34:I34) -> 3.3333333 | K34: =表1温室气体盘查表!AL37 -> 46435.196 | L34: =K34/$K$101 -> 0.0029911808 | M34: =J34*L34 -> 0.0099706026
A35: 33 | B35: =表1温室气体盘查表!C38 -> 轻烧白云石生产 | C35: =表1温室气体盘查表!D38 -> 转炉、电炉 | D35: 定期量测/抄表/铭牌 | E35: 国际排放因子 | F35: 校准且合格 | G35: =IF(D35="自动连续量测",6,IF(D35="定期量测/抄表/铭牌",3,1)) -> 3 | H35: =IF(E35="量测/质量平衡排放因子",6,IF(E35="制程/设备排放因子",5,IF(E35="制造商提供的排放因子",4,IF(E35="区域排放因子",3,IF(E35="国家排放因子",2,1))))) -> 1 | I35: =IF(F35="校准且合格",6,IF(F35="未校准",1,3)) -> 6 | J35: =AVERAGE(G35:I35) -> 3.3333333 | K35: =表1温室气体盘查表!AL38 -> 363.20886 | L35: =K35/$K$101 -> 2.3396549e-05 | M35: =J35*L35 -> 7.7988498e-05
A36: 34 | B36: =表1温室气体盘查表!C39 -> 球团生产 | C36: =表1温室气体盘查表!D39 -> 高炉、转炉 | D36: 定期量测/抄表/铭牌 | E36: 国际排放因子 | F36: 校准且合格 | G36: =IF(D36="自动连续量测",6,IF(D36="定期量测/抄表/铭牌",3,1)) -> 3 | H36: =IF(E36="量测/质量平衡排放因子",6,IF(E36="制程/设备排放因子",5,IF(E36="制造商提供的排放因子",4,IF(E36="区域排放因子",3,IF(E36="国家排放因子",2,1))))) -> 1 | I36: =IF(F36="校准且合格",6,IF(F36="未校准",1,3)) -> 6 | J36: =AVERAGE(G36:I36) -> 3.3333333 | K36: =表1温室气体盘查表!AL39 -> 71601.051 | L36: =K36/$K$101 -> 0.0046122705 | M36: =J36*L36 -> 0.015374235
A37: 35 | B37: =表1温室气体盘查表!C40 -> 废钢生产 | C37: =表1温室气体盘查表!D40 -> 转炉、电炉 | D37: 定期量测/抄表/铭牌 | E37: 国际排放因子 | F37: 校准且合格 | G37: =IF(D37="自动连续量测",6,IF(D37="定期量测/抄表/铭牌",3,1)) -> 3 | H37: =IF(E37="量测/质量平衡排放因子",6,IF(E37="制程/设备排放因子",5,IF(E37="制造商提供的排放因子",4,IF(E37="区域排放因子",3,IF(E37="国家排放因子",2,1))))) -> 1 | I37: =IF(F37="校准且合格",6,IF(F37="未校准",1,3)) -> 6 | J37: =AVERAGE(G37:I37) -> 3.3333333 | K37: =表1温室气体盘查表!AL40 -> 79944.388 | L37: =K37/$K$101 -> 0.005149717 | M37: =J37*L37 -> 0.017165723
A38: 36 | B38: =表1温室气体盘查表!C41 -> 电极生产 | C38: =表1温室气体盘查表!D41 -> 转炉、电炉 | D38: 定期量测/抄表/铭牌 | E38: 国际排放因子 | F38: 校准且合格 | G38: =IF(D38="自动连续量测",6,IF(D38="定期量测/抄表/铭牌",3,1)) -> 3 | H38: =IF(E38="量测/质量平衡排放因子",6,IF(E38="制程/设备排放因子",5,IF(E38="制造商提供的排放因子",4,IF(E38="区域排放因子",3,IF(E38="国家排放因子",2,1))))) -> 1 | I38: =IF(F38="校准且合格",6,IF(F38="未校准",1,3)) -> 6 | J38: =AVERAGE(G38:I38) -> 3.3333333 | K38: =表1温室气体盘查表!AL41 -> 37742.812 | L38: =K38/$K$101 -> 0.0024312501 | M38: =J38*L38 -> 0.0081041669
A39: 37 | B39: =表1温室气体盘查表!C42 -> 锰铁生产 | C39: =表1温室气体盘查表!D42 -> 转炉、电炉 | D39: 定期量测/抄表/铭牌 | E39: 国际排放因子 | F39: 校准且合格 | G39: =IF(D39="自动连续量测",6,IF(D39="定期量测/抄表/铭牌",3,1)) -> 3 | H39: =IF(E39="量测/质量平衡排放因子",6,IF(E39="制程/设备排放因子",5,IF(E39="制造商提供的排放因子",4,IF(E39="区域排放因子",3,IF(E39="国家排放因子",2,1))))) -> 1 | I39: =IF(F39="校准且合格",6,IF(F39="未校准",1,3)) -> 6 | J39: =AVERAGE(G39:I39) -> 3.3333333 | K39: =表1温室气体盘查表!AL42 -> 141868.58 | L39: =K39/$K$101 -> 0.0091386407 | M39: =J39*L39 -> 0.030462136
A40: 38 | B40: =表1温室气体盘查表!C43 -> 镍铁生产 | C40: =表1温室气体盘查表!D43 -> 转炉、电炉 | D40: 定期量测/抄表/铭牌 | E40: 国际排放因子 | F40: 校准且合格 | G40: =IF(D40="自动连续量测",6,IF(D40="定期量测/抄表/铭牌",3,1)) -> 3 | H40: =IF(E40="量测/质量平衡排放因子",6,IF(E40="制程/设备排放因子",5,IF(E40="制造商提供的排放因子",4,IF(E40="区域排放因子",3,IF(E40="国家排放因子",2,1))))) -> 1 | I40: =IF(F40="校准且合格",6,IF(F40="未校准",1,3)) -> 6 | J40: =AVERAGE(G40:I40) -> 3.3333333 | K40: =表1温室气体盘查表!AL43 -> 84819.123 | L40: =K40/$K$101 -> 0.0054637291 | M40: =J40*L40 -> 0.01821243
A41: 39 | B41: =表1温室气体盘查表!C44 -> 铬铁生产 | C41: =表1温室气体盘查表!D44 -> 转炉、电炉 | D41: 定期量测/抄表/铭牌 | E41: 国际排放因子 | F41: 校准且合格 | G41: =IF(D41="自动连续量测",6,IF(D41="定期量测/抄表/铭牌",3,1)) -> 3 | H41: =IF(E41="量测/质量平衡排放因子",6,IF(E41="制程/设备排放因子",5,IF(E41="制造商提供的排放因子",4,IF(E41="区域排放因子",3,IF(E41="国家排放因子",2,1))))) -> 1 | I41: =IF(F41="校准且合格",6,IF(F41="未校准",1,3)) -> 6 | J41: =AVERAGE(G41:I41) -> 3.3333333 | K41: =表1温室气体盘查表!AL44 -> 345101.44 | L41: =K41/$K$101 -> 0.022230138 | M41: =J41*L41 -> 0.074100459
A42: 40 | B42: =表1温室气体盘查表!C45 -> 萤石生产 | C42: =表1温室气体盘查表!D45 -> 转炉、电炉 | D42: 定期量测/抄表/铭牌 | E42: 国际排放因子 | F42: 校准且合格 | G42: =IF(D42="自动连续量测",6,IF(D42="定期量测/抄表/铭牌",3,1)) -> 3 | H42: =IF(E42="量测/质量平衡排放因子",6,IF(E42="制程/设备排放因子",5,IF(E42="制造商提供的排放因子",4,IF(E42="区域排放因子",3,IF(E42="国家排放因子",2,1))))) -> 1 | I42: =IF(F42="校准且合格",6,IF(F42="未校准",1,3)) -> 6 | J42: =AVERAGE(G42:I42) -> 3.3333333 | K42: =表1温室气体盘查表!AL45 -> 685.06219 | L42: =K42/$K$101 -> 4.4129131e-05 | M42: =J42*L42 -> 0.0001470971
... A100: 98 | B100: =表1温室气体盘查表!C103 -> 产品报废 | C100: =表1温室气体盘查表!D103 -> 下游钢铁厂 | D100: 自行推估 | E100: 国际排放因子 | F100: 校准但不合格/未校准但数据可查证 | G100: =IF(D100="自动连续量测",6,IF(D100="定期量测/抄表/铭牌",3,1)) -> 1 | H100: =IF(E100="量测/质量平衡排放因子",6,IF(E100="制程/设备排放因子",5,IF(E100="制造商提供的排放因子",4,IF(E100="区域排放因子",3,IF(E100="国家排放因子",2,1))))) -> 1 | I100: =IF(F100="校准且合格",6,IF(F100="未校准",1,3)) -> 3 | J100: =AVERAGE(G100:I100) -> 1.6666667 | K100: =表1温室气体盘查表!AL103 -> 3747.347 | L100: =K100/$K$101 -> 0.00024139 | M100: =J100*L100 -> 0.00040231667
K101: =SUM(K3:K100) -> 15524035 | L101: 加权合计 | M101: =SUM(M3:M100) -> 3.717969 | N101: uncertainty_score_location_based
L102: 加权等级 | M102: =IF(M101<2,"差",IF(M101<3,"一般",IF(M101<4,"良",IF(M101<5,"优","优+")))) -> 良
A112: 优+ | B112: >=5.0
A113: 优 | B113: <5.0,>=4.0
A114: 良 | B114: <4.0,>=3.0
A115: 一般 | B115: <3.0,>=2.0
A116: 差 | B116: <2.0

Sheet 表2.1不确定性评估——基于市场
A1: 不确定性评估表
A2: 编号 | B2: 排放源 | C2: 设施 | D2: 活动数据类别 | E2: 排放因子类别 | F2: 校准频率 | G2: 活动数据级别 | H2: 排放因子级别 | I2: 校准级别 | J2: 平均得分 | K2: 排放量(tCO2e) | L2: 排放量占比 | M2: 加权平均积分
A3: 1 | B3: =表1温室气体盘查表!C5 -> 天然气燃烧 | C3: =表1温室气体盘查表!D5 -> 热处理炉（加热炉） | D3: 自动连续量测 | E3: 国际排放因子 | F3: 校准且合格 | G3: =IF(D3="自动连续量测",6,IF(D3="定期量测/抄表/铭牌",3,1)) -> 6 | H3: =IF(E3="量测/质量平衡排放因子",6,IF(E3="制程/设备排放因子",5,IF(E3="制造商提供的排放因子",4,IF(E3="区域排放因子",3,IF(E3="国家排放因子",2,1))))) -> 1 | I3: =IF(F3="校准且合格",6,IF(F3="未校准",1,3)) -> 6 | J3: =AVERAGE(G3:I3) -> 4.3333333 | K3: =表1温室气体盘查表!AL5 -> 38881.726 | L3: =K3/$K$101 -> 0.0024897758 | M3: =J3*L3 -> 0.010789029
A4: 2 | B4: =表1温室气体盘查表!C6 -> 液化石油气燃烧 | C4: =表1温室气体盘查表!D6 -> 冶钢宾馆 | D4: 定期量测/抄表/铭牌 | E4: 国际排放因子 | F4: 校准且合格 | G4: =IF(D4="自动连续量测",6,IF(D4="定期量测/抄表/铭牌",3,1)) -> 3 | H4: =IF(E4="量测/质量平衡排放因子",6,IF(E4="制程/设备排放因子",5,IF(E4="制造商提供的排放因子",4,IF(E4="区域排放因子",3,IF(E4="国家排放因子",2,1))))) -> 1 | I4: =IF(F4="校准且合格",6,IF(F4="未校准",1,3)) -> 6 | J4: =AVERAGE(G4:I4) -> 3.3333333 | K4: =表1温室气体盘查表!AL6 -> 29.162368 | L4: =K4/$K$101 -> 1.8674006e-06 | M4: =J4*L4 -> 6.2246687e-06
A5: 3 | B5: =表1温室气体盘查表!C7 -> 烟煤燃烧 | C5: =表1温室气体盘查表!D7 -> 高炉 | D5: 自动连续量测 | E5: 国际排放因子 | F5: 校准且合格 | G5: =IF(D5="自动连续量测",6,IF(D5="定期量测/抄表/铭牌",3,1)) -> 6 | H5: =IF(E5="量测/质量平衡排放因子",6,IF(E5="制程/设备排放因子",5,IF(E5="制造商提供的排放因子",4,IF(E5="区域排放因子",3,IF(E5="国家排放因子",2,1))))) -> 1 | I5: =IF(F5="校准且合格",6,IF(F5="未校准",1,3)) -> 6 | J5: =AVERAGE(G5:I5) -> 4.3333333 | K5: =表1温室气体盘查表!AL7 -> 925941.32 | L5: =K5/$K$101 -> 0.059292283 | M5: =J5*L5 -> 0.25693323
A6: 4 | B6: =表1温室气体盘查表!C8 -> 无烟煤燃烧 | C6: =表1温室气体盘查表!D8 -> 高炉、烧结 | D6: 自动连续量测 | E6: 国际排放因子 | F6: 校准且合格 | G6: =IF(D6="自动连续量测",6,IF(D6="定期量测/抄表/铭牌",3,1)) -> 6 | H6: =IF(E6="量测/质量平衡排放因子",6,IF(E6="制程/设备排放因子",5,IF(E6="制造商提供的排放因子",4,IF(E6="区域排放因子",3,IF(E6="国家排放因子",2,1))))) -> 1 | I6: =IF(F6="校准且合格",6,IF(F6="未校准",1,3)) -> 6 | J6: =AVERAGE(G6:I6) -> 4.3333333 | K6: =表1温室气体盘查表!AL8 -> 637282.39 | L6: =K6/$K$101 -> 0.040808124 | M6: =J6*L6 -> 0.1768352
A7: 5 | B7: =表1温室气体盘查表!C9 -> 洗精煤燃烧 | C7: =表1温室气体盘查表!D9 -> 焦炉 | D7: 自动连续量测 | E7: 国际排放因子 | F7: 校准且合格 | G7: =IF(D7="自动连续量测",6,IF(D7="定期量测/抄表/铭牌",3,1)) -> 6 | H7: =IF(E7="量测/质量平衡排放因子",6,IF(E7="制程/设备排放因子",5,IF(E7="制造商提供的排放因子",4,IF(E7="区域排放因子",3,IF(E7="国家排放因子",2,1))))) -> 1 | I7: =IF(F7="校准且合格",6,IF(F7="未校准",1,3)) -> 6 | J7: =AVERAGE(G7:I7) -> 4.3333333 | K7: =表1温室气体盘查表!AL9 -> 4824841.6 | L7: =K7/$K$101 -> 0.30895681 | M7: =J7*L7 -> 1.3388128
A8: 6 | B8: =表1温室气体盘查表!C10 -> 焦炭燃烧 | C8: =表1温室气体盘查表!D10 -> 高炉 | D8: 自动连续量测 | E8: 国际排放因子 | F8: 校准且合格 | G8: =IF(D8="自动连续量测",6,IF(D8="定期量测/抄表/铭牌",3,1)) -> 6 | H8: =IF(E8="量测/质量平衡排放因子",6,IF(E8="制程/设备排放因子",5,IF(E8="制造商提供的排放因子",4,IF(E8="区域排放因子",3,IF(E8="国家排放因子",2,1))))) -> 1 | I8: =IF(F8="校准且合格",6,IF(F8="未校准",1,3)) -> 6 | J8: =AVERAGE(G8:I8) -> 4.3333333 | K8: =表1温室气体盘查表!AL10 -> 439843.84 | L8: =K8/$K$101 -> 0.028165225 | M8: =J8*L8 -> 0.12204931
A9: 7 | B9: =表1温室气体盘查表!C11 -> 焦屑燃烧 | C9: =表1温室气体盘查表!D11 -> 烧结、高炉 | D9: 自动连续量测 | E9: 国际排放因子 | F9: 校准且合格 | G9: =IF(D9="自动连续量测",6,IF(D9="定期量测/抄表/铭牌",3,1)) -> 6 | H9: =IF(E9="量测/质量平衡排放因子",6,IF(E9="制程/设备排放因子",5,IF(E9="制造商提供的排放因子",4,IF(E9="区域排放因子",3,IF(E9="国家排放因子",2,1))))) -> 1 | I9: =IF(F9="校准且合格",6,IF(F9="未校准",1,3)) -> 6 | J9: =AVERAGE(G9:I9) -> 4.3333333 | K9: =表1温室气体盘查表!AL11 -> 364657.36 | L9: =K9/$K$101 -> 0.023350689 | M9: =J9*L9 -> 0.10118632
A10: 8 | B10: =表1温室气体盘查表!C12 -> 焦炉煤气燃烧 | C10: =表1温室气体盘查表!D12 -> 外售 | D10: 自动连续量测 | E10: 国际排放因子 | F10: 校准且合格 | G10: =IF(D10="自动连续量测",6,IF(D10="定期量测/抄表/铭牌",3,1)) -> 6 | H10: =IF(E10="量测/质量平衡排放因子",6,IF(E10="制程/设备排放因子",5,IF(E10="制造商提供的排放因子",4,IF(E10="区域排放因子",3,IF(E10="国家排放因子",2,1))))) -> 1 | I10: =IF(F10="校准且合格",6,IF(F10="未校准",1,3)) -> 6 | J10: =AVERAGE(G10:I10) -> 4.3333333 | K10: =表1温室气体盘查表!AL12 -> -3833.1355 | L10: =K10/$K$101 -> -0.0002454533 | M10: =J10*L10 -> -0.001063631
A11: 9 | B11: =表1温室气体盘查表!C13 -> 0#柴油燃烧 | C11: =表1温室气体盘查表!D13 -> 场内运输 | D11: 定期量测/抄表/铭牌 | E11: 国际排放因子 | F11: 校准但不合格/未校准但数据可查证 | G11: =IF(D11="自动连续量测",6,IF(D11="定期量测/抄表/铭牌",3,1)) -> 3 | H11: =IF(E11="量测/质量平衡排放因子",6,IF(E11="制程/设备排放因子",5,IF(E11="制造商提供的排放因子",4,IF(E11="区域排放因子",3,IF(E11="国家排放因子",2,1))))) -> 1 | I11: =IF(F11="校准且合格",6,IF(F11="未校准",1,3)) -> 3 | J11: =AVERAGE(G11:I11) -> 2.3333333 | K11: =表1温室气体盘查表!AL13 -> 4417.0726 | L11: =K11/$K$101 -> 0.00028284548 | M11: =J11*L11 -> 0.0006599728
A12: 10 | B12: =表1温室气体盘查表!C14 -> 92#汽油燃烧 | C12: =表1温室气体盘查表!D14 -> 公务车 | D12: 定期量测/抄表/铭牌 | E12: 国际排放因子 | F12: 校准但不合格/未校准但数据可查证 | G12: =IF(D12="自动连续量测",6,IF(D12="定期量测/抄表/铭牌",3,1)) -> 3 | H12: =IF(E12="量测/质量平衡排放因子",6,IF(E12="制程/设备排放因子",5,IF(E12="制造商提供的排放因子",4,IF(E12="区域排放因子",3,IF(E12="国家排放因子",2,1))))) -> 1 | I12: =IF(F12="校准且合格",6,IF(F12="未校准",1,3)) -> 3 | J12: =AVERAGE(G12:I12) -> 2.3333333 | K12: =表1温室气体盘查表!AL14 -> 149.47012 | L12: =K12/$K$101 -> 9.5712598e-06 | M12: =J12*L12 -> 2.233294e-05
A13: 11 | B13: =表1温室气体盘查表!C15 -> 制冷剂逸散（R32） | C13: =表1温室气体盘查表!D15 -> 分体式空调 | D13: 定期量测/抄表/铭牌 | E13: 国家排放因子 | F13: 校准且合格 | G13: =IF(D13="自动连续量测",6,IF(D13="定期量测/抄表/铭牌",3,1)) -> 3 | H13: =IF(E13="量测/质量平衡排放因子",6,IF(E13="制程/设备排放因子",5,IF(E13="制造商提供的排放因子",4,IF(E13="区域排放因子",3,IF(E13="国家排放因子",2,1))))) -> 2 | I13: =IF(F13="校准且合格",6,IF(F13="未校准",1,3)) -> 6 | J13: =AVERAGE(G13:I13) -> 3.6666667 | K13: =表1温室气体盘查表!AL15 -> 717.03 | L13: =K13/$K$101 -> 4.591473e-05 | M13: =J13*L13 -> 0.00016835401
A14: 12 | B14: =表1温室气体盘查表!C16 -> CO2逸散 | C14: =表1温室气体盘查表!D16 -> 二氧化碳灭火器 | D14: 定期量测/抄表/铭牌 | E14: 国家排放因子 | F14: 校准且合格 | G14: =IF(D14="自动连续量测",6,IF(D14="定期量测/抄表/铭牌",3,1)) -> 3 | H14: =IF(E14="量测/质量平衡排放因子",6,IF(E14="制程/设备排放因子",5,IF(E14="制造商提供的排放因子",4,IF(E14="区域排放因子",3,IF(E14="国家排放因子",2,1))))) -> 2 | I14: =IF(F14="校准且合格",6,IF(F14="未校准",1,3)) -> 6 | J14: =AVERAGE(G14:I14) -> 3.6666667 | K14: =表1温室气体盘查表!AL16 -> 0.66 | L14: =K14/$K$101 -> 4.2262837e-08 | M14: =J14*L14 -> 1.5496374e-07
... A29: 27 | B29: =表1温室气体盘查表!C31 -> 煤焦油 | C29: =表1温室气体盘查表!D31 -> 危废处置 | D29: 定期量测/抄表/铭牌 | E29: 国家排放因子 | F29: 校准且合格 | G29: =IF(D29="自动连续量测",6,IF(D29="定期量测/抄表/铭牌",3,1)) -> 3 | H29: =IF(E29="量测/质量平衡排放因子",6,IF(E29="制程/设备排放因子",5,IF(E29="制造商提供的排放因子",4,IF(E29="区域排放因子",3,IF(E29="国家排放因子",2,1))))) -> 2 | I29: =IF(F29="校准且合格",6,IF(F29="未校准",1,3)) -> 6 | J29: =AVERAGE(G29:I29) -> 3.6666667 | K29: =表1温室气体盘查表!AL31 -> -159387.02 | L29: =K29/$K$101 -> -0.010206284 | M29: =J29*L29 -> -0.037423042
A30: 28 | B30: =表1温室气体盘查表!C33 -> 外购电力（基于市场） | C30: =表1温室气体盘查表!D33 -> 用电设备 | D30: 自动连续量测 | E30: 国家排放因子 | F30: 校准且合格 | G30: =IF(D30="自动连续量测",6,IF(D30="定期量测/抄表/铭牌",3,1)) -> 6 | H30: =IF(E30="量测/质量平衡排放因子",6,IF(E30="制程/设备排放因子",5,IF(E30="制造商提供的排放因子",4,IF(E30="区域排放因子",3,IF(E30="国家排放因子",2,1))))) -> 2 | I30: =IF(F30="校准且合格",6,IF(F30="未校准",1,3)) -> 6 | J30: =AVERAGE(G30:I30) -> 4.6666667 | K30: =表1温室气体盘查表!AL33 -> 1161900.3 | L30: =K30/$K$101 -> 0.074401825 | M30: =J30*L30 -> 0.34720852
A31: 29 | B31: =表1温室气体盘查表!C34 -> 铁矿石生产 | C31: =表1温室气体盘查表!D34 -> 烧结 | D31: 定期量测/抄表/铭牌 | E31: 国家排放因子 | F31: 校准且合格 | G31: =IF(D31="自动连续量测",6,IF(D31="定期量测/抄表/铭牌",3,1)) -> 3 | H31: =IF(E31="量测/质量平衡排放因子",6,IF(E31="制程/设备排放因子",5,IF(E31="制造商提供的排放因子",4,IF(E31="区域排放因子",3,IF(E31="国家排放因子",2,1))))) -> 2 | I31: =IF(F31="校准且合格",6,IF(F31="未校准",1,3)) -> 6 | J31: =AVERAGE(G31:I31) -> 3.6666667 | K31: =表1温室气体盘查表!AL34 -> 448588.58 | L31: =K31/$K$101 -> 0.028725191 | M31: =J31*L31 -> 0.1053257
A32: 30 | B32: =表1温室气体盘查表!C35 -> 生石灰生产 | C32: =表1温室气体盘查表!D35 -> 烧结、转炉、电炉 | D32: 定期量测/抄表/铭牌 | E32: 国际排放因子 | F32: 校准且合格 | G32: =IF(D32="自动连续量测",6,IF(D32="定期量测/抄表/铭牌",3,1)) -> 3 | H32: =IF(E32="量测/质量平衡排放因子",6,IF(E32="制程/设备排放因子",5,IF(E32="制造商提供的排放因子",4,IF(E32="区域排放因子",3,IF(E32="国家排放因子",2,1))))) -> 1 | I32: =IF(F32="校准且合格",6,IF(F32="未校准",1,3)) -> 6 | J32: =AVERAGE(G32:I32) -> 3.3333333 | K32: =表1温室气体盘查表!AL35 -> 727500.38 | L32: =K32/$K$101 -> 0.046585197 | M32: =J32*L32 -> 0.15528399
A33: 31 | B33: =表1温室气体盘查表!C36 -> 石灰石生产 | C33: =表1温室气体盘查表!D36 -> 转炉 | D33: 定期量测/抄表/铭牌 | E33: 国际排放因子 | F33: 校准且合格 | G33: =IF(D33="自动连续量测",6,IF(D33="定期量测/抄表/铭牌",3,1)) -> 3 | H33: =IF(E33="量测/质量平衡排放因子",6,IF(E33="制程/设备排放因子",5,IF(E33="制造商提供的排放因子",4,IF(E33="区域排放因子",3,IF(E33="国家排放因子",2,1))))) -> 1 | I33: =IF(F33="校准且合格",6,IF(F33="未校准",1,3)) -> 6 | J33: =AVERAGE(G33:I33) -> 3.3333333 | K33: =表1温室气体盘查表!AL36 -> 58.676347 | L33: =K33/$K$101 -> 3.7573165e-06 | M33: =J33*L33 -> 1.2524388e-05
A34: 32 | B34: =表1温室气体盘查表!C37 -> 白云石生产 | C34: =表1温室气体盘查表!D37 -> 烧结、转炉、电炉 | D34: 定期量测/抄表/铭牌 | E34: 国际排放因子 | F34: 校准且合格 | G34: =IF(D34="自动连续量测",6,IF(D34="定期量测/抄表/铭牌",3,1)) -> 3 | H34: =IF(E34="量测/质量平衡排放因子",6,IF(E34="制程/设备排放因子",5,IF(E34="制造商提供的排放因子",4,IF(E34="区域排放因子",3,IF(E34="国家排放因子",2,1))))) -> 1 | I34: =IF(F34="校准且合格",6,IF(F34="未校准",1,3)) -> 6 | J34: =AVERAGE(G34:I34) -> 3.3333333 | K34: =表1温室气体盘查表!AL37 -> 46435.196 | L34: =K34/$K$101 -> 0.0029734593 | M34: =J34*L34 -> 0.009911531
A35: 33 | B35: =表1温室气体盘查表!C38 -> 轻烧白云石生产 | C35: =表1温室气体盘查表!D38 -> 转炉、电炉 | D35: 定期量测/抄表/铭牌 | E35: 国际排放因子 | F35: 校准且合格 | G35: =IF(D35="自动连续量测",6,IF(D35="定期量测/抄表/铭牌",3,1)) -> 3 | H35: =IF(E35="量测/质量平衡排放因子",6,IF(E35="制程/设备排放因子",5,IF(E35="制造商提供的排放因子",4,IF(E35="区域排放因子",3,IF(E35="国家排放因子",2,1))))) -> 1 | I35: =IF(F35="校准且合格",6,IF(F35="未校准",1,3)) -> 6 | J35: =AVERAGE(G35:I35) -> 3.3333333 | K35: =表1温室气体盘查表!AL38 -> 363.20886 | L35: =K35/$K$101 -> 2.3257934e-05 | M35: =J35*L35 -> 7.7526448e-05
A36: 34 | B36: =表1温室气体盘查表!C39 -> 球团生产 | C36: =表1温室气体盘查表!D39 -> 高炉、转炉 | D36: 定期量测/抄表/铭牌 | E36: 国际排放因子 | F36: 校准且合格 | G36: =IF(D36="自动连续量测",6,IF(D36="定期量测/抄表/铭牌",3,1)) -> 3 | H36: =IF(E36="量测/质量平衡排放因子",6,IF(E36="制程/设备排放因子",5,IF(E36="制造商提供的排放因子",4,IF(E36="区域排放因子",3,IF(E36="国家排放因子",2,1))))) -> 1 | I36: =IF(F36="校准且合格",6,IF(F36="未校准",1,3)) -> 6 | J36: =AVERAGE(G36:I36) -> 3.3333333 | K36: =表1温室气体盘查表!AL39 -> 71601.051 | L36: =K36/$K$101 -> 0.0045849448 | M36: =J36*L36 -> 0.015283149
A37: 35 | B37: =表1温室气体盘查表!C40 -> 废钢生产 | C37: =表1温室气体盘查表!D40 -> 转炉、电炉 | D37: 定期量测/抄表/铭牌 | E37: 国际排放因子 | F37: 校准且合格 | G37: =IF(D37="自动连续量测",6,IF(D37="定期量测/抄表/铭牌",3,1)) -> 3 | H37: =IF(E37="量测/质量平衡排放因子",6,IF(E37="制程/设备排放因子",5,IF(E37="制造商提供的排放因子",4,IF(E37="区域排放因子",3,IF(E37="国家排放因子",2,1))))) -> 1 | I37: =IF(F37="校准且合格",6,IF(F37="未校准",1,3)) -> 6 | J37: =AVERAGE(G37:I37) -> 3.3333333 | K37: =表1温室气体盘查表!AL40 -> 79944.388 | L37: =K37/$K$101 -> 0.005119207 | M37: =J37*L37 -> 0.017064023
A38: 36 | B38: =表1温室气体盘查表!C41 -> 电极生产 | C38: =表1温室气体盘查表!D41 -> 转炉、电炉 | D38: 定期量测/抄表/铭牌 | E38: 国际排放因子 | F38: 校准且合格 | G38: =IF(D38="自动连续量测",6,IF(D38="定期量测/抄表/铭牌",3,1)) -> 3 | H38: =IF(E38="量测/质量平衡排放因子",6,IF(E38="制程/设备排放因子",5,IF(E38="制造商提供的排放因子",4,IF(E38="区域排放因子",3,IF(E38="国家排放因子",2,1))))) -> 1 | I38: =IF(F38="校准且合格",6,IF(F38="未校准",1,3)) -> 6 | J38: =AVERAGE(G38:I38) -> 3.3333333 | K38: =表1温室气体盘查表!AL41 -> 37742.812 | L38: =K38/$K$101 -> 0.0024168459 | M38: =J38*L38 -> 0.0080561531
A39: 37 | B39: =表1温室气体盘查表!C42 -> 锰铁生产 | C39: =表1温室气体盘查表!D42 -> 转炉、电炉 | D39: 定期量测/抄表/铭牌 | E39: 国际排放因子 | F39: 校准且合格 | G39: =IF(D39="自动连续量测",6,IF(D39="定期量测/抄表/铭牌",3,1)) -> 3 | H39: =IF(E39="量测/质量平衡排放因子",6,IF(E39="制程/设备排放因子",5,IF(E39="制造商提供的排放因子",4,IF(E39="区域排放因子",3,IF(E39="国家排放因子",2,1))))) -> 1 | I39: =IF(F39="校准且合格",6,IF(F39="未校准",1,3)) -> 6 | J39: =AVERAGE(G39:I39) -> 3.3333333 | K39: =表1温室气体盘查表!AL42 -> 141868.58 | L39: =K39/$K$101 -> 0.0090844981 | M39: =J39*L39 -> 0.03028166
A40: 38 | B40: =表1温室气体盘查表!C43 -> 镍铁生产 | C40: =表1温室气体盘查表!D43 -> 转炉、电炉 | D40: 定期量测/抄表/铭牌 | E40: 国际排放因子 | F40: 校准且合格 | G40: =IF(D40="自动连续量测",6,IF(D40="定期量测/抄表/铭牌",3,1)) -> 3 | H40: =IF(E40="量测/质量平衡排放因子",6,IF(E40="制程/设备排放因子",5,IF(E40="制造商提供的排放因子",4,IF(E40="区域排放因子",3,IF(E40="国家排放因子",2,1))))) -> 1 | I40: =IF(F40="校准且合格",6,IF(F40="未校准",1,3)) -> 6 | J40: =AVERAGE(G40:I40) -> 3.3333333 | K40: =表1温室气体盘查表!AL43 -> 84819.123 | L40: =K40/$K$101 -> 0.0054313587 | M40: =J40*L40 -> 0.018104529
A41: 39 | B41: =表1温室气体盘查表!C44 -> 铬铁生产 | C41: =表1温室气体盘查表!D44 -> 转炉、电炉 | D41: 定期量测/抄表/铭牌 | E41: 国际排放因子 | F41: 校准且合格 | G41: =IF(D41="自动连续量测",6,IF(D41="定期量测/抄表/铭牌",3,1)) -> 3 | H41: =IF(E41="量测/质量平衡排放因子",6,IF(E41="制程/设备排放因子",5,IF(E41="制造商提供的排放因子",4,IF(E41="区域排放因子",3,IF(E41="国家排放因子",2,1))))) -> 1 | I41: =IF(F41="校准且合格",6,IF(F41="未校准",1,3)) -> 6 | J41: =AVERAGE(G41:I41) -> 3.3333333 | K41: =表1温室气体盘查表!AL44 -> 345101.44 | L41: =K41/$K$101 -> 0.022098434 | M41: =J41*L41 -> 0.073661445
... A100: 98 | B100: =表1温室气体盘查表!C103 -> 产品报废 | C100: =表1温室气体盘查表!D103 -> 下游钢铁厂 | D100: 自行推估 | E100: 国际排放因子 | F100: 校准但不合格/未校准但数据可查证 | G100: =IF(D100="自动连续量测",6,IF(D100="定期量测/抄表/铭牌",3,1)) -> 1 | H100: =IF(E100="量测/质量平衡排放因子",6,IF(E100="制程/设备排放因子",5,IF(E100="制造商提供的排放因子",4,IF(E100="区域排放因子",3,IF(E100="国家排放因子",2,1))))) -> 1 | I100: =IF(F100="校准且合格",6,IF(F100="未校准",1,3)) -> 3 | J100: =AVERAGE(G100:I100) -> 1.6666667 | K100: =表1温室气体盘查表!AL103 -> 3747.347 | L100: =K100/$K$101 -> 0.00023995987 | M100: =J100*L100 -> 0.00039993312
K101: =SUM(K3:K100) -> 15616557 | L101: 加权合计 | M101: =SUM(M3:M100) -> 3.7235896 | N101: uncertainty_score_market_based
L102: 加权等级 | M102: =IF(M101<2,"差",IF(M101<3,"一般",IF(M101<4,"良",IF(M101<5,"优","优+")))) -> 良 | N102: uncertainty_level_market_based
A112: 优+ | B112: >=5.0
A113: 优 | B113: <5.0,>=4.0
A114: 良 | B114: <4.0,>=3.0
A115: 一般 | B115: <3.0,>=2.0
A116: 差 | B116: <2.0

Sheet 附表1-GWP TABLE
B2: 工业名称 | C2: 中文名称/化学分子式 | D2: 组成比例（%） | E2: GWP | F2: GWP(HFCs) | G2: GWP(PFCs) | H2: 来源 | I2: 备注
B3: CO2 | C3: 二氧化碳 | E3: 1 | H3: 2021年IPCC第六次评估报告AR6
B4: CH4 | C4: 甲烷 | E4: 27.9 | H4: =H3 -> 2021年IPCC第六次评估报告AR6
B5: N2O | C5: 氧化亚氮 | E5: 273 | H5: =H3 -> 2021年IPCC第六次评估报告AR6
B6: HCFC-22 | C6: R-22，一氟二氯甲烷，CHCl2F | F6: 1960 | H6: =H$3 -> 2021年IPCC第六次评估报告AR6
B7: HFC-23 | C7: R-23，三氟甲烷，CHF3 | F7: 14600 | H7: =H$3 -> 2021年IPCC第六次评估报告AR6
B8: HFC-32 | C8: R-32，二氟甲烷，CH2F2 | F8: 771 | H8: =H$3 -> 2021年IPCC第六次评估报告AR6
B9: HFC-41 | C9: 一氟甲烷，CH3F | F9: 135 | H9: =H$3 -> 2021年IPCC第六次评估报告AR6
B10: HFC-125 | C10: R-125，1,1,1,2,2-五氟乙烷，C2HF5 | F10: 3740 | H10: =H$3 -> 2021年IPCC第六次评估报告AR6
B11: HFC-134 | C11: R-134，1,1,2,2-四氟乙烷，C2H2F4 | F11: 1260 | H11: =H$3 -> 2021年IPCC第六次评估报告AR6
B12: HFC-134a | C12: R-134a，1,1,1,2-四氟乙烷，C2H2F4 | F12: 1530 | H12: =H$3 -> 2021年IPCC第六次评估报告AR6
B13: HFC-143 | C13: R-143，1,1,2-三氟乙烷，CHF2CH2F | F13: 364 | H13: =H$3 -> 2021年IPCC第六次评估报告AR6
B14: HFC-143a | C14: R-143a，1,1,1-三氟乙烷，C2H3F3 | F14: 5810 | H14: =H$3 -> 2021年IPCC第六次评估报告AR6
B15: HFC-152 | C15: R-152，1,2-二氟乙烷，CH2FCH2F | F15: 21.5 | H15: =H$3 -> 2021年IPCC第六次评估报告AR6
B16: HFC-152a | C16: R-152a，1,1-二氟乙烷，C2H4F2 | F16: 164 | H16: =H$3 -> 2021年IPCC第六次评估报告AR6
B17: HFC-161 | C17: R-161，一氟乙烷，CH3CH2F | F17: 4.84 | H17: =H$3 -> 2021年IPCC第六次评估报告AR6
... B25: HFC-43-10mee | C25: R-43-10mee，1,1,1,2,2,3,4,5,5,5-十氟戊烷，CF3CHFCHFCF2CF3 | F25: 1600 | H25: =H$3 -> 2021年IPCC第六次评估报告AR6
B26: R401A | D26: R22/152a/R124（53/13/34） | F26: =F16*13% -> 21.32 | H26: =H$3 -> 2021年IPCC第六次评估报告AR6 | I26: 只考虑了R152a
B27: R401B | D27: R22/152a/R124（61/11/28） | F27: =F16*11% -> 18.04 | H27: =H$3 -> 2021年IPCC第六次评估报告AR6 | I27: 只考虑了R152a
B28: R404A | D28: R125/143a/R134a（44/52/4） | F28: =F10*44%+F14*52%+F12*4% -> 4728 | H28: =H$3 -> 2021年IPCC第六次评估报告AR6
B29: R407A | D29: R32/R125/R134a（20/40/40） | F29: =F8*20%+F10*40%+F12*40% -> 2262.2 | H29: =H$3 -> 2021年IPCC第六次评估报告AR6
B30: R407B | D30: R32/R125/R134a（10/70/20） | F30: =F8*10%+F10*70%+F12*20% -> 3001.1 | H30: =H$3 -> 2021年IPCC第六次评估报告AR6
B31: R407C | D31: R32/R125/R134a（23/25/52） | F31: =F8*23%+F10*25%+F12*52% -> 1907.93 | H31: =H$3 -> 2021年IPCC第六次评估报告AR6
B32: R408A | D32: R125/R143a/R22（7/46/47） | F32: =F10*7%+F14*46% -> 2934.4 | H32: =H$3 -> 2021年IPCC第六次评估报告AR6 | I32: 未考虑R22
B33: R410A | D33: R32/R125（50/50） | F33: =F8*50%+F10*50% -> 2255.5 | H33: =H$3 -> 2021年IPCC第六次评估报告AR6
B34: R413A | D34: R218/R134a/R600a(9/88/3） | F34: =G42*9%+F12*88%+0 -> 2182.5 | H34: =H$3 -> 2021年IPCC第六次评估报告AR6
B35: R417A | D35: R125/R134a/R600a(46.6/50/3.4) | F35: =F10*46.6%+F12*50%+0 -> 2507.84 | H35: =H$3 -> 2021年IPCC第六次评估报告AR6
B36: R503 | D36: R23/R13（40.1/59.9） | F36: =F7*40.1% -> 5854.6 | H36: =H$3 -> 2021年IPCC第六次评估报告AR6 | I36: 只考虑了R23,未考虑R13
B37: R507A | D37: R125/R143a（50.0/50.0） | F37: =F10*50%+F14*50% -> 4775 | H37: =H$3 -> 2021年IPCC第六次评估报告AR6
B38: R508A | D38: R23/R116（39.0/61.0） | F38: =F7*39%+G40*61% -> 13258 | H38: =H$3 -> 2021年IPCC第六次评估报告AR6
B39: R508B | D39: R23/R116（46.0/54.0） | F39: =F7*46%+G40*54% -> 13412 | H39: =H$3 -> 2021年IPCC第六次评估报告AR6
B40: PFC-116 | C40: R-116，六氟乙烷，C2F6 | G40: 12400 | H40: =H$3 -> 2021年IPCC第六次评估报告AR6
B41: PFC-14 | C41: R-14，四氟化碳，CF4 | G41: 7380 | H41: =H$3 -> 2021年IPCC第六次评估报告AR6
B42: PFC-218 | C42: C3F8，全氟丙烷 | G42: 9290 | H42: =H$3 -> 2021年IPCC第六次评估报告AR6
B43: PFC-318 | C43: c-C4F8，八氟环丁烷 | G43: 10200 | H43: =H$3 -> 2021年IPCC第六次评估报告AR6
B44: PFC-31-10 | C44: C4F10，全氟丁烷 | G44: 10000 | H44: =H$3 -> 2021年IPCC第六次评估报告AR6
B45: PFC-41-12 | C45: C5F12，全氟戊烷 | G45: 9220 | H45: =H$3 -> 2021年IPCC第六次评估报告AR6
B46: PFC-51-14 | C46: C6F14，全氟己烷 | G46: 8620 | H46: =H$3 -> 2021年IPCC第六次评估报告AR6
B47: NF3 | C47: 三氟化氮 | E47: 17400 | H47: =H3 -> 2021年IPCC第六次评估报告AR6
B48: SF6 | C48: 六氟化硫 | E48: 24300 | H48: =H3 -> 2021年IPCC第六次评估报告AR6

Sheet 附表2-EF
B2: 编号 | C2: GHG排放类别 | D2: 排放源 | E2: 设施 | F2: 低位发热量 | G2: 单位 | H2: 氧化率 | I2: 基于热值排放系数，t GHG/GJ | L2: 排放因子，t GHG/10000m³
I3: IPCC-2006缺省值 | L3: 计算值
F4: 企业温室气体排放核算与报告指南 钢铁行业 | H4: 企业温室气体排放核算与报告指南 钢铁行业 | I4: CO2 | J4: CH4 | K4: N2O | L4: CO2 | M4: CH4 | N4: N2O
B5: 1 | C5: 范围一 固定燃烧排放 | D5: 天然气燃烧 | E5: 热处理炉 | F5: 389.31 | G5: GJ/104Nm3 | H5: 0.99 | I5: =56100/10^6 -> 0.0561 | J5: =1/10^6 -> 1e-06 | K5: =0.1/10^6 -> 1e-07 | L5: =F5*H5*I5 -> 21.621888 | M5: =F5*H5*J5 -> 0.0003854169 | N5: =F5*H5*K5 -> 3.854169e-05
B6: 2 | C6: 范围一 固定燃烧排放 | D6: 液化石油气燃烧 | E6: 冶钢宾馆 | F6: 50.179 | G6: GJ/t | H6: 0.98 | I6: =63100/10^6 -> 0.0631 | J6: =1/10^6 -> 1e-06 | K6: =0.1/10^6 -> 1e-07 | L6: =F6*H6*I6 -> 3.102969 | M6: =F6*H6*J6 -> 4.917542e-05 | N6: =F6*H6*K6 -> 4.917542e-06
B7: 3 | C7: 范围一 固定燃烧排放 | D7: 烟煤燃烧 | E7: 高炉 | F7: 23.736 | G7: GJ/t | H7: 0.99 | I7: =98300/10^6 -> 0.0983 | J7: =1/10^6 -> 1e-06 | K7: =1.5/10^6 -> 1.5e-06 | L7: =F7*H7*I7 -> 2.3099163 | M7: =F7*H7*J7 -> 2.349864e-05 | N7: =F7*H7*K7 -> 3.524796e-05
B8: 4 | C8: 范围一 固定燃烧排放 | D8: 无烟煤燃烧 | E8: 高炉 | F8: 25.024 | G8: GJ/t | H8: 0.99 | I8: =98300/10^6 -> 0.0983 | J8: =1/10^6 -> 1e-06 | K8: =1.5/10^6 -> 1.5e-06 | L8: =F8*H8*I8 -> 2.4352606 | M8: =F8*H8*J8 -> 2.477376e-05 | N8: =F8*H8*K8 -> 3.716064e-05
B9: 5 | C9: 范围一 固定燃烧排放 | D9: 洗精煤燃烧 | E9: 焦炉 | F9: 26.344 | G9: GJ/t | H9: 0.99 | I9: =94600/10^6 -> 0.0946 | J9: =1/10^6 -> 1e-06 | K9: =1.5/10^6 -> 1.5e-06 | L9: =F9*H9*I9 -> 2.467221 | M9: =F9*H9*J9 -> 2.608056e-05 | N9: =F9*H9*K9 -> 3.912084e-05
B10: 6 | C10: 范围一 固定燃烧排放 | D10: 焦炭/焦屑/焦丁燃烧 | E10: 焦炉 | F10: 28.435 | G10: GJ/t | H10: 0.99 | I10: =107000/10^6 -> 0.107 | J10: =1/10^6 -> 1e-06 | K10: =1.5/10^6 -> 1.5e-06 | L10: =F10*H10*I10 -> 3.0121195 | M10: =F10*H10*J10 -> 2.815065e-05 | N10: =F10*H10*K10 -> 4.2225975e-05
B11: 7 | C11: 范围一 固定燃烧排放 | D11: 焦炉煤气燃烧 | E11: 外售 | F11: 173.854 | G11: GJ/104Nm3 | H11: 0.99 | I11: =44400/10^6 -> 0.0444 | J11: =1/10^6 -> 1e-06 | K11: =0.1/10^6 -> 1e-07 | L11: =F11*H11*I11 -> 7.6419264 | M11: =F11*H11*J11 -> 0.00017211546 | N11: =F11*H11*K11 -> 1.7211546e-05
B12: 8 | C12: 范围一 移动燃烧排放 | D12: 柴油燃烧 | E12: 火车/货车 | F12: 42.652 | G12: GJ/t | H12: 0.98 | I12: 0.0741 | J12: =0.0039/10^3 -> 3.9e-06 | K12: =0.0039/10^3 -> 3.9e-06 | L12: =$F$12*$H$12*I12 -> 3.0973029 | M12: =$F$12*$H$12*J12 -> 0.00016301594 | N12: =$F$12*$H$12*K12 -> 0.00016301594
B13: 9 | C13: 范围一 移动燃烧排放 | D13: 汽油燃烧 | E13: 公务车 | F13: 43.07 | G13: GJ/t | H13: 0.98 | I13: 0.0693 | J13: =0.025/10^3 -> 2.5e-05 | K13: =0.008/10^3 -> 8e-06 | L13: =$F$13*$H$13*I13 -> 2.925056 | M13: =$F$13*$H$13*J13 -> 0.001055215 | N13: =$F$13*$H$13*K13 -> 0.0003376688
B15: 编号 | C15: GHG排放类别 | D15: 排放源 | E15: 设施 | F15: CO2排放因子 | G15: 单位
F16: 企业温室气体排放核算与报告指南 钢铁行业
B17: 1 | C17: 范围一 制程排放 | D17: 粗苯 | E17: 外售 | F17: 3.382 | G17: tCO2/t
B18: 2 | C18: 范围一 制程排放 | D18: 煤焦油 | E18: 外售 | F18: 2.699 | G18: tCO2/t
B19: 3 | C19: 范围一 制程排放 | D19: 石灰石 | E19: 石灰窑 | F19: 0.44 | G19: tCO2/t
B20: 4 | C20: 范围一 制程排放 | D20: 白云石 | E20: 高炉 | F20: 0.476 | G20: tCO2/t
B21: 5 | C21: 范围一 制程排放 | D21: 电极 | E21: 炼钢 | F21: 3.663 | G21: tCO2/t
B22: 6 | C22: 范围一 制程排放 | D22: 镍铁合金 | E22: 炼钢 | F22: 0.037 | G22: tCO2/t
B23: 7 | C23: 范围一 制程排放 | D23: 铬铁合金 | E23: 炼钢 | F23: 0.348 | G23: tCO2/t
B24: 8 | C24: 范围一 制程排放 | D24: 钼铁合金 | E24: 炼钢 | F24: 0.018 | G24: tCO2/t
B25: 9 | C25: 范围一 制程排放 | D25: 硅铁合金 | E25: 炼钢 | F25: 0.007 | G25: tCO2/t
B26: 10 | C26: 范围一 制程排放 | D26: 锰铁合金 | E26: 炼钢 | F26: 0.275 | G26: tCO2/t
B27: 11 | C27: 范围一 制程排放 | D27: 废钢 | E27: 炼钢 | F27: 0.037 | G27: tCO2/t
B28: 12 | C28: 范围一 制程排放 | D28: 粗钢 | E28: 固碳产品 | F28: 0.037 | G28: tCO2/t
B31: 编号 | C31: GHG排放类别 | D31: 排放源 | E31: 设施 | F31: HFCs/PFCs | H31: MCF | I31: Bo | J31: 排放因子 | K31: 单位 | L31: 排放因子引用源
F32: EF估计值 | G32: 单位
B33: 1 | C33: 范围一 逸散排放 | D33: SF6逸散 | E33: 高压开关 | F33: 0.005 | G33: kgSF6/kg | L33: GB/T8905-2008 六氟化硫电气设备中气体管理和检测导则9.3
B34: 2 | C34: 范围一 逸散排放 | D34: CO2逸散 | E34: 二氧化碳灭火器 | F34: 1 | G34: kgCO2/kg | L34: 质量平衡
B35: 3 | C35: 范围一 逸散排放 | D35: 制冷剂逸散（R32） | E35: 分体式空调 | F35: 1 | G35: kgGHG/kg | L35: 质量平衡
B36: 4 | C36: 范围一 逸散排放 | D36: CH4逸散 | E36: 化粪池 | H36: 0.3 | I36: 0.6 | J36: =H36*I36 -> 0.18 | K36: kgCH4/kgBOD | L36: 2006年IPCC国家温室气体清单指南V5_6_Ch6 Table6.2/6.3;公式6.1/6.2
B37: 5 | C37: 范围一 逸散排放 | D37: CH4逸散 | E37: 厌氧池 | H37: 0.3 | I37: 0.25 | J37: =H37*I37 -> 0.075 | K37: kgCH4/kgCOD | L37: 2006年IPCC国家温室气体清单指南V5_6_Ch6 Table6.2/6.3;公式6.1/6.2
B38: 6 | C38: 范围一 逸散排放 | D38: CH4逸散 | E38: 厌氧池、厕所、下水道等 | J38: 40 | K38: gBOD/人·天 | L38: 2006年IPCC国家温室气体清单指南V5_6_Ch6 Table 6.4;公式6.3
B40: 编号 | C40: GHG排放类别 | D40: 排放源 | E40: 设施 | F40: EF | G40: 单位 | H40: 排放因子引用源
B41: 1 | C41: 范围二 外购能源间接排放 | D41: 电力 | E41: 用电设备 | F41: 0.5366 | G41: tCO2/MWh | H41: 生态环境部、国家能源局发布2022年电力二氧化碳排放因子的公告（2022年全国电力排放因子）
B42: 2 | C42: 范围二 外购能源间接排放 | D42: 电力 | E42: 用电设备 | F42: 0.5856 | G42: tCO2/MWh | H42: 生态环境部、国家能源局发布2022年电力二氧化碳排放因子的公告（2022年全国电力平均二氧化碳排放因子（不包括市场化交易的非化石能源电量））
B44: 编号 | C44: GHG排放类别 | D44: 排放源 | E44: Activity name | F44: Geography | G44: CO2 | I44: 引用源
G45: 排放因子 | H45: 单位 | I45: 缺省排放因子
B46: 1 | C46: 范围三 类别1 外购商品和服务的上游排放 | D46: =表1温室气体盘查表!C34 -> 铁矿石生产 | E46: marker for Iron ore,crude ore,63% Fe | F46: Global (GLO) | G46: 0.098847 | H46: tCO2/t | I46: ecoinvent 3.10-cut off
B47: 2 | C47: 范围三 类别1 外购商品和服务的上游排放 | D47: =表1温室气体盘查表!C35 -> 生石灰生产 | E47: market for quicklime, in pieces, loose | F47: Rest-of-World (RoW) | G47: 1.1896699 | H47: tCO2/t | I47: ecoinvent 3.10-cut off
B48: 3 | C48: 范围三 类别1 外购商品和服务的上游排放 | D48: =表1温室气体盘查表!C36 -> 石灰石生产 | E48: market for limestone, crushed, for mill | F48: Rest-of-World (RoW) | G48: 0.0030299 | H48: tCO2/t | I48: ecoinvent 3.10-cut off
B49: 4 | C49: 范围三 类别1 外购商品和服务的上游排放 | D49: =表1温室气体盘查表!C37 -> 白云石生产 | E49: marker for dolomite | F49: Rest-of-World (RoW) | G49: 0.13033 | H49: tCO2/t | I49: ecoinvent 3.10-cut off
B50: 5 | C50: 范围三 类别1 外购商品和服务的上游排放 | D50: =表1温室气体盘查表!C39 -> 球团生产 | E50: market for iron pellet | F50: Global (GLO) | G50: 0.10446 | H50: tCO2/t | I50: ecoinvent 3.10-cut off
B51: 6 | C51: 范围三 类别1 外购商品和服务的上游排放 | D51: =表1温室气体盘查表!C40 -> 废钢生产 | E51: market for waste reinforcement steel | F51: Rest-of-World (RoW) | G51: 0.074179 | H51: tCO2/t | I51: ecoinvent 3.10-cut off
B52: 7 | C52: 范围三 类别1 外购商品和服务的上游排放 | D52: =表1温室气体盘查表!C41 -> 电极生产 | E52: market for electrode, negative, LiC6 | F52: Global (GLO) | G52: 8.4370514 | H52: tCO2/t | I52: ecoinvent 3.10-cut off
B53: 8 | C53: 范围三 类别1 外购商品和服务的上游排放 | D53: =表1温室气体盘查表!C42 -> 锰铁生产 | E53: market for ferromanganese,high-coal,74.5% Mn | F53: Global (GLO) | G53: 2.9772 | H53: tCO2/t | I53: ecoinvent 3.10-cut off
B54: 9 | C54: 范围三 类别1 外购商品和服务的上游排放 | D54: =表1温室气体盘查表!C43 -> 镍铁生产 | E54: market for ferronickel | F54: Global (GLO) | G54: 8.7547 | H54: tCO2/t | I54: ecoinvent 3.10-cut off
B55: 10 | C55: 范围三 类别1 外购商品和服务的上游排放 | D55: =表1温室气体盘查表!C44 -> 铬铁生产 | E55: market for ferrochromium,high-carbom.55% Cr | F55: Global (GLO) | G55: 5.0921 | H55: tCO2/t | I55: ecoinvent 3.10-cut off
B56: 11 | C56: 范围三 类别1 外购商品和服务的上游排放 | D56: =表1温室气体盘查表!C45 -> 萤石生产 | E56: market for fluorspar, 97% purity | F56: Global (GLO) | G56: 0.21158 | H56: tCO2/t | I56: ecoinvent 3.10-cut off
B57: 12 | C57: 范围三 类别1 外购商品和服务的上游排放 | D57: =表1温室气体盘查表!C46 -> 硅铁生产 | E57: ferrosilicon production | F57: China (CN) | G57: 10.145 | H57: tCO2/t | I57: ecoinvent 3.10-cut off
B58: 13 | C58: 范围三 类别1 外购商品和服务的上游排放 | D58: =表1温室气体盘查表!C47 -> 钼铁生产 | E58: Ferro-Molybdenum | G58: 8.5 | H58: tCO2/t | I58: CO2 data collection user guide, version 11, WSA
B59: 14 | C59: 范围三 类别1 外购商品和服务的上游排放 | D59: =表1温室气体盘查表!C48 -> 铝铁生产 | E59: market for aluminium,cast alloy | F59: global warming potential (GWP100) | G59: 5.7320082 | H59: tCO2/t | I59: ecoinvent 3.10-cut off
B60: 15 | C60: 范围三 类别1 外购商品和服务的上游排放 | D60: =表1温室气体盘查表!C49 -> 铝生产 | E60: market for aluminium,primary,ingot | F60: Rest-of-World (RoW) | G60: 22.290561 | H60: tCO2/t | I60: ecoinvent 3.10-cut off
B61: 16 | C61: 范围三 类别1 外购商品和服务的上游排放 | D61: =表1温室气体盘查表!C50 -> 增碳剂生产 | E61: market for recarburizer | F61: China (CN) | G61: 1.6645335 | H61: tCO2/t | I61: ecoinvent 3.11-cut off
B62: 17 | C62: 范围三 类别1 外购商品和服务的上游排放 | D62: =表1温室气体盘查表!C51 -> 铁鳞生产 | E62: market for iron scrap, unsorted | F62: Global (GLO) | G62: 0.0035231057 | H62: tCO2/t | I62: ecoinvent 3.10-cut off
B63: 18 | C63: 范围三 类别1 外购商品和服务的上游排放 | D63: =表1温室气体盘查表!C52 -> 氨水生产 | E63: market for ammonia, anhydrous, liquid | F63: China (CN) | G63: 5.4368448 | H63: tCO2/t | I63: ecoinvent 3.10-cut off
B64: 19 | C64: 范围三 类别1 外购商品和服务的上游排放 | D64: =表1温室气体盘查表!C53 -> 碳化硅生产 | E64: market for silicon carbide | F64: Global (GLO) | G64: 7.2790711 | H64: tCO2/t | I64: ecoinvent 3.10-cut off
B65: 20 | C65: 范围三 类别1 外购商品和服务的上游排放 | D65: =表1温室气体盘查表!C54 -> 镁生产 | E65: market for magnesium | F65: Global (GLO) | G65: 26.345188 | H65: tCO2/t | I65: ecoinvent 3.10-cut off
B66: 21 | C66: 范围三 类别1 外购商品和服务的上游排放 | D66: 所有其他纸制品加工制造 | E66: All Other Converted Paper Product Manufacturing | G66: 0.000343 | H66: t CO2e/2022 USD, purchaser price | I66: SupplyChainGHGEmissionFactors_v1.3.0_NAICS_CO2e_USD2022
B67: 22 | C67: 范围三 类别1 外购商品和服务的上游排放 | D67: =表1温室气体盘查表!C56 -> 办公用品(纸张除外)制造 | E67: Office Supplies (except Paper) Manufacturing | G67: 0.000265 | H67: t CO2e/2022 USD, purchaser price | I67: SupplyChainGHGEmissionFactors_v1.3.0_NAICS_CO2e_USD2022
B68: 23 | C68: 范围三 类别1 外购商品和服务的上游排放 | D68: =表1温室气体盘查表!C57 -> 源水 | E68: market for tap water | F68: Rest-of-World (RoW) | G68: 0.0012784698 | H68: tCO2/t | I68: ecoinvent 3.10-cut off
B71: 编号 | C71: GHG排放类别 | D71: 排放源 | E71: Activity name | F71: CO2 | H71: 引用源
F72: 排放因子 | G72: 单位 | H72: 缺省排放因子
B73: 1 | C73: 范围三 类别2 资本货物 | D73: =表1温室气体盘查表!C58 -> 采购产品空调和暖空气加热设备和商业和工业制冷设备制造 | E73: Warm Air Heating and Air-Conditioning Equipment and Supplies Merchant Wholesalers | F73: =0.108/1000 -> 0.000108 | G73: t CO2e/2022 USD, purchaser price | H73: SupplyChainGHGEmissionFactors_v1.3.0_NAICS_CO2e_USD2022
B74: 2 | C74: 范围三 类别2 资本货物 | D74: =表1温室气体盘查表!C59 -> 电子计算机制造 | E74: Electronic Computer Manufacturing | F74: =0.058/1000 -> 5.8e-05 | G74: t CO2e/2022 USD, purchaser price | H74: SupplyChainGHGEmissionFactors_v1.3.0_NAICS_CO2e_USD2022
B75: 3 | C75: 范围三 类别2 资本货物 | D75: =表1温室气体盘查表!C60 -> 焊接及焊接设备制造 | E75: Welding and Soldering Equipment Manufacturing | F75: =0.249/1000 -> 0.000249 | G75: t CO2e/2022 USD, purchaser price | H75: SupplyChainGHGEmissionFactors_v1.3.0_NAICS_CO2e_USD2022
B76: 4 | C76: 范围三 类别2 资本货物 | D76: =表1温室气体盘查表!C61 -> 其他工业设备制造 | E76: Other Industrial Machinery Manufacturing | F76: =0.185/1000 -> 0.000185 | G76: t CO2e/2022 USD, purchaser price | H76: SupplyChainGHGEmissionFactors_v1.3.0_NAICS_CO2e_USD2022
B77: 5 | C77: 范围三 类别2 资本货物 | D77: =表1温室气体盘查表!C62 -> 测量和测试电力和电气信号的仪器制造 | E77: Instrument Manufacturing for Measuring and Testing Electricity and Electrical Signals | F77: =0.079/1000 -> 7.9e-05 | G77: t CO2e/2022 USD, purchaser price | H77: SupplyChainGHGEmissionFactors_v1.3.0_NAICS_CO2e_USD2022
B78: 6 | C78: 范围三 类别2 资本货物 | D78: =表1温室气体盘查表!C63 -> 计算机系统设计服务 | E78: Computer Systems Design Services | F78: =0.089/1000 -> 8.9e-05 | G78: t CO2e/2022 USD, purchaser price | H78: SupplyChainGHGEmissionFactors_v1.3.0_NAICS_CO2e_USD2022
B79: 7 | C79: 范围三 类别2 资本货物 | D79: 机械动力传动设备制造 | E79: Mechanical Power Transmission Equipment Manufacturing | F79: =0.209/1000 -> 0.000209 | G79: t CO2e/2022 USD, purchaser price | H79: SupplyChainGHGEmissionFactors_v1.3.0_NAICS_CO2e_USD2022
B80: 8 | C80: 范围三 类别2 资本货物 | D80: 测量、分配及其他泵类设备制造 | E80: Measuring, Dispensing, and Other Pumping Equipment Manufacturing | F80: =0.223/1000 -> 0.000223 | G80: t CO2e/2022 USD, purchaser price | H80: SupplyChainGHGEmissionFactors_v1.3.0_NAICS_CO2e_USD2022
B81: 9 | C81: 范围三 类别2 资本货物 | D81: 用于测量、显示和控制工业过程变量的仪器及相关产品制造 | E81: Instruments and Related Products Manufacturing for Measuring, Displaying, and Controlling Industrial Process Variables | F81: =0.063/1000 -> 6.3e-05 | G81: t CO2e/2022 USD, purchaser price | H81: SupplyChainGHGEmissionFactors_v1.3.0_NAICS_CO2e_USD2022
B82: 10 | C82: 范围三 类别2 资本货物 | D82: =表1温室气体盘查表!C67 -> 所有其他杂项电气设备及元件制造 | E82: All Other Miscellaneous Electrical Equipment and Component Manufacturing | F82: =0.128/1000 -> 0.000128 | G82: t CO2e/2022 USD, purchaser price | H82: SupplyChainGHGEmissionFactors_v1.3.0_NAICS_CO2e_USD2022
B83: 11 | C83: 范围三 类别2 资本货物 | D83: =表1温室气体盘查表!C68 -> 所有其他杂项制造 | E83: All Other Miscellaneous Manufacturing | F83: =0.182/1000 -> 0.000182 | G83: t CO2e/2022 USD, purchaser price | H83: SupplyChainGHGEmissionFactors_v1.3.0_NAICS_CO2e_USD2022
B85: 编号 | C85: GHG排放类别 | D85: 排放源 | E85: Activity name | F85: Geography | G85: CO2 | I85: 引用源
G86: 排放因子 | H86: 单位 | I86: 缺省排放因子
B87: 1 | C87: 范围三 类别3 范围一、二之外燃料和能源相关的活动产生的排放 | D87: =表1温室气体盘查表!C69 -> 液化石油气生产 | E87: market for liquefied petroleum gas | F87: Rest-of-World (RoW) | G87: 1.0062256 | H87: tCO2/t | I87: ecoinvent 3.10-cut off
B88: 1 | C88: 范围三 类别3 范围一、二之外燃料和能源相关的活动产生的排放 | D88: =表1温室气体盘查表!C70 -> 洗精煤生产 | E88: market for hard coal | F88: China (CN) | G88: 0.57555 | H88: tCO2/t | I88: ecoinvent 3.10-cut off
B89: 2 | C89: 范围三 类别3 范围一、二之外燃料和能源相关的活动产生的排放 | D89: =表1温室气体盘查表!C71 -> 柴油生产 | E89: market for diesel | F89: Rest-of-World (RoW) | G89: 0.84212 | H89: tCO2/t | I89: ecoinvent 3.10-cut off
B90: 3 | C90: 范围三 类别3 范围一、二之外燃料和能源相关的活动产生的排放 | D90: =表1温室气体盘查表!C72 -> 汽油生产 | E90: market for petrol, unleaded | F90: Rest-of-World (RoW) | G90: 0.98733031 | H90: tCO2/t | I90: ecoinvent 3.10-cut off
B91: 4 | C91: 范围三 类别3 范围一、二之外燃料和能源相关的活动产生的排放 | D91: =表1温室气体盘查表!C73 -> 焦炭生产 | E91: market for coke | F91: China (CN) | G91: 1.2676 | H91: tCO2/t | I91: ecoinvent 3.10-cut off
B92: 5 | C92: 范围三 类别3 范围一、二之外燃料和能源相关的活动产生的排放 | D92: =表1温室气体盘查表!C74 -> 焦屑生产 | E92: market for coke | F92: China (CN) | G92: 1.2676 | H92: tCO2/t | I92: ecoinvent 3.10-cut off
B93: 6 | C93: 范围三 类别3 范围一、二之外燃料和能源相关的活动产生的排放 | D93: =表1温室气体盘查表!C75 -> 烟煤生产 | E93: market for hard coal | F93: China (CN) | G93: 0.57555 | H93: tCO2/t | I93: ecoinvent 3.10-cut off
B94: 7 | C94: 范围三 类别3 范围一、二之外燃料和能源相关的活动产生的排放 | D94: =表1温室气体盘查表!C76 -> 无烟煤生产 | E94: market for hard coal | F94: China (CN) | G94: 0.57555 | H94: tCO2/t | I94: ecoinvent 3.10-cut off
B95: 8 | C95: 范围三 类别3 范围一、二之外燃料和能源相关的活动产生的排放 | D95: =表1温室气体盘查表!C77 -> 天然气生产 | E95: market for natural gas, high pressure | F95: China (CN) | G95: 6.19 | H95: tCO2/10000Nm³ | I95: ecoinvent 3.10-cut off
B96: 9 | C96: 范围三 类别3 范围一、二之外燃料和能源相关的活动产生的排放 | D96: =表1温室气体盘查表!C78 -> 外购电力上游排放 | F96: China (CN) | G96: =0.6205-0.5366 -> 0.0839 | H96: tCO2/MWh | I96: 2023年全国电力平均碳足迹因子、2022年全国电力平均排放因子
B98: 编号 | C98: GHG排放类别 | D98: 排放源 | E98: Activity name | F98: Geography | G98: CO2 | I98: 引用源
G99: 排放因子 | H99: 单位 | I99: 缺省排放因子
B100: 1 | C100: 范围三 类别4 上下游运输配送产生的排放 | D100: 船运 | E100: market for transport, freight, inland waterways, barge | F100: Rest-of-World (RoW) | G100: 5.1968558e-05 | H100: tCO2-Eq/tkm | I100: ecoinvent 3.10-cut off
B101: 2 | C101: 范围三 类别4 上下游运输配送产生的排放 | D101: 汽运 | E101: market group for transport, freight, lorry, unspecified | F101: Global (GLO) | G101: 0.00015196288 | H101: tCO2-Eq/tkm | I101: ecoinvent 3.10-cut off
B102: 3 | C102: 范围三 类别4 上下游运输配送产生的排放 | D102: 铁路运输 | E102: market for transport, freight train | F102: China (CN) | G102: 4.8531851e-05 | H102: tCO2-Eq/tkm | I102: ecoinvent 3.10-cut off
B104: 编号 | C104: GHG排放类别 | D104: 排放源 | E104: Activity name | F104: Geography | G104: CO2 | I104: 引用源
G105: 排放因子 | H105: 单位 | I105: 缺省排放因子
B106: 1 | C106: 范围三 类别5 运营中产生的废物排放 | D106: 生活垃圾处理站 | E106: market for average incineration residue | F106: Rest-of-World (RoW) | G106: 0.3713343 | H106: tCO2/t | I106: ecoinvent 3.10-cut off
B107: 2 | C107: 范围三 类别5 运营中产生的废物排放 | D107: 废油 | E107: treatment of waste mineral oil, hazardous waste incineration | F107: Rest-of-World (RoW) | G107: 2.849057 | H107: tCO2/t | I107: ecoinvent 3.10-cut off
B108: 3 | C108: 范围三 类别5 运营中产生的废物排放 | D108: 废油水 | E108: treatment of waste mineral oil, hazardous waste incineration | F108: Rest-of-World (RoW) | G108: 2.849057 | H108: tCO2/t | I108: ecoinvent 3.10-cut off
B109: 4 | C109: 范围三 类别5 运营中产生的废物排放 | D109: 煤焦油 | E109: treatment of hazardous waste, hazardous waste incineration | F109: Rest-of-World (RoW) | G109: 2.5237125 | H109: tCO2/t | I109: ecoinvent 3.10-cut off
B111: 编号 | C111: GHG排放类别 | D111: 排放源 | E111: Activity name | F111: Geography | G111: CO2 | I111: 引用源
G112: 排放因子 | H112: 单位 | I112: 缺省排放因子
...

Sheet 减排行动统计
B2: 2024年已实施的节能减排措施
B3: 序号 | C3: 节能实施方案名称 | D3: 方案具体描述 | E3: 责任部门 | F3: 项目实施进度概况 | G3: 节能量预估 | I3: 序号 | J3: 节能实施方案名称 | K3: 方案具体描述 | L3: 责任部门 | M3: 项目实施进度概况 | N3: 节能量预估
B4: 1 | C4: 节电 | D4: 通过选择经济购电套餐、错峰用电、降低计费容量等方式，2024年外购电价同比去年下降0.0784元/kWh（含年度交易电价下降0.0330元/kWh），减少外购电费13263万元，全年减少外购电费15560万元。 | E4: 能源环保部 | F4: 已完成 | G4: 预计全年减少外购电3800万kWh | I4: {%tr for item in implemented_reduction_items %}
B5: 2 | C5: 减少天然气外购 | D5: 推进焦气替代天然气项目，减少天然气外购，降低燃气成本。 | E5: 能源环保部 | F5: 已完成 | G5: 预计全年减少采购费用2000万元 | I5: {{loop.index}} | J5: {{item.plan_name}} | K5: {{item.description}} | L5: {{item.department}} | M5: {{item.progress}} | N5: {{item.estimated_savings}}
B6: 3 | C6: 提升回收转炉煤气量 | D6: 通过改善回收条件、风机提频、管道清灰等措施提升转炉煤气回收量。 | E6: 能源环保部 | F6: 已完成 | G6: 预计全年创效1020万元 | I6: {%tr endfor %}
B7: 4 | C7: 管理类节能 | D7: 氩气提产降耗、提升转炉煤气回收等。 | E7: 能源环保部 | F7: 已完成 | G7: 吨钢氩气消耗量较去年下降1.3m³/t，转炉煤气回收较去年月均提高16.52m³/t
B9: 2025年计划实施的节能减排措施
B10: 序号 | C10: 节能实施方案名称 | D10: 方案具体描述 | E10: 责任部门 | F10: 项目实施进度概况 | G10: 节能量预估 | I10: 序号 | J10: 节能实施方案名称 | K10: 方案具体描述 | L10: 责任部门 | M10: 项目实施进度概况 | N10: 节能量预估
B11: 1 | C11: 提升绿电消耗量 | D11: 增加自建光伏发电面积，加大外购绿电消耗量 | E11: 能源环保部 | F11: 实施中 | G11: 实现建筑物可利用面积光伏利用率≥90%，力争外购绿电消耗占比达10% | I11: {%tr for item in planned_reduction_items %}
B12: 2 | C12: 提升焦炉煤气外送量 | D12: 按预定计划完成外供逸洋制管能源介质项目 | E12: 能源环保部 | F12: 实施中 | G12: 计划全年外供煤气1800万m³，减少碳排放1.37万吨 | I12: {{loop.index}} | J12: {{item.plan_name}} | K12: {{item.description}} | L12: {{item.department}} | M12: {{item.progress}} | N12: {{item.estimated_savings}}
I13: {%tr endfor %}

Sheet 活动数据汇总表（GHG基于位置）
A1: 各排放源明细
A2: 编号 | B2: GHG排放类别 | C2: 排放源 | D2: 报告边界 | E2: 活动数据 | G2: 排放因子&系数 | AD2: 排放量
G3: CO2 | J3: CH4 | M3: N2O | P3: HFCs | T3: PFCs | X3: SF6 | AA3: NF3 | AD3: =G3 -> CO2 | AE3: =J3 -> CH4 | AF3: =M3 -> N2O | AG3: =P3 -> HFCs | AH3: =T3 -> PFCs | AI3: =X3 -> SF6 | AJ3: =AA3 -> NF3 | AK3: 总量
E4: 数值 | F4: 计量单位 | G4: EF | H4: 计量单位 | I4: GWP | J4: EF | K4: 计量单位 | L4: GWP | M4: EF | N4: 计量单位 | O4: GWP | P4: EF | Q4: 计量单位 | R4: GWP | S4: 型号 | T4: EF | U4: 计量单位 | V4: GWP | W4: 型号 | X4: EF | Y4: 计量单位 | Z4: GWP | AA4: EF | AB4: 计量单位 | AC4: GWP | AD4: tCO2e
A5: 1 | B5: =表1温室气体盘查表!B5 -> 固定燃烧 | C5: =表1温室气体盘查表!C5 -> 天然气燃烧 | D5: =表1温室气体盘查表!E5 -> 范围一 | E5: =表1温室气体盘查表!F5 -> 1796.49 | F5: =表1温室气体盘查表!G5 -> 10000Nm3 | G5: ='附表2-EF'!K5*10 -> 1e-06 | H5: tCO2/10000Nm3 | I5: ='附表1-GWP TABLE'!E3 -> 1 | AD5: =表1温室气体盘查表!AE5 -> 38843.506 | AE5: =表1温室气体盘查表!AF5 -> 19.317893 | AF5: =表1温室气体盘查表!AG5 -> 18.902455 | AG5: =表1温室气体盘查表!AH5 -> 0 | AH5: =表1温室气体盘查表!AI5 -> 0 | AI5: =表1温室气体盘查表!AJ5 -> 0 | AJ5: =表1温室气体盘查表!AK5 -> 0 | AK5: =表1温室气体盘查表!AL5 -> 38881.726
A6: 2 | B6: =表1温室气体盘查表!B6 -> 固定燃烧 | C6: =表1温室气体盘查表!C6 -> 液化石油气燃烧 | D6: =表1温室气体盘查表!E6 -> 范围一 | E6: =表1温室气体盘查表!F6 -> 9.39 | F6: =表1温室气体盘查表!G6 -> t | G6: ='附表2-EF'!K6*10 -> 1e-06 | H6: tCO2/10000Nm4 | I6: ='附表1-GWP TABLE'!E4 -> 27.9 | AD6: =表1温室气体盘查表!AE6 -> 29.136879 | AE6: =表1温室气体盘查表!AF6 -> 0.012883026 | AF6: =表1温室气体盘查表!AG6 -> 0.012605971 | AG6: =表1温室气体盘查表!AH6 -> 0 | AH6: =表1温室气体盘查表!AI6 -> 0 | AI6: =表1温室气体盘查表!AJ6 -> 0 | AJ6: =表1温室气体盘查表!AK6 -> 0 | AK6: =表1温室气体盘查表!AL6 -> 29.162368
A7: 3 | B7: =表1温室气体盘查表!B7 -> 固定燃烧 | C7: =表1温室气体盘查表!C7 -> 烟煤燃烧 | D7: =表1温室气体盘查表!E7 -> 范围一 | E7: =表1温室气体盘查表!F7 -> 399079.16 | F7: =表1温室气体盘查表!G7 -> t | G7: ='附表2-EF'!K7*10 -> 1.5e-05 | H7: tCO2/10000Nm5 | I7: ='附表1-GWP TABLE'!E5 -> 273 | AD7: =表1温室气体盘查表!AE7 -> 921839.46 | AE7: =表1温室气体盘查表!AF7 -> 261.64111 | AF7: =表1温室气体盘查表!AG7 -> 3840.2163 | AG7: =表1温室气体盘查表!AH7 -> 0 | AH7: =表1温室气体盘查表!AI7 -> 0 | AI7: =表1温室气体盘查表!AJ7 -> 0 | AJ7: =表1温室气体盘查表!AK7 -> 0 | AK7: =表1温室气体盘查表!AL7 -> 925941.32
A8: 4 | B8: =表1温室气体盘查表!B8 -> 固定燃烧 | C8: =表1温室气体盘查表!C8 -> 无烟煤燃烧 | D8: =表1温室气体盘查表!E8 -> 范围一 | E8: =表1温室气体盘查表!F8 -> 260530.34 | F8: =表1温室气体盘查表!G8 -> t | G8: ='附表2-EF'!K8*10 -> 1.5e-05 | H8: tCO2/10000Nm6 | I8: ='附表1-GWP TABLE'!E6 -> 0 | AD8: =表1温室气体盘查表!AE8 -> 634459.27 | AE8: =表1温室气体盘查表!AF8 -> 180.07542 | AF8: =表1温室气体盘查表!AG8 -> 2643.0424 | AG8: =表1温室气体盘查表!AH8 -> 0 | AH8: =表1温室气体盘查表!AI8 -> 0 | AI8: =表1温室气体盘查表!AJ8 -> 0 | AJ8: =表1温室气体盘查表!AK8 -> 0 | AK8: =表1温室气体盘查表!AL8 -> 637282.39
A9: 5 | B9: =表1温室气体盘查表!B9 -> 固定燃烧 | C9: =表1温室气体盘查表!C9 -> 洗精煤燃烧 | D9: =表1温室气体盘查表!E9 -> 范围一 | E9: =表1温室气体盘查表!F9 -> 1946577.1 | F9: =表1温室气体盘查表!G9 -> t | G9: ='附表2-EF'!K9*10 -> 1.5e-05 | H9: tCO2/10000Nm7 | I9: ='附表1-GWP TABLE'!E7 -> 0 | AD9: =表1温室气体盘查表!AE9 -> 4802635.7 | AE9: =表1温室气体盘查表!AF9 -> 1416.4222 | AF9: =表1温室气体盘查表!AG9 -> 20789.422 | AG9: =表1温室气体盘查表!AH9 -> 0 | AH9: =表1温室气体盘查表!AI9 -> 0 | AI9: =表1温室气体盘查表!AJ9 -> 0 | AJ9: =表1温室气体盘查表!AK9 -> 0 | AK9: =表1温室气体盘查表!AL9 -> 4824841.6
A10: 6 | B10: =表1温室气体盘查表!B10 -> 固定燃烧 | C10: =表1温室气体盘查表!C10 -> 焦炭燃烧 | D10: =表1温室气体盘查表!E10 -> 范围一 | E10: =表1温室气体盘查表!F10 -> 145430.2 | F10: =表1温室气体盘查表!G10 -> t | G10: ='附表2-EF'!K10*10 -> 1.5e-05 | H10: tCO2/10000Nm8 | I10: ='附表1-GWP TABLE'!E8 -> 0 | AD10: =表1温室气体盘查表!AE10 -> 438053.15 | AE10: =表1温室气体盘查表!AF10 -> 114.22134 | AF10: =表1温室气体盘查表!AG10 -> 1676.4744 | AG10: =表1温室气体盘查表!AH10 -> 0 | AH10: =表1温室气体盘查表!AI10 -> 0 | AI10: =表1温室气体盘查表!AJ10 -> 0 | AJ10: =表1温室气体盘查表!AK10 -> 0 | AK10: =表1温室气体盘查表!AL10 -> 439843.84
A11: 7 | B11: =表1温室气体盘查表!B11 -> 固定燃烧 | C11: =表1温室气体盘查表!C11 -> 焦屑燃烧 | D11: =表1温室气体盘查表!E11 -> 范围一 | E11: =表1温室气体盘查表!F11 -> 120570.5 | F11: =表1温室气体盘查表!G11 -> t | G11: ='附表2-EF'!K11*10 -> 1e-06 | H11: tCO2/10000Nm9 | I11: ='附表1-GWP TABLE'!E9 -> 0 | AD11: =表1温室气体盘查表!AE11 -> 363172.76 | AE11: =表1温室气体盘查表!AF11 -> 94.696449 | AF11: =表1温室气体盘查表!AG11 -> 1389.8995 | AG11: =表1温室气体盘查表!AH11 -> 0 | AH11: =表1温室气体盘查表!AI11 -> 0 | AI11: =表1温室气体盘查表!AJ11 -> 0 | AJ11: =表1温室气体盘查表!AK11 -> 0 | AK11: =表1温室气体盘查表!AL11 -> 364657.36
A12: 8 | B12: =表1温室气体盘查表!B12 -> 固定燃烧 | C12: =表1温室气体盘查表!C12 -> 焦炉煤气燃烧 | D12: =表1温室气体盘查表!E12 -> 范围一 | E12: =表1温室气体盘查表!F12 -> -500.97 | F12: =表1温室气体盘查表!G12 -> 10000Nm3 | G12: ='附表2-EF'!K12*10 -> 3.9e-05 | H12: tCO2/10000Nm10 | I12: ='附表1-GWP TABLE'!E10 -> 0 | AD12: =表1温室气体盘查表!AE12 -> -3828.3759 | AE12: =表1温室气体盘查表!AF12 -> -2.4056686 | AF12: =表1温室气体盘查表!AG12 -> -2.3539338 | AG12: =表1温室气体盘查表!AH12 -> 0 | AH12: =表1温室气体盘查表!AI12 -> 0 | AI12: =表1温室气体盘查表!AJ12 -> 0 | AJ12: =表1温室气体盘查表!AK12 -> 0 | AK12: =表1温室气体盘查表!AL12 -> -3833.1355
A13: 9 | B13: =表1温室气体盘查表!B13 -> 移动燃烧 | C13: =表1温室气体盘查表!C13 -> 0#柴油燃烧 | D13: =表1温室气体盘查表!E13 -> 范围一 | E13: =表1温室气体盘查表!F13 -> 1403.87 | F13: =表1温室气体盘查表!G13 -> t | G13: ='附表2-EF'!K13*10 -> 8e-05 | H13: tCO2/10000Nm11 | I13: ='附表1-GWP TABLE'!E11 -> 0 | AD13: =表1温室气体盘查表!AE13 -> 4348.2107 | AE13: =表1温室气体盘查表!AF13 -> 6.3850041 | AF13: =表1温室气体盘查表!AG13 -> 62.476922 | AG13: =表1温室气体盘查表!AH13 -> 0 | AH13: =表1温室气体盘查表!AI13 -> 0 | AI13: =表1温室气体盘查表!AJ13 -> 0 | AJ13: =表1温室气体盘查表!AK13 -> 0 | AK13: =表1温室气体盘查表!AL13 -> 4417.0726
A14: 10 | B14: =表1温室气体盘查表!B14 -> 移动燃烧 | C14: =表1温室气体盘查表!C14 -> 92#汽油燃烧 | D14: =表1温室气体盘查表!E14 -> 范围一 | E14: =表1温室气体盘查表!F14 -> 49.06 | F14: =表1温室气体盘查表!G14 -> t | G14: ='附表2-EF'!K14*10 -> 0 | H14: tCO2/10000Nm12 | I14: ='附表1-GWP TABLE'!E12 -> 0 | AD14: =表1温室气体盘查表!AE14 -> 143.50325 | AE14: =表1温室气体盘查表!AF14 -> 1.4443509 | AF14: =表1温室气体盘查表!AG14 -> 4.5225266 | AG14: =表1温室气体盘查表!AH14 -> 0 | AH14: =表1温室气体盘查表!AI14 -> 0 | AI14: =表1温室气体盘查表!AJ14 -> 0 | AJ14: =表1温室气体盘查表!AK14 -> 0 | AK14: =表1温室气体盘查表!AL14 -> 149.47012
A15: 11 | B15: =表1温室气体盘查表!B15 -> 逸散排放 | C15: =表1温室气体盘查表!C15 -> 制冷剂逸散（R32） | D15: =表1温室气体盘查表!E15 -> 范围一 | E15: =表1温室气体盘查表!F15 -> 0.93 | F15: =表1温室气体盘查表!G15 -> t | G15: ='附表2-EF'!K15*10 -> 0 | H15: tCO2/10000Nm13 | I15: ='附表1-GWP TABLE'!E13 -> 0 | AD15: =表1温室气体盘查表!AE15 -> 0 | AE15: =表1温室气体盘查表!AF15 -> 0 | AF15: =表1温室气体盘查表!AG15 -> 0 | AG15: =表1温室气体盘查表!AH15 -> 717.03 | AH15: =表1温室气体盘查表!AI15 -> 0 | AI15: =表1温室气体盘查表!AJ15 -> 0 | AJ15: =表1温室气体盘查表!AK15 -> 0 | AK15: =表1温室气体盘查表!AL15 -> 717.03
A16: 12 | B16: =表1温室气体盘查表!B16 -> 逸散排放 | C16: =表1温室气体盘查表!C16 -> CO2逸散 | D16: =表1温室气体盘查表!E16 -> 范围一 | E16: =表1温室气体盘查表!F16 -> 0.66 | F16: =表1温室气体盘查表!G16 -> t | G16: ='附表2-EF'!K16*10 -> 0 | H16: tCO2/10000Nm14 | I16: ='附表1-GWP TABLE'!E14 -> 0 | AD16: =表1温室气体盘查表!AE16 -> 0.66 | AE16: =表1温室气体盘查表!AF16 -> 0 | AF16: =表1温室气体盘查表!AG16 -> 0 | AG16: =表1温室气体盘查表!AH16 -> 0 | AH16: =表1温室气体盘查表!AI16 -> 0 | AI16: =表1温室气体盘查表!AJ16 -> 0 | AJ16: =表1温室气体盘查表!AK16 -> 0 | AK16: =表1温室气体盘查表!AL16 -> 0.66
... A30: 26 | B30: =表1温室气体盘查表!B30 -> 制程排放 | C30: =表1温室气体盘查表!C30 -> 粗苯 | D30: =表1温室气体盘查表!E30 -> 范围一 | E30: =表1温室气体盘查表!F30 -> -19501.18 | F30: =表1温室气体盘查表!G30 -> t | G30: ='附表2-EF'!K30*10 -> 0 | H30: tCO2/10000Nm28 | I30: ='附表1-GWP TABLE'!E28 -> 0 | AD30: =表1温室气体盘查表!AE30 -> -65952.991 | AE30: =表1温室气体盘查表!AF30 -> 0 | AF30: =表1温室气体盘查表!AG30 -> 0 | AG30: =表1温室气体盘查表!AH30 -> 0 | AH30: =表1温室气体盘查表!AI30 -> 0 | AI30: =表1温室气体盘查表!AJ30 -> 0 | AJ30: =表1温室气体盘查表!AK30 -> 0 | AK30: =表1温室气体盘查表!AL30 -> -65952.991
A31: 27 | B31: =表1温室气体盘查表!B31 -> 制程排放 | C31: =表1温室气体盘查表!C31 -> 煤焦油 | D31: =表1温室气体盘查表!E31 -> 范围一 | E31: =表1温室气体盘查表!F31 -> -59054.1 | F31: =表1温室气体盘查表!G31 -> t | G31: ='附表2-EF'!G31*10 -> 0 | H31: tCO2/10000Nm29 | I31: ='附表1-GWP TABLE'!E29 -> 0 | AD31: =表1温室气体盘查表!AE31 -> -159387.02 | AE31: =表1温室气体盘查表!AF31 -> 0 | AF31: =表1温室气体盘查表!AG31 -> 0 | AG31: =表1温室气体盘查表!AH31 -> 0 | AH31: =表1温室气体盘查表!AI31 -> 0 | AI31: =表1温室气体盘查表!AJ31 -> 0 | AJ31: =表1温室气体盘查表!AK31 -> 0 | AK31: =表1温室气体盘查表!AL31 -> -159387.02
A32: 28 | B32: =表1温室气体盘查表!B32 -> 输入能源间接温室气体排放 | C32: =表1温室气体盘查表!C32 -> 外购电力（基于位置） | D32: =表1温室气体盘查表!E32 -> 范围二 | E32: =表1温室气体盘查表!F32 -> 1992878.8 | F32: =表1温室气体盘查表!G32 -> MWh | G32: ='附表2-EF'!G32*10 -> #VALUE! | H32: tCO2/10000Nm30 | I32: ='附表1-GWP TABLE'!E30 -> 0 | AD32: =表1温室气体盘查表!AE32 -> 1069378.7 | AE32: =表1温室气体盘查表!AF32 -> 0 | AF32: =表1温室气体盘查表!AG32 -> 0 | AG32: =表1温室气体盘查表!AH32 -> 0 | AH32: =表1温室气体盘查表!AI32 -> 0 | AI32: =表1温室气体盘查表!AJ32 -> 0 | AJ32: =表1温室气体盘查表!AK32 -> 0 | AK32: =表1温室气体盘查表!AL32 -> 1069378.7
A33: 29 | B33: =表1温室气体盘查表!B34 -> 外购商品和服务的上游排放 | C33: =表1温室气体盘查表!C34 -> 铁矿石生产 | D33: =表1温室气体盘查表!E34 -> 范围三 类别1 | E33: =表1温室气体盘查表!F34 -> 4538211.3 | F33: =表1温室气体盘查表!G34 -> t | G33: ='附表2-EF'!G34*10 -> #VALUE! | H33: tCO2/10000Nm32 | I33: ='附表1-GWP TABLE'!E32 -> 0 | AD33: =表1温室气体盘查表!AE34 -> 448588.58 | AE33: =表1温室气体盘查表!AF34 -> 0 | AF33: =表1温室气体盘查表!AG34 -> 0 | AG33: =表1温室气体盘查表!AH34 -> 0 | AH33: =表1温室气体盘查表!AI34 -> 0 | AI33: =表1温室气体盘查表!AJ34 -> 0 | AJ33: =表1温室气体盘查表!AK34 -> 0 | AK33: =表1温室气体盘查表!AL34 -> 448588.58
A34: 30 | B34: =表1温室气体盘查表!B35 -> 外购商品和服务的上游排放 | C34: =表1温室气体盘查表!C35 -> 生石灰生产 | D34: =表1温室气体盘查表!E35 -> 范围三 类别1 | E34: =表1温室气体盘查表!F35 -> 611514.48 | F34: =表1温室气体盘查表!G35 -> t | G34: ='附表2-EF'!G36*10 -> 0 | H34: tCO2/10000Nm33 | I34: ='附表1-GWP TABLE'!E33 -> 0 | AD34: =表1温室气体盘查表!AE35 -> 727500.38 | AE34: =表1温室气体盘查表!AF35 -> 0 | AF34: =表1温室气体盘查表!AG35 -> 0 | AG34: =表1温室气体盘查表!AH35 -> 0 | AH34: =表1温室气体盘查表!AI35 -> 0 | AI34: =表1温室气体盘查表!AJ35 -> 0 | AJ34: =表1温室气体盘查表!AK35 -> 0 | AK34: =表1温室气体盘查表!AL35 -> 727500.38
A35: 31 | B35: =表1温室气体盘查表!B36 -> 外购商品和服务的上游排放 | C35: =表1温室气体盘查表!C36 -> 石灰石生产 | D35: =表1温室气体盘查表!E36 -> 范围三 类别1 | E35: =表1温室气体盘查表!F36 -> 19365.77 | F35: =表1温室气体盘查表!G36 -> t | G35: ='附表2-EF'!G37*10 -> 0 | H35: tCO2/10000Nm34 | I35: ='附表1-GWP TABLE'!E34 -> 0 | AD35: =表1温室气体盘查表!AE36 -> 58.676347 | AE35: =表1温室气体盘查表!AF36 -> 0 | AF35: =表1温室气体盘查表!AG36 -> 0 | AG35: =表1温室气体盘查表!AH36 -> 0 | AH35: =表1温室气体盘查表!AI36 -> 0 | AI35: =表1温室气体盘查表!AJ36 -> 0 | AJ35: =表1温室气体盘查表!AK36 -> 0 | AK35: =表1温室气体盘查表!AL36 -> 58.676347
A36: 32 | B36: =表1温室气体盘查表!B37 -> 外购商品和服务的上游排放 | C36: =表1温室气体盘查表!C37 -> 白云石生产 | D36: =表1温室气体盘查表!E37 -> 范围三 类别1 | E36: =表1温室气体盘查表!F37 -> 356289.39 | F36: =表1温室气体盘查表!G37 -> t | G36: ='附表2-EF'!G38*10 -> 0 | H36: tCO2/10000Nm35 | I36: ='附表1-GWP TABLE'!E35 -> 0 | AD36: =表1温室气体盘查表!AE37 -> 46435.196 | AE36: =表1温室气体盘查表!AF37 -> 0 | AF36: =表1温室气体盘查表!AG37 -> 0 | AG36: =表1温室气体盘查表!AH37 -> 0 | AH36: =表1温室气体盘查表!AI37 -> 0 | AI36: =表1温室气体盘查表!AJ37 -> 0 | AJ36: =表1温室气体盘查表!AK37 -> 0 | AK36: =表1温室气体盘查表!AL37 -> 46435.196
A37: 33 | B37: =表1温室气体盘查表!B38 -> 外购商品和服务的上游排放 | C37: =表1温室气体盘查表!C38 -> 轻烧白云石生产 | D37: =表1温室气体盘查表!E38 -> 范围三 类别1 | E37: =表1温室气体盘查表!F38 -> 2786.84 | F37: =表1温室气体盘查表!G38 -> t | G37: ='附表2-EF'!K39*10 -> 0 | H37: tCO2/10000Nm36 | I37: ='附表1-GWP TABLE'!E36 -> 0 | AD37: =表1温室气体盘查表!AE38 -> 363.20886 | AE37: =表1温室气体盘查表!AF38 -> 0 | AF37: =表1温室气体盘查表!AG38 -> 0 | AG37: =表1温室气体盘查表!AH38 -> 0 | AH37: =表1温室气体盘查表!AI38 -> 0 | AI37: =表1温室气体盘查表!AJ38 -> 0 | AJ37: =表1温室气体盘查表!AK38 -> 0 | AK37: =表1温室气体盘查表!AL38 -> 363.20886
A38: 34 | B38: =表1温室气体盘查表!B39 -> 外购商品和服务的上游排放 | C38: =表1温室气体盘查表!C39 -> 球团生产 | D38: =表1温室气体盘查表!E39 -> 范围三 类别1 | E38: =表1温室气体盘查表!F39 -> 685439.89 | F38: =表1温室气体盘查表!G39 -> t | G38: ='附表2-EF'!K40*10 -> 0 | H38: tCO2/10000Nm37 | I38: ='附表1-GWP TABLE'!E37 -> 0 | AD38: =表1温室气体盘查表!AE39 -> 71601.051 | AE38: =表1温室气体盘查表!AF39 -> 0 | AF38: =表1温室气体盘查表!AG39 -> 0 | AG38: =表1温室气体盘查表!AH39 -> 0 | AH38: =表1温室气体盘查表!AI39 -> 0 | AI38: =表1温室气体盘查表!AJ39 -> 0 | AJ38: =表1温室气体盘查表!AK39 -> 0 | AK38: =表1温室气体盘查表!AL39 -> 71601.051
A39: 35 | B39: =表1温室气体盘查表!B40 -> 外购商品和服务的上游排放 | C39: =表1温室气体盘查表!C40 -> 废钢生产 | D39: =表1温室气体盘查表!E40 -> 范围三 类别1 | E39: =表1温室气体盘查表!F40 -> 1077722.6 | F39: =表1温室气体盘查表!G40 -> t | G39: ='附表2-EF'!K41*10 -> 0 | H39: tCO2/10000Nm38 | I39: ='附表1-GWP TABLE'!E38 -> 0 | AD39: =表1温室气体盘查表!AE40 -> 79944.388 | AE39: =表1温室气体盘查表!AF40 -> 0 | AF39: =表1温室气体盘查表!AG40 -> 0 | AG39: =表1温室气体盘查表!AH40 -> 0 | AH39: =表1温室气体盘查表!AI40 -> 0 | AI39: =表1温室气体盘查表!AJ40 -> 0 | AJ39: =表1温室气体盘查表!AK40 -> 0 | AK39: =表1温室气体盘查表!AL40 -> 79944.388
A40: 36 | B40: =表1温室气体盘查表!B41 -> 外购商品和服务的上游排放 | C40: =表1温室气体盘查表!C41 -> 电极生产 | D40: =表1温室气体盘查表!E41 -> 范围三 类别1 | E40: =表1温室气体盘查表!F41 -> 4473.46 | F40: =表1温室气体盘查表!G41 -> t | G40: ='附表2-EF'!K42*10 -> 0 | H40: tCO2/10000Nm39 | I40: ='附表1-GWP TABLE'!E39 -> 0 | AD40: =表1温室气体盘查表!AE41 -> 37742.812 | AE40: =表1温室气体盘查表!AF41 -> 0 | AF40: =表1温室气体盘查表!AG41 -> 0 | AG40: =表1温室气体盘查表!AH41 -> 0 | AH40: =表1温室气体盘查表!AI41 -> 0 | AI40: =表1温室气体盘查表!AJ41 -> 0 | AJ40: =表1温室气体盘查表!AK41 -> 0 | AK40: =表1温室气体盘查表!AL41 -> 37742.812
A41: 37 | B41: =表1温室气体盘查表!B42 -> 外购商品和服务的上游排放 | C41: =表1温室气体盘查表!C42 -> 锰铁生产 | D41: =表1温室气体盘查表!E42 -> 范围三 类别1 | E41: =表1温室气体盘查表!F42 -> 47651.68 | F41: =表1温室气体盘查表!G42 -> t | G41: ='附表2-EF'!#REF!*10 -> #REF! | H41: tCO2/10000Nm40 | I41: ='附表1-GWP TABLE'!E40 -> 0 | AD41: =表1温室气体盘查表!AE42 -> 141868.58 | AE41: =表1温室气体盘查表!AF42 -> 0 | AF41: =表1温室气体盘查表!AG42 -> 0 | AG41: =表1温室气体盘查表!AH42 -> 0 | AH41: =表1温室气体盘查表!AI42 -> 0 | AI41: =表1温室气体盘查表!AJ42 -> 0 | AJ41: =表1温室气体盘查表!AK42 -> 0 | AK41: =表1温室气体盘查表!AL42 -> 141868.58
A42: 38 | B42: =表1温室气体盘查表!B43 -> 外购商品和服务的上游排放 | C42: =表1温室气体盘查表!C43 -> 镍铁生产 | D42: =表1温室气体盘查表!E43 -> 范围三 类别1 | E42: =表1温室气体盘查表!F43 -> 9688.41 | F42: =表1温室气体盘查表!G43 -> t | G42: ='附表2-EF'!#REF!*10 -> #REF! | H42: tCO2/10000Nm41 | I42: ='附表1-GWP TABLE'!E41 -> 0 | AD42: =表1温室气体盘查表!AE43 -> 84819.123 | AE42: =表1温室气体盘查表!AF43 -> 0 | AF42: =表1温室气体盘查表!AG43 -> 0 | AG42: =表1温室气体盘查表!AH43 -> 0 | AH42: =表1温室气体盘查表!AI43 -> 0 | AI42: =表1温室气体盘查表!AJ43 -> 0 | AJ42: =表1温室气体盘查表!AK43 -> 0 | AK42: =表1温室气体盘查表!AL43 -> 84819.123
A43: 39 | B43: =表1温室气体盘查表!B44 -> 外购商品和服务的上游排放 | C43: =表1温室气体盘查表!C44 -> 铬铁生产 | D43: =表1温室气体盘查表!E44 -> 范围三 类别1 | E43: =表1温室气体盘查表!F44 -> 67771.93 | F43: =表1温室气体盘查表!G44 -> t | G43: ='附表2-EF'!K43*10 -> 0 | H43: tCO2/10000Nm42 | I43: ='附表1-GWP TABLE'!E42 -> 0 | AD43: =表1温室气体盘查表!AE44 -> 345101.44 | AE43: =表1温室气体盘查表!AF44 -> 0 | AF43: =表1温室气体盘查表!AG44 -> 0 | AG43: =表1温室气体盘查表!AH44 -> 0 | AH43: =表1温室气体盘查表!AI44 -> 0 | AI43: =表1温室气体盘查表!AJ44 -> 0 | AJ43: =表1温室气体盘查表!AK44 -> 0 | AK43: =表1温室气体盘查表!AL44 -> 345101.44
A44: 40 | B44: =表1温室气体盘查表!B45 -> 外购商品和服务的上游排放 | C44: =表1温室气体盘查表!C45 -> 萤石生产 | D44: =表1温室气体盘查表!E45 -> 范围三 类别1 | E44: =表1温室气体盘查表!F45 -> 3237.84 | F44: =表1温室气体盘查表!G45 -> t | G44: ='附表2-EF'!#REF!*10 -> #REF! | H44: tCO2/10000Nm43 | I44: ='附表1-GWP TABLE'!E43 -> 0 | AD44: =表1温室气体盘查表!AE45 -> 685.06219 | AE44: =表1温室气体盘查表!AF45 -> 0 | AF44: =表1温室气体盘查表!AG45 -> 0 | AG44: =表1温室气体盘查表!AH45 -> 0 | AH44: =表1温室气体盘查表!AI45 -> 0 | AI44: =表1温室气体盘查表!AJ45 -> 0 | AJ44: =表1温室气体盘查表!AK45 -> 0 | AK44: =表1温室气体盘查表!AL45 -> 685.06219
A45: 41 | B45: =表1温室气体盘查表!B46 -> 外购商品和服务的上游排放 | C45: =表1温室气体盘查表!C46 -> 硅铁生产 | D45: =表1温室气体盘查表!E46 -> 范围三 类别1 | E45: =表1温室气体盘查表!F46 -> 10209.54 | F45: =表1温室气体盘查表!G46 -> t | G45: ='附表2-EF'!#REF!*10 -> #REF! | H45: tCO2/10000Nm44 | I45: ='附表1-GWP TABLE'!E44 -> 0 | AD45: =表1温室气体盘查表!AE46 -> 103575.78 | AE45: =表1温室气体盘查表!AF46 -> 0 | AF45: =表1温室气体盘查表!AG46 -> 0 | AG45: =表1温室气体盘查表!AH46 -> 0 | AH45: =表1温室气体盘查表!AI46 -> 0 | AI45: =表1温室气体盘查表!AJ46 -> 0 | AJ45: =表1温室气体盘查表!AK46 -> 0 | AK45: =表1温室气体盘查表!AL46 -> 103575.78
A46: 42 | B46: =表1温室气体盘查表!B47 -> 外购商品和服务的上游排放 | C46: =表1温室气体盘查表!C47 -> 钼铁生产 | D46: =表1温室气体盘查表!E47 -> 范围三 类别1 | E46: =表1温室气体盘查表!F47 -> 7772.4 | F46: =表1温室气体盘查表!G47 -> t | G46: ='附表2-EF'!#REF!*10 -> #REF! | H46: tCO2/10000Nm45 | I46: ='附表1-GWP TABLE'!E45 -> 0 | AD46: =表1温室气体盘查表!AE47 -> 66065.4 | AE46: =表1温室气体盘查表!AF47 -> 0 | AF46: =表1温室气体盘查表!AG47 -> 0 | AG46: =表1温室气体盘查表!AH47 -> 0 | AH46: =表1温室气体盘查表!AI47 -> 0 | AI46: =表1温室气体盘查表!AJ47 -> 0 | AJ46: =表1温室气体盘查表!AK47 -> 0 | AK46: =表1温室气体盘查表!AL47 -> 66065.4
A47: 43 | B47: =表1温室气体盘查表!B48 -> 外购商品和服务的上游排放 | C47: =表1温室气体盘查表!C48 -> 铝铁生产 | D47: =表1温室气体盘查表!E48 -> 范围三 类别1 | E47: =表1温室气体盘查表!F48 -> 11018.51 | F47: =表1温室气体盘查表!G48 -> t | G47: ='附表2-EF'!#REF!*10 -> #REF! | H47: tCO2/10000Nm46 | I47: ='附表1-GWP TABLE'!E46 -> 0 | AD47: =表1温室气体盘查表!AE48 -> 63158.19 | AE47: =表1温室气体盘查表!AF48 -> 0 | AF47: =表1温室气体盘查表!AG48 -> 0 | AG47: =表1温室气体盘查表!AH48 -> 0 | AH47: =表1温室气体盘查表!AI48 -> 0 | AI47: =表1温室气体盘查表!AJ48 -> 0 | AJ47: =表1温室气体盘查表!AK48 -> 0 | AK47: =表1温室气体盘查表!AL48 -> 63158.19
A48: 44 | B48: =表1温室气体盘查表!B49 -> 外购商品和服务的上游排放 | C48: =表1温室气体盘查表!C49 -> 铝生产 | D48: =表1温室气体盘查表!E49 -> 范围三 类别1 | E48: =表1温室气体盘查表!F49 -> 2841.66 | F48: =表1温室气体盘查表!G49 -> t | G48: ='附表2-EF'!#REF!*10 -> #REF! | H48: tCO2/10000Nm47 | I48: ='附表1-GWP TABLE'!E47 -> 17400 | AD48: =表1温室气体盘查表!AE49 -> 63342.195 | AE48: =表1温室气体盘查表!AF49 -> 0 | AF48: =表1温室气体盘查表!AG49 -> 0 | AG48: =表1温室气体盘查表!AH49 -> 0 | AH48: =表1温室气体盘查表!AI49 -> 0 | AI48: =表1温室气体盘查表!AJ49 -> 0 | AJ48: =表1温室气体盘查表!AK49 -> 0 | AK48: =表1温室气体盘查表!AL49 -> 63342.195
A49: 45 | B49: =表1温室气体盘查表!B50 -> 外购商品和服务的上游排放 | C49: =表1温室气体盘查表!C50 -> 增碳剂生产 | D49: =表1温室气体盘查表!E50 -> 范围三 类别1 | E49: =表1温室气体盘查表!F50 -> 10680.664 | F49: =表1温室气体盘查表!G50 -> t | G49: ='附表2-EF'!#REF!*10 -> #REF! | H49: tCO2/10000Nm48 | I49: ='附表1-GWP TABLE'!E48 -> 24300 | AD49: =表1温室气体盘查表!AE50 -> 17778.323 | AE49: =表1温室气体盘查表!AF50 -> 0 | AF49: =表1温室气体盘查表!AG50 -> 0 | AG49: =表1温室气体盘查表!AH50 -> 0 | AH49: =表1温室气体盘查表!AI50 -> 0 | AI49: =表1温室气体盘查表!AJ50 -> 0 | AJ49: =表1温室气体盘查表!AK50 -> 0 | AK49: =表1温室气体盘查表!AL50 -> 17778.323
A50: 46 | B50: =表1温室气体盘查表!B51 -> 外购商品和服务的上游排放 | C50: =表1温室气体盘查表!C51 -> 铁鳞生产 | D50: =表1温室气体盘查表!E51 -> 范围三 类别1 | E50: =表1温室气体盘查表!F51 -> 172683.99 | F50: =表1温室气体盘查表!G51 -> t | G50: ='附表2-EF'!#REF!*10 -> #REF! | H50: tCO2/10000Nm49 | I50: ='附表1-GWP TABLE'!E49 -> 0 | AD50: =表1温室气体盘查表!AE51 -> 608.38394 | AE50: =表1温室气体盘查表!AF51 -> 0 | AF50: =表1温室气体盘查表!AG51 -> 0 | AG50: =表1温室气体盘查表!AH51 -> 0 | AH50: =表1温室气体盘查表!AI51 -> 0 | AI50: =表1温室气体盘查表!AJ51 -> 0 | AJ50: =表1温室气体盘查表!AK51 -> 0 | AK50: =表1温室气体盘查表!AL51 -> 608.38394
A51: 47 | B51: =表1温室气体盘查表!B52 -> 外购商品和服务的上游排放 | C51: =表1温室气体盘查表!C52 -> 氨水生产 | D51: =表1温室气体盘查表!E52 -> 范围三 类别1 | E51: =表1温室气体盘查表!F52 -> 4496.14 | F51: =表1温室气体盘查表!G52 -> t | G51: ='附表2-EF'!#REF!*10 -> #REF! | H51: tCO2/10000Nm50 | I51: ='附表1-GWP TABLE'!E50 -> 0 | AD51: =表1温室气体盘查表!AE52 -> 24444.815 | AE51: =表1温室气体盘查表!AF52 -> 0 | AF51: =表1温室气体盘查表!AG52 -> 0 | AG51: =表1温室气体盘查表!AH52 -> 0 | AH51: =表1温室气体盘查表!AI52 -> 0 | AI51: =表1温室气体盘查表!AJ52 -> 0 | AJ51: =表1温室气体盘查表!AK52 -> 0 | AK51: =表1温室气体盘查表!AL52 -> 24444.815
A52: 48 | B52: =表1温室气体盘查表!B53 -> 外购商品和服务的上游排放 | C52: =表1温室气体盘查表!C53 -> 碳化硅生产 | D52: =表1温室气体盘查表!E53 -> 范围三 类别1 | E52: =表1温室气体盘查表!F53 -> 6614.798 | F52: =表1温室气体盘查表!G53 -> t | G52: ='附表2-EF'!#REF!*10 -> #REF! | H52: tCO2/10000Nm51 | I52: ='附表1-GWP TABLE'!E51 -> 0 | AD52: =表1温室气体盘查表!AE53 -> 48149.585 | AE52: =表1温室气体盘查表!AF53 -> 0 | AF52: =表1温室气体盘查表!AG53 -> 0 | AG52: =表1温室气体盘查表!AH53 -> 0 | AH52: =表1温室气体盘查表!AI53 -> 0 | AI52: =表1温室气体盘查表!AJ53 -> 0 | AJ52: =表1温室气体盘查表!AK53 -> 0 | AK52: =表1温室气体盘查表!AL53 -> 48149.585
A53: 49 | B53: =表1温室气体盘查表!B54 -> 外购商品和服务的上游排放 | C53: =表1温室气体盘查表!C54 -> 镁生产 | D53: =表1温室气体盘查表!E54 -> 范围三 类别1 | E53: =表1温室气体盘查表!F54 -> 11710.709 | F53: =表1温室气体盘查表!G54 -> t | G53: ='附表2-EF'!#REF!*10 -> #REF! | H53: tCO2/10000Nm52 | I53: ='附表1-GWP TABLE'!E52 -> 0 | AD53: =表1温室气体盘查表!AE54 -> 308520.83 | AE53: =表1温室气体盘查表!AF54 -> 0 | AF53: =表1温室气体盘查表!AG54 -> 0 | AG53: =表1温室气体盘查表!AH54 -> 0 | AH53: =表1温室气体盘查表!AI54 -> 0 | AI53: =表1温室气体盘查表!AJ54 -> 0 | AJ53: =表1温室气体盘查表!AK54 -> 0 | AK53: =表1温室气体盘查表!AL54 -> 308520.83
A54: 50 | B54: =表1温室气体盘查表!B55 -> 外购商品和服务的上游排放 | C54: =表1温室气体盘查表!C55 -> 所有其他纸制品加工制造 | D54: =表1温室气体盘查表!E55 -> 范围三 类别1 | E54: =表1温室气体盘查表!F55 -> 16162.17 | F54: =表1温室气体盘查表!G55 -> $ | G54: ='附表2-EF'!#REF!*10 -> #REF! | H54: tCO2/10000Nm53 | I54: ='附表1-GWP TABLE'!E53 -> 0 | AD54: =表1温室气体盘查表!AE55 -> 5.5436243 | AE54: =表1温室气体盘查表!AF55 -> 0 | AF54: =表1温室气体盘查表!AG55 -> 0 | AG54: =表1温室气体盘查表!AH55 -> 0 | AH54: =表1温室气体盘查表!AI55 -> 0 | AI54: =表1温室气体盘查表!AJ55 -> 0 | AJ54: =表1温室气体盘查表!AK55 -> 0 | AK54: =表1温室气体盘查表!AL55 -> 5.5436243
A55: 51 | B55: =表1温室气体盘查表!B56 -> 外购商品和服务的上游排放 | C55: =表1温室气体盘查表!C56 -> 办公用品(纸张除外)制造 | D55: =表1温室气体盘查表!E56 -> 范围三 类别1 | E55: =表1温室气体盘查表!F56 -> 177487.76 | F55: =表1温室气体盘查表!G56 -> $ | G55: ='附表2-EF'!#REF!*10 -> #REF! | H55: tCO2/10000Nm54 | I55: ='附表1-GWP TABLE'!E54 -> 0 | AD55: =表1温室气体盘查表!AE56 -> 47.034256 | AE55: =表1温室气体盘查表!AF56 -> 0 | AF55: =表1温室气体盘查表!AG56 -> 0 | AG55: =表1温室气体盘查表!AH56 -> 0 | AH55: =表1温室气体盘查表!AI56 -> 0 | AI55: =表1温室气体盘查表!AJ56 -> 0 | AJ55: =表1温室气体盘查表!AK56 -> 0 | AK55: =表1温室气体盘查表!AL56 -> 47.034256
... A68: 64 | B68: =表1温室气体盘查表!B69 -> 范围一、二相关燃料和能源相关的活动产生的排放 | C68: =表1温室气体盘查表!C69 -> 液化石油气生产 | D68: =表1温室气体盘查表!E69 -> 范围三 类别3 | E68: =表1温室气体盘查表!F69 -> 9.39 | F68: =表1温室气体盘查表!G69 -> t | G68: ='附表2-EF'!#REF!*10 -> #REF! | H68: tCO2/10000Nm67 | I68: ='附表1-GWP TABLE'!E67 -> 0 | AD68: =表1温室气体盘查表!AE69 -> 9.448458 | AE68: =表1温室气体盘查表!AF69 -> 0 | AF68: =表1温室气体盘查表!AG69 -> 0 | AG68: =表1温室气体盘查表!AH69 -> 0 | AH68: =表1温室气体盘查表!AI69 -> 0 | AI68: =表1温室气体盘查表!AJ69 -> 0 | AJ68: =表1温室气体盘查表!AK69 -> 0 | AK68: =表1温室气体盘查表!AL69 -> 9.448458
A69: 65 | B69: =表1温室气体盘查表!B70 -> 范围一、二相关燃料和能源相关的活动产生的排放 | C69: =表1温室气体盘查表!C70 -> 洗精煤生产 | D69: =表1温室气体盘查表!E70 -> 范围三 类别3 | E69: =表1温室气体盘查表!F70 -> 1946577.1 | F69: =表1温室气体盘查表!G70 -> t | G69: ='附表2-EF'!K69*10 -> 0 | H69: tCO2/10000Nm68 | I69: ='附表1-GWP TABLE'!E68 -> 0 | AD69: =表1温室气体盘查表!AE70 -> 1120352.4 | AE69: =表1温室气体盘查表!AF70 -> 0 | AF69: =表1温室气体盘查表!AG70 -> 0 | AG69: =表1温室气体盘查表!AH70 -> 0 | AH69: =表1温室气体盘查表!AI70 -> 0 | AI69: =表1温室气体盘查表!AJ70 -> 0 | AJ69: =表1温室气体盘查表!AK70 -> 0 | AK69: =表1温室气体盘查表!AL70 -> 1120352.4
A70: 66 | B70: =表1温室气体盘查表!B71 -> 范围一、二相关燃料和能源相关的活动产生的排放 | C70: =表1温室气体盘查表!C71 -> 柴油生产 | D70: =表1温室气体盘查表!E71 -> 范围三 类别3 | E70: =表1温室气体盘查表!F71 -> 1403.87 | F70: =表1温室气体盘查表!G71 -> t | G70: ='附表2-EF'!K70*10 -> 0 | H70: tCO2/10000Nm69 | I70: ='附表1-GWP TABLE'!E69 -> 0 | AD70: =表1温室气体盘查表!AE71 -> 1182.227 | AE70: =表1温室气体盘查表!AF71 -> 0 | AF70: =表1温室气体盘查表!AG71 -> 0 | AG70: =表1温室气体盘查表!AH71 -> 0 | AH70: =表1温室气体盘查表!AI71 -> 0 | AI70: =表1温室气体盘查表!AJ71 -> 0 | AJ70: =表1温室气体盘查表!AK71 -> 0 | AK70: =表1温室气体盘查表!AL71 -> 1182.227
A71: 67 | B71: =表1温室气体盘查表!B72 -> 范围一、二相关燃料和能源相关的活动产生的排放 | C71: =表1温室气体盘查表!C72 -> 汽油生产 | D71: =表1温室气体盘查表!E72 -> 范围三 类别3 | E71: =表1温室气体盘查表!F72 -> 49.06 | F71: =表1温室气体盘查表!G72 -> t | G71: ='附表2-EF'!#REF!*10 -> #REF! | H71: tCO2/10000Nm70 | I71: ='附表1-GWP TABLE'!E70 -> 0 | AD71: =表1温室气体盘查表!AE72 -> 48.438425 | AE71: =表1温室气体盘查表!AF72 -> 0 | AF71: =表1温室气体盘查表!AG72 -> 0 | AG71: =表1温室气体盘查表!AH72 -> 0 | AH71: =表1温室气体盘查表!AI72 -> 0 | AI71: =表1温室气体盘查表!AJ72 -> 0 | AJ71: =表1温室气体盘查表!AK72 -> 0 | AK71: =表1温室气体盘查表!AL72 -> 48.438425
A72: 68 | B72: =表1温室气体盘查表!B73 -> 范围一、二相关燃料和能源相关的活动产生的排放 | C72: =表1温室气体盘查表!C73 -> 焦炭生产 | D72: =表1温室气体盘查表!E73 -> 范围三 类别3 | E72: =表1温室气体盘查表!F73 -> 145430.2 | F72: =表1温室气体盘查表!G73 -> t | G72: ='附表2-EF'!#REF!*10 -> #REF! | H72: tCO2/10000Nm71 | I72: ='附表1-GWP TABLE'!E71 -> 0 | AD72: =表1温室气体盘查表!AE73 -> 184347.32 | AE72: =表1温室气体盘查表!AF73 -> 0 | AF72: =表1温室气体盘查表!AG73 -> 0 | AG72: =表1温室气体盘查表!AH73 -> 0 | AH72: =表1温室气体盘查表!AI73 -> 0 | AI72: =表1温室气体盘查表!AJ73 -> 0 | AJ72: =表1温室气体盘查表!AK73 -> 0 | AK72: =表1温室气体盘查表!AL73 -> 184347.32
A73: 69 | B73: =表1温室气体盘查表!B74 -> 范围一、二相关燃料和能源相关的活动产生的排放 | C73: =表1温室气体盘查表!C74 -> 焦屑生产 | D73: =表1温室气体盘查表!E74 -> 范围三 类别3 | E73: =表1温室气体盘查表!F74 -> 120570.5 | F73: =表1温室气体盘查表!G74 -> t | G73: ='附表2-EF'!#REF!*10 -> #REF! | H73: tCO2/10000Nm72 | I73: ='附表1-GWP TABLE'!E72 -> 0 | AD73: =表1温室气体盘查表!AE74 -> 152835.17 | AE73: =表1温室气体盘查表!AF74 -> 0 | AF73: =表1温室气体盘查表!AG74 -> 0 | AG73: =表1温室气体盘查表!AH74 -> 0 | AH73: =表1温室气体盘查表!AI74 -> 0 | AI73: =表1温室气体盘查表!AJ74 -> 0 | AJ73: =表1温室气体盘查表!AK74 -> 0 | AK73: =表1温室气体盘查表!AL74 -> 152835.17
A74: 70 | B74: =表1温室气体盘查表!B75 -> 范围一、二相关燃料和能源相关的活动产生的排放 | C74: =表1温室气体盘查表!C75 -> 烟煤生产 | D74: =表1温室气体盘查表!E75 -> 范围三 类别3 | E74: =表1温室气体盘查表!F75 -> 399079.16 | F74: =表1温室气体盘查表!G75 -> t | G74: ='附表2-EF'!#REF!*10 -> #REF! | H74: tCO2/10000Nm73 | I74: ='附表1-GWP TABLE'!E73 -> 0 | AD74: =表1温室气体盘查表!AE75 -> 229690.01 | AE74: =表1温室气体盘查表!AF75 -> 0 | AF74: =表1温室气体盘查表!AG75 -> 0 | AG74: =表1温室气体盘查表!AH75 -> 0 | AH74: =表1温室气体盘查表!AI75 -> 0 | AI74: =表1温室气体盘查表!AJ75 -> 0 | AJ74: =表1温室气体盘查表!AK75 -> 0 | AK74: =表1温室气体盘查表!AL75 -> 229690.01
A75: 71 | B75: =表1温室气体盘查表!B76 -> 范围一、二相关燃料和能源相关的活动产生的排放 | C75: =表1温室气体盘查表!C76 -> 无烟煤生产 | D75: =表1温室气体盘查表!E76 -> 范围三 类别3 | E75: =表1温室气体盘查表!F76 -> 260530.34 | F75: =表1温室气体盘查表!G76 -> t | G75: ='附表2-EF'!#REF!*10 -> #REF! | H75: tCO2/10000Nm74 | I75: ='附表1-GWP TABLE'!E74 -> 0 | AD75: =表1温室气体盘查表!AE76 -> 149948.24 | AE75: =表1温室气体盘查表!AF76 -> 0 | AF75: =表1温室气体盘查表!AG76 -> 0 | AG75: =表1温室气体盘查表!AH76 -> 0 | AH75: =表1温室气体盘查表!AI76 -> 0 | AI75: =表1温室气体盘查表!AJ76 -> 0 | AJ75: =表1温室气体盘查表!AK76 -> 0 | AK75: =表1温室气体盘查表!AL76 -> 149948.24
A76: 72 | B76: =表1温室气体盘查表!B77 -> 范围一、二相关燃料和能源相关的活动产生的排放 | C76: =表1温室气体盘查表!C77 -> 天然气生产 | D76: =表1温室气体盘查表!E77 -> 范围三 类别3 | E76: =表1温室气体盘查表!F77 -> 1796.49 | F76: =表1温室气体盘查表!G77 -> 10000Nm3 | G76: ='附表2-EF'!#REF!*10 -> #REF! | H76: tCO2/10000Nm75 | I76: ='附表1-GWP TABLE'!E75 -> 0 | AD76: =表1温室气体盘查表!AE77 -> 11120.273 | AE76: =表1温室气体盘查表!AF77 -> 0 | AF76: =表1温室气体盘查表!AG77 -> 0 | AG76: =表1温室气体盘查表!AH77 -> 0 | AH76: =表1温室气体盘查表!AI77 -> 0 | AI76: =表1温室气体盘查表!AJ77 -> 0 | AJ76: =表1温室气体盘查表!AK77 -> 0 | AK76: =表1温室气体盘查表!AL77 -> 11120.273
A77: 73 | B77: =表1温室气体盘查表!B78 -> 范围一、二相关燃料和能源相关的活动产生的排放 | C77: =表1温室气体盘查表!C78 -> 外购电力上游排放 | D77: =表1温室气体盘查表!E78 -> 范围三 类别3 | E77: =表1温室气体盘查表!F78 -> 1992878.8 | F77: =表1温室气体盘查表!G78 -> MWh | G77: ='附表2-EF'!#REF!*10 -> #REF! | H77: tCO2/10000Nm76 | I77: ='附表1-GWP TABLE'!E76 -> 0 | AD77: =表1温室气体盘查表!AE78 -> 167202.53 | AE77: =表1温室气体盘查表!AF78 -> 0 | AF77: =表1温室气体盘查表!AG78 -> 0 | AG77: =表1温室气体盘查表!AH78 -> 0 | AH77: =表1温室气体盘查表!AI78 -> 0 | AI77: =表1温室气体盘查表!AJ78 -> 0 | AJ77: =表1温室气体盘查表!AK78 -> 0 | AK77: =表1温室气体盘查表!AL78 -> 167202.53
A78: 74 | B78: =表1温室气体盘查表!B79 -> 上游运输配送产生的排放 | C78: =表1温室气体盘查表!C79 -> 船运 | D78: =表1温室气体盘查表!E79 -> 范围三 类别4 | E78: =表1温室气体盘查表!F79 -> 4.9377735e+09 | F78: =表1温室气体盘查表!G79 -> tkm | G78: ='附表2-EF'!#REF!*10 -> #REF! | H78: tCO2/10000Nm77 | I78: ='附表1-GWP TABLE'!E77 -> 0 | AD78: =表1温室气体盘查表!AE79 -> 256608.97 | AE78: =表1温室气体盘查表!AF79 -> 0 | AF78: =表1温室气体盘查表!AG79 -> 0 | AG78: =表1温室气体盘查表!AH79 -> 0 | AH78: =表1温室气体盘查表!AI79 -> 0 | AI78: =表1温室气体盘查表!AJ79 -> 0 | AJ78: =表1温室气体盘查表!AK79 -> 0 | AK78: =表1温室气体盘查表!AL79 -> 256608.97
A79: 75 | B79: =表1温室气体盘查表!B80 -> 上游运输配送产生的排放 | C79: =表1温室气体盘查表!C80 -> 汽运 | D79: =表1温室气体盘查表!E80 -> 范围三 类别4 | E79: =表1温室气体盘查表!F80 -> 3.0369596e+08 | F79: =表1温室气体盘查表!G80 -> tkm | G79: ='附表2-EF'!#REF!*10 -> #REF! | H79: tCO2/10000Nm78 | I79: ='附表1-GWP TABLE'!E78 -> 0 | AD79: =表1温室气体盘查表!AE80 -> 46150.512 | AE79: =表1温室气体盘查表!AF80 -> 0 | AF79: =表1温室气体盘查表!AG80 -> 0 | AG79: =表1温室气体盘查表!AH80 -> 0 | AH79: =表1温室气体盘查表!AI80 -> 0 | AI79: =表1温室气体盘查表!AJ80 -> 0 | AJ79: =表1温室气体盘查表!AK80 -> 0 | AK79: =表1温室气体盘查表!AL80 -> 46150.512
A80: 76 | B80: =表1温室气体盘查表!B81 -> 上游运输配送产生的排放 | C80: =表1温室气体盘查表!C81 -> 铁路运输 | D80: =表1温室气体盘查表!E81 -> 范围三 类别4 | E80: =表1温室气体盘查表!F81 -> 1.2265094e+09 | F80: =表1温室气体盘查表!G81 -> tkm | G80: ='附表2-EF'!#REF!*10 -> #REF! | H80: tCO2/10000Nm79 | I80: ='附表1-GWP TABLE'!E79 -> 0 | AD80: =表1温室气体盘查表!AE81 -> 59524.772 | AE80: =表1温室气体盘查表!AF81 -> 0 | AF80: =表1温室气体盘查表!AG81 -> 0 | AG80: =表1温室气体盘查表!AH81 -> 0 | AH80: =表1温室气体盘查表!AI81 -> 0 | AI80: =表1温室气体盘查表!AJ81 -> 0 | AJ80: =表1温室气体盘查表!AK81 -> 0 | AK80: =表1温室气体盘查表!AL81 -> 59524.772
A81: 77 | B81: =表1温室气体盘查表!B82 -> 运营中产生的废物排放 | C81: =表1温室气体盘查表!C82 -> 生活垃圾和厨余垃圾 | D81: =表1温室气体盘查表!E82 -> 范围三 类别5 | E81: =表1温室气体盘查表!F82 -> 2610.16 | F81: =表1温室气体盘查表!G82 -> t | G81: ='附表2-EF'!#REF!*10 -> #REF! | H81: tCO2/10000Nm80 | I81: ='附表1-GWP TABLE'!E80 -> 0 | AD81: =表1温室气体盘查表!AE82 -> 969.24193 | AE81: =表1温室气体盘查表!AF82 -> 0 | AF81: =表1温室气体盘查表!AG82 -> 0 | AG81: =表1温室气体盘查表!AH82 -> 0 | AH81: =表1温室气体盘查表!AI82 -> 0 | AI81: =表1温室气体盘查表!AJ82 -> 0 | AJ81: =表1温室气体盘查表!AK82 -> 0 | AK81: =表1温室气体盘查表!AL82 -> 969.24193
A82: 78 | B82: =表1温室气体盘查表!B83 -> 运营中产生的废物排放 | C82: =表1温室气体盘查表!C83 -> 废油 | D82: =表1温室气体盘查表!E83 -> 范围三 类别5 | E82: =表1温室气体盘查表!F83 -> 36.75 | F82: =表1温室气体盘查表!G83 -> t | G82: ='附表2-EF'!#REF!*10 -> #REF! | H82: tCO2/10000Nm81 | I82: ='附表1-GWP TABLE'!E81 -> 0 | AD82: =表1温室气体盘查表!AE83 -> 104.70285 | AE82: =表1温室气体盘查表!AF83 -> 0 | AF82: =表1温室气体盘查表!AG83 -> 0 | AG82: =表1温室气体盘查表!AH83 -> 0 | AH82: =表1温室气体盘查表!AI83 -> 0 | AI82: =表1温室气体盘查表!AJ83 -> 0 | AJ82: =表1温室气体盘查表!AK83 -> 0 | AK82: =表1温室气体盘查表!AL83 -> 104.70285
A83: 79 | B83: =表1温室气体盘查表!B84 -> 运营中产生的废物排放 | C83: =表1温室气体盘查表!C84 -> 废油水 | D83: =表1温室气体盘查表!E84 -> 范围三 类别5 | E83: =表1温室气体盘查表!F84 -> 229.5 | F83: =表1温室气体盘查表!G84 -> t | G83: ='附表2-EF'!#REF!*10 -> #REF! | H83: tCO2/10000Nm82 | I83: ='附表1-GWP TABLE'!E82 -> 0 | AD83: =表1温室气体盘查表!AE84 -> 653.85859 | AE83: =表1温室气体盘查表!AF84 -> 0 | AF83: =表1温室气体盘查表!AG84 -> 0 | AG83: =表1温室气体盘查表!AH84 -> 0 | AH83: =表1温室气体盘查表!AI84 -> 0 | AI83: =表1温室气体盘查表!AJ84 -> 0 | AJ83: =表1温室气体盘查表!AK84 -> 0 | AK83: =表1温室气体盘查表!AL84 -> 653.85859
A84: 80 | B84: =表1温室气体盘查表!B85 -> 运营中产生的废物排放 | C84: =表1温室气体盘查表!C85 -> 煤焦油 | D84: =表1温室气体盘查表!E85 -> 范围三 类别5 | E84: =表1温室气体盘查表!F85 -> 57478.34 | F84: =表1温室气体盘查表!G85 -> t | G84: ='附表2-EF'!K84*10 -> 0 | H84: tCO2/10000Nm83 | I84: ='附表1-GWP TABLE'!E83 -> 0 | AD84: =表1温室气体盘查表!AE85 -> 145058.8 | AE84: =表1温室气体盘查表!AF85 -> 0 | AF84: =表1温室气体盘查表!AG85 -> 0 | AG84: =表1温室气体盘查表!AH85 -> 0 | AH84: =表1温室气体盘查表!AI85 -> 0 | AI84: =表1温室气体盘查表!AJ85 -> 0 | AJ84: =表1温室气体盘查表!AK85 -> 0 | AK84: =表1温室气体盘查表!AL85 -> 145058.8
A85: 81 | B85: =表1温室气体盘查表!B86 -> 运营中产生的废物排放 | C85: =表1温室气体盘查表!C86 -> 废弃物运输 | D85: =表1温室气体盘查表!E86 -> 范围三 类别5 | E85: =表1温室气体盘查表!F86 -> 5589690 | F85: =表1温室气体盘查表!G86 -> tkm | G85: ='附表2-EF'!#REF!*10 -> #REF! | H85: tCO2/10000Nm84 | I85: ='附表1-GWP TABLE'!E84 -> 0 | AD85: =表1温室气体盘查表!AE86 -> 849.42539 | AE85: =表1温室气体盘查表!AF86 -> 0 | AF85: =表1温室气体盘查表!AG86 -> 0 | AG85: =表1温室气体盘查表!AH86 -> 0 | AH85: =表1温室气体盘查表!AI86 -> 0 | AI85: =表1温室气体盘查表!AJ86 -> 0 | AJ85: =表1温室气体盘查表!AK86 -> 0 | AK85: =表1温室气体盘查表!AL86 -> 849.42539
A86: 82 | B86: =表1温室气体盘查表!B87 -> 商务旅行产生的排放 | C86: =表1温室气体盘查表!C87 -> 航运 | D86: =表1温室气体盘查表!E87 -> 范围三 类别6 | E86: =表1温室气体盘查表!F87 -> 3901916.5 | F86: =表1温室气体盘查表!G87 -> passenger*km | G86: ='附表2-EF'!#REF!*10 -> #REF! | H86: tCO2/10000Nm85 | I86: ='附表1-GWP TABLE'!E85 -> 0 | AD86: =表1温室气体盘查表!AE87 -> 327.76099 | AE86: =表1温室气体盘查表!AF87 -> 0 | AF86: =表1温室气体盘查表!AG87 -> 0 | AG86: =表1温室气体盘查表!AH87 -> 0 | AH86: =表1温室气体盘查表!AI87 -> 0 | AI86: =表1温室气体盘查表!AJ87 -> 0 | AJ86: =表1温室气体盘查表!AK87 -> 0 | AK86: =表1温室气体盘查表!AL87 -> 327.76099
A87: 83 | B87: =表1温室气体盘查表!B88 -> 商务旅行产生的排放 | C87: =表1温室气体盘查表!C88 -> 铁路运输 | D87: =表1温室气体盘查表!E88 -> 范围三 类别6 | E87: =表1温室气体盘查表!F88 -> 8277796.5 | F87: =表1温室气体盘查表!G88 -> passenger*km | G87: ='附表2-EF'!#REF!*10 -> #REF! | H87: tCO2/10000Nm86 | I87: ='附表1-GWP TABLE'!E86 -> 0 | AD87: =表1温室气体盘查表!AE88 -> 619.78797 | AE87: =表1温室气体盘查表!AF88 -> 0 | AF87: =表1温室气体盘查表!AG88 -> 0 | AG87: =表1温室气体盘查表!AH88 -> 0 | AH87: =表1温室气体盘查表!AI88 -> 0 | AI87: =表1温室气体盘查表!AJ88 -> 0 | AJ87: =表1温室气体盘查表!AK88 -> 0 | AK87: =表1温室气体盘查表!AL88 -> 619.78797
A88: 84 | B88: =表1温室气体盘查表!B89 -> 商务旅行产生的排放 | C88: =表1温室气体盘查表!C89 -> 员工差旅住宿 | D88: =表1温室气体盘查表!E89 -> 范围三 类别6 | E88: =表1温室气体盘查表!F89 -> 13507 | F88: =表1温室气体盘查表!G89 -> 总间*晚 | G88: ='附表2-EF'!#REF!*10 -> #REF! | H88: tCO2/10000Nm87 | I88: ='附表1-GWP TABLE'!E87 -> 0 | AD88: =表1温室气体盘查表!AE89 -> 722.6245 | AE88: =表1温室气体盘查表!AF89 -> 0 | AF88: =表1温室气体盘查表!AG89 -> 0 | AG88: =表1温室气体盘查表!AH89 -> 0 | AH88: =表1温室气体盘查表!AI89 -> 0 | AI88: =表1温室气体盘查表!AJ89 -> 0 | AJ88: =表1温室气体盘查表!AK89 -> 0 | AK88: =表1温室气体盘查表!AL89 -> 722.6245
A89: 85 | B89: =表1温室气体盘查表!B90 -> 员工通勤产生的排放 | C89: =表1温室气体盘查表!C90 -> 通勤车 | D89: =表1温室气体盘查表!E90 -> 范围三 类别7 | E89: =表1温室气体盘查表!F90 -> 12637097 | F89: =表1温室气体盘查表!G90 -> passenger*km | G89: ='附表2-EF'!#REF!*10 -> #REF! | H89: tCO2/10000Nm88 | I89: ='附表1-GWP TABLE'!E88 -> 0 | AD89: =表1温室气体盘查表!AE90 -> 111.20645 | AE89: =表1温室气体盘查表!AF90 -> 0 | AF89: =表1温室气体盘查表!AG90 -> 0 | AG89: =表1温室气体盘查表!AH90 -> 0 | AH89: =表1温室气体盘查表!AI90 -> 0 | AI89: =表1温室气体盘查表!AJ90 -> 0 | AJ89: =表1温室气体盘查表!AK90 -> 0 | AK89: =表1温室气体盘查表!AL90 -> 111.20645
A90: 86 | B90: =表1温室气体盘查表!B91 -> 员工通勤产生的排放 | C90: =表1温室气体盘查表!C91 -> 电动车 | D90: =表1温室气体盘查表!E91 -> 范围三 类别7 | E90: =表1温室气体盘查表!F91 -> 17561466 | F90: =表1温室气体盘查表!G91 -> passenger*km | G90: ='附表2-EF'!#REF!*10 -> #REF! | H90: tCO2/10000Nm89 | I90: ='附表1-GWP TABLE'!E89 -> 0 | AD90: =表1温室气体盘查表!AE91 -> 474.51538 | AE90: =表1温室气体盘查表!AF91 -> 0 | AF90: =表1温室气体盘查表!AG91 -> 0 | AG90: =表1温室气体盘查表!AH91 -> 0 | AH90: =表1温室气体盘查表!AI91 -> 0 | AI90: =表1温室气体盘查表!AJ91 -> 0 | AJ90: =表1温室气体盘查表!AK91 -> 0 | AK90: =表1温室气体盘查表!AL91 -> 474.51538
A91: 87 | B91: =表1温室气体盘查表!B92 -> 员工通勤产生的排放 | C91: =表1温室气体盘查表!C92 -> 自驾油车 | D91: =表1温室气体盘查表!E92 -> 范围三 类别7 | E91: =表1温室气体盘查表!F92 -> 31405120 | F91: =表1温室气体盘查表!G92 -> km | G91: ='附表2-EF'!#REF!*10 -> #REF! | H91: tCO2/10000Nm90 | I91: ='附表1-GWP TABLE'!E90 -> 0 | AD91: =表1温室气体盘查表!AE92 -> 11664.729 | AE91: =表1温室气体盘查表!AF92 -> 0 | AF91: =表1温室气体盘查表!AG92 -> 0 | AG91: =表1温室气体盘查表!AH92 -> 0 | AH91: =表1温室气体盘查表!AI92 -> 0 | AI91: =表1温室气体盘查表!AJ92 -> 0 | AJ91: =表1温室气体盘查表!AK92 -> 0 | AK91: =表1温室气体盘查表!AL92 -> 11664.729
A92: 88 | B92: =表1温室气体盘查表!B93 -> 员工通勤产生的排放 | C92: =表1温室气体盘查表!C93 -> 自驾电车 | D92: =表1温室气体盘查表!E93 -> 范围三 类别7 | E92: =表1温室气体盘查表!F93 -> 2886500 | F92: =表1温室气体盘查表!G93 -> km | G92: ='附表2-EF'!#REF!*10 -> #REF! | H92: tCO2/10000Nm91 | I92: ='附表1-GWP TABLE'!E91 -> 0 | AD92: =表1温室气体盘查表!AE93 -> 1072.1258 | AE92: =表1温室气体盘查表!AF93 -> 0 | AF92: =表1温室气体盘查表!AG93 -> 0 | AG92: =表1温室气体盘查表!AH93 -> 0 | AH92: =表1温室气体盘查表!AI93 -> 0 | AI92: =表1温室气体盘查表!AJ93 -> 0 | AJ92: =表1温室气体盘查表!AK93 -> 0 | AK92: =表1温室气体盘查表!AL93 -> 1072.1258
A93: 89 | B93: =表1温室气体盘查表!B94 -> 下游运输配送产生的排放 | C93: =表1温室气体盘查表!C94 -> 船运 | D93: =表1温室气体盘查表!E94 -> 范围三 类别9 | E93: =表1温室气体盘查表!F94 -> 1.0290483e+09 | F93: =表1温室气体盘查表!G94 -> tkm | G93: ='附表2-EF'!#REF!*10 -> #REF! | H93: tCO2/10000Nm92 | I93: ='附表1-GWP TABLE'!E92 -> 0 | AD93: =表1温室气体盘查表!AE94 -> 53478.156 | AE93: =表1温室气体盘查表!AF94 -> 0 | AF93: =表1温室气体盘查表!AG94 -> 0 | AG93: =表1温室气体盘查表!AH94 -> 0 | AH93: =表1温室气体盘查表!AI94 -> 0 | AI93: =表1温室气体盘查表!AJ94 -> 0 | AJ93: =表1温室气体盘查表!AK94 -> 0 | AK93: =表1温室气体盘查表!AL94 -> 53478.156
A94: 90 | B94: =表1温室气体盘查表!B95 -> 下游运输配送产生的排放 | C94: =表1温室气体盘查表!C95 -> 汽运 | D94: =表1温室气体盘查表!E95 -> 范围三 类别9 | E94: =表1温室气体盘查表!F95 -> 1.369081e+09 | F94: =表1温室气体盘查表!G95 -> tkm | G94: ='附表2-EF'!#REF!*10 -> #REF! | H94: tCO2/10000Nm93 | I94: ='附表1-GWP TABLE'!E93 -> 0 | AD94: =表1温室气体盘查表!AE95 -> 208049.49 | AE94: =表1温室气体盘查表!AF95 -> 0 | AF94: =表1温室气体盘查表!AG95 -> 0 | AG94: =表1温室气体盘查表!AH95 -> 0 | AH94: =表1温室气体盘查表!AI95 -> 0 | AI94: =表1温室气体盘查表!AJ95 -> 0 | AJ94: =表1温室气体盘查表!AK95 -> 0 | AK94: =表1温室气体盘查表!AL95 -> 208049.49
A95: 91 | B95: =表1温室气体盘查表!B96 -> 下游运输配送产生的排放 | C95: =表1温室气体盘查表!C96 -> 铁路运输 | D95: =表1温室气体盘查表!E96 -> 范围三 类别9 | E95: =表1温室气体盘查表!F96 -> 2.2843703e+08 | F95: =表1温室气体盘查表!G96 -> tkm | G95: ='附表2-EF'!#REF!*10 -> #REF! | H95: tCO2/10000Nm94 | I95: ='附表1-GWP TABLE'!E94 -> 0 | AD95: =表1温室气体盘查表!AE96 -> 11086.472 | AE95: =表1温室气体盘查表!AF96 -> 0 | AF95: =表1温室气体盘查表!AG96 -> 0 | AG95: =表1温室气体盘查表!AH96 -> 0 | AH95: =表1温室气体盘查表!AI96 -> 0 | AI95: =表1温室气体盘查表!AJ96 -> 0 | AJ95: =表1温室气体盘查表!AK96 -> 0 | AK95: =表1温室气体盘查表!AL96 -> 11086.472
A96: 92 | B96: =表1温室气体盘查表!B97 -> 下游运输配送产生的排放 | C96: =表1温室气体盘查表!C97 -> 汽运-副产品 | D96: =表1温室气体盘查表!E97 -> 范围三 类别9 | E96: =表1温室气体盘查表!F97 -> 12973524 | F96: =表1温室气体盘查表!G97 -> tkm | G96: ='附表2-EF'!#REF!*10 -> #REF! | H96: tCO2/10000Nm95 | I96: ='附表1-GWP TABLE'!E95 -> 0 | AD96: =表1温室气体盘查表!AE97 -> 1971.494 | AE96: =表1温室气体盘查表!AF97 -> 0 | AF96: =表1温室气体盘查表!AG97 -> 0 | AG96: =表1温室气体盘查表!AH97 -> 0 | AH96: =表1温室气体盘查表!AI97 -> 0 | AI96: =表1温室气体盘查表!AJ97 -> 0 | AJ96: =表1温室气体盘查表!AK97 -> 0 | AK96: =表1温室气体盘查表!AL97 -> 1971.494
A97: 93 | B97: =表1温室气体盘查表!B98 -> 外销产品加工产生的排放 | C97: =表1温室气体盘查表!C98 -> 锻材加工 | D97: =表1温室气体盘查表!E98 -> 范围三 类别10 | E97: =表1温室气体盘查表!F98 -> 149966 | F97: =表1温室气体盘查表!G98 -> t | G97: ='附表2-EF'!K97*10 -> 0 | H97: tCO2/10000Nm96 | I97: ='附表1-GWP TABLE'!E96 -> 0 | AD97: =表1温室气体盘查表!AE98 -> 113275.66 | AE97: =表1温室气体盘查表!AF98 -> 0 | AF97: =表1温室气体盘查表!AG98 -> 0 | AG97: =表1温室气体盘查表!AH98 -> 0 | AH97: =表1温室气体盘查表!AI98 -> 0 | AI97: =表1温室气体盘查表!AJ98 -> 0 | AJ97: =表1温室气体盘查表!AK98 -> 0 | AK97: =表1温室气体盘查表!AL98 -> 113275.66
A98: 94 | B98: =表1温室气体盘查表!B99 -> 外销产品加工产生的排放 | C98: =表1温室气体盘查表!C99 -> 棒材加工 | D98: =表1温室气体盘查表!E99 -> 范围三 类别10 | E98: =表1温室气体盘查表!F99 -> 2033971 | F98: =表1温室气体盘查表!G99 -> t | G98: ='附表2-EF'!#REF!*10 -> #REF! | H98: tCO2/10000Nm97 | I98: ='附表1-GWP TABLE'!E97 -> 0 | AD98: =表1温室气体盘查表!AE99 -> 1357195.2 | AE98: =表1温室气体盘查表!AF99 -> 0 | AF98: =表1温室气体盘查表!AG99 -> 0 | AG98: =表1温室气体盘查表!AH99 -> 0 | AH98: =表1温室气体盘查表!AI99 -> 0 | AI98: =表1温室气体盘查表!AJ99 -> 0 | AJ98: =表1温室气体盘查表!AK99 -> 0 | AK98: =表1温室气体盘查表!AL99 -> 1357195.2
A99: 95 | B99: =表1温室气体盘查表!B100 -> 外销产品加工产生的排放 | C99: =表1温室气体盘查表!C100 -> 钢管加工 | D99: =表1温室气体盘查表!E100 -> 范围三 类别10 | E99: =表1温室气体盘查表!F100 -> 760435.74 | F99: =表1温室气体盘查表!G100 -> t | G99: ='附表2-EF'!#REF!*10 -> #REF! | H99: tCO2/10000Nm98 | I99: ='附表1-GWP TABLE'!E98 -> 0 | AD99: =表1温室气体盘查表!AE100 -> 72250.341 | AE99: =表1温室气体盘查表!AF100 -> 0 | AF99: =表1温室气体盘查表!AG100 -> 0 | AG99: =表1温室气体盘查表!AH100 -> 0 | AH99: =表1温室气体盘查表!AI100 -> 0 | AI99: =表1温室气体盘查表!AJ100 -> 0 | AJ99: =表1温室气体盘查表!AK100 -> 0 | AK99: =表1温室气体盘查表!AL100 -> 72250.341
A100: 96 | B100: =表1温室气体盘查表!B101 -> 外销产品加工产生的排放 | C100: =表1温室气体盘查表!C101 -> 钢坯加工 | D100: =表1温室气体盘查表!E101 -> 范围三 类别10 | E100: =表1温室气体盘查表!F101 -> 702589.87 | F100: =表1温室气体盘查表!G101 -> t | G100: ='附表2-EF'!#REF!*10 -> #REF! | H100: tCO2/10000Nm99 | I100: ='附表1-GWP TABLE'!E99 -> 0 | AD100: =表1温室气体盘查表!AE101 -> 203898.73 | AE100: =表1温室气体盘查表!AF101 -> 0 | AF100: =表1温室气体盘查表!AG101 -> 0 | AG100: =表1温室气体盘查表!AH101 -> 0 | AH100: =表1温室气体盘查表!AI101 -> 0 | AI100: =表1温室气体盘查表!AJ101 -> 0 | AJ100: =表1温室气体盘查表!AK101 -> 0 | AK100: =表1温室气体盘查表!AL101 -> 203898.73
A101: 97 | B101: =表1温室气体盘查表!B102 -> 外销产品使用产生的排放 | C101: =表1温室气体盘查表!C102 -> 外售焦炉煤气燃烧 | D101: =表1温室气体盘查表!E102 -> 范围三 类别11 | E101: =表1温室气体盘查表!F102 -> 500.97 | F101: =表1温室气体盘查表!G102 -> 10000Nm3 | AD101: =表1温室气体盘查表!AE102 -> 3828.3759 | AE101: =表1温室气体盘查表!AF102 -> 2.4056686 | AF101: =表1温室气体盘查表!AG102 -> 2.3539338 | AG101: =表1温室气体盘查表!AH102 -> 0 | AH101: =表1温室气体盘查表!AI102 -> 0 | AI101: =表1温室气体盘查表!AJ102 -> 0 | AJ101: =表1温室气体盘查表!AK102 -> 0 | AK101: =表1温室气体盘查表!AL102 -> 3833.1355
A102: 98 | B102: =表1温室气体盘查表!B103 -> 外售产品报废产生的排放 | C102: =表1温室气体盘查表!C103 -> 产品报废 | D102: =表1温室气体盘查表!E103 -> 范围三 类别12 | E102: =表1温室气体盘查表!F103 -> 598329.8 | F102: =表1温室气体盘查表!G103 -> t | G102: ='附表2-EF'!#REF!*10 -> #REF! | H102: tCO2/10000Nm100 | I102: ='附表1-GWP TABLE'!E100 -> 0 | AD102: =表1温室气体盘查表!AE103 -> 3747.347 | AE102: =表1温室气体盘查表!AF103 -> 0 | AF102: =表1温室气体盘查表!AG103 -> 0 | AG102: =表1温室气体盘查表!AH103 -> 0 | AH102: =表1温室气体盘查表!AI103 -> 0 | AI102: =表1温室气体盘查表!AJ103 -> 0 | AJ102: =表1温室气体盘查表!AK103 -> 0 | AK102: =表1温室气体盘查表!AL103 -> 3747.347
AD103: =SUM(AD5:AD102) -> 15487862 | AE103: =SUM(AE5:AE102) -> 2572.0892 | AF103: =SUM(AF5:AF102) -> 30424.969 | AG103: =SUM(AG5:AG102) -> 717.03 | AH103: =SUM(AH5:AH102) -> 0 | AI103: =SUM(AI5:AI102) -> 2459.16 | AJ103: =SUM(AJ5:AJ102) -> 0 | AK103: =SUM(AK5:AK102) -> 15524035

Sheet 活动数据汇总表（GHG基于市场）
A1: 各排放源明细
A2: 编号 | B2: GHG排放类别 | C2: 排放源 | D2: 报告边界 | E2: 活动数据 | G2: 排放因子&系数 | AD2: 排放量
G3: CO2 | J3: CH4 | M3: N2O | P3: HFCs | T3: PFCs | X3: SF6 | AA3: NF3 | AD3: =G3 -> CO2 | AE3: =J3 -> CH4 | AF3: =M3 -> N2O | AG3: =P3 -> HFCs | AH3: =T3 -> PFCs | AI3: =X3 -> SF6 | AJ3: =AA3 -> NF3 | AK3: 总量
E4: 数值 | F4: 计量单位 | G4: EF | H4: 计量单位 | I4: GWP | J4: EF | K4: 计量单位 | L4: GWP | M4: EF | N4: 计量单位 | O4: GWP | P4: EF | Q4: 计量单位 | R4: GWP | S4: 型号 | T4: EF | U4: 计量单位 | V4: GWP | W4: 型号 | X4: EF | Y4: 计量单位 | Z4: GWP | AA4: EF | AB4: 计量单位 | AC4: GWP | AD4: tCO2e
A5: 1 | B5: =表1温室气体盘查表!B5 -> 固定燃烧 | C5: =表1温室气体盘查表!C5 -> 天然气燃烧 | D5: =表1温室气体盘查表!E5 -> 范围一 | E5: =表1温室气体盘查表!F5 -> 1796.49 | F5: =表1温室气体盘查表!G5 -> 10000Nm3 | G5: ='附表2-EF'!K5*10 -> 1e-06 | H5: tCO2/10000Nm3 | I5: ='附表1-GWP TABLE'!E3 -> 1 | AD5: =表1温室气体盘查表!AE5 -> 38843.506 | AE5: =表1温室气体盘查表!AF5 -> 19.317893 | AF5: =表1温室气体盘查表!AG5 -> 18.902455 | AG5: =表1温室气体盘查表!AH5 -> 0 | AH5: =表1温室气体盘查表!AI5 -> 0 | AI5: =表1温室气体盘查表!AJ5 -> 0 | AJ5: =表1温室气体盘查表!AK5 -> 0 | AK5: =表1温室气体盘查表!AL5 -> 38881.726
A6: 2 | B6: =表1温室气体盘查表!B6 -> 固定燃烧 | C6: =表1温室气体盘查表!C6 -> 液化石油气燃烧 | D6: =表1温室气体盘查表!E6 -> 范围一 | E6: =表1温室气体盘查表!F6 -> 9.39 | F6: =表1温室气体盘查表!G6 -> t | G6: ='附表2-EF'!K6*10 -> 1e-06 | H6: tCO2/10000Nm4 | I6: ='附表1-GWP TABLE'!E4 -> 27.9 | AD6: =表1温室气体盘查表!AE6 -> 29.136879 | AE6: =表1温室气体盘查表!AF6 -> 0.012883026 | AF6: =表1温室气体盘查表!AG6 -> 0.012605971 | AG6: =表1温室气体盘查表!AH6 -> 0 | AH6: =表1温室气体盘查表!AI6 -> 0 | AI6: =表1温室气体盘查表!AJ6 -> 0 | AJ6: =表1温室气体盘查表!AK6 -> 0 | AK6: =表1温室气体盘查表!AL6 -> 29.162368
A7: 3 | B7: =表1温室气体盘查表!B7 -> 固定燃烧 | C7: =表1温室气体盘查表!C7 -> 烟煤燃烧 | D7: =表1温室气体盘查表!E7 -> 范围一 | E7: =表1温室气体盘查表!F7 -> 399079.16 | F7: =表1温室气体盘查表!G7 -> t | G7: ='附表2-EF'!K7*10 -> 1.5e-05 | H7: tCO2/10000Nm5 | I7: ='附表1-GWP TABLE'!E5 -> 273 | AD7: =表1温室气体盘查表!AE7 -> 921839.46 | AE7: =表1温室气体盘查表!AF7 -> 261.64111 | AF7: =表1温室气体盘查表!AG7 -> 3840.2163 | AG7: =表1温室气体盘查表!AH7 -> 0 | AH7: =表1温室气体盘查表!AI7 -> 0 | AI7: =表1温室气体盘查表!AJ7 -> 0 | AJ7: =表1温室气体盘查表!AK7 -> 0 | AK7: =表1温室气体盘查表!AL7 -> 925941.32
A8: 4 | B8: =表1温室气体盘查表!B8 -> 固定燃烧 | C8: =表1温室气体盘查表!C8 -> 无烟煤燃烧 | D8: =表1温室气体盘查表!E8 -> 范围一 | E8: =表1温室气体盘查表!F8 -> 260530.34 | F8: =表1温室气体盘查表!G8 -> t | G8: ='附表2-EF'!K8*10 -> 1.5e-05 | H8: tCO2/10000Nm6 | I8: ='附表1-GWP TABLE'!E6 -> 0 | AD8: =表1温室气体盘查表!AE8 -> 634459.27 | AE8: =表1温室气体盘查表!AF8 -> 180.07542 | AF8: =表1温室气体盘查表!AG8 -> 2643.0424 | AG8: =表1温室气体盘查表!AH8 -> 0 | AH8: =表1温室气体盘查表!AI8 -> 0 | AI8: =表1温室气体盘查表!AJ8 -> 0 | AJ8: =表1温室气体盘查表!AK8 -> 0 | AK8: =表1温室气体盘查表!AL8 -> 637282.39
A9: 5 | B9: =表1温室气体盘查表!B9 -> 固定燃烧 | C9: =表1温室气体盘查表!C9 -> 洗精煤燃烧 | D9: =表1温室气体盘查表!E9 -> 范围一 | E9: =表1温室气体盘查表!F9 -> 1946577.1 | F9: =表1温室气体盘查表!G9 -> t | G9: ='附表2-EF'!K9*10 -> 1.5e-05 | H9: tCO2/10000Nm7 | I9: ='附表1-GWP TABLE'!E7 -> 0 | AD9: =表1温室气体盘查表!AE9 -> 4802635.7 | AE9: =表1温室气体盘查表!AF9 -> 1416.4222 | AF9: =表1温室气体盘查表!AG9 -> 20789.422 | AG9: =表1温室气体盘查表!AH9 -> 0 | AH9: =表1温室气体盘查表!AI9 -> 0 | AI9: =表1温室气体盘查表!AJ9 -> 0 | AJ9: =表1温室气体盘查表!AK9 -> 0 | AK9: =表1温室气体盘查表!AL9 -> 4824841.6
A10: 6 | B10: =表1温室气体盘查表!B10 -> 固定燃烧 | C10: =表1温室气体盘查表!C10 -> 焦炭燃烧 | D10: =表1温室气体盘查表!E10 -> 范围一 | E10: =表1温室气体盘查表!F10 -> 145430.2 | F10: =表1温室气体盘查表!G10 -> t | G10: ='附表2-EF'!K10*10 -> 1.5e-05 | H10: tCO2/10000Nm8 | I10: ='附表1-GWP TABLE'!E8 -> 0 | AD10: =表1温室气体盘查表!AE10 -> 438053.15 | AE10: =表1温室气体盘查表!AF10 -> 114.22134 | AF10: =表1温室气体盘查表!AG10 -> 1676.4744 | AG10: =表1温室气体盘查表!AH10 -> 0 | AH10: =表1温室气体盘查表!AI10 -> 0 | AI10: =表1温室气体盘查表!AJ10 -> 0 | AJ10: =表1温室气体盘查表!AK10 -> 0 | AK10: =表1温室气体盘查表!AL10 -> 439843.84
A11: 7 | B11: =表1温室气体盘查表!B11 -> 固定燃烧 | C11: =表1温室气体盘查表!C11 -> 焦屑燃烧 | D11: =表1温室气体盘查表!E11 -> 范围一 | E11: =表1温室气体盘查表!F11 -> 120570.5 | F11: =表1温室气体盘查表!G11 -> t | G11: ='附表2-EF'!K11*10 -> 1e-06 | H11: tCO2/10000Nm9 | I11: ='附表1-GWP TABLE'!E9 -> 0 | AD11: =表1温室气体盘查表!AE11 -> 363172.76 | AE11: =表1温室气体盘查表!AF11 -> 94.696449 | AF11: =表1温室气体盘查表!AG11 -> 1389.8995 | AG11: =表1温室气体盘查表!AH11 -> 0 | AH11: =表1温室气体盘查表!AI11 -> 0 | AI11: =表1温室气体盘查表!AJ11 -> 0 | AJ11: =表1温室气体盘查表!AK11 -> 0 | AK11: =表1温室气体盘查表!AL11 -> 364657.36
A12: 8 | B12: =表1温室气体盘查表!B12 -> 固定燃烧 | C12: =表1温室气体盘查表!C12 -> 焦炉煤气燃烧 | D12: =表1温室气体盘查表!E12 -> 范围一 | E12: =表1温室气体盘查表!F12 -> -500.97 | F12: =表1温室气体盘查表!G12 -> 10000Nm3 | G12: ='附表2-EF'!K12*10 -> 3.9e-05 | H12: tCO2/10000Nm10 | I12: ='附表1-GWP TABLE'!E10 -> 0 | AD12: =表1温室气体盘查表!AE12 -> -3828.3759 | AE12: =表1温室气体盘查表!AF12 -> -2.4056686 | AF12: =表1温室气体盘查表!AG12 -> -2.3539338 | AG12: =表1温室气体盘查表!AH12 -> 0 | AH12: =表1温室气体盘查表!AI12 -> 0 | AI12: =表1温室气体盘查表!AJ12 -> 0 | AJ12: =表1温室气体盘查表!AK12 -> 0 | AK12: =表1温室气体盘查表!AL12 -> -3833.1355
A13: 9 | B13: =表1温室气体盘查表!B13 -> 移动燃烧 | C13: =表1温室气体盘查表!C13 -> 0#柴油燃烧 | D13: =表1温室气体盘查表!E13 -> 范围一 | E13: =表1温室气体盘查表!F13 -> 1403.87 | F13: =表1温室气体盘查表!G13 -> t | G13: ='附表2-EF'!K13*10 -> 8e-05 | H13: tCO2/10000Nm11 | I13: ='附表1-GWP TABLE'!E11 -> 0 | AD13: =表1温室气体盘查表!AE13 -> 4348.2107 | AE13: =表1温室气体盘查表!AF13 -> 6.3850041 | AF13: =表1温室气体盘查表!AG13 -> 62.476922 | AG13: =表1温室气体盘查表!AH13 -> 0 | AH13: =表1温室气体盘查表!AI13 -> 0 | AI13: =表1温室气体盘查表!AJ13 -> 0 | AJ13: =表1温室气体盘查表!AK13 -> 0 | AK13: =表1温室气体盘查表!AL13 -> 4417.0726
A14: 10 | B14: =表1温室气体盘查表!B14 -> 移动燃烧 | C14: =表1温室气体盘查表!C14 -> 92#汽油燃烧 | D14: =表1温室气体盘查表!E14 -> 范围一 | E14: =表1温室气体盘查表!F14 -> 49.06 | F14: =表1温室气体盘查表!G14 -> t | G14: ='附表2-EF'!K14*10 -> 0 | H14: tCO2/10000Nm12 | I14: ='附表1-GWP TABLE'!E12 -> 0 | AD14: =表1温室气体盘查表!AE14 -> 143.50325 | AE14: =表1温室气体盘查表!AF14 -> 1.4443509 | AF14: =表1温室气体盘查表!AG14 -> 4.5225266 | AG14: =表1温室气体盘查表!AH14 -> 0 | AH14: =表1温室气体盘查表!AI14 -> 0 | AI14: =表1温室气体盘查表!AJ14 -> 0 | AJ14: =表1温室气体盘查表!AK14 -> 0 | AK14: =表1温室气体盘查表!AL14 -> 149.47012
A15: 11 | B15: =表1温室气体盘查表!B15 -> 逸散排放 | C15: =表1温室气体盘查表!C15 -> 制冷剂逸散（R32） | D15: =表1温室气体盘查表!E15 -> 范围一 | E15: =表1温室气体盘查表!F15 -> 0.93 | F15: =表1温室气体盘查表!G15 -> t | G15: ='附表2-EF'!K15*10 -> 0 | H15: tCO2/10000Nm13 | I15: ='附表1-GWP TABLE'!E13 -> 0 | AD15: =表1温室气体盘查表!AE15 -> 0 | AE15: =表1温室气体盘查表!AF15 -> 0 | AF15: =表1温室气体盘查表!AG15 -> 0 | AG15: =表1温室气体盘查表!AH15 -> 717.03 | AH15: =表1温室气体盘查表!AI15 -> 0 | AI15: =表1温室气体盘查表!AJ15 -> 0 | AJ15: =表1温室气体盘查表!AK15 -> 0 | AK15: =表1温室气体盘查表!AL15 -> 717.03
A16: 12 | B16: =表1温室气体盘查表!B16 -> 逸散排放 | C16: =表1温室气体盘查表!C16 -> CO2逸散 | D16: =表1温室气体盘查表!E16 -> 范围一 | E16: =表1温室气体盘查表!F16 -> 0.66 | F16: =表1温室气体盘查表!G16 -> t | G16: ='附表2-EF'!K16*10 -> 0 | H16: tCO2/10000Nm14 | I16: ='附表1-GWP TABLE'!E14 -> 0 | AD16: =表1温室气体盘查表!AE16 -> 0.66 | AE16: =表1温室气体盘查表!AF16 -> 0 | AF16: =表1温室气体盘查表!AG16 -> 0 | AG16: =表1温室气体盘查表!AH16 -> 0 | AH16: =表1温室气体盘查表!AI16 -> 0 | AI16: =表1温室气体盘查表!AJ16 -> 0 | AJ16: =表1温室气体盘查表!AK16 -> 0 | AK16: =表1温室气体盘查表!AL16 -> 0.66
... A30: 26 | B30: =表1温室气体盘查表!B30 -> 制程排放 | C30: =表1温室气体盘查表!C30 -> 粗苯 | D30: =表1温室气体盘查表!E30 -> 范围一 | E30: =表1温室气体盘查表!F30 -> -19501.18 | F30: =表1温室气体盘查表!G30 -> t | G30: ='附表2-EF'!K30*10 -> 0 | H30: tCO2/10000Nm28 | I30: ='附表1-GWP TABLE'!E28 -> 0 | AD30: =表1温室气体盘查表!AE30 -> -65952.991 | AE30: =表1温室气体盘查表!AF30 -> 0 | AF30: =表1温室气体盘查表!AG30 -> 0 | AG30: =表1温室气体盘查表!AH30 -> 0 | AH30: =表1温室气体盘查表!AI30 -> 0 | AI30: =表1温室气体盘查表!AJ30 -> 0 | AJ30: =表1温室气体盘查表!AK30 -> 0 | AK30: =表1温室气体盘查表!AL30 -> -65952.991
A31: 27 | B31: =表1温室气体盘查表!B31 -> 制程排放 | C31: =表1温室气体盘查表!C31 -> 煤焦油 | D31: =表1温室气体盘查表!E31 -> 范围一 | E31: =表1温室气体盘查表!F31 -> -59054.1 | F31: =表1温室气体盘查表!G31 -> t | G31: ='附表2-EF'!G31*10 -> 0 | H31: tCO2/10000Nm29 | I31: ='附表1-GWP TABLE'!E29 -> 0 | AD31: =表1温室气体盘查表!AE31 -> -159387.02 | AE31: =表1温室气体盘查表!AF31 -> 0 | AF31: =表1温室气体盘查表!AG31 -> 0 | AG31: =表1温室气体盘查表!AH31 -> 0 | AH31: =表1温室气体盘查表!AI31 -> 0 | AI31: =表1温室气体盘查表!AJ31 -> 0 | AJ31: =表1温室气体盘查表!AK31 -> 0 | AK31: =表1温室气体盘查表!AL31 -> -159387.02
A32: 28 | B32: =表1温室气体盘查表!B32 -> 输入能源间接温室气体排放 | C32: =表1温室气体盘查表!C33 -> 外购电力（基于市场） | D32: =表1温室气体盘查表!E33 -> 范围二 | E32: =表1温室气体盘查表!F33 -> 1984119.4 | F32: =表1温室气体盘查表!G33 -> MWh | G32: ='附表2-EF'!G33*10 -> #VALUE! | H32: tCO2/10000Nm31 | I32: ='附表1-GWP TABLE'!E31 -> 0 | AD32: =表1温室气体盘查表!AE33 -> 1161900.3 | AE32: =表1温室气体盘查表!AF33 -> 0 | AF32: =表1温室气体盘查表!AG33 -> 0 | AG32: =表1温室气体盘查表!AH33 -> 0 | AH32: =表1温室气体盘查表!AI33 -> 0 | AI32: =表1温室气体盘查表!AJ33 -> 0 | AJ32: =表1温室气体盘查表!AK33 -> 0 | AK32: =表1温室气体盘查表!AL33 -> 1161900.3
